Workbook
Name CostoVentasBase: Inputs!$C$40
Name DeltaModQ2: Inputs!$D$75
Name DeltaModQ3: Inputs!$D$76
Name DeltaModQ4: Inputs!$D$77
Name DeltaVtasQ2: Inputs!$E$75
Name DeltaVtasQ3: Inputs!$E$76
Name DeltaVtasQ4: Inputs!$E$77
Name GtosAdminBase: Inputs!$C$44
Name GtosNoOpBase: Inputs!$C$54
Name GtosOpInflado: Inputs!$D$55
Name GtosVentasBase: Inputs!$C$48
Name InflacionAnual: Inputs!$C$11
Name IngNoOpBase: Inputs!$C$53
Name TasaDeudaLp: Inputs!$C$28
Name TasaImpuesto: Inputs!$C$25
Name TrmLargoPlazo: Inputs!$C$6

Sheet Burn & RunW
B2: ANÁLISIS CONSOLIDADO — INGRESOS, MÁRGENES, FCF BURN Y RUNWAY
B6: INDICADORES ACUMULADOS CONSOLIDADOS — ENE-JUL 2026 (Colombia real a julio; internacional hasta junio)
B7: Indicador | C7: Valor | D7: Unidad | E7: Explicación / criterio
B8: Ingresos acumulados año | C8: =(Inputs!$N$132+SUM('Consolidado '!C6:E7)*'Consolidado '!F4+SUM('Consolidado '!H6:J7)*'Consolidado '!K4+SUM('Consolidado '!M6:O7)*'Consolidado '!P4)/1000000 -> 5292.1427 | D8: COP MM | E8: Ingresos reales consolidados: Colombia enero-julio (estados financieros) más USA, Perú y Costa Rica disponibles para abril-junio; sin doble contar Colombia.
B9: Ingresos acumulados presupuesto | C9: =(SUM('Informe Accionista'!C65:F65)*'Informe Accionista'!$M$3+SUM('Informe Accionista'!G58:I58)*'Informe Accionista'!$M$2)/1000000 -> 8516.2305 | D9: COP MM | E9: Presupuesto acumulado consolidado: enero-abril utiliza el presupuesto original anual de USD 4,555,726; mayo-julio utiliza el nuevo presupuesto consolidado anual de USD 4,067,468 (~USD 4.0MM).
B10: Quema neta acumulada año — Colombia | C10: =MAX(0,('Modelo Base'!$E$34-Inputs!$J$93)/1000000) -> 57.192074 | D10: COP MM | E10: Acumulado enero-julio 2026. Fórmula: MAX(0, Caja inicial al 31-dic-2025 − Caja final al 31-jul-2026). Equivale a sumar todas las variaciones mensuales de la caja histórica de Colombia. No utiliza CapEx estimado.
B11: Quema neta acumulada año — otros países | C11: =MAX(0,-SUM(C15:C17)) -> 341.56351 | D11: COP MM | E11: Acumulado 2026 con información disponible de abril-junio para USA, Perú y Costa Rica. Fórmula: MAX(0, −SUMA de los flujos netos bancarios mensuales). Cada flujo mensual corresponde a cobros menos pagos, convertido a COP con la TRM del mes; excluye Colombia.
B12: Quema neta acumulada año — consolidada | C12: =C10+C11 -> 398.75558 | D12: COP MM | E12: Acumulado 2026: quema neta histórica de Colombia a julio más quema neta de USA, Perú y Costa Rica disponible de abril-junio (julio internacional aún sin información bancaria).
B14: Cumplimeinto Acumulado Presupuesto | C14: =C8/C9 -> 0.62141844
B15: Flujo neto abril — otros países | C15: =SUM(_xlfn.XLOOKUP("Utilidad",'Consolidado '!$B$6:$B$17,'Consolidado '!$C$6:$E$17))*'Consolidado '!$F$4/1000000 -> -154.56619 | D15: COP MM | E15: XLOOKUP busca la fila Utilidad y suma USA, Perú y Costa Rica de abril.
B16: Flujo neto mayo — otros países | C16: =SUM(_xlfn.XLOOKUP("Utilidad",'Consolidado '!$B$6:$B$17,'Consolidado '!$H$6:$J$17))*'Consolidado '!$K$4/1000000 -> -105.79334 | D16: COP MM | E16: XLOOKUP busca la fila Utilidad y suma USA, Perú y Costa Rica de mayo.
B17: Flujo neto junio — otros países | C17: =SUM(_xlfn.XLOOKUP("Utilidad",'Consolidado '!$B$6:$B$17,'Consolidado '!$M$6:$O$17))*'Consolidado '!$P$4/1000000 -> -81.203976 | D17: COP MM | E17: XLOOKUP busca la fila Utilidad y suma USA, Perú y Costa Rica de junio.
B18: El análisis usa la caja total consolidada y el FCF burn consolidado. Colombia proviene de los estados financieros (reales hasta julio); el flujo internacional (USA, Perú y Costa Rica) está incorporado hasta junio, excluyendo Colombia del Consolidado USD para evitar doble conteo. Julio aún no incluye flujo internacional.
B19: FCF BURN Y CAMBIO DE CAJA MENSUAL — ENE-JUL 2026 (COP MM)
B20: Mes | C20: CFO Colombia | D20: CapEx Colombia | E20: Flujo caja internacional | F20: FCF / Flujo caja consolidado | G20: FCF Burn | H20: Pre-WC Burn | I20: Cambio neto caja consolidado | J20: Lectura
B21: Ene-26 | C21: ='Modelo Base'!F168/1000000 -> 254.49508 | D21: ='Modelo Base'!F171/1000000 -> -7.880549 | F21: =SUM(C21:E21) -> 246.61453 | G21: =MAX(0,-F21) -> 0 | H21: =MAX(0,-(('Informe Accionista'!C129/1000000)+D21)) -> 0 | I21: ='Modelo Base'!F179/1000000 -> 229.38317 | J21: Enero concentra el mayor FCF burn del periodo.
B22: Feb-26 | C22: ='Modelo Base'!G168/1000000 -> -267.33079 | D22: ='Modelo Base'!G171/1000000 -> -6.729228 | F22: =SUM(C22:E22) -> -274.06002 | G22: =MAX(0,-F22) -> 274.06002 | H22: =MAX(0,-(('Informe Accionista'!D129/1000000)+D22)) -> 0 | I22: ='Modelo Base'!G179/1000000 -> -268.3655 | J22: Este mes explica el burn del periodo.
B23: Mar-26 | C23: ='Modelo Base'!H168/1000000 -> 51.916596 | D23: ='Modelo Base'!H171/1000000 -> -0.985518 | F23: =SUM(C23:E23) -> 50.931078 | G23: =MAX(0,-F23) -> 0 | H23: =MAX(0,-(('Informe Accionista'!E129/1000000)+D23)) -> 23.228311 | I23: ='Modelo Base'!H179/1000000 -> 74.756784 | J23: FCF positivo; solo se ve presión en la vista pre-WC.
B24: Abr-26 | C24: ='Modelo Base'!I168/1000000 -> 89.724697 | D24: ='Modelo Base'!I171/1000000 -> -3213.6098 | E24: =(('Consolidado '!C6+'Consolidado '!C11)+('Consolidado '!D6-'Consolidado '!D15)+('Consolidado '!E6+'Consolidado '!E7+'Consolidado '!E11+'Consolidado '!E15))*'Consolidado '!F4/1000000 -> -154.56619 | F24: =SUM(C24:E24) -> -3278.4513 | G24: =MAX(0,-F24) -> 3278.4513 | H24: =MAX(0,-(('Informe Accionista'!F129/1000000)+D24)) -> 3208.7715 | I24: ='Modelo Base'!I179/1000000 -> -3773.5938 | J24: Abr: flujo histórico Colombia más caja internacional real disponible.
B25: May-26 | C25: =(Inputs!H155+(Inputs!H109-Inputs!G109)+(Inputs!H113-Inputs!G113)+(Inputs!H112-Inputs!G112)-(Inputs!H96-Inputs!G96)-(Inputs!H94-Inputs!G94)-(Inputs!H97-Inputs!G97))/1000000 -> -86.36183 | D25: =-(Inputs!H101-Inputs!G101)/1000000 -> -7.792981 | E25: =(SUM('Consolidado '!H6:J7)-SUM('Consolidado '!H9:J9,'Consolidado '!H11:J13,'Consolidado '!H15:J15))*'Consolidado '!K4/1000000 -> -105.79334 | F25: =SUM(C25:E25) -> -199.94815 | G25: =MAX(0,-F25) -> 199.94815 | H25: =MAX(0,-('Informe Accionista'!G129/1000000+D25)) -> 0 | I25: =(Inputs!H93-Inputs!G93)/1000000 -> -112.93482 | J25: May: flujo histórico Colombia más caja internacional real disponible.
B26: Jun-26 | C26: =(Inputs!I155+(Inputs!I109-Inputs!H109)+(Inputs!I113-Inputs!H113)+(Inputs!I112-Inputs!H112)-(Inputs!I96-Inputs!H96)-(Inputs!I94-Inputs!H94)-(Inputs!I97-Inputs!H97))/1000000 -> -112.21246 | D26: =-(Inputs!I101-Inputs!H101)/1000000 -> 0 | E26: =J47 -> -81.203976 | F26: =SUM(C26:E26) -> -193.41644 | G26: =MAX(0,-F26) -> 193.41644 | H26: =MAX(0,-(('Informe Accionista'!H129/1000000)+D26)) -> 0 | I26: =(Inputs!I93-Inputs!H93)/1000000+E26 -> -210.58496 | J26: Jun: Colombia más flujo bancario de USA, Perú y Costa Rica calculado solo con filas 1–16 del consolidado.
B27: Jul-26 | C27: =(Inputs!J155+(Inputs!J109-Inputs!I109)+(Inputs!J113-Inputs!I113)+(Inputs!J112-Inputs!I112)-(Inputs!J96-Inputs!I96)-(Inputs!J94-Inputs!I94)-(Inputs!J97-Inputs!I97))/1000000 -> 37.553515 | D27: =-(Inputs!J101-Inputs!I101)/1000000 -> 0 | E27: 0 | F27: =SUM(C27:E27) -> 37.553515 | G27: =MAX(0,-F27) -> 0 | I27: =(Inputs!J93-Inputs!I93)/1000000+E27 -> 58.825564 | J27: Jul: solo Colombia (estados financieros julio); flujo internacional de julio pendiente — Consolidado llega a junio.
B28: YTD Ene-Jul | C28: =SUM(C21:C27) -> -32.215191 | D28: =SUM(D21:D27) -> -3236.9981 | E28: =SUM(E21:E27) -> -341.56351 | F28: =SUM(F21:F27) -> -3610.7768 | G28: =SUM(G21:G27) -> 3945.8759 | H28: =SUM(H21:H27) -> 3231.9998 | I28: =SUM(I21:I27) -> -4002.5136 | J28: Acumulado Ene-Jun. FCF neto total incluye junio.
B29: Promedio 3M May-Jul | C29: =AVERAGE(C25:C27) -> -53.673592 | D29: =AVERAGE(D25:D27) -> -2.5976603 | E29: =AVERAGE(E25:E27) -> -62.332438 | F29: =AVERAGE(F25:F27) -> -118.60369 | G29: =AVERAGE(G25:G27) -> 131.12153 | H29: =AVERAGE(H25:H27) -> 0 | I29: =AVERAGE(I25:I27) -> -88.231404 | J29: Promedio 3M (Abr-Jun) usado para runway.
B31: Ingresos presupuesto vs ejecutado (USD MM y COP MM) — Ene a Jul 2026
B32: Mes | C32: Ppto USD MM | D32: Ejec. USD MM | E32: Gap USD MM | F32: Cumplimiento % | G32: Ppto COP MM | H32: Ejec. COP MM | I32: Gap COP MM
B33: Ene-26 | C33: 0.186 | D33: ='Informe Accionista'!C122/Inputs!$C$27/1000000 -> 0.16592079 | E33: =D33-C33 -> -0.020079214 | F33: =IF(C33=0,"N/A",D33/C33) -> 0.89204724 | G33: =C33*Inputs!$C$27 -> 686.34 | H33: ='Informe Accionista'!C122/1000000 -> 612.2477 | I33: =H33-G33 -> -74.092299
B34: Feb-26 | C34: 0.354 | D34: ='Informe Accionista'!D122/Inputs!$C$27/1000000 -> 0.20168513 | E34: =D34-C34 -> -0.15231487 | F34: =IF(C34=0,"N/A",D34/C34) -> 0.56973201 | G34: =C34*Inputs!$C$27 -> 1306.26 | H34: ='Informe Accionista'!D122/1000000 -> 744.21814 | I34: =H34-G34 -> -562.04186
B35: Mar-26 | C35: 0.396 | D35: ='Informe Accionista'!E122/Inputs!$C$27/1000000 -> 0.21329029 | E35: =D35-C35 -> -0.18270971 | F35: =IF(C35=0,"N/A",D35/C35) -> 0.53861185 | G35: =C35*Inputs!$C$27 -> 1461.24 | H35: ='Informe Accionista'!E122/1000000 -> 787.04119 | I35: =H35-G35 -> -674.19881
B36: Abr-26 | C36: 0.359 | D36: ='Informe Accionista'!F122/Inputs!$C$27/1000000 -> 0.20348717 | E36: =D36-C36 -> -0.15551283 | F36: =IF(C36=0,"N/A",D36/C36) -> 0.56681663 | G36: =C36*Inputs!$C$27 -> 1324.71 | H36: ='Informe Accionista'!F122/1000000 -> 750.86766 | I36: =H36-G36 -> -573.84234
B37: May-26 | C37: 0.403 | D37: ='Informe Accionista'!G122/Inputs!$C$27/1000000 -> 0.22398774 | E37: =D37-C37 -> -0.17901226 | F37: =IF(C37=0,"N/A",D37/C37) -> 0.55580083 | G37: =C37*Inputs!$C$27 -> 1487.07 | H37: ='Informe Accionista'!G122/1000000 -> 826.51475 | I37: =H37-G37 -> -660.55525
B38: Jun-26 | C38: ='Informe Accionista'!H65/1000000 -> 0.375559 | D38: ='Informe Accionista'!H122/Inputs!$C$27/1000000 -> 0.20364588 | E38: =D38-C38 -> -0.17191312 | F38: =IF(C38=0,"N/A",D38/C38) -> 0.54224738 | G38: =C38*Inputs!$C$27 -> 1385.8127 | H38: ='Informe Accionista'!H122/1000000 -> 751.45331 | I38: =H38-G38 -> -634.3594
B39: Jul-26 | C39: ='Informe Accionista'!I65/1000000 -> 0.388085 | D39: ='Modelo Base'!L51/Inputs!$C$27/1000000 -> 0.18425218 | E39: =D39-C39 -> -0.20383282 | F39: =IF(C39=0,"N/A",D39/C39) -> 0.47477275 | G39: =C39*Inputs!$C$27 -> 1432.0337 | H39: ='Modelo Base'!L51/1000000 -> 679.89055 | I39: =H39-G39 -> -752.1431
B40: Total Ene-Jul | C40: =SUM(C33:C39) -> 2.461644 | D40: =SUM(D33:D39) -> 1.3962692 | E40: =D40-C40 -> -1.0653748 | F40: =IF(C40=0,"N/A",D40/C40) -> 0.56721004 | G40: =SUM(G33:G39) -> 9083.4664 | H40: =SUM(H33:H39) -> 5152.2333 | I40: =H40-G40 -> -3931.2331
B42: Puente de caja Jun → Jul 2026 (COP MM) | F42: Flujo de caja internacional — Jun-26 (excluye Colombia)
B43: Concepto | C43: COP MM | D43: Comentario | F43: País | G43: Ingresos USD | H43: Egresos USD | I43: Flujo neto USD | J43: Flujo neto COP MM
B44: Caja inicial (jun-26) | C44: =Inputs!I93/1000000 -> 115.44136 | F44: USA | G44: =SUM('Consolidado '!M6:M7) -> 5664.45 | H44: =-SUM('Consolidado '!M9,'Consolidado '!M11:M13,'Consolidado '!M15) -> -27968.27 | I44: =SUM(G44:H44) -> -22303.82 | J44: =I44*$J$49/1000000 -> -78.180874
B45: (+) Utilidad neta de julio | C45: =Inputs!J155/1000000 -> 24.707052 | D45: Julio fue rentable | F45: Perú | G45: =SUM('Consolidado '!N6:N7) -> 1821.5125 | H45: =-SUM('Consolidado '!N9,'Consolidado '!N11:N13,'Consolidado '!N15) -> -11.967695 | I45: =SUM(G45:H45) -> 1809.5448 | J45: =I45*$J$49/1000000 -> 6.34294
B46: (−) Aumento de Clientes (CxC) | C46: =-(Inputs!J96-Inputs!I96)/1000000 -> 110.97319 | D46: Recuperación de cartera: cobros superaron la facturación a crédito | F46: Costa Rica | G46: =SUM('Consolidado '!O6:O7) -> 0 | H46: =-SUM('Consolidado '!O9,'Consolidado '!O11:O13,'Consolidado '!O15) -> -2671.99 | I46: =SUM(G46:H46) -> -2671.99 | J46: =I46*$J$49/1000000 -> -9.3660419
B47: (−) Aumento otros deudores/anticipos | C47: =-(Inputs!J97-Inputs!I97)/1000000 -> -31.840709 | F47: Total internacional | I47: =SUM(I44:I46) -> -23166.265 | J47: =SUM(J44:J46) -> -81.203976
B48: (−) Pago a proveedores | C48: =(Inputs!J109-Inputs!I109)/1000000 -> -79.630602
B49: (+/−) Δ Impuestos por pagar | C49: =(Inputs!J112-Inputs!I112)/1000000 -> -4.096021 | F49: TRM junio | J49: ='Consolidado '!P4 -> 3505.2683
B50: (−) Pago obligaciones laborales | C50: =(Inputs!J113-Inputs!I113)/1000000 -> 18.141309 | D50: Aumento de provisiones/obligaciones laborales (fuente de caja) | F50: Fuente / criterio | G50: Transacciones bancarias de junio tomadas únicamente de las filas 1–16; USA, Perú y Costa Rica. Se excluyen Colombia y todas las filas desde la 17.
B51: = Flujo operativo neto | C51: =SUM(C45:C50) -> 38.254216
B52: (+) Venta de inversiones (fiducia) | C52: =-(Inputs!J94-Inputs!I94)/1000000 -> -0.700701 | D52: Liquidación para cubrir caja
B53: (−) CapEx (Δ PPE neto) | C53: =-(Inputs!J101-Inputs!I101)/1000000 -> 0
B54: (−) Pago tarjetas / oblig. financieras | C54: =(Inputs!J108-Inputs!I108)/1000000 -> 21.051248
B55: (+/−) Movimiento neto con socios | C55: =(Inputs!J116-Inputs!I116)/1000000 -> 0.2208
B56: = Caja final (jul-26) calculada | C56: =C44+C51+SUM(C52:C55) -> 174.26693
B57: Caja final (jul-26) reportada | C57: =Inputs!J93/1000000 -> 174.26693
B58: Diferencia (chequeo; tolerancia COP 5) | C58: =C56-C57 -> -1e-06 | D58: =IF(ABS(C58)<=0.000005,"OK","REVISAR") -> OK
B60: Consumo neto de caja Colombia del mes | C60: =C57-C44 -> 58.825564
B62: Sensibilidad: caja según días de cobro (DSO clientes)
B63: CxC clientes = ingreso mensual × DSO/30. Parte del cierre real de julio. Cifras COP MM.
B64: Ingreso mensual (jul) | C64: ='Modelo Base'!L51/1000000 -> 679.89055
B65: CxC clientes actual | C65: =Inputs!J96/1000000 -> 1688.4579
B66: DSO actual clientes (días) | C66: =Inputs!J96/'Modelo Base'!L51*30 -> 74.502782
B67: Caja actual | C67: =Inputs!J93/1000000 -> 174.26693
B68: Caja mínima operativa | C68: ='Modelo Base'!E32/1000000 -> 231.459
B70: DSO objetivo | C70: CxC clientes | D70: Caja liberada | E70: Caja resultante | F70: vs mínimo
B71: 50 | C71: =$C$64*B71/30 -> 1133.1509 | D71: =$C$65-C71 -> 555.30699 | E71: =$C$67+D71 -> 729.57392 | F71: =IF(E71>=$C$68,"OK","Bajo mínimo") -> OK
B72: 60 | C72: =$C$64*B72/30 -> 1359.7811 | D72: =$C$65-C72 -> 328.67681 | E72: =$C$67+D72 -> 502.94374 | F72: =IF(E72>=$C$68,"OK","Bajo mínimo") -> OK | G72: Fuente / alcance | H72: Colombia: estados financieros firmados. Internacional: Consolidado USD filas 1–16, únicamente USA, Perú y Costa Rica; Colombia excluida.
B73: =$C$66 -> 74.502782 | C73: =$C$64*B73/30 -> 1688.4579 | D73: =$C$65-C73 -> 0 | E73: =$C$67+D73 -> 174.26693 | F73: =IF(E73>=$C$68,"OK","Bajo mínimo") -> Bajo mínimo
B74: 80 | C74: =$C$64*B74/30 -> 1813.0415 | D74: =$C$65-C74 -> -124.58356 | E74: =$C$67+D74 -> 49.683369 | F74: =IF(E74>=$C$68,"OK","Bajo mínimo") -> Bajo mínimo
B75: 90 | C75: =$C$64*B75/30 -> 2039.6717 | D75: =$C$65-C75 -> -351.21374 | E75: =$C$67+D75 -> -176.94681 | F75: =IF(E75>=$C$68,"OK","Bajo mínimo") -> Bajo mínimo
B76: 100 | C76: =$C$64*B76/30 -> 2266.3018 | D76: =$C$65-C76 -> -577.84393 | E76: =$C$67+D76 -> -403.577 | F76: =IF(E76>=$C$68,"OK","Bajo mínimo") -> Bajo mínimo
B78: Palanca adicional: recuperación de otros deudores
B79: Otros deudores/anticipos/terceros al cierre jul. Incluye inversiones de terceros y anticipo de impuestos. COP MM.
B80: Otros deudores actual | C80: =Inputs!J97/1000000 -> 3529.697
B81: % recuperado | C81: Caja liberada | D81: Caja resultante | E81: vs mínimo
B82: 0.1 | C82: =$C$80*B82 -> 352.9697 | D82: =$C$67+C82 -> 527.23663 | E82: =IF(D82>=$C$68,"OK","Bajo mínimo") -> OK
B83: 0.25 | C83: =$C$80*B83 -> 882.42426 | D83: =$C$67+C83 -> 1056.6912 | E83: =IF(D83>=$C$68,"OK","Bajo mínimo") -> OK
B84: 0.5 | C84: =$C$80*B84 -> 1764.8485 | D84: =$C$67+C84 -> 1939.1154 | E84: =IF(D84>=$C$68,"OK","Bajo mínimo") -> OK
B86: RESUMEN EJECUTIVO CONSOLIDADO — CAJA, BURN Y RUNWAY
B87: Cifras consolidadas a julio de 2026. La caja de Colombia proviene de los estados financieros de julio; el burn internacional (USA, Perú y Costa Rica) está actualizado a junio por falta de información bancaria de julio, por lo que el burn consolidado de julio refleja solo Colombia.
B89: Indicador | C89: Valor | D89: Unidad | E89: Explicación / lectura para accionistas
B90: Caja Colombia | C90: =Inputs!J93/1000000 -> 174.26693 | D90: COP MM | E90: Saldo de efectivo y equivalentes reportado en el balance de julio.
B91: Caja EE.UU. | C91: 365.316 | D91: USD k | E91: Saldo de caja mantenido en Estados Unidos.
B92: TRM aplicada | C92: 3248.87 | D92: COP / USD | E92: Tasa utilizada para convertir la caja de Estados Unidos a pesos colombianos.
B93: Caja EE.UU. convertida | C93: =C91*C92/1000 -> 1186.8642 | D93: COP MM | E93: Equivalente en pesos de la caja mantenida en Estados Unidos.
B94: Caja total consolidada | C94: =SUM(C90,C93) -> 1361.1311 | D94: COP MM | E94: ="Liquidez consolidada disponible de COP "&TEXT(C94,"#,##0.0")&"MM; equivale a USD "&TEXT(C94*1000/C92,"#,##0.0")&"k." -> Liquidez consolidada disponible de COP 1,361.1MM; equivale a USD 419.0k.
B95: Consumo neto caja consolidado julio | C95: =MAX(0,-I27) -> 0 | D95: COP MM | E95: Mide la disminución real total de la caja durante julio. En julio la caja aumentó, por lo que el consumo neto es cero. Incluye operación, capital de trabajo, CapEx y otros movimientos de inversión o financiación.
B96: FCF burn consolidado julio | C96: =G27 -> 0 | D96: COP MM / mes | E96: Mide el consumo generado por el flujo operativo más CapEx. En julio el FCF fue positivo, por lo que no hubo burn. Excluye otros movimientos de inversión y financiación.
B97: Runway consolidado al burn de julio | C97: =IF(C96<=0,"N/A",C94/C96) -> N/A | D97: Meses | E97: No aplica: en julio no hubo quema de caja, de modo que el runway al ritmo del mes es indefinido.
B98: Runway promedio May-Jul | C98: =IF(AVERAGE(G25:G27)<=0,"N/A",C94/AVERAGE(G25:G27)) -> 10.380684 | D98: Meses | E98: Escenario reciente: promedio de burn de mayo a julio; julio no aportó quema y mejora el promedio trimestral.
B99: Runway promedio Ene-Jul | C99: =IF(AVERAGE(G21:G27)<=0,"N/A",C94/AVERAGE(G21:G27)) -> 2.4146522 | D99: Meses | E99: Escenario conservador, afectado por el consumo extraordinariamente alto registrado en enero.
B100: Mensaje clave | C100: ="La compañía cuenta con COP "&TEXT(C94,"#,##0.0")&"MM de caja total consolidada. "&IF(C96<=0,"En julio no hubo quema de caja: el saldo aumentó COP "&TEXT(I27,"#,##0.0")&"MM, por lo que el runway al ritmo del mes no aplica. ","Al ritmo consolidado de julio la cobertura es de "&TEXT(C97,"0.0")&" meses. ")&"Con el burn promedio May-Jul el runway es de "&TEXT(C98,"0.0")&" meses y con el promedio Ene-Jul de "&TEXT(C99,"0.0")&" meses." -> La compañía cuenta con COP 1,361.1MM de caja total consolidada. En julio no hubo quema de caja: el saldo aumentó COP 58.8MM, por lo que el runway al ritmo del mes no aplica. Con el burn promedio May-Jul el runway es de 10.4 meses y con el promedio Ene-Jul de 2.4 meses.
B101: Diferencia consumo neto vs FCF burn | C101: =C95-C96 -> 0 | D101: COP MM | E101: La diferencia corresponde a movimientos de caja por fuera del FCF, principalmente inversión, obligaciones financieras, socios u otros movimientos no operativos.
B102: RUNWAY PROYECTADO AGO–DIC 2026 — PRESUPUESTO MODELO BASE
B103: ="El presupuesto anual del modelo suma USD "&TEXT(SUM('Modelo Base'!F281:Q281)/1000000,"0.00")&"MM (aprox. USD 3.9MM). La proyección parte de la caja total consolidada de COP "&TEXT($C$94,"#,##0.0")&"MM." -> El presupuesto anual del modelo suma USD 3.78MM (aprox. USD 3.9MM). La proyección parte de la caja total consolidada de COP 1,361.1MM.
B105: Mes | C105: Ingresos presupuesto | D105: Flujo neto de caja | E105: Caja total proyectada | F105: Estado / explicación
B106: ='Modelo Base'!M279 -> Ago-26 | C106: ='Modelo Base'!M281/1000 -> 426.45693 | D106: ='Modelo Base'!M179/1000000 -> -1792.2623 | E106: =$C$94+D106 -> -431.13113 | F106: =IF(E106<0,"Déficit","Caja positiva")&" — el salto de capital de trabajo del presupuesto (CxC a "&TEXT('Modelo Base'!$E$27,"0")&" días sobre ingresos muy superiores a los reales) concentra el consumo en agosto." -> Déficit — el salto de capital de trabajo del presupuesto (CxC a 84 días sobre ingresos muy superiores a los reales) concentra el consumo en agosto.
B107: ='Modelo Base'!N279 -> Sep-26 | C107: ='Modelo Base'!N281/1000 -> 451.23074 | D107: ='Modelo Base'!N179/1000000 -> 313.51645 | E107: =E106+D107 -> -117.61468 | F107: =IF(E107<0,"Déficit","Caja positiva")&" — el flujo mensual proyectado vuelve a ser positivo." -> Déficit — el flujo mensual proyectado vuelve a ser positivo.
B108: ='Modelo Base'!O279 -> Oct-26 | C108: ='Modelo Base'!O281/1000 -> 476.00455 | D108: ='Modelo Base'!O179/1000000 -> 372.95705 | E108: =E107+D108 -> 255.34236 | F108: =IF(E108<0,"Déficit","Caja positiva")&" — la recuperación operativa recompone la liquidez." -> Caja positiva — la recuperación operativa recompone la liquidez.
B109: ='Modelo Base'!P279 -> Nov-26 | C109: ='Modelo Base'!P281/1000 -> 500.77836 | D109: ='Modelo Base'!P179/1000000 -> 432.97063 | E109: =E108+D109 -> 688.31299 | F109: =IF(E109<0,"Déficit","Caja positiva")&" — continúa la generación de caja presupuestada." -> Caja positiva — continúa la generación de caja presupuestada.
B110: ='Modelo Base'!Q279 -> Dic-26 | C110: ='Modelo Base'!Q281/1000 -> 525.55217 | D110: ='Modelo Base'!Q179/1000000 -> 480.91036 | E110: =E109+D110 -> 1169.2234 | F110: =IF(E110<0,"Déficit","Caja positiva")&" — cierre de año proyectado." -> Caja positiva — cierre de año proyectado.
B113: Presupuesto anual de ingresos | C113: =SUM('Modelo Base'!F281:Q281)/1000000 -> 3.7762919 | D113: USD MM | E113: Presupuesto total de ingresos 2026 incluido en el Modelo Base.
B114: Ingresos presupuestados Ago–Dic | C114: =SUM(C106:C110)/1000 -> 2.3800227 | D114: USD MM | E114: Ingresos pendientes del segundo semestre incluidos en la proyección.
B115: Runway hasta primer déficit | C115: =IF(E106<0,$C$94/ABS(D106),IF(E107<0,1+E106/ABS(D107),5)) -> 0.75944863 | D115: Meses | E115: Meses que cubre la caja consolidada de julio antes del primer déficit proyectado, si los flujos del presupuesto ocurren exactamente como están modelados.
B116: Necesidad máxima temporal de liquidez | C116: =MAX(0,-MIN(E106:E110)) -> 431.13113 | D116: COP MM | E116: Déficit máximo proyectado antes de la recuperación de caja desde septiembre.
...

Sheet Ppto Ene. 2026
A1: COCO TECNOLOGÍAS — P&L × 3 Escenarios 2026
C5: Inflación | H5: 0.051
C6: Tasa de Cambio | H6: 4000
B7: P&L 2026 — Monthly (Level 4) — Phase 1: Revenue lines (COP & USD)
U9: Total 2026
A10: PUC | B10: Account | E10: Currency | G10: 2026-01 | H10: 2026-02 | I10: 2026-03 | J10: 2026-04 | K10: 2026-05 | L10: 2026-06 | M10: 2026-07 | N10: 2026-08 | O10: 2026-09 | P10: 2026-10 | Q10: 2026-11 | R10: 2026-12
U11: =SUM(G12:R12) -> 1.8222904e+10
A12: 4170 | B12: Otras actividades de servicios comunitarios, sociales y personales | E12: COP | G12: 7.4492961e+08 | H12: 1.4172832e+09 | I12: 1.5849544e+09 | J12: 1.436763e+09 | K12: 1.6123205e+09 | L12: 1.5022355e+09 | M12: 1.5523381e+09 | N12: 1.5343577e+09 | O12: 1.6970537e+09 | P12: 1.6798161e+09 | Q12: 1.692867e+09 | R12: 1.7679851e+09
U13: =SUM(G14:R14) -> 4555726
A14: 4170 | B14: Otras actividades de servicios comunitarios, sociales y personales | E14: USD | G14: 186232.4 | H14: 354320.8 | I14: 396238.6 | J14: 359190.75 | K14: 403080.12 | L14: 375558.87 | M14: 388084.53 | N14: 383589.42 | O14: 424263.43 | P14: 419954.03 | Q14: 423216.76 | R14: 441996.28
F16: Ponderador Mensual
D17: Cifra 2025 | E17: Cifra 2026 | F17: =1/12 -> 0.083333333
F19: =G10 -> 2026-01 | G19: =H10 -> 2026-02 | H19: =I10 -> 2026-03 | I19: =J10 -> 2026-04 | J19: =K10 -> 2026-05 | K19: =L10 -> 2026-06 | L19: =M10 -> 2026-07 | M19: =N10 -> 2026-08 | ... Q19: =R10 -> 2026-12 | S19: =U9 -> Total 2026
A20: Moneda COP
A22: Ingresos Operacionales | F22: =G12 -> 7.4492961e+08 | G22: =H12 -> 1.4172832e+09 | H22: =I12 -> 1.5849544e+09 | I22: =J12 -> 1.436763e+09 | J22: =K12 -> 1.6123205e+09 | K22: =L12 -> 1.5022355e+09 | L22: =M12 -> 1.5523381e+09 | M22: =N12 -> 1.5343577e+09 | ... Q22: =R12 -> 1.7679851e+09 | S22: =SUM(F22:Q22) -> 1.8222904e+10
D24: %
A25: Costo de Ventas | B25: 5.0860033e+09 | C25: =B25*(1+$H$5) -> 5.3453895e+09 | F25: =$C25*$F$17 -> 4.4544912e+08 | G25: =$C25*$F$17 -> 4.4544912e+08 | H25: =$C25*$F$17 -> 4.4544912e+08 | I25: =$C25*$F$17 -> 4.4544912e+08 | J25: =$C25*$F$17 -> 4.4544912e+08 | K25: =$C25*$F$17 -> 4.4544912e+08 | L25: =$C25*$F$17 -> 4.4544912e+08 | M25: =$C25*$F$17 -> 4.4544912e+08 | ... Q25: =$C25*$F$17 -> 4.4544912e+08 | S25: =SUM(F25:Q25) -> 5.3453895e+09
A26: Mano de Obra Directa | B26: 3.096729e+09 | C26: =B26*(1+$H$5) -> 3.2546622e+09 | F26: =$C26*$F$17 -> 2.7122185e+08 | G26: =$C26*$F$17 -> 2.7122185e+08 | H26: =$C26*$F$17 -> 2.7122185e+08 | I26: =$C26*$F$17 -> 2.7122185e+08 | J26: =$C26*$F$17 -> 2.7122185e+08 | K26: =$C26*$F$17 -> 2.7122185e+08 | L26: =$C26*$F$17 -> 2.7122185e+08 | M26: =$C26*$F$17 -> 2.7122185e+08 | ... Q26: =$C26*$F$17 -> 2.7122185e+08 | S26: =SUM(F26:Q26) -> 3.2546622e+09
A27: Operacionales de Desarrollo | B27: 1.9892743e+09 | C27: =B27*(1+$H$5) -> 2.0907273e+09 | F27: =$C27*$F$17 -> 1.7422727e+08 | G27: =$C27*$F$17 -> 1.7422727e+08 | H27: =$C27*$F$17 -> 1.7422727e+08 | I27: =$C27*$F$17 -> 1.7422727e+08 | J27: =$C27*$F$17 -> 1.7422727e+08 | K27: =$C27*$F$17 -> 1.7422727e+08 | L27: =$C27*$F$17 -> 1.7422727e+08 | M27: =$C27*$F$17 -> 1.7422727e+08 | ... Q27: =$C27*$F$17 -> 1.7422727e+08 | S27: =SUM(F27:Q27) -> 2.0907273e+09
A29: Utilidad Bruta | F29: =F22-F26-F27 -> 2.9948049e+08 | G29: =G22-G26-G27 -> 9.7183409e+08 | H29: =H22-H26-H27 -> 1.1395053e+09 | I29: =I22-I26-I27 -> 9.9131388e+08 | J29: =J22-J26-J27 -> 1.1668714e+09 | K29: =K22-K26-K27 -> 1.0567864e+09 | L29: =L22-L26-L27 -> 1.106889e+09 | M29: =M22-M26-M27 -> 1.0889086e+09 | ... Q29: =Q22-Q26-Q27 -> 1.322536e+09 | S29: =SUM(F29:Q29) -> 1.2877515e+10
A32: Operacionales de Administración | B32: 1.5320319e+09 | C32: =B32*(1+$H$5) -> 1.6101656e+09 | F32: =$C32*$F$17 -> 1.3418046e+08 | G32: =$C32*$F$17 -> 1.3418046e+08 | H32: =$C32*$F$17 -> 1.3418046e+08 | I32: =$C32*$F$17 -> 1.3418046e+08 | J32: =$C32*$F$17 -> 1.3418046e+08 | K32: =$C32*$F$17 -> 1.3418046e+08 | L32: =$C32*$F$17 -> 1.3418046e+08 | M32: =$C32*$F$17 -> 1.3418046e+08 | ... Q32: =$C32*$F$17 -> 1.3418046e+08 | S32: =SUM(F32:Q32) -> 1.6101656e+09
A33: Gastos de Personal | B33: 705937048 | C33: =B33*(1+$H$5) -> 7.4193984e+08 | D33: 0.46 | F33: =$C33*$F$17 -> 61828320 | G33: =$C33*$F$17 -> 61828320 | H33: =$C33*$F$17 -> 61828320 | I33: =$C33*$F$17 -> 61828320 | J33: =$C33*$F$17 -> 61828320 | K33: =$C33*$F$17 -> 61828320 | L33: =$C33*$F$17 -> 61828320 | M33: =$C33*$F$17 -> 61828320 | ... Q33: =$C33*$F$17 -> 61828320 | S33: =SUM(F33:Q33) -> 7.4193984e+08
A34: Otros Gastos de Administración Operacionales | B34: 8.2609489e+08 | C34: =B34*(1+$H$5) -> 8.6822573e+08 | F34: =$C34*$F$17 -> 72352144 | G34: =$C34*$F$17 -> 72352144 | H34: =$C34*$F$17 -> 72352144 | I34: =$C34*$F$17 -> 72352144 | J34: =$C34*$F$17 -> 72352144 | K34: =$C34*$F$17 -> 72352144 | L34: =$C34*$F$17 -> 72352144 | M34: =$C34*$F$17 -> 72352144 | ... Q34: =$C34*$F$17 -> 72352144 | S34: =SUM(F34:Q34) -> 8.6822573e+08
S35: =SUM(F35:Q35) -> 0
S36: =SUM(F36:Q36) -> 0
A37: Operacionales de Ventas | B37: 2.4666933e+09 | C37: =B37*(1+$H$5) -> 2.5924947e+09 | F37: =$C37*$F$17 -> 2.1604123e+08 | G37: =$C37*$F$17 -> 2.1604123e+08 | H37: =$C37*$F$17 -> 2.1604123e+08 | I37: =$C37*$F$17 -> 2.1604123e+08 | J37: =$C37*$F$17 -> 2.1604123e+08 | K37: =$C37*$F$17 -> 2.1604123e+08 | L37: =$C37*$F$17 -> 2.1604123e+08 | M37: =$C37*$F$17 -> 2.1604123e+08 | ... Q37: =$C37*$F$17 -> 2.1604123e+08 | S37: =SUM(F37:Q37) -> 2.5924947e+09
A38: Gastos de Personal | B38: 1099685429 | C38: =B38*(1+$H$5) -> 1.1557694e+09 | F38: =$C38*$F$17 -> 96314115 | G38: =$C38*$F$17 -> 96314115 | H38: =$C38*$F$17 -> 96314115 | I38: =$C38*$F$17 -> 96314115 | J38: =$C38*$F$17 -> 96314115 | K38: =$C38*$F$17 -> 96314115 | L38: =$C38*$F$17 -> 96314115 | M38: =$C38*$F$17 -> 96314115 | ... Q38: =$C38*$F$17 -> 96314115 | S38: =SUM(F38:Q38) -> 1.1557694e+09
A39: Honorarios | B39: 4.6489068e+08 | C39: =B39*(1+$H$5) -> 4.8860011e+08 | F39: =$C39*$F$17 -> 40716675 | G39: =$C39*$F$17 -> 40716675 | H39: =$C39*$F$17 -> 40716675 | I39: =$C39*$F$17 -> 40716675 | J39: =$C39*$F$17 -> 40716675 | K39: =$C39*$F$17 -> 40716675 | L39: =$C39*$F$17 -> 40716675 | M39: =$C39*$F$17 -> 40716675 | ... Q39: =$C39*$F$17 -> 40716675 | S39: =SUM(F39:Q39) -> 4.8860011e+08
A40: Otros Gastos de Ventas Operacionales | B40: 9.0211724e+08 | C40: =B40*(1+$H$5) -> 9.4812522e+08 | F40: =$C40*$F$17 -> 79010435 | G40: =$C40*$F$17 -> 79010435 | H40: =$C40*$F$17 -> 79010435 | I40: =$C40*$F$17 -> 79010435 | J40: =$C40*$F$17 -> 79010435 | K40: =$C40*$F$17 -> 79010435 | L40: =$C40*$F$17 -> 79010435 | M40: =$C40*$F$17 -> 79010435 | ... Q40: =$C40*$F$17 -> 79010435 | S40: =SUM(F40:Q40) -> 9.4812522e+08
S41: =SUM(F41:Q41) -> 0
A42: Utilidad Operacional | F42: =F29-F32-F37 -> -50741202 | G42: =G29-G32-G37 -> 6.2161241e+08 | H42: =H29-H32-H37 -> 7.8928359e+08 | I42: =I29-I32-I37 -> 6.4109219e+08 | J42: =J29-J32-J37 -> 8.1664966e+08 | K42: =K29-K32-K37 -> 7.0656469e+08 | L42: =L29-L32-L37 -> 7.566673e+08 | M42: =M29-M32-M37 -> 7.3868689e+08 | ... Q42: =Q29-Q32-Q37 -> 9.7231431e+08 | S42: =SUM(F42:Q42) -> 8.6748543e+09
S43: =SUM(F43:Q43) -> 0
A44: Ingresos no Operacionales | B44: 36272911 | C44: =B44*(1+$H$5) -> 38122829 | F44: =$C44*$F$17 -> 3176902.4 | G44: =$C44*$F$17 -> 3176902.4 | H44: =$C44*$F$17 -> 3176902.4 | I44: =$C44*$F$17 -> 3176902.4 | J44: =$C44*$F$17 -> 3176902.4 | K44: =$C44*$F$17 -> 3176902.4 | L44: =$C44*$F$17 -> 3176902.4 | M44: =$C44*$F$17 -> 3176902.4 | ... Q44: =$C44*$F$17 -> 3176902.4 | S44: =SUM(F44:Q44) -> 38122829
A45: Gastos no Operacionales | B45: 92043202 | C45: =B45*(1+$H$5) -> 96737405 | F45: =$C45*$F$17 -> 8061450.4 | G45: =$C45*$F$17 -> 8061450.4 | H45: =$C45*$F$17 -> 8061450.4 | I45: =$C45*$F$17 -> 8061450.4 | J45: =$C45*$F$17 -> 8061450.4 | K45: =$C45*$F$17 -> 8061450.4 | L45: =$C45*$F$17 -> 8061450.4 | M45: =$C45*$F$17 -> 8061450.4 | ... Q45: =$C45*$F$17 -> 8061450.4 | S45: =SUM(F45:Q45) -> 96737405
A47: Utilidad Antes de Impuestos | F47: =F42+F44-F45 -> -55625750 | G47: =G42+G44-G45 -> 6.1672786e+08 | H47: =H42+H44-H45 -> 7.8439904e+08 | I47: =I42+I44-I45 -> 6.3620764e+08 | J47: =J42+J44-J45 -> 8.1176512e+08 | K47: =K42+K44-K45 -> 7.0168014e+08 | L47: =L42+L44-L45 -> 7.5178275e+08 | M47: =M42+M44-M45 -> 7.3380234e+08 | ... Q47: =Q42+Q44-Q45 -> 9.6742977e+08 | S47: =SUM(F47:Q47) -> 8.6162397e+09
A49: Impuestos | F49: =IF(F47>0,F47*35%,0) -> 0 | G49: =IF(G47>0,G47*35%,0) -> 2.1585475e+08 | H49: =IF(H47>0,H47*35%,0) -> 2.7453966e+08 | I49: =IF(I47>0,I47*35%,0) -> 2.2267268e+08 | J49: =IF(J47>0,J47*35%,0) -> 2.8411779e+08 | K49: =IF(K47>0,K47*35%,0) -> 2.4558805e+08 | L49: =IF(L47>0,L47*35%,0) -> 2.6312396e+08 | M49: =IF(M47>0,M47*35%,0) -> 2.5683082e+08 | ... Q49: =IF(Q47>0,Q47*35%,0) -> 3.3860042e+08 | S49: =SUM(F49:Q49) -> 3.0351529e+09
S50: =SUM(F50:Q50) -> 0
A51: Utilidad Neta | F51: =F47-F49 -> -55625750 | G51: =G47-G49 -> 4.0087311e+08 | H51: =H47-H49 -> 5.0985938e+08 | I51: =I47-I49 -> 4.1353497e+08 | J51: =J47-J49 -> 5.2764733e+08 | K51: =K47-K49 -> 4.5609209e+08 | L51: =L47-L49 -> 4.8865879e+08 | M51: =M47-M49 -> 4.7697152e+08 | ... Q51: =Q47-Q49 -> 6.2882935e+08 | S51: =SUM(F51:Q51) -> 5.5810868e+09
S52: =SUM(F52:Q52) -> 0
AB56: Objetivo de Ingresos | AC56: 1
F59: =F19 -> 2026-01 | G59: =G19 -> 2026-02 | H59: =H19 -> 2026-03 | I59: =I19 -> 2026-04 | J59: =J19 -> 2026-05 | K59: =K19 -> 2026-06 | L59: =L19 -> 2026-07 | M59: =M19 -> 2026-08 | ... Q59: =Q19 -> 2026-12 | S59: =S19 -> Total 2026 | AC59: Total 2026
A60: Moneda USD | S60: =SUM(F60:Q60) -> 0 | AB60: Moneda USD
S61: =SUM(F61:Q61) -> 0 | AB61: =A62 -> Ingresos operacionales (Total) | AC61: =IFERROR(S62,"") -> 4555726 | AE61: =AC61/$AC$61 -> 1 | AH61: =AB61 -> Ingresos operacionales (Total) | AI61: =AC61 -> 4555726
A62: Ingresos operacionales (Total) | F62: =G14 -> 186232.4 | G62: =H14 -> 354320.8 | H62: =I14 -> 396238.6 | I62: =J14 -> 359190.75 | J62: =K14 -> 403080.12 | K62: =L14 -> 375558.87 | L62: =M14 -> 388084.53 | M62: =N14 -> 383589.42 | ... Q62: =R14 -> 441996.28 | S62: =SUM(F62:Q62) -> 4555726 | AE62: =AC62/$AC$61 -> 0 | AH62: =AB64 -> Costo de Ventas | AI62: =-AC64 -> -1336347.4
AE63: =AC63/$AC$61 -> 0 | AH63: =AB71 -> Operacionales de Administración | AI63: =-AC71 -> -402541.39
AB64: =A65 -> Costo de Ventas | AC64: =IFERROR(S65,"") -> 1336347.4 | AE64: =AC64/$AC$61 -> 0.29333357 | AH64: =AB75 -> Operacionales de Ventas | AI64: =-AC75 -> -648123.68
A65: =IFERROR(A25,"") -> Costo de Ventas | F65: =F25/$H$6 -> 111362.28 | G65: =G25/$H$6 -> 111362.28 | H65: =H25/$H$6 -> 111362.28 | I65: =I25/$H$6 -> 111362.28 | J65: =J25/$H$6 -> 111362.28 | K65: =K25/$H$6 -> 111362.28 | L65: =L25/$H$6 -> 111362.28 | M65: =M25/$H$6 -> 111362.28 | ... Q65: =Q25/$H$6 -> 111362.28 | S65: =SUM(F65:Q65) -> 1336347.4 | AB65: =A66 -> Mano de Obra Directa | AC65: =IFERROR(S66,"") -> 813665.55 | AE65: =AC65/$AC$61 -> 0.17860283 | AH65: =AB83 -> Ingresos no Operacionales | AI65: =AC83 -> 9530.7073
A66: =IFERROR(A26,"") -> Mano de Obra Directa | F66: =F26/$H$6 -> 67805.463 | G66: =G26/$H$6 -> 67805.463 | H66: =H26/$H$6 -> 67805.463 | I66: =I26/$H$6 -> 67805.463 | J66: =J26/$H$6 -> 67805.463 | K66: =K26/$H$6 -> 67805.463 | L66: =L26/$H$6 -> 67805.463 | M66: =M26/$H$6 -> 67805.463 | ... Q66: =Q26/$H$6 -> 67805.463 | S66: =SUM(F66:Q66) -> 813665.55 | AB66: =A67 -> Operacionales de Desarrollo | AC66: =IFERROR(S67,"") -> 522681.82 | AE66: =AC66/$AC$61 -> 0.11473074 | AH66: =AB84 -> Gastos no Operacionales | AI66: =-AC84 -> -24184.351
A67: =IFERROR(A27,"") -> Operacionales de Desarrollo | F67: =F27/$H$6 -> 43556.818 | G67: =G27/$H$6 -> 43556.818 | H67: =H27/$H$6 -> 43556.818 | I67: =I27/$H$6 -> 43556.818 | J67: =J27/$H$6 -> 43556.818 | K67: =K27/$H$6 -> 43556.818 | L67: =L27/$H$6 -> 43556.818 | M67: =M27/$H$6 -> 43556.818 | ... Q67: =Q27/$H$6 -> 43556.818 | S67: =SUM(F67:Q67) -> 522681.82 | AE67: =AC67/$AC$61 -> 0 | AH67: =AB88 -> Impuestos | AI67: =-AC88 -> -758788.23
AB68: =A70 -> Utilidad Bruta | AC68: =IFERROR(S70,"") -> 3219378.6 | AE68: =AC68/$AC$61 -> 0.70666643 | AH68: =AB90 -> Utilidad Neta | AI68: =AC90 -> 1395271.7
S69: =SUM(F69:Q69) -> 0 | AB69: =A71 -> Margen Bruto | AC69: =IFERROR(S71,"") -> 0.70666643 | AE69: =AC69/$AC$61 -> 1.551161e-07
A70: =IFERROR(A29,"") -> Utilidad Bruta | F70: =F29/$H$6 -> 74870.122 | G70: =G29/$H$6 -> 242958.52 | H70: =H29/$H$6 -> 284876.32 | I70: =I29/$H$6 -> 247828.47 | J70: =J29/$H$6 -> 291717.84 | K70: =K29/$H$6 -> 264196.59 | L70: =L29/$H$6 -> 276722.25 | M70: =M29/$H$6 -> 272227.14 | ... Q70: =Q29/$H$6 -> 330634 | S70: =SUM(F70:Q70) -> 3219378.6 | AE70: =AC70/$AC$61 -> 0
A71: Margen Bruto | F71: =F70/F$62 -> 0.40202522 | G71: =G70/G$62 -> 0.68570211 | H71: =H70/H$62 -> 0.71895146 | I71: =I70/I$62 -> 0.6899634 | J71: =J70/J$62 -> 0.72372172 | K71: =K70/K$62 -> 0.70347584 | L71: =L70/L$62 -> 0.71304633 | M71: =M70/M$62 -> 0.70968365 | ... Q71: =Q70/Q$62 -> 0.74804702 | S71: =S70/S$62 -> 0.70666643 | AB71: =A73 -> Operacionales de Administración | AC71: =IFERROR(S73,"") -> 402541.39 | AE71: =AC71/$AC$61 -> 0.088359438
AB72: =A74 -> Gastos de Personal | AC72: =IFERROR(S74,"") -> 185484.96 | AE72: =AC72/$AC$61 -> 0.040714687
A73: =IFERROR(A32,"") -> Operacionales de Administración | F73: =F32/$H$6 -> 33545.116 | G73: =G32/$H$6 -> 33545.116 | H73: =H32/$H$6 -> 33545.116 | I73: =I32/$H$6 -> 33545.116 | J73: =J32/$H$6 -> 33545.116 | K73: =K32/$H$6 -> 33545.116 | L73: =L32/$H$6 -> 33545.116 | M73: =M32/$H$6 -> 33545.116 | ... Q73: =Q32/$H$6 -> 33545.116 | S73: =SUM(F73:Q73) -> 402541.39 | AB73: =A75 -> Otros Gastos de Administración Operacionales | AC73: =IFERROR(S75,"") -> 217056.43 | AE73: =AC73/$AC$61 -> 0.047644751
A74: =IFERROR(A33,"") -> Gastos de Personal | F74: =F33/$H$6 -> 15457.08 | G74: =G33/$H$6 -> 15457.08 | H74: =H33/$H$6 -> 15457.08 | I74: =I33/$H$6 -> 15457.08 | J74: =J33/$H$6 -> 15457.08 | K74: =K33/$H$6 -> 15457.08 | L74: =L33/$H$6 -> 15457.08 | M74: =M33/$H$6 -> 15457.08 | ... Q74: =Q33/$H$6 -> 15457.08 | S74: =SUM(F74:Q74) -> 185484.96 | AE74: =AC74/$AC$61 -> 0
A75: =IFERROR(A34,"") -> Otros Gastos de Administración Operacionales | F75: =F34/$H$6 -> 18088.036 | G75: =G34/$H$6 -> 18088.036 | H75: =H34/$H$6 -> 18088.036 | I75: =I34/$H$6 -> 18088.036 | J75: =J34/$H$6 -> 18088.036 | K75: =K34/$H$6 -> 18088.036 | L75: =L34/$H$6 -> 18088.036 | M75: =M34/$H$6 -> 18088.036 | ... Q75: =Q34/$H$6 -> 18088.036 | S75: =SUM(F75:Q75) -> 217056.43 | AB75: =A77 -> Operacionales de Ventas | AC75: =IFERROR(S77,"") -> 648123.68 | AE75: =AC75/$AC$61 -> 0.14226573
AB76: =A78 -> Gastos de Personal | AC76: =IFERROR(S78,"") -> 288942.35 | AE76: =AC76/$AC$61 -> 0.063423996
A77: =IFERROR(A37,"") -> Operacionales de Ventas | F77: =F37/$H$6 -> 54010.306 | G77: =G37/$H$6 -> 54010.306 | H77: =H37/$H$6 -> 54010.306 | I77: =I37/$H$6 -> 54010.306 | J77: =J37/$H$6 -> 54010.306 | K77: =K37/$H$6 -> 54010.306 | L77: =L37/$H$6 -> 54010.306 | M77: =M37/$H$6 -> 54010.306 | ... Q77: =Q37/$H$6 -> 54010.306 | S77: =SUM(F77:Q77) -> 648123.68 | AB77: =A79 -> Honorarios | AC77: =IFERROR(S79,"") -> 122150.03 | AE77: =AC77/$AC$61 -> 0.026812417
A78: =IFERROR(A38,"") -> Gastos de Personal | F78: =F38/$H$6 -> 24078.529 | G78: =G38/$H$6 -> 24078.529 | H78: =H38/$H$6 -> 24078.529 | I78: =I38/$H$6 -> 24078.529 | J78: =J38/$H$6 -> 24078.529 | K78: =K38/$H$6 -> 24078.529 | L78: =L38/$H$6 -> 24078.529 | M78: =M38/$H$6 -> 24078.529 | ... Q78: =Q38/$H$6 -> 24078.529 | S78: =SUM(F78:Q78) -> 288942.35 | AB78: =A80 -> Otros Gastos de Ventas Operacionales | AC78: =IFERROR(S80,"") -> 237031.3 | AE78: =AC78/$AC$61 -> 0.052029315
A79: =IFERROR(A39,"") -> Honorarios | F79: =F39/$H$6 -> 10179.169 | G79: =G39/$H$6 -> 10179.169 | H79: =H39/$H$6 -> 10179.169 | I79: =I39/$H$6 -> 10179.169 | J79: =J39/$H$6 -> 10179.169 | K79: =K39/$H$6 -> 10179.169 | L79: =L39/$H$6 -> 10179.169 | M79: =M39/$H$6 -> 10179.169 | ... Q79: =Q39/$H$6 -> 10179.169 | S79: =SUM(F79:Q79) -> 122150.03 | AE79: =AC79/$AC$61 -> 0
A80: =IFERROR(A40,"") -> Otros Gastos de Ventas Operacionales | F80: =F40/$H$6 -> 19752.609 | G80: =G40/$H$6 -> 19752.609 | H80: =H40/$H$6 -> 19752.609 | I80: =I40/$H$6 -> 19752.609 | J80: =J40/$H$6 -> 19752.609 | K80: =K40/$H$6 -> 19752.609 | L80: =L40/$H$6 -> 19752.609 | M80: =M40/$H$6 -> 19752.609 | ... Q80: =Q40/$H$6 -> 19752.609 | S80: =SUM(F80:Q80) -> 237031.3 | AB80: =A82 -> Utilidad Operacional / EBITDA | AC80: =IFERROR(S82,"") -> 2168713.6 | AE80: =AC80/$AC$61 -> 0.47604126
AB81: =A83 -> Margen Ebitda | AC81: =IFERROR(S83,"") -> 0.47604126 | AE81: =AC81/$AC$61 -> 1.0449295e-07
A82: Utilidad Operacional / EBITDA | F82: =F42/$H$6 -> -12685.301 | G82: =G42/$H$6 -> 155403.1 | H82: =H42/$H$6 -> 197320.9 | I82: =I42/$H$6 -> 160273.05 | J82: =J42/$H$6 -> 204162.42 | K82: =K42/$H$6 -> 176641.17 | L82: =L42/$H$6 -> 189166.82 | M82: =M42/$H$6 -> 184671.72 | ... Q82: =Q42/$H$6 -> 243078.58 | S82: =SUM(F82:Q82) -> 2168713.6 | AE82: =AC82/$AC$61 -> 0
A83: Margen Ebitda | F83: =F82/F$62 -> -0.068115432 | G83: =G82/G$62 -> 0.43859435 | H83: =H82/H$62 -> 0.49798504 | I83: =I82/I$62 -> 0.44620594 | J83: =J82/J$62 -> 0.50650579 | K83: =K82/K$62 -> 0.47034216 | L83: =L82/L$62 -> 0.48743717 | M83: =M82/M$62 -> 0.48143069 | ... Q83: =Q82/Q$62 -> 0.54995616 | S83: =S82/S$62 -> 0.47604126 | AB83: =A85 -> Ingresos no Operacionales | AC83: =IFERROR(S85,"") -> 9530.7073 | AE83: =AC83/$AC$61 -> 0.0020920282
AB84: =A86 -> Gastos no Operacionales | AC84: =IFERROR(S86,"") -> 24184.351 | AE84: =AC84/$AC$61 -> 0.0053085614
A85: =IFERROR(A44,"") -> Ingresos no Operacionales | F85: =F44/$H$6 -> 794.22561 | G85: =G44/$H$6 -> 794.22561 | H85: =H44/$H$6 -> 794.22561 | I85: =I44/$H$6 -> 794.22561 | J85: =J44/$H$6 -> 794.22561 | K85: =K44/$H$6 -> 794.22561 | L85: =L44/$H$6 -> 794.22561 | M85: =M44/$H$6 -> 794.22561 | ... Q85: =Q44/$H$6 -> 794.22561 | S85: =SUM(F85:Q85) -> 9530.7073 | AE85: =AC85/$AC$61 -> 0
A86: =IFERROR(A45,"") -> Gastos no Operacionales | F86: =F45/$H$6 -> 2015.3626 | G86: =G45/$H$6 -> 2015.3626 | H86: =H45/$H$6 -> 2015.3626 | I86: =I45/$H$6 -> 2015.3626 | J86: =J45/$H$6 -> 2015.3626 | K86: =K45/$H$6 -> 2015.3626 | L86: =L45/$H$6 -> 2015.3626 | M86: =M45/$H$6 -> 2015.3626 | ... Q86: =Q45/$H$6 -> 2015.3626 | S86: =SUM(F86:Q86) -> 24184.351 | AB86: =A88 -> Utilidad Antes de Impuestos / EBT | AC86: =IFERROR(S88,"") -> 2154059.9 | AE86: =AC86/$AC$61 -> 0.47282473
AE87: =AC87/$AC$61 -> 0
A88: Utilidad Antes de Impuestos / EBT | F88: =F47/$H$6 -> -13906.438 | G88: =G47/$H$6 -> 154181.96 | H88: =H47/$H$6 -> 196099.76 | I88: =I47/$H$6 -> 159051.91 | J88: =J47/$H$6 -> 202941.28 | K88: =K47/$H$6 -> 175420.03 | L88: =L47/$H$6 -> 187945.69 | M88: =M47/$H$6 -> 183450.58 | ... Q88: =Q47/$H$6 -> 241857.44 | S88: =SUM(F88:Q88) -> 2154059.9 | AB88: =A90 -> Impuestos | AC88: =IFERROR(S90,"") -> 758788.23 | AE88: =AC88/$AC$61 -> 0.16655704
AE89: =AC89/$AC$61 -> 0
A90: =IFERROR(A49,"") -> Impuestos | F90: =F49/$H$6 -> 0 | G90: =G49/$H$6 -> 53963.688 | H90: =H49/$H$6 -> 68634.916 | I90: =I49/$H$6 -> 55668.169 | J90: =J49/$H$6 -> 71029.448 | K90: =K49/$H$6 -> 61397.012 | L90: =L49/$H$6 -> 65780.991 | M90: =M49/$H$6 -> 64207.705 | ... Q90: =Q49/$H$6 -> 84650.105 | S90: =SUM(F90:Q90) -> 758788.23 | AB90: =A92 -> Utilidad Neta | AC90: =IFERROR(S92,"") -> 1395271.7 | AE90: =AC90/$AC$61 -> 0.30626769
AB91: =A93 -> Margen Neto | AC91: =IFERROR(S93,"") -> 0.30626769 | AE91: =AC91/$AC$61 -> 6.7226978e-08
A92: =IFERROR(A51,"") -> Utilidad Neta | F92: =F51/$H$6 -> -13906.438 | G92: =G51/$H$6 -> 100218.28 | H92: =H51/$H$6 -> 127464.84 | I92: =I51/$H$6 -> 103383.74 | J92: =J51/$H$6 -> 131911.83 | K92: =K51/$H$6 -> 114023.02 | L92: =L51/$H$6 -> 122164.7 | M92: =M51/$H$6 -> 119242.88 | ... Q92: =Q51/$H$6 -> 157207.34 | S92: =SUM(F92:Q92) -> 1395271.7
A93: Margen Neto | F93: =F92/F$62 -> -0.074672492 | G93: =G92/G$62 -> 0.28284615 | H93: =H92/H$62 -> 0.32168709 | I93: =I92/I$62 -> 0.28782407 | J93: =J92/J$62 -> 0.32725958 | K93: =K92/K$62 -> 0.30360892 | L93: =L92/L$62 -> 0.31478889 | M93: =M92/M$62 -> 0.31086071 | ... Q93: =Q92/Q$62 -> 0.3556757 | S93: =S92/S$62 -> 0.30626769
A289: SUPUESTOS DE ESCENARIOS
A291: Línea de Ingreso | B291: Base (USD) | C291: % Optimista | D291: Optimista (USD) | E291: % Pesimista | F291: Pesimista (USD) | I291: RIESGOS CLAVE
A292: MRR | B292: 176435.77 | C292: 0.1 | D292: =B292*(1+C292) -> 194079.35 | E292: -0.1 | F292: =B292*(1+E292) -> 158792.19 | I292: 1. TRM fija en $4,000 — sin cobertura cambiaria
A293: Upsell / Cross-sell | B293: 36800.024 | C293: 0.25 | D293: =B293*(1+C293) -> 46000.03 | E293: -0.2 | F293: =B293*(1+E293) -> 29440.019 | I293: 2. Costos presupuestados 100% fijos (inflación 5.1%)
A294: New Business LATAM | B294: 110400.07 | C294: 0.25 | D294: =B294*(1+C294) -> 138000.09 | E294: -0.25 | F294: =B294*(1+E294) -> 82800.054 | I294: 3. New Biz Gob/Enterprise ($1M) sin pipeline detallado
A295: New Business Gob/Enterprise | B295: 102187.77 | C295: 0.3 | D295: =B295*(1+C295) -> 132844.1 | E295: -0.3 | F295: =B295*(1+E295) -> 71531.441 | I295: 4. No hay inversión incremental para soportar crecimiento 2.5x
A296: One-off (Implementation) | B296: 10512.217 | C296: 0.15 | D296: =B296*(1+C296) -> 12089.049 | E296: -0.15 | F296: =B296*(1+E296) -> 8935.3844 | I296: 5. Churn asumido bajo (0.5%/mes) — sensible a calidad de servicio
A297: One-off (Interoperability) | B297: 5660.4245 | C297: 0.15 | D297: =B297*(1+C297) -> 6509.4882 | E297: -0.15 | F297: =B297*(1+E297) -> 4811.3608 | I297: 6. Estacionalidad basada en 2025 — puede variar
A298: TOTAL INGRESOS | B298: =SUM(B292:B297) -> 441996.28 | C298: =D298/B298-1 -> 0.1980239 | D298: =SUM(D292:D297) -> 529522.11 | E298: =F298/B298-1 -> -0.19386097 | F298: =SUM(F292:F297) -> 356310.45
A300: Nota: Los % de variación (en azul) son editables. Los costos varían proporcionalmente al ingreso en cada escenario.
A302: DATA BRIDGE — Referencias locales (PYG & SalesPlan)
A304: Línea | B304: 2026-01 | C304: 2026-02 | D304: 2026-03 | E304: 2026-04 | F304: 2026-05 | G304: 2026-06 | H304: 2026-07 | I304: 2026-08 | J304: 2026-09 | K304: 2026-10 | L304: 2026-11 | M304: 2026-12 | N304: Total 2026
A305: MRR | B305: 176186.49 | C305: 175305.55 | D305: 175643.79 | E305: 175731.61 | F305: 175819.48 | G305: 175907.39 | H305: 175995.34 | I305: 176083.34 | J305: 176171.38 | K305: 176259.47 | L305: 176347.6 | M305: 176435.77 | N305: =SUM(B305:M305) -> 2111887.2
A306: Upsell / Cross-sell | B306: 0 | C306: 24807.022 | D306: 30568.906 | E306: 25422.834 | F306: 31492.623 | G306: 27666.687 | H306: 29390.24 | I306: 28755.137 | J306: 34379.333 | K306: 33769.952 | L306: 34209.872 | M306: 36800.024 | N306: =SUM(B306:M306) -> 337262.63
A307: New Business LATAM | B307: 0 | C307: 74421.067 | D307: 91706.718 | E307: 76268.501 | F307: 94477.869 | G307: 83000.061 | H307: 88170.72 | I307: 86265.412 | J307: 103138 | K307: 101309.86 | L307: 102629.61 | M307: 110400.07 | N307: =SUM(B307:M307) -> 1011787.9
A308: New Biz Gob/Enterprise | B308: 0 | C308: 68885.127 | D308: 84884.955 | E308: 70595.137 | F308: 87449.969 | G308: 76825.958 | H308: 81611.989 | I308: 79848.41 | J308: 95465.901 | K308: 93773.748 | L308: 94995.334 | M308: 102187.77 | N308: =SUM(B308:M308) -> 936524.3
A309: One-off (Implementation) | B309: 6529.8451 | C309: 7086.3215 | D309: 8732.2489 | E309: 7262.2328 | F309: 8996.116 | G309: 7903.2072 | H309: 8395.5537 | I309: 8214.1316 | J309: 9820.7275 | K309: 9646.6531 | L309: 9772.3195 | M309: 10512.217 | N309: =SUM(B309:M309) -> 102871.57
A310: One-off (Interoperability) | B310: 3516.0704 | C310: 3815.7116 | D310: 4701.9802 | E310: 3910.4331 | F310: 4844.0624 | G310: 4255.5731 | H310: 4520.6828 | I310: 4422.9939 | J310: 5288.084 | K310: 5194.3516 | L310: 5262.0182 | M310: 5660.4245 | N310: =SUM(B310:M310) -> 55392.386
A311: Ingresos Base (Total) | B311: =SUM(B305:B310) -> 186232.4 | C311: =SUM(C305:C310) -> 354320.8 | D311: =SUM(D305:D310) -> 396238.6 | E311: =SUM(E305:E310) -> 359190.75 | F311: =SUM(F305:F310) -> 403080.12 | G311: =SUM(G305:G310) -> 375558.87 | H311: =SUM(H305:H310) -> 388084.53 | I311: =SUM(I305:I310) -> 383589.42 | ... M311: =SUM(M305:M310) -> 441996.28 | N311: =SUM(B311:M311) -> 4555726
A313: Costo de Ventas | B313: ='Ppto Ene. 2026'!F65 -> 111362.28 | C313: ='Ppto Ene. 2026'!G65 -> 111362.28 | D313: ='Ppto Ene. 2026'!H65 -> 111362.28 | E313: ='Ppto Ene. 2026'!I65 -> 111362.28 | F313: ='Ppto Ene. 2026'!J65 -> 111362.28 | G313: ='Ppto Ene. 2026'!K65 -> 111362.28 | H313: ='Ppto Ene. 2026'!L65 -> 111362.28 | I313: ='Ppto Ene. 2026'!M65 -> 111362.28 | ... M313: ='Ppto Ene. 2026'!Q65 -> 111362.28 | N313: =SUM(B313:M313) -> 1336347.4
A314: Op. Administración | B314: ='Ppto Ene. 2026'!F73 -> 33545.116 | C314: ='Ppto Ene. 2026'!G73 -> 33545.116 | D314: ='Ppto Ene. 2026'!H73 -> 33545.116 | E314: ='Ppto Ene. 2026'!I73 -> 33545.116 | F314: ='Ppto Ene. 2026'!J73 -> 33545.116 | G314: ='Ppto Ene. 2026'!K73 -> 33545.116 | H314: ='Ppto Ene. 2026'!L73 -> 33545.116 | I314: ='Ppto Ene. 2026'!M73 -> 33545.116 | ... M314: ='Ppto Ene. 2026'!Q73 -> 33545.116 | N314: =SUM(B314:M314) -> 402541.39
A315: Op. Ventas | B315: ='Ppto Ene. 2026'!F77 -> 54010.306 | C315: ='Ppto Ene. 2026'!G77 -> 54010.306 | D315: ='Ppto Ene. 2026'!H77 -> 54010.306 | E315: ='Ppto Ene. 2026'!I77 -> 54010.306 | F315: ='Ppto Ene. 2026'!J77 -> 54010.306 | G315: ='Ppto Ene. 2026'!K77 -> 54010.306 | H315: ='Ppto Ene. 2026'!L77 -> 54010.306 | I315: ='Ppto Ene. 2026'!M77 -> 54010.306 | ... M315: ='Ppto Ene. 2026'!Q77 -> 54010.306 | N315: =SUM(B315:M315) -> 648123.68
A316: Ing. no Operacionales | B316: ='Ppto Ene. 2026'!F85 -> 794.22561 | C316: ='Ppto Ene. 2026'!G85 -> 794.22561 | D316: ='Ppto Ene. 2026'!H85 -> 794.22561 | E316: ='Ppto Ene. 2026'!I85 -> 794.22561 | F316: ='Ppto Ene. 2026'!J85 -> 794.22561 | G316: ='Ppto Ene. 2026'!K85 -> 794.22561 | H316: ='Ppto Ene. 2026'!L85 -> 794.22561 | I316: ='Ppto Ene. 2026'!M85 -> 794.22561 | ... M316: ='Ppto Ene. 2026'!Q85 -> 794.22561 | N316: =SUM(B316:M316) -> 9530.7073
A317: Gasto no Operacionales | B317: ='Ppto Ene. 2026'!F86 -> 2015.3626 | C317: ='Ppto Ene. 2026'!G86 -> 2015.3626 | D317: ='Ppto Ene. 2026'!H86 -> 2015.3626 | E317: ='Ppto Ene. 2026'!I86 -> 2015.3626 | F317: ='Ppto Ene. 2026'!J86 -> 2015.3626 | G317: ='Ppto Ene. 2026'!K86 -> 2015.3626 | H317: ='Ppto Ene. 2026'!L86 -> 2015.3626 | I317: ='Ppto Ene. 2026'!M86 -> 2015.3626 | ... M317: ='Ppto Ene. 2026'!Q86 -> 2015.3626 | N317: =SUM(B317:M317) -> 24184.351
A318: Impuestos Base | B318: ='Ppto Ene. 2026'!F90 -> 0 | C318: ='Ppto Ene. 2026'!G90 -> 53963.688 | D318: ='Ppto Ene. 2026'!H90 -> 68634.916 | E318: ='Ppto Ene. 2026'!I90 -> 55668.169 | F318: ='Ppto Ene. 2026'!J90 -> 71029.448 | G318: ='Ppto Ene. 2026'!K90 -> 61397.012 | H318: ='Ppto Ene. 2026'!L90 -> 65780.991 | I318: ='Ppto Ene. 2026'!M90 -> 64207.705 | ... M318: ='Ppto Ene. 2026'!Q90 -> 84650.105 | N318: =SUM(B318:M318) -> 758788.23

Sheet Revenue
B3: Plan Comercial 2026 (USD) + Puente de MRR
B4: Legacy drivers (not used after target alignment)
B5: Stream | C5: Annual Target (USD) | D5: 2026-01 | E5: 2026-02 | F5: 2026-03 | G5: 2026-04 | H5: 2026-05 | I5: 2026-06 | J5: 2026-07 | K5: 2026-08 | L5: 2026-09 | M5: 2026-10 | N5: 2026-11 | O5: 2026-12 | P5: Total 2026
B6: MRR | C6: =Inputs!$H$5*(Inputs!C58/SUM(Inputs!$C$58:$C$61)) -> 1257936.3 | D6: =$C6*Inputs!D$31 -> 79848.386 | E6: =$C6*Inputs!E$31 -> 86653.102 | F6: =$C6*Inputs!F$31 -> 106779.87 | G6: =$C6*Inputs!G$31 -> 88804.185 | H6: =$C6*Inputs!H$31 -> 110006.49 | I6: =$C6*Inputs!I$31 -> 96642.16 | J6: =$C6*Inputs!J$31 -> 102662.68 | K6: =$C6*Inputs!K$31 -> 100444.21 | L6: =$C6*Inputs!N$31 -> 120090.02 | M6: =$C6*Inputs!O$31 -> 117961.4 | N6: =$C6*Inputs!P$31 -> 119498.08 | O6: =$C6*Inputs!Q$31 -> 128545.71 | P6: =SUM(D6:O6) -> 1257936.3
B7: Upsell / Cross-sell (expansion) | C7: =Inputs!$H$5*(Inputs!C59/SUM(Inputs!$C$58:$C$61)) -> 262373.56 | D7: =$C7*Inputs!D$31 -> 16654.345 | E7: =$C7*Inputs!E$31 -> 18073.636 | F7: =$C7*Inputs!F$31 -> 22271.568 | G7: =$C7*Inputs!G$31 -> 18522.297 | H7: =$C7*Inputs!H$31 -> 22944.56 | I7: =$C7*Inputs!I$31 -> 20157.1 | J7: =$C7*Inputs!J$31 -> 21412.828 | K7: =$C7*Inputs!K$31 -> 20950.111 | L7: =$C7*Inputs!N$31 -> 25047.728 | M7: =$C7*Inputs!O$31 -> 24603.752 | N7: =$C7*Inputs!P$31 -> 24924.264 | O7: =$C7*Inputs!Q$31 -> 26811.369 | P7: =SUM(D7:O7) -> 262373.56
B8: New Business LATAM | C8: =Inputs!$H$5*(Inputs!C60/SUM(Inputs!$C$58:$C$61)) -> 787120.74 | D8: =$C8*Inputs!D$31 -> 49963.04 | E8: =$C8*Inputs!E$31 -> 54220.913 | F8: =$C8*Inputs!F$31 -> 66814.709 | G8: =$C8*Inputs!G$31 -> 55566.897 | H8: =$C8*Inputs!H$31 -> 68833.685 | I8: =$C8*Inputs!I$31 -> 60471.305 | J8: =$C8*Inputs!J$31 -> 64238.489 | K8: =$C8*Inputs!K$31 -> 62850.34 | L8: =$C8*Inputs!N$31 -> 75143.191 | M8: =$C8*Inputs!O$31 -> 73811.263 | N8: =$C8*Inputs!P$31 -> 74772.798 | O8: =$C8*Inputs!Q$31 -> 80434.115 | P8: =SUM(D8:O8) -> 787120.74
B9: New Business Gobierno y Enterprise | C9: =Inputs!$H$5*(Inputs!C61/SUM(Inputs!$C$58:$C$61)) -> 728569.41 | D9: =$C9*Inputs!D$31 -> 46246.453 | E9: =$C9*Inputs!E$31 -> 50187.596 | F9: =$C9*Inputs!F$31 -> 61844.581 | G9: =$C9*Inputs!G$31 -> 51433.457 | H9: =$C9*Inputs!H$31 -> 63713.372 | I9: =$C9*Inputs!I$31 -> 55973.042 | J9: =$C9*Inputs!J$31 -> 59459.998 | K9: =$C9*Inputs!K$31 -> 58175.109 | L9: =$C9*Inputs!N$31 -> 69553.535 | M9: =$C9*Inputs!O$31 -> 68320.684 | N9: =$C9*Inputs!P$31 -> 69210.694 | O9: =$C9*Inputs!Q$31 -> 74450.885 | P9: =SUM(D9:O9) -> 728569.41
B10: One-off (Implementation) | C10: =Inputs!$C$13*Inputs!$C$19 -> 171600 | D10: =$C10*Inputs!D$31 -> 10892.43 | E10: =$C10*Inputs!E$31 -> 11820.688 | F10: =$C10*Inputs!F$31 -> 14566.258 | G10: =$C10*Inputs!G$31 -> 12114.125 | H10: =$C10*Inputs!H$31 -> 15006.415 | I10: =$C10*Inputs!I$31 -> 13183.334 | J10: =$C10*Inputs!J$31 -> 14004.617 | K10: =$C10*Inputs!K$31 -> 13701.987 | L10: =$C10*Inputs!N$31 -> 16381.949 | M10: =$C10*Inputs!O$31 -> 16091.575 | N10: =$C10*Inputs!P$31 -> 16301.199 | O10: =$C10*Inputs!Q$31 -> 17535.422 | P10: =SUM(D10:O10) -> 171600
B11: One-off (Interoperability) | C11: =Inputs!$C$13*Inputs!$C$20 -> 92400 | D11: =$C11*Inputs!D$31 -> 5865.1546 | E11: =$C11*Inputs!E$31 -> 6364.9858 | F11: =$C11*Inputs!F$31 -> 7843.3699 | G11: =$C11*Inputs!G$31 -> 6522.9906 | H11: =$C11*Inputs!H$31 -> 8080.3772 | I11: =$C11*Inputs!I$31 -> 7098.7185 | J11: =$C11*Inputs!J$31 -> 7540.9477 | K11: =$C11*Inputs!K$31 -> 7377.9931 | L11: =$C11*Inputs!N$31 -> 8821.0493 | M11: =$C11*Inputs!O$31 -> 8664.6943 | N11: =$C11*Inputs!P$31 -> 8777.5688 | O11: =$C11*Inputs!Q$31 -> 9442.1502 | P11: =SUM(D11:O11) -> 92400
B12: TOTAL | C12: =SUM(C6:C11) -> 3300000 | D12: =SUM(D6:D11) -> 209469.81 | E12: =SUM(E6:E11) -> 227320.92 | F12: =SUM(F6:F11) -> 280120.35 | G12: =SUM(G6:G11) -> 232963.95 | H12: =SUM(H6:H11) -> 288584.9 | I12: =SUM(I6:I11) -> 253525.66 | J12: =SUM(J6:J11) -> 269319.56 | ... P12: =SUM(P6:P11) -> 3300000
B15: MRR BRIDGE 2026 (USD)
B17: Metric | C17: 2026-01 | D17: 2026-02 | E17: 2026-03 | F17: 2026-04 | G17: 2026-05 | H17: 2026-06 | I17: 2026-07 | J17: 2026-08 | K17: 2026-09 | L17: 2026-10 | M17: 2026-11 | N17: 2026-12 | O17: Total/End
B18: Starting MRR (USD) | C18: =Inputs!$H$6 -> 190988.06 | D18: =C21 -> 382745.34 | E18: =D21 -> 589966.86 | F18: =E21 -> 844727.75 | G18: =F21 -> 1054831 | H18: =G21 -> 1315054.9 | I18: =H21 -> 1541723.2 | J18: =I21 -> 1781788.6 | K18: =J21 -> 2015299.4 | ... O18: =N21 -> 3139866.5
B19: New MRR (from SalesPlan) (USD) | C19: =D6+D7+D8+D9 -> 192712.22 | D19: =E6+E7+E8+E9 -> 209135.25 | E19: =F6+F7+F8+F9 -> 257710.72 | F19: =G6+G7+G8+G9 -> 214326.84 | G19: =H6+H7+H8+H9 -> 265498.11 | H19: =I6+I7+I8+I9 -> 233243.61 | I19: =J6+J7+J8+J9 -> 247774 | J19: =K6+K7+K8+K9 -> 242419.77 | ... N19: =O6+O7+O8+O9 -> 310242.08 | O19: =SUM(C19:N19) -> 3036000
B20: Churned MRR (USD) | C20: =-C18*Inputs!$C$9 -> -954.94031 | D20: =-D18*Inputs!$C$9 -> -1913.7267 | E20: =-E18*Inputs!$C$9 -> -2949.8343 | F20: =-F18*Inputs!$C$9 -> -4223.6388 | G20: =-G18*Inputs!$C$9 -> -5274.1548 | H20: =-H18*Inputs!$C$9 -> -6575.2745 | I20: =-I18*Inputs!$C$9 -> -7708.6162 | J20: =-J18*Inputs!$C$9 -> -8908.9431 | ... O20: =-O18*Inputs!$C$9 -> -15699.333
B21: Ending MRR (USD) | C21: =C18+C19+C20 -> 382745.34 | D21: =D18+D19+D20 -> 589966.86 | E21: =E18+E19+E20 -> 844727.75 | F21: =F18+F19+F20 -> 1054831 | G21: =G18+G19+G20 -> 1315054.9 | H21: =H18+H19+H20 -> 1541723.2 | I21: =I18+I19+I20 -> 1781788.6 | J21: =J18+J19+J20 -> 2015299.4 | ... N21: =N18+N19+N20 -> 3139866.5 | O21: =N21 -> 3139866.5
B23: MRR Promedio mes (USD) | C23: =AVERAGE(C18,C21) -> 286866.7 | D23: =AVERAGE(D18,D21) -> 486356.1 | E23: =AVERAGE(E18,E21) -> 717347.31 | F23: =AVERAGE(F18,F21) -> 949779.35 | G23: =AVERAGE(G18,G21) -> 1184942.9 | H23: =AVERAGE(H18,H21) -> 1428389.1 | I23: =AVERAGE(I18,I21) -> 1661755.9 | J23: =AVERAGE(J18,J21) -> 1898544 | ... O23: =AVERAGE(O18,O21) -> 3139866.5
B25: CHECKS & KPIs (sanity check rápido)
B27: Check | C27: Valor | D27: Status
B28: Target total (recurrente + one-off) (USD) | C28: =Inputs!$C$12 -> 3300000
B29: Total plan comercial (USD) | C29: =P12 -> 3300000
B30: Brecha (USD) | C30: =C29-C28 -> 0 | D30: =IF(ABS(C30)<1000,"OK","GAP") -> OK
B32: MRR final dic-2026 (USD) | C32: =N21 -> 3139866.5
B33: Target run-rate mensual (USD) | C33: =Inputs!$C$15 -> 3036000
B34: Brecha vs target (USD) | C34: =C32-C33 -> 103866.53 | D34: =IF(C34>0,"ABOVE","BELOW") -> ABOVE
B36: Devoluciones implícitas (% bruto, ref) | C36: =Inputs!C21 -> 0.112 | D36: Referencia — modelo usa revenue neto
B38: Ingresos brutos implicitos (USD) | C38: =P12/(1-Inputs!C21) -> 3716216.2
B39: Devoluciones implicitas (USD) | C39: =C38-P12 -> 416216.22
B40: Devoluciones implicitas (COP) | C40: =C39*Inputs!C6 -> 1.5358378e+09
B43: PROYECCIÓN DE INGRESOS 2026 — 3 ESCENARIOS (COP)
B44: Cifras en pesos colombianos (COP). TRM utilizada: INPUTS!B5. Distribución mensual: pesos de estacionalidad INPUTS!C30:N30.
B46: ESCENARIO CONSERVADOR (COP) | C46: Total Anual | D46: Ene | E46: Feb | F46: Mar | G46: Abr | H46: May | I46: Jun | J46: Jul | K46: Ago | L46: Sep | M46: Oct | N46: Nov | O46: Dic | P46: % del total
B47: Ingresos (COP) | C47: =Inputs!$N$7*Inputs!$C$6 -> 8856000000 | D47: =C47*Inputs!D$31 -> 5.6214079e+08 | E47: =C47*Inputs!E$31 -> 6.1004669e+08 | F47: =C47*Inputs!F$31 -> 7.5174116e+08 | G47: =C47*Inputs!G$31 -> 6.2519053e+08 | H47: =C47*Inputs!H$31 -> 7.7445693e+08 | I47: =C47*Inputs!I$31 -> 6.8037068e+08 | J47: =C47*Inputs!J$31 -> 7.2275577e+08 | K47: =C47*Inputs!K$31 -> 7.0713752e+08 | L47: =C47*Inputs!N$31 -> 8.4544602e+08 | M47: =C47*Inputs!O$31 -> 8.3046032e+08 | N47: =C47*Inputs!P$31 -> 8.4127868e+08 | O47: =C47*Inputs!Q$31 -> 9.0497491e+08 | P47: =SUM(D47:O47)/C47 -> 1
B48: Check suma meses | C48: =SUM(D47:O47) -> 8856000000 | D48: =IF(ABS(C47-C48)<1,"OK","ERROR") -> OK
B51: ESCENARIO BASE (COP) | C51: Total Anual | D51: Ene | E51: Feb | F51: Mar | G51: Abr | H51: May | I51: Jun | J51: Jul | K51: Ago | L51: Sep | M51: Oct | N51: Nov | O51: Dic | P51: % del total
B52: Ingresos (COP) | C52: =Inputs!$N$8*Inputs!$C$6 -> 12177000000 | D52: =C52*Inputs!D$31 -> 7.7294359e+08 | E52: =C52*Inputs!E$31 -> 8.388142e+08 | F52: =C52*Inputs!F$31 -> 1.0336441e+09 | G52: =C52*Inputs!G$31 -> 8.5963698e+08 | H52: =C52*Inputs!H$31 -> 1.0648783e+09 | I52: =C52*Inputs!I$31 -> 9.3550969e+08 | J52: =C52*Inputs!J$31 -> 9.9378918e+08 | K52: =C52*Inputs!K$31 -> 9.7231409e+08 | L52: =C52*Inputs!N$31 -> 1.1624883e+09 | M52: =C52*Inputs!O$31 -> 1.1418829e+09 | N52: =C52*Inputs!P$31 -> 1.1567582e+09 | O52: =C52*Inputs!Q$31 -> 1.2443405e+09 | P52: =SUM(D52:O52)/C52 -> 1
B53: Check suma meses | C53: =SUM(D52:O52) -> 12177000000 | D53: =IF(ABS(C52-C53)<1,"OK","ERROR") -> OK
B56: ESCENARIO OPTIMISTA (COP) | C56: Total Anual | D56: Ene | E56: Feb | F56: Mar | G56: Abr | H56: May | I56: Jun | J56: Jul | K56: Ago | L56: Sep | M56: Oct | N56: Nov | O56: Dic | P56: % del total
B57: Ingresos (COP) | C57: =Inputs!$N$9*Inputs!$C$6 -> 16605000000 | D57: =C57*Inputs!D$31 -> 1.054014e+09 | E57: =C57*Inputs!E$31 -> 1.1438375e+09 | F57: =C57*Inputs!F$31 -> 1.4095147e+09 | G57: =C57*Inputs!G$31 -> 1.1722322e+09 | H57: =C57*Inputs!H$31 -> 1.4521067e+09 | I57: =C57*Inputs!I$31 -> 1.275695e+09 | J57: =C57*Inputs!J$31 -> 1.3551671e+09 | K57: =C57*Inputs!K$31 -> 1.3258828e+09 | L57: =C57*Inputs!N$31 -> 1.5852113e+09 | M57: =C57*Inputs!O$31 -> 1.5571131e+09 | N57: =C57*Inputs!P$31 -> 1.5773975e+09 | O57: =C57*Inputs!Q$31 -> 1.696828e+09 | P57: =SUM(D57:O57)/C57 -> 1
B58: Check suma meses | C58: =SUM(D57:O57) -> 1.6605e+10 | D58: =IF(ABS(C57-C58)<1,"OK","ERROR") -> OK
B61: PROYECCIÓN DE INGRESOS 2026 — 3 ESCENARIOS (USD)
B62: Cifras en dólares (USD). Fuente: COP / TRM (INPUTS!B5). Misma distribución mensual por estacionalidad.
B64: ESCENARIO CONSERVADOR (USD) | C64: Total Anual | D64: Ene | E64: Feb | F64: Mar | G64: Abr | H64: May | I64: Jun | J64: Jul | K64: Ago | L64: Sep | M64: Oct | N64: Nov | O64: Dic
B65: Ingresos (USD) | C65: =Inputs!$N$7 -> 2400000 | D65: =D47/Inputs!$C$6 -> 152341.68 | E65: =E47/Inputs!$C$6 -> 165324.31 | F65: =F47/Inputs!$C$6 -> 203723.89 | G65: =G47/Inputs!$C$6 -> 169428.33 | H65: =H47/Inputs!$C$6 -> 209879.93 | I65: =I47/Inputs!$C$6 -> 184382.3 | J65: =J47/Inputs!$C$6 -> 195868.77 | K65: =K47/Inputs!$C$6 -> 191636.18 | ... O65: =O47/Inputs!$C$6 -> 245250.65
B69: ESCENARIO BASE (USD) | C69: Total Anual | D69: Ene | E69: Feb | F69: Mar | G69: Abr | H69: May | I69: Jun | J69: Jul | K69: Ago | L69: Sep | M69: Oct | N69: Nov | O69: Dic
B70: Ingresos (USD) | C70: =Inputs!$N$8 -> 3300000 | D70: =D52/Inputs!$C$6 -> 209469.81 | E70: =E52/Inputs!$C$6 -> 227320.92 | F70: =F52/Inputs!$C$6 -> 280120.35 | G70: =G52/Inputs!$C$6 -> 232963.95 | H70: =H52/Inputs!$C$6 -> 288584.9 | I70: =I52/Inputs!$C$6 -> 253525.66 | J70: =J52/Inputs!$C$6 -> 269319.56 | K70: =K52/Inputs!$C$6 -> 263499.75 | ... O70: =O52/Inputs!$C$6 -> 337219.65
B74: ESCENARIO OPTIMISTA (USD) | C74: Total Anual | D74: Ene | E74: Feb | F74: Mar | G74: Abr | H74: May | I74: Jun | J74: Jul | K74: Ago | L74: Sep | M74: Oct | N74: Nov | O74: Dic
B75: Ingresos (USD) | C75: =Inputs!$N$9 -> 4500000 | D75: =D57/Inputs!$C$6 -> 285640.65 | E75: =E57/Inputs!$C$6 -> 309983.07 | F75: =F57/Inputs!$C$6 -> 381982.3 | G75: =G57/Inputs!$C$6 -> 317678.12 | H75: =H57/Inputs!$C$6 -> 393524.86 | I75: =I57/Inputs!$C$6 -> 345716.81 | J75: =J57/Inputs!$C$6 -> 367253.95 | K75: =K57/Inputs!$C$6 -> 359317.84 | ... O75: =O57/Inputs!$C$6 -> 459844.98

Sheet Inputs
B2: INPUTS — CocoTech 2026 Budget Model (All Assumptions Consolidated) | Q2: temp
E4: Calculado | K4: Escenarios target 2026 (USD)
E5: ARR target (USD) = Total - One-off | H5: =C15 -> 3036000 | K5: Escenario | N5: Total target (USD) | O5: One-off (USD) | P5: Recurrente implícito (USD) | Q5: Run-rate mensual (USD)
B6: FX rate (COP per USD) | C6: 3690 | D6: TrmLargoPlazo | E6: Calculado / Referencia | H6: =(C7*(1+C11))/C6 -> 190988.06
B7: MRR Dec-2025 (COP) | C7: 670548000 | D7: MrrDic25 | E7: Referencia: Ene-2026 neto real (COP) | H7: 612247701 | K7: Conservador | N7: 2400000 | O7: =N7*$C$14 -> 192000 | P7: =N7-O7 -> 2208000 | Q7: =P7/12 -> 184000
B8: Customers Dec-2025 (count) | C8: 90 | D8: ClientesDic25 | K8: Base | N8: 3300000 | O8: =N8*$C$14 -> 264000 | P8: =N8-O8 -> 3036000 | Q8: =P8/12 -> 253000
B9: Monthly churn rate (revenue) | C9: 0.005 | D9: ChurnMensual | K9: Optimista | N9: 4500000 | O9: =N9*$C$14 -> 360000 | P9: =N9-O9 -> 4140000 | Q9: =P9/12 -> 345000
B10: Monthly churn rate (revenue) | C10: 0.005 | D10: ChurnMensual
B11: Annual price increase applied in Jan | C11: 0.051 | D11: InflacionAnual | K11: Escenario activo | N11: Base
B12: 2026 Total target (ARR + One-off) (USD) | C12: =INDEX($N$7:$N$9,MATCH($N$11,$K$7:$K$9,0)) -> 3300000 | D12: TargetTotal26
B13: Otros ingresos / One-off anual (USD) | C13: =C12*C14 -> 264000 | D13: OtrosIngresos | K13: Ingreso Meta 2026 por Hoja | N13: Total (USD) | O13: One-off (USD) | P13: Recurrente (USD) | Q13: Run-rate mensual
B14: Procentaje de Otros Ingresos | C14: 0.08 | D14: PctOtrosIng | K14: Conservador | N14: =N7 -> 2400000 | O14: =O7 -> 192000 | P14: =P7 -> 2208000 | Q14: =Q7 -> 184000
B15: Target recurrente anual (USD) | C15: =C12-C13 -> 3036000 | D15: TargetRecurrente | K15: Base | N15: =N8 -> 3300000 | O15: =O8 -> 264000 | P15: =P8 -> 3036000 | Q15: =Q8 -> 253000
B16: Check: Total = Recurrente + One-off | C16: =IF(ABS(C12-C15-C13)<1,"OK","ERROR") -> OK | D16: CheckTotal | K16: Optimista | N16: =N9 -> 4500000 | O16: =O9 -> 360000 | P16: =P9 -> 4140000 | Q16: =Q9 -> 345000
B17: Check: Target anual = Ingresos proyectados | C17: =IF(ABS(C12-SUM(D36:Q36))<100,"OK","ERROR") -> ERROR | D17: CheckIngresos
B18: NRR target | C18: 1.09 | D18: NrrTarget
B19: One-off split: % Implementation | C19: 0.65 | D19: PctImplement
B20: One-off split: % Interoperability | C20: =1-C19 -> 0.35 | D20: PctInterop
B21: Devoluciones (% de ingresos brutos) | C21: 0.112 | D21: PctDevoluciones
B22: FX & Tax Assumptions
B23: FX Low scenario (COP/USD) | C23: 3600 | D23: TrmBajo
B24: FX High scenario (COP/USD) | C24: 4400 | D24: TrmAlto
B25: Tax rate (statutory) | C25: 0.35 | D25: TasaImpuesto
B26: Caja Subsidiaria (USD) | C26: 325080 | D26: CajaSubsidiaria
B27: TRM Subsidiaria (COP/USD) | C27: 3690 | D27: TrmSubsidiaria
B28: Tasa de interés deuda LP (anual) | C28: 0.1 | D28: TasaDeudaLp
B29: Tasa de interés deuda CP (anual) | C29: 0.12 | D29: TasaDeudaCp | E29: Feb | F29: Mar | G29: Abr | H29: May | I29: Jun | J29: Jul | K29: Ago | N29: Sep | O29: Oct | P29: Nov | Q29: Dic | R29: TOTAL
B30: 2025 Monthly Revenue (COP) | C30: COP | D30: 483452000 | E30: 524652000 | F30: 646512000 | G30: 537676000 | H30: 666048000 | I30: 585132000 | J30: 621584000 | K30: 608152000 | N30: 727100000 | O30: 714212000 | P30: 723516000 | Q30: 778296000 | R30: 7616332000
B31: Weights (sum to 1.0) | D31: =D30/SUM($D$30:$Q$30) -> 0.063475699 | E31: =E30/SUM($D$30:$Q$30) -> 0.068885127 | F31: =F30/SUM($D$30:$Q$30) -> 0.084884955 | G31: =G30/SUM($D$30:$Q$30) -> 0.070595137 | H31: =H30/SUM($D$30:$Q$30) -> 0.087449969 | I31: =I30/SUM($D$30:$Q$30) -> 0.076825958 | J31: =J30/SUM($D$30:$Q$30) -> 0.081611989 | K31: =K30/SUM($D$30:$Q$30) -> 0.07984841 | N31: =N30/SUM($D$30:$Q$30) -> 0.095465901 | O31: =O30/SUM($D$30:$Q$30) -> 0.093773748 | P31: =P30/SUM($D$30:$Q$30) -> 0.094995334 | Q31: =Q30/SUM($D$30:$Q$30) -> 0.10218777 | R31: =SUM(D31:Q31) -> 1
B32: Index | C32: x | D32: 0.76170839 | E32: 0.82662153 | F32: 1.0186195 | G32: 0.84718762 | H32: 1.0493891 | I32: 0.92190076 | J32: 0.97934386 | K32: 0.95818092 | N32: 1.1459108 | O32: 1.1251173 | P32: 1.1397767 | Q32: 1.226505 | R32: 12
B33: Check: sum weights = 1 | C33: =SUM(D31:Q31) -> 1 | R33: 1
C34: 0 | R34: 0
B35: MRR PLAN (USD) — Base | D35: Ene | E35: Feb | F35: Mar | G35: Abr | H35: May | I35: Jun | J35: Jul | K35: Ago | N35: Sep | O35: Oct | P35: Nov | Q35: Dic | R35: TOTAL
B36: USD | C36: USD | D36: 176186.49 | E36: 175305.55 | F36: 175643.79 | G36: 230718.12 | H36: 264031.05 | I36: 275673.04 | J36: 274294.68 | K36: 285467.08 | N36: 284039.74 | O36: 282619.54 | P36: 281206.45 | Q36: 279800.41 | R36: 2984986
B37: Check: Total Plan USD | C37: Calc | D37: 2984986 | R37: 2984986
B38: COSTOS BASE 2025 (COP) — Ajustados por inflación en P&L
B39: Cuenta | C39: Base 2025 (COP) | D39: 2026 = Base×(1+Infl.) (COP)
B40: Costo de Ventas | C40: =C135 -> 3795959000 | D40: =C40*(1+$C$11) -> 3.9895529e+09 | E40: CostoVentasBase
C41: 3795959000 | D41: 3989552909
B42: Otros costos directos / desarrollo | C42: 0 | D42: 0
B44: Op. Administración | C44: =C139 -> 1545956000 | D44: =C44*(1+$C$11) -> 1624799756 | E44: GtosAdminBase
B45: Gastos de Personal | C45: 0 | D45: 0
C46: 1545956000 | D46: 1624799756
B48: Op. Ventas | C48: =C142 -> 2481297000 | D48: =C48*(1+$C$11) -> 2607843147 | E48: GtosVentasBase
B49: Gastos de Personal Ventas | C49: 0 | D49: 0
B50: Honorarios | C50: 0 | D50: 0
C51: 2481297000 | D51: 2607843147
B53: Ingresos no Operacionales | C53: =C146 -> 133664000 | D53: =C53*(1+$C$11) -> 140480864 | E53: IngNoOpBase
B54: Gastos no Operacionales | C54: =C150 -> 92043000 | D54: =C54*(1+$C$11) -> 96737193 | E54: GtosNoOpBase
B55: Gastos Operacionales / Proyectos | C55: =C141 -> 1290488000 | D55: =C55*(1+$C$11) -> 1356302888 | E55: GtosOpProyectosBase
B56: SUPUESTOS DE ESCENARIOS (% variación vs Base)
B57: Línea de Ingreso | C57: Base (USD/mes Dic) | D57: % Optimista | E57: % Pesimista
B58: MRR | C58: 176435.77 | D58: 0.1 | E58: -0.1
B59: Upsell / Cross-sell | C59: 36800.02 | D59: 0.25 | E59: -0.2
B60: New Business LATAM | C60: 110400.07 | D60: 0.25 | E60: -0.25
B61: New Business Gob/Enterprise | C61: 102187.77 | D61: 0.3 | E61: -0.3
B62: One-off (Implementation) | C62: 10512.22 | D62: 0.15 | E62: -0.15
B63: One-off (Interoperability) | C63: 5660.42 | D63: 0.15 | E63: -0.15
B64: TOTAL INGRESOS | C64: =SUM(C58:C63) -> 441996.27 | D64: ~19.8% | E64: ~-19.4%
B66: NUEVAS CONTRATACIONES — Pipeline Trimestral 2026 (mismo grupo cada 3 meses, acumulativo)
B67: Cargo | C67: Qty | D67: Costo Empresa/mes (COP) | E67: Línea P&L
B68: Implementador | C68: 1 | D68: 4531575 | E68: COGS → Mano de Obra Directa
B69: Aprendiz | C69: 2 | D69: 2748792 | E69: COGS → Mano de Obra Directa
B70: Customer Success | C70: 1 | D70: 6781385 | E70: Ventas → Gastos de Personal
B71: Mes contratación | C71: Abr-2026 | D71: Impacto desde | E71: Contrataciones se ejecutan a finales del trimestre
B73: CALENDARIO DE IMPACTO ACUMULATIVO | C73: Rondas acum. | D73: Δ MOD (COP) | E73: Δ Ventas (COP)
B74: Ene – Mar (sin incremento) | C74: 0 | D74: 0 | E74: 0
B75: Abr – Jun (Ronda 1: contratación Mar) | C75: 1 | D75: =C75*D80 -> 10029159 | E75: =C75*D81 -> 6781385 | F75: DeltaModQ2 / DeltaVtasQ2
B76: Jul – Sep (Ronda 2: contratación Jun) | C76: 2 | D76: =C76*D80 -> 20058318 | E76: =C76*D81 -> 13562770 | F76: DeltaModQ3 / DeltaVtasQ3
B77: Oct – Dic (Ronda 3: contratación Sep) | C77: 3 | D77: =C77*D80 -> 30087477 | E77: =C77*D81 -> 20344155 | F77: DeltaModQ4 / DeltaVtasQ4
B79: Resumen: mismo grupo cada trimestre
B80: Δ mensual → MOD (COP) por ronda | D80: {=SUMPRODUCT((E68:E69="COGS → Mano de Obra Directa")*C68:C69*D68:D69)} -> 10029159 | E80: ´= Implementadores×2 + Aprendices×2
B81: Δ mensual → Gtos Personal Ventas (COP) por ronda | D81: {=SUMPRODUCT((E70="Ventas → Gastos de Personal")*C70*D70)} -> 6781385 | E81: ´= Customer Success×1
B84: ESTADOS FINANCIEROS — ENERO A JULIO 2026
B85: Fuente: balance de comprobación / saldos finales compartidos en chat; Jun-26: Estados Financieros Junio 2026 (PDF); Jul-26: EF Julio COCO 2026 (PDF)
B88: BALANCE GENERAL — ENERO A JULIO 2026
B90: Concepto | C90: COP Dic-25 | D90: COP Ene | E90: COP Feb | F90: COP Mar | G90: COP Abr | H90: COP May | I90: COP Jun | J90: COP Jul | K90: Var $ (Jun→Jul) | L90: Var % | N90: Fuente / Nota
B91: ACTIVO
B92: ACTIVOS CORRIENTES
B93: Efectivo y equivalentes de efectivo | D93: 425594626 | E93: 120301539 | F93: 269488711 | G93: 357757161 | H93: 244822345 | I93: 115441362 | J93: 174266926 | K93: =J93-I93 -> 58825564 | L93: =IF(I93=0,"-",(J93-I93)/ABS(I93)) -> 0.50957095 | N93: Nota 03
B94: Inversiones | D94: 92548595 | E94: 93008823 | F94: 93705293 | G94: 94574157 | H94: 175907394 | I94: 77569331 | J94: 78270032 | K94: =J94-I94 -> 700701 | L94: =IF(I94=0,"-",(J94-I94)/ABS(I94)) -> 0.0090332222 | N94: Nota 04
B95: Cuentas comerciales y otras cuentas por cobrar | D95: 4922286580 | E95: 5157064970 | F95: 5088484812 | G95: 5045610659 | H95: 5144264271 | I95: 5297287438 | J95: 5218154960 | K95: =J95-I95 -> -79132478 | L95: =IF(I95=0,"-",(J95-I95)/ABS(I95)) -> -0.014938302 | N95: Nota 05
B96: Clientes | D96: 1590540829 | E96: 1797557189 | F96: 1690589814 | G96: 1612589704 | H96: 1675346692 | I96: 1799431102 | J96: 1688457915 | K96: =J96-I96 -> -110973187 | L96: =IF(I96=0,"-",(J96-I96)/ABS(I96)) -> -0.061671262 | N96: Nota 05
B97: Otros deudores / anticipos / terceros | D97: 3331745751 | E97: 3359507781 | F97: 3397894998 | G97: 3433020955 | H97: =H95-H96 -> 3468917579 | I97: =I95-I96 -> 3497856336 | J97: =J95-J96 -> 3529697045 | K97: =J97-I97 -> 31840709 | L97: =IF(I97=0,"-",(J97-I97)/ABS(I97)) -> 0.0091029207 | N97: Nota 05
B98: Total activos corrientes | D98: =SUM(D93:D95) -> 5440429801 | E98: =SUM(E93:E95) -> 5370375332 | F98: =SUM(F93:F95) -> 5451678816 | G98: =SUM(G93:G95) -> 5497941977 | H98: =SUM(H93:H95) -> 5564994010 | I98: =SUM(I93:I95) -> 5490298131 | J98: =SUM(J93:J95) -> 5470691918 | K98: =J98-I98 -> -19606213 | L98: =IF(I98=0,"-",(J98-I98)/ABS(I98)) -> -0.0035710653 | N98: Estado financiero
B100: ACTIVOS NO CORRIENTES
B101: Propiedad, planta y equipo neto | D101: 216571954 | E101: 222840954 | F101: 223130002 | G101: 218182533 | H101: 225975514 | I101: 225975514 | J101: 225975514 | K101: =J101-I101 -> 0 | L101: =IF(I101=0,"-",(J101-I101)/ABS(I101)) -> 0 | N101: Nota 06, excluye intangibles
B102: Intangibles (software) | D102: 410000000 | E102: 410000000 | F102: 410000000 | G102: 410000000 | H102: 410000000 | I102: 410000000 | J102: 410000000 | K102: =J102-I102 -> 0 | L102: =IF(I102=0,"-",(J102-I102)/ABS(I102)) -> 0 | N102: Nota 06
B103: Total activos no corrientes | D103: =SUM(D101:D102) -> 626571954 | E103: =SUM(E101:E102) -> 632840954 | F103: =SUM(F101:F102) -> 633130002 | G103: =SUM(G101:G102) -> 628182533 | H103: =SUM(H101:H102) -> 635975514 | I103: =SUM(I101:I102) -> 635975514 | J103: =SUM(J101:J102) -> 635975514 | K103: =J103-I103 -> 0 | L103: =IF(I103=0,"-",(J103-I103)/ABS(I103)) -> 0 | N103: Estado financiero
B104: TOTAL ACTIVO | D104: =SUM(D98,D103) -> 6067001755 | E104: =SUM(E98,E103) -> 6003216286 | F104: =SUM(F98,F103) -> 6084808818 | G104: =SUM(G98,G103) -> 6126124510 | H104: =SUM(H98,H103) -> 6200969524 | I104: =SUM(I98,I103) -> 6126273645 | J104: =SUM(J98,J103) -> 6106667432 | K104: =J104-I104 -> -19606213 | L104: =IF(I104=0,"-",(J104-I104)/ABS(I104)) -> -0.0032003489 | N104: Estado de Situación Financiera
B106: PASIVO
B107: PASIVO CORRIENTE
B108: Obligaciones financieras (tarjetas) | D108: 72783461 | E108: 101365099 | F108: 104189980 | G108: 112563470 | H108: 99589767 | I108: 83503947 | J108: 104555195 | K108: =J108-I108 -> 21051248 | L108: =IF(I108=0,"-",(J108-I108)/ABS(I108)) -> 0.25209884 | N108: Nota 07
B109: Proveedores y cuentas por pagar terceros | D109: 502128241 | E109: 493782297 | F109: 571037565 | G109: 563841763 | H109: 502311050 | I109: 483390906 | J109: =SUM(J110:J111) -> 403760304 | K109: =J109-I109 -> -79630602 | L109: =IF(I109=0,"-",(J109-I109)/ABS(I109)) -> -0.16473335 | N109: Nota 07: proveedores + CxP terceros
B110: Proveedores | C110: 544703000 | D110: 496565120 | E110: 4.7607384e+08 | F110: 555649841 | G110: 547636362 | H110: 500381050 | I110: 469974009 | J110: 384931931 | K110: =J110-I110 -> -85042078 | L110: =IF(I110=0,"-",(J110-I110)/ABS(I110)) -> -0.1809506 | N110: Nota 07
B111: Cuentas por pagar a terceros | D111: =D109-D110 -> 5563121 | E111: =E109-E110 -> 17708457 | F111: =F109-F110 -> 15387724 | G111: =G109-G110 -> 16205401 | H111: =H109-H110 -> 1930000 | I111: =I109-I110 -> 13416897 | J111: 18828373 | K111: =J111-I111 -> 5411476 | L111: =IF(I111=0,"-",(J111-I111)/ABS(I111)) -> 0.4033329 | N111: Nota 07
B112: Impuestos por pagar | D112: 14350080 | E112: 1791700 | F112: 25570584 | G112: 24496645 | H112: 22513416 | I112: 23325495 | J112: 19229474 | K112: =J112-I112 -> -4096021 | L112: =IF(I112=0,"-",(J112-I112)/ABS(I112)) -> -0.17560275 | N112: Nota 07
B113: Obligaciones laborales | D113: 344307623 | E113: 241683051 | F113: 236353731 | G113: 271532869 | H113: 320296862 | I113: 247533920 | J113: 265675229 | K113: =J113-I113 -> 18141309 | L113: =IF(I113=0,"-",(J113-I113)/ABS(I113)) -> 0.073288174 | N113: Nota 07
B114: Total pasivo corriente | D114: =SUM(D108:D109,D112:D113) -> 933569405 | E114: =SUM(E108:E109,E112:E113) -> 838622147 | F114: =SUM(F108:F109,F112:F113) -> 937151860 | G114: =SUM(G108:G109,G112:G113) -> 972434747 | H114: =SUM(H108:H109,H112:H113) -> 944711095 | I114: =SUM(I108:I109,I112:I113) -> 837754268 | J114: =SUM(J108:J109,J112:J113) -> 793220202 | K114: =J114-I114 -> -44534066 | L114: =IF(I114=0,"-",(J114-I114)/ABS(I114)) -> -0.053158865 | N114: Estado financiero
B115: PASIVO NO CORRIENTE
...

Sheet Modelo Base
B2: Coco Tecnologías — Modelo Financiero 3 Estados | E2: Dic-25 | F2: Ene-26 | G2: Feb-26 | H2: Mar-26 | I2: Abr-26 | J2: May-26 | K2: Jun-26 | L2: Jul-26 | M2: Ago-26 | N2: Sep-26 | O2: Oct-26 | P2: Nov-26 | Q2: Dic-26
B4: SUPUESTOS Y DRIVERS (COP)
B5: Cifras en pesos colombianos. Fuente: INPUTS + EEFF reales Feb/Mar-26
B6: Tasa de Cambio (COP/USD) | C6: TRM | E6: =TrmLargoPlazo -> 3690 | F6: 3690 | G6: 3690 | H6: 3690 | I6: 3690 | J6: 3690 | K6: 3690 | L6: 3690 | M6: 3690 | N6: 3690 | O6: 3690 | P6: 3690 | Q6: 3690
B7: Tasa de Impuestos | C7: % Estatutario | E7: =TasaImpuesto -> 0.35 | F7: =TasaImpuesto -> 0.35 | G7: =TasaImpuesto -> 0.35 | H7: =TasaImpuesto -> 0.35 | I7: =TasaImpuesto -> 0.35 | J7: =TasaImpuesto -> 0.35 | K7: =TasaImpuesto -> 0.35 | L7: =TasaImpuesto -> 0.35 | ... Q7: =TasaImpuesto -> 0.35
B9: Drivers del Estado de Resultados | S9: Total COP | T9: Total USD
B10: Ingresos Mensuales (COP) | C10: fuente: P&L | F10: =Inputs!$D$132 -> 612247701 | G10: =Inputs!$E$132 -> 744218137 | H10: =Inputs!$F$132 -> 787041187 | I10: =Inputs!$G$132 -> 750867662 | J10: =Inputs!$H$132 -> 826514746 | K10: =Inputs!$I$132 -> 751453314 | L10: =Inputs!$J$132 -> 679890552 | M10: {=INDEX(Revenue!K:K,$E$18)} -> 9.7231409e+08 | N10: {=INDEX(Revenue!L:L,$E$18)} -> 1.1624883e+09 | O10: {=INDEX(Revenue!M:M,$E$18)} -> 1.1418829e+09 | P10: {=INDEX(Revenue!N:N,$E$18)} -> 1.1567582e+09 | Q10: {=INDEX(Revenue!O:O,$E$18)} -> 1.2443405e+09 | S10: =SUM(F10:Q10) -> 1.0830017e+10 | T10: =S10/TrmLargoPlazo -> 2934964
B11: Costo de Ventas Mensual (COP) | C11: fuente: P&L | F11: =Inputs!$D$135 -> 238535794 | G11: =Inputs!$E$135 -> 343308791 | H11: =Inputs!$F$135 -> 455639201 | I11: =Inputs!$G$135 -> 379273594 | J11: =Inputs!H135 -> 355470523 | K11: =Inputs!I135 -> 348477606 | L11: =Inputs!J135 -> 321917838 | M11: =CostoVentasBase*(1+InflacionAnual)*(1/12)+DeltaModQ3 -> 3.5252106e+08 | N11: =CostoVentasBase*(1+InflacionAnual)*(1/12)+DeltaModQ3 -> 3.5252106e+08 | O11: =CostoVentasBase*(1+InflacionAnual)*(1/12)+DeltaModQ3 -> 3.5252106e+08 | P11: =CostoVentasBase*(1+InflacionAnual)*(1/12)+DeltaModQ4 -> 3.6255022e+08 | Q11: =CostoVentasBase*(1+InflacionAnual)*(1/12)+DeltaModQ4 -> 3.6255022e+08 | S11: =SUM(F11:Q11) -> 4.225287e+09 | T11: =S11/TrmLargoPlazo -> 1145064.2
B12: Gastos Administrativos (COP) | F12: =Inputs!$D$139 -> 98722435 | G12: =Inputs!$E$139 -> 105633472 | H12: =Inputs!$F$139 -> 141811865 | I12: =Inputs!$G$139 -> 114280887 | J12: =Inputs!H139 -> 116808824 | K12: =Inputs!I139 -> 112288693 | L12: =Inputs!J139 -> 107932742 | M12: =GtosAdminBase*(1+InflacionAnual)*(1/12) -> 1.3539998e+08 | N12: =GtosAdminBase*(1+InflacionAnual)*(1/12) -> 1.3539998e+08 | O12: =GtosAdminBase*(1+InflacionAnual)*(1/12) -> 1.3539998e+08 | P12: =GtosAdminBase*(1+InflacionAnual)*(1/12) -> 1.3539998e+08 | Q12: =GtosAdminBase*(1+InflacionAnual)*(1/12) -> 1.3539998e+08 | S12: =SUM(F12:Q12) -> 1.4744788e+09 | T12: =S12/TrmLargoPlazo -> 399587.76
B13: Gastos de Ventas (COP) | F13: =Inputs!$D$142 -> 131600259 | G13: =Inputs!$E$142 -> 173632204 | H13: =Inputs!$F$142 -> 139615776 | I13: =Inputs!$G$142 -> 130090415 | J13: =Inputs!H142 -> 120233213 | K13: =Inputs!I142 -> 146803460 | L13: =Inputs!J142 -> 117761236 | M13: =GtosVentasBase*(1+InflacionAnual)*(1/12)+DeltaVtasQ3 -> 2.3088303e+08 | N13: =GtosVentasBase*(1+InflacionAnual)*(1/12)+DeltaVtasQ3 -> 2.3088303e+08 | O13: =GtosVentasBase*(1+InflacionAnual)*(1/12)+DeltaVtasQ3 -> 2.3088303e+08 | P13: =GtosVentasBase*(1+InflacionAnual)*(1/12)+DeltaVtasQ4 -> 2.3766442e+08 | Q13: =GtosVentasBase*(1+InflacionAnual)*(1/12)+DeltaVtasQ4 -> 2.3766442e+08 | S13: =SUM(F13:Q13) -> 2.1277145e+09 | T13: =S13/TrmLargoPlazo -> 576616.39
B14: Gastos Operativos/Proyectos (COP) | F14: =Inputs!$D$141 -> 73409852 | G14: =Inputs!$E$141 -> 75509638 | H14: =Inputs!$F$141 -> 72217138 | I14: =Inputs!$G$141 -> 122384514 | J14: =Inputs!H141 -> 120992711 | K14: =Inputs!I141 -> 108908060 | L14: =Inputs!J141 -> 102936374 | M14: =GtosOpInflado*(1/12) -> 1.1302524e+08 | N14: =GtosOpInflado*(1/12) -> 1.1302524e+08 | O14: =GtosOpInflado*(1/12) -> 1.1302524e+08 | P14: =GtosOpInflado*(1/12) -> 1.1302524e+08 | Q14: =GtosOpInflado*(1/12) -> 1.1302524e+08 | S14: =SUM(F14:Q14) -> 1.2414845e+09 | T14: =S14/TrmLargoPlazo -> 336445.66
B15: Ingresos No Operacionales (COP) | F15: =Inputs!$D$146 -> 597687 | G15: =Inputs!$E$146 -> 13488976 | H15: =Inputs!$F$146 -> -10197660 | I15: =Inputs!$G$146 -> 906545 | J15: =Inputs!H146 -> 1366339 | K15: =Inputs!I146 -> 3920249 | L15: =Inputs!J146 -> 718311 | M15: =IngNoOpBase*(1+InflacionAnual)*(1/12) -> 11706739 | N15: =IngNoOpBase*(1+InflacionAnual)*(1/12) -> 11706739 | O15: =IngNoOpBase*(1+InflacionAnual)*(1/12) -> 11706739 | P15: =IngNoOpBase*(1+InflacionAnual)*(1/12) -> 11706739 | Q15: =IngNoOpBase*(1+InflacionAnual)*(1/12) -> 11706739 | S15: =SUM(F15:Q15) -> 69334140 | T15: =S15/TrmLargoPlazo -> 18789.74
B16: Gastos No Operacionales (COP) | F16: =Inputs!$D$150 -> 7091551 | G16: =Inputs!$E$150 -> 5574093 | H16: =Inputs!$F$150 -> 5497554 | I16: =Inputs!$G$150 -> 5038594 | J16: =Inputs!$H$150 -> 6000846 | K16: =Inputs!$I$150 -> 5552094 | L16: =Inputs!$J$150 -> 5353621 | M16: =GtosNoOpBase*(1+InflacionAnual)*(1/12) -> 8061432.8 | N16: =GtosNoOpBase*(1+InflacionAnual)*(1/12) -> 8061432.8 | O16: =GtosNoOpBase*(1+InflacionAnual)*(1/12) -> 8061432.8 | P16: =GtosNoOpBase*(1+InflacionAnual)*(1/12) -> 8061432.8 | Q16: =GtosNoOpBase*(1+InflacionAnual)*(1/12) -> 8061432.8 | S16: =SUM(F16:Q16) -> 80415517 | T16: =S16/TrmLargoPlazo -> 21792.823
B18: Escenario | C18: Base | D18: fila fuente en Revenue → | E18: =IF(C18="Conservador",47,IF(C18="Optimista",57,52)) -> 52 | F18: =IF($C$18="Optimista",1,IF($C$18="Conservador",2,3)) -> 3
B19: Moneda EEFF | C19: USD | D19: ← conmuta moneda e idioma del bloque EEFF (filas 281-301)
B20: 3 Escenarios de Ingresos | F20: =F2 -> Ene-26 | G20: =G2 -> Feb-26 | H20: =H2 -> Mar-26 | I20: =I2 -> Abr-26 | J20: =J2 -> May-26 | K20: =K2 -> Jun-26 | L20: =L2 -> Jul-26 | M20: =M2 -> Ago-26 | ... Q20: =Q2 -> Dic-26 | S20: Total COP | T20: Total USD
B21: ='Consol. Pptos'!B40 -> Proyección mensual COP — Ppto Metas | E21: Optimista | F21: =F10 -> 612247701 | G21: =G10 -> 744218137 | H21: =H10 -> 787041187 | I21: =I10 -> 750867662 | J21: ='Consol. Pptos'!H63 -> 1013200000 | K21: ='Consol. Pptos'!I63 -> 1.1866154e+09 | L21: ='Consol. Pptos'!J63 -> 1.3600307e+09 | M21: ='Consol. Pptos'!K63 -> 1.5334461e+09 | N21: ='Consol. Pptos'!L63 -> 1.7068614e+09 | O21: ='Consol. Pptos'!M63 -> 1.8802768e+09 | P21: ='Consol. Pptos'!N63 -> 2.0536921e+09 | Q21: ='Consol. Pptos'!O63 -> 2227107500 | S21: =SUM(F21:Q21) -> 15855604687 | T21: =S21/TrmLargoPlazo -> 4296911.8
B22: ='Consol. Pptos'!B108 -> Proyección mensual COP — Ppto Intnl | E22: Conservador | F22: =F10 -> 612247701 | G22: =G10 -> 744218137 | H22: =H10 -> 787041187 | I22: =I10 -> 750867662 | J22: ='Consol. Pptos'!H122 -> 1.2184027e+09 | K22: ='Consol. Pptos'!I122 -> 7.5947894e+08 | L22: ='Consol. Pptos'!J122 -> 8.0343646e+08 | M22: ='Consol. Pptos'!K122 -> 1.2436402e+09 | N22: ='Consol. Pptos'!L122 -> 1.2490402e+09 | O22: ='Consol. Pptos'!M122 -> 1.3504209e+09 | P22: ='Consol. Pptos'!N122 -> 1.3558209e+09 | Q22: ='Consol. Pptos'!O122 -> 1.3612209e+09 | S22: =SUM(F22:Q22) -> 1.2235836e+10 | T22: =S22/TrmLargoPlazo -> 3315944.7
B23: ='Consol. Pptos'!B177 -> Proyección mensual COP — Ppto Consolidado | E23: Base | F23: =F10 -> 612247701 | G23: =G10 -> 744218137 | H23: =H10 -> 787041187 | I23: =I10 -> 750867662 | J23: =Inputs!H132 -> 826514746 | K23: =Inputs!I132 -> 751453314 | L23: ='Consol. Pptos'!J202 -> 1.0474069e+09 | M23: ='Consol. Pptos'!K202 -> 1.5736261e+09 | N23: ='Consol. Pptos'!L202 -> 1.6650414e+09 | O23: ='Consol. Pptos'!M202 -> 1.7564568e+09 | P23: ='Consol. Pptos'!N202 -> 1.8478721e+09 | Q23: ='Consol. Pptos'!O202 -> 1939287500 | S23: =SUM(F23:Q23) -> 1.4302034e+10 | T23: =S23/TrmLargoPlazo -> 3875889.9
B26: Drivers del Balance General | R26: Préstamo Intercompany - Coco Delaware
B27: DSO (Días de Cobro) | C27: Días | E27: 84 | R27: Prestamista | S27: Nombre | T27: Coco Delaware
B28: DPO (Días de Pago) | C28: Días | E28: 52 | R28: Fondos USA disponibles | S28: USD | T28: 338508
B29: Vida Útil PPE (meses) | C29: Meses | E29: 60 | R29: Cupo máximo Coco Delaware | S29: COP | T29: =$T$28*$E$6 -> 1249094520
B30: CapEx mensual proyectado (COP) | C30: COP | E30: 7360092 | R30: Tasa interés intercompany | S30: % anual | T30: 0
B31: Impuestos x Pagar (% de Impuestos) | C31: % | E31: 1 | R31: Inicio de mecánica | S31: Mes | T31: May-26
B32: Caja mínima operativa (COP) | C32: COP | E32: =E34 -> 231459000
B33: Saldos Iniciales (Dic-25, COP)
B34: Efectivo | E34: 231459000 | F34: =Inputs!D93 -> 425594626 | G34: =Inputs!E93 -> 120301539 | H34: =Inputs!F93 -> 269488711 | I34: =Inputs!G93 -> 357757161 | J34: =Inputs!H93 -> 244822345 | K34: =Inputs!I93 -> 115441362 | L34: =Inputs!J93 -> 174266926
B35: CxC Clientes | E35: 1833296000 | F35: =Inputs!D96 -> 1590540829 | G35: =Inputs!E96 -> 1797557189 | H35: =Inputs!F96 -> 1690589814 | I35: =Inputs!G96 -> 1612589704 | J35: =Inputs!H96 -> 1675346692 | K35: =Inputs!I96 -> 1799431102 | L35: =Inputs!J96 -> 1688457915
B36: Inversiones | E36: 92028000 | F36: =Inputs!D94 -> 92548595 | G36: =Inputs!E94 -> 93008823 | H36: =Inputs!F94 -> 93705293 | I36: =Inputs!G94 -> 94574157 | J36: =Inputs!H94 -> 175907394 | K36: =Inputs!I94 -> 77569331 | L36: =Inputs!J94 -> 78270032
B37: Otros Deudores | E37: 3301925000 | F37: =Inputs!D97 -> 3331745751 | G37: =Inputs!E97 -> 3359507781 | H37: =Inputs!F97 -> 3397894998 | I37: =Inputs!G97 -> 3433020955 | J37: =Inputs!H97 -> 3468917579 | K37: =Inputs!I97 -> 3497856336 | L37: =Inputs!J97 -> 3529697045
B38: PPE (neto) | E38: 209212000 | F38: =Inputs!D101 -> 216571954 | G38: =Inputs!E101 -> 222840954 | H38: =Inputs!F101 -> 223130002 | I38: =Inputs!G101 -> 218182533 | J38: =Inputs!H101 -> 225975514 | K38: =Inputs!I101 -> 225975514 | L38: =Inputs!J101 -> 225975514
B39: Intangibles | E39: 410000000 | F39: =Inputs!D102 -> 410000000 | G39: =Inputs!E102 -> 410000000 | H39: =Inputs!F102 -> 410000000 | I39: =Inputs!G102 -> 410000000 | J39: =Inputs!H102 -> 410000000 | K39: =Inputs!I102 -> 410000000 | L39: =Inputs!J102 -> 410000000
B40: CxP Proveedores | E40: 544703000 | F40: =Inputs!D109 -> 502128241 | G40: =Inputs!E109 -> 493782297 | H40: =Inputs!F109 -> 571037565 | I40: =Inputs!G109 -> 563841763 | J40: =Inputs!H109 -> 502311050 | K40: =Inputs!I109 -> 483390906 | L40: =Inputs!J109 -> 403760304
B41: CxP Socios/Terceros | E41: 2654919000 | F41: =Inputs!D116 -> 2645015181 | G41: =Inputs!E116 -> 2622128056 | H41: =Inputs!F116 -> 2643128881 | I41: =Inputs!G116 -> 2648455481 | J41: =Inputs!H116 -> 2642649181 | K41: =Inputs!I116 -> 2641566481 | L41: =Inputs!J116 -> 2641787281
B42: Impuestos x Pagar | E42: 40077000 | F42: =Inputs!D112 -> 14350080 | G42: =Inputs!E112 -> 1791700 | H42: =Inputs!F112 -> 25570584 | I42: =Inputs!G112 -> 24496645 | J42: =Inputs!H112 -> 22513416 | K42: =Inputs!I112 -> 23325495 | L42: =Inputs!J112 -> 19229474
B43: Obligaciones Laborales | E43: 333178000 | F43: =Inputs!D113 -> 344307623 | G43: =Inputs!E113 -> 241683051 | H43: =Inputs!F113 -> 236353731 | I43: =Inputs!G113 -> 271532869 | J43: =Inputs!H113 -> 320296862 | K43: =Inputs!I113 -> 247533920 | L43: =Inputs!J113 -> 265675229
B44: Obligaciones Financieras | E44: 80111000 | F44: =Inputs!D108 -> 72783461 | G44: =Inputs!E108 -> 101365099 | H44: =Inputs!F108 -> 104189980 | I44: =Inputs!G108 -> 112563470 | J44: =Inputs!H108 -> 99589767 | K44: =Inputs!I108 -> 83503947 | L44: =Inputs!J108 -> 104555195
B45: Capital Social + Superávit | E45: 1210339000 | F45: =Inputs!D121 -> 1210339000 | G45: =Inputs!E121 -> 1210339000 | H45: =Inputs!F121 -> 1210339000 | I45: =Inputs!G121 -> 1210339000 | J45: =Inputs!H121 -> 1210339000 | K45: =Inputs!I121 -> 1210339000 | L45: =Inputs!J121 -> 1210339000
B46: Utilidades Acumuladas | E46: 1214593000 | F46: =Inputs!D122 -> 1278078168 | G46: =Inputs!E122 -> 1332127083 | H46: =Inputs!F122 -> 1294189077 | I46: =Inputs!G122 -> 1294895280 | J46: =Inputs!H122 -> 1403270248 | K46: =Inputs!I122 -> 1436613897 | L46: =Inputs!J122 -> 1461320949
B48: Estado de Resultados (COP)
F50: =F2 -> Ene-26 | G50: =G2 -> Feb-26 | H50: =H2 -> Mar-26 | I50: =I2 -> Abr-26 | J50: =J2 -> May-26 | K50: =K2 -> Jun-26 | L50: =L2 -> Jul-26 | M50: =M2 -> Ago-26 | ... Q50: =Q2 -> Dic-26 | S50: TOTAL 2026
B51: Ingresos Operacionales | F51: =F23 -> 612247701 | G51: =G23 -> 744218137 | H51: =H23 -> 787041187 | I51: =I23 -> 750867662 | J51: =J23 -> 826514746 | K51: =K23 -> 751453314 | L51: =L10 -> 679890552 | M51: {=INDEX(M$21:M$23,$F$18)} -> 1.5736261e+09 | N51: {=INDEX(N$21:N$23,$F$18)} -> 1.6650414e+09 | O51: {=INDEX(O$21:O$23,$F$18)} -> 1.7564568e+09 | P51: {=INDEX(P$21:P$23,$F$18)} -> 1.8478721e+09 | Q51: {=INDEX(Q$21:Q$23,$F$18)} -> 1939287500 | S51: =SUM(F51:Q51) -> 1.3934517e+10
B52: Costo de Ventas | F52: =F11 -> 238535794 | G52: =G11 -> 343308791 | H52: =H11 -> 455639201 | I52: =I11 -> 379273594 | J52: =J11 -> 355470523 | K52: =K11 -> 348477606 | L52: =L11 -> 321917838 | M52: =M11 -> 3.5252106e+08 | ... Q52: =Q11 -> 3.6255022e+08 | S52: =SUM(F52:Q52) -> 4.225287e+09
B53: Utilidad Bruta | F53: =F51-F52 -> 373711907 | G53: =G51-G52 -> 400909346 | H53: =H51-H52 -> 331401986 | I53: =I51-I52 -> 371594068 | J53: =J51-J52 -> 471044223 | K53: =K51-K52 -> 402975708 | L53: =L51-L52 -> 357972714 | M53: =M51-M52 -> 1.221105e+09 | ... Q53: =Q51-Q52 -> 1.5767373e+09 | S53: =SUM(F53:Q53) -> 9.7092303e+09
B54: Margen Bruto % | F54: =IF(F51=0,0,F53/F51) -> 0.61039332 | G54: =IF(G51=0,0,G53/G51) -> 0.5386987 | H54: =IF(H51=0,0,H53/H51) -> 0.42107324 | I54: =IF(I51=0,0,I53/I51) -> 0.49488623 | J54: =IF(J51=0,0,J53/J51) -> 0.5699163 | K54: =IF(K51=0,0,K53/K51) -> 0.5362618 | L54: =IF(L51=0,0,L53/L51) -> 0.52651521 | M54: =IF(M51=0,0,M53/M51) -> 0.77598169 | ... Q54: =IF(Q51=0,0,Q53/Q51) -> 0.81304978 | S54: =IF(S51=0,0,S53/S51) -> 0.6967755
B56: Gastos Administrativos | F56: =F12 -> 98722435 | G56: =G12 -> 105633472 | H56: =H12 -> 141811865 | I56: =I12 -> 114280887 | J56: =J12 -> 116808824 | K56: =K12 -> 112288693 | L56: =L12 -> 107932742 | M56: =M12 -> 1.3539998e+08 | ... Q56: =Q12 -> 1.3539998e+08 | S56: =SUM(F56:Q56) -> 1.4744788e+09
B57: Gastos de Ventas | F57: =F13 -> 131600259 | G57: =G13 -> 173632204 | H57: =H13 -> 139615776 | I57: =I13 -> 130090415 | J57: =J13 -> 120233213 | K57: =K13 -> 146803460 | L57: =L13 -> 117761236 | M57: =M13 -> 2.3088303e+08 | ... Q57: =Q13 -> 2.3766442e+08 | S57: =SUM(F57:Q57) -> 2.1277145e+09
B58: Gastos Operativos/Proyectos | F58: =F14 -> 73409852 | G58: =G14 -> 75509638 | H58: =H14 -> 72217138 | I58: =I14 -> 122384514 | J58: =J14 -> 120992711 | K58: =K14 -> 108908060 | L58: =L14 -> 102936374 | M58: =M14 -> 1.1302524e+08 | ... Q58: =Q14 -> 1.1302524e+08 | S58: =SUM(F58:Q58) -> 1.2414845e+09
B59: EBITDA | F59: =F53-F56-F57-F58 -> 69979361 | G59: =G53-G56-G57-G58 -> 46134032 | H59: =H53-H56-H57-H58 -> -22242793 | I59: =I53-I56-I57-I58 -> 4838252 | J59: =J53-J56-J57-J58 -> 113009475 | K59: =K53-K56-K57-K58 -> 34975495 | L59: =L53-L56-L57-L58 -> 29342362 | M59: =M53-M56-M57-M58 -> 7.4179676e+08 | ... Q59: =Q53-Q56-Q57-Q58 -> 1090647643 | S59: =SUM(F59:Q59) -> 4.8655525e+09
B60: (-) Depreciación y Amortización | F60: =0 -> 0 | G60: =0 -> 0 | H60: =0 -> 0 | I60: =0 -> 0 | J60: 0 | K60: 0 | L60: =0 -> 0 | M60: =M167 -> 3826155.8 | N60: =N167 -> 3885054.7 | O60: =O167 -> 3942972 | P60: =P167 -> 3999924 | Q60: =Q167 -> 4055926.8 | S60: =SUM(F60:Q60) -> 19710033
B61: EBIT (Utilidad Operativa) | F61: =F59-F60 -> 69979361 | G61: =G59-G60 -> 46134032 | H61: =H59-H60 -> -22242793 | I61: =I59-I60 -> 4838252 | J61: =J59-J60 -> 113009475 | K61: =K59-K60 -> 34975495 | L61: =L59-L60 -> 29342362 | M61: =M59-M60 -> 7.379706e+08 | ... Q61: =Q59-Q60 -> 1.0865917e+09 | S61: =SUM(F61:Q61) -> 4.8458424e+09
B62: Margen EBIT % | F62: =IF(F51=0,0,F61/F51) -> 0.1142991 | G62: =IF(G51=0,0,G61/G51) -> 0.061989932 | H62: =IF(H51=0,0,H61/H51) -> -0.028261282 | I62: =IF(I51=0,0,I61/I51) -> 0.0064435482 | J62: =IF(J51=0,0,J61/J51) -> 0.13673014 | K62: =IF(K51=0,0,K61/K51) -> 0.046543803 | L62: =IF(L51=0,0,L61/L51) -> 0.043157479 | M62: =IF(M51=0,0,M61/M51) -> 0.46896186 | ... Q62: =IF(Q51=0,0,Q61/Q51) -> 0.5603046 | S62: =IF(S51=0,0,S61/S51) -> 0.34775819
B64: Ingresos No Operacionales | F64: =F15 -> 597687 | G64: =G15 -> 13488976 | H64: =H15 -> -10197660 | I64: =I15 -> 906545 | J64: =J15 -> 1366339 | K64: =K15 -> 3920249 | L64: =L15 -> 718311 | M64: =M15 -> 11706739 | ... Q64: =Q15 -> 11706739 | S64: =SUM(F64:Q64) -> 69334140
B65: Gastos No Operacionales | F65: =F16 -> 7091551 | G65: =G16 -> 5574093 | H65: =H16 -> 5497554 | I65: =I16 -> 5038594 | J65: =J16 -> 6000846 | K65: =K16 -> 5552094 | L65: =L16 -> 5353621 | M65: =M16+M138 -> 8757299 | N65: =N16+N138 -> 8757299 | O65: =O16+O138 -> 8757299 | P65: =P16+P138 -> 8757299 | Q65: =Q16+Q138 -> 8757299 | S65: =SUM(F65:Q65) -> 83894848
B67: Utilidad Antes de Impuestos (UAI) | F67: =F61+F64-F65 -> 63485497 | G67: =G61+G64-G65 -> 54048915 | H67: =H61+H64-H65 -> -37938007 | I67: =I61+I64-I65 -> 706203 | J67: =J61+J64-J65 -> 108374968 | K67: =K61+K64-K65 -> 33343650 | L67: =L61+L64-L65 -> 24707052 | M67: =M61+M64-M65 -> 7.4092004e+08 | ... Q67: =Q61+Q64-Q65 -> 1.0895412e+09 | S67: =SUM(F67:Q67) -> 4.8312817e+09
B69: Impuesto de Renta | F69: =Inputs!D154 -> 0 | G69: =Inputs!$E$154 -> 0 | H69: =Inputs!$F$154 -> 0 | I69: =Inputs!$G$154 -> 0 | J69: =Inputs!H154 -> 0 | K69: =Inputs!I154 -> 0 | L69: =Inputs!J154 -> 0 | M69: =IF(M67>0,M67*M$7,0) -> 2.5932201e+08 | N69: =IF(N67>0,N67*N$7,0) -> 2.9129678e+08 | O69: =IF(O67>0,O67*O$7,0) -> 3.2327188e+08 | P69: =IF(P67>0,P67*P$7,0) -> 3.4936363e+08 | Q69: =IF(Q67>0,Q67*Q$7,0) -> 3.813394e+08 | S69: =SUM(F69:Q69) -> 1.6045937e+09
B70: Utilidad Neta | F70: =F67-F69 -> 63485497 | G70: =G67-G69 -> 54048915 | H70: =H67-H69 -> -37938007 | I70: =I67-I69 -> 706203 | J70: =J67-J69 -> 108374968 | K70: =K67-K69 -> 33343650 | L70: =L67-L69 -> 24707052 | M70: =M67-M69 -> 4.8159803e+08 | ... Q70: =Q67-Q69 -> 7.0820175e+08 | S70: =SUM(F70:Q70) -> 3.226688e+09
B71: Margen Neto % | F71: =IF(F51=0,0,F70/F51) -> 0.1036925 | G71: =IF(G51=0,0,G70/G51) -> 0.072625098 | H71: =IF(H51=0,0,H70/H51) -> -0.048203331 | I71: =IF(I51=0,0,I70/I51) -> 0.00094051593 | J71: =IF(J51=0,0,J70/J51) -> 0.13112285 | K71: =IF(K51=0,0,K70/K51) -> 0.044372218 | L71: =IF(L51=0,0,L70/L51) -> 0.036339749 | M71: =IF(M51=0,0,M70/M51) -> 0.3060435 | ... Q71: =IF(Q51=0,0,Q70/Q51) -> 0.36518657 | S71: =IF(S51=0,0,S70/S51) -> 0.2315608
B74: Balance General (COP)
E76: 2025 | F76: Ene-26 | G76: Feb-26 | H76: Mar-26 | I76: Abr-26 | J76: May-26 | K76: Jun-26 | L76: Jul-26 | M76: Ago-26 | N76: Sep-26 | O76: Oct-26 | P76: Nov-26 | Q76: Dic-26 | S76: Total 2026
B77: ACTIVOS
B78: Efectivo | E78: =E34 -> 231459000 | F78: =F34 -> 425594626 | G78: =G34 -> 120301539 | H78: =H34 -> 269488711 | I78: =I34 -> 357757161 | J78: =J34 -> 244822345 | K78: =K34 -> 115441362 | L78: =L34 -> 174266926 | M78: =M186 -> -1.6179953e+09 | N78: =N186 -> -1.3044789e+09 | O78: =O186 -> -9.3152183e+08 | P78: =P186 -> -4.985512e+08 | Q78: =Q186 -> -17640842 | S78: =Q78 -> -17640842
B79: CxC Clientes | E79: =E35 -> 1833296000 | F79: =F35 -> 1590540829 | G79: =G35 -> 1797557189 | H79: =H35 -> 1690589814 | I79: =I35 -> 1612589704 | J79: =J35 -> 1675346692 | K79: =K35 -> 1799431102 | L79: =L35 -> 1688457915 | M79: =M51*$E$27/30 -> 4406153000 | N79: =N51*$E$27/30 -> 4662116000 | O79: =O51*$E$27/30 -> 4918079000 | P79: =P51*$E$27/30 -> 5174042000 | Q79: =Q51*$E$27/30 -> 5430005000 | S79: =Q79 -> 5430005000
B80: Inversiones | E80: =E36 -> 92028000 | F80: =F36 -> 92548595 | G80: =G36 -> 93008823 | H80: =H36 -> 93705293 | I80: =I36 -> 94574157 | J80: =J36 -> 175907394 | K80: =K36 -> 77569331 | L80: =L36 -> 78270032 | M80: =$I80 -> 94574157 | N80: =$I80 -> 94574157 | O80: =$I80 -> 94574157 | P80: =$I80 -> 94574157 | Q80: =$I80 -> 94574157 | S80: =Q80 -> 94574157
B81: Otros Deudores | E81: =E37 -> 3301925000 | F81: =F37 -> 3331745751 | G81: =G37 -> 3359507781 | H81: =H37 -> 3397894998 | I81: =I37 -> 3433020955 | J81: =J37 -> 3468917579 | K81: =K37 -> 3497856336 | L81: =L37 -> 3529697045 | M81: =$I81 -> 3433020955 | N81: =$I81 -> 3433020955 | O81: =$I81 -> 3433020955 | P81: =$I81 -> 3433020955 | Q81: =$I81 -> 3433020955 | S81: =Q81 -> 3433020955
B82: Total Activos Corrientes | E82: =SUM(E78:E81) -> 5458708000 | F82: =SUM(F78:F81) -> 5440429801 | G82: =SUM(G78:G81) -> 5370375332 | H82: =SUM(H78:H81) -> 5451678816 | I82: =SUM(I78:I81) -> 5497941977 | J82: =SUM(J78:J81) -> 5564994010 | K82: =SUM(K78:K81) -> 5490298131 | L82: =SUM(L78:L81) -> 5470691918 | ... Q82: =SUM(Q78:Q81) -> 8.9399593e+09 | S82: =Q82 -> 8.9399593e+09
B83: PPE (neto) | E83: =E38 -> 209212000 | F83: =F38 -> 216571954 | G83: =G38 -> 222840954 | H83: =H38 -> 223130002 | I83: =I38 -> 218182533 | J83: =J38 -> 225975514 | K83: =K38 -> 225975514 | L83: =L38 -> 225975514 | M83: =M126 -> 2.3310328e+08 | N83: =N126 -> 2.3657832e+08 | O83: =O126 -> 2.3999544e+08 | P83: =P126 -> 2.4335561e+08 | Q83: =Q126 -> 2.4665977e+08 | S83: =Q83 -> 2.4665977e+08
B84: Intangibles | E84: =E39 -> 410000000 | F84: =F39 -> 410000000 | G84: =G39 -> 410000000 | H84: =H39 -> 410000000 | I84: =I39 -> 410000000 | J84: =J39 -> 410000000 | K84: =K39 -> 410000000 | L84: =L39 -> 410000000 | M84: =$I84 -> 410000000 | N84: =$I84 -> 410000000 | O84: =$I84 -> 410000000 | P84: =$I84 -> 410000000 | Q84: =$I84 -> 410000000 | S84: =Q84 -> 410000000
B85: TOTAL ACTIVOS | E85: =E82+E83+E84 -> 6077920000 | F85: =SUM(F82:F84) -> 6067001755 | G85: =SUM(G82:G84) -> 6003216286 | H85: =SUM(H82:H84) -> 6084808818 | I85: =SUM(I82:I84) -> 6126124510 | J85: =J82+J83+J84 -> 6200969524 | K85: =K82+K83+K84 -> 6126273645 | L85: =L82+L83+L84 -> 6106667432 | M85: =M82+M83+M84 -> 6.9588561e+09 | N85: =N82+N83+N84 -> 7.5318106e+09 | O85: =O82+O83+O84 -> 8.1641477e+09 | P85: =P82+P83+P84 -> 8.8564415e+09 | Q85: =Q82+Q83+Q84 -> 9.596619e+09 | S85: =Q85 -> 9.596619e+09
B87: PASIVOS
B88: Obligaciones Financieras / Tarjetas + CxP Relacionada Coco Delaware | E88: =E44 -> 80111000 | F88: =F44 -> 72783461 | G88: =G44 -> 101365099 | H88: =H44 -> 104189980 | I88: =I44 -> 112563470 | J88: =J44 -> 99589767 | K88: =K44 -> 83503947 | L88: =L44 -> 104555195 | M88: =M133+M144 -> 2725070428 | N88: =N133+N144 -> 2725070428 | O88: =O133+O144 -> 2725070428 | P88: =P133+P144 -> 2725070428 | Q88: =Q133+Q144 -> 2725070428 | S88: =Q88 -> 2725070428
B89: CxP Proveedores | E89: =E40 -> 544703000 | F89: =F40 -> 502128241 | G89: =G40 -> 493782297 | H89: =H40 -> 571037565 | I89: =I40 -> 563841763 | J89: =J40 -> 502311050 | K89: =K40 -> 483390906 | L89: =L40 -> 403760304 | M89: =M52*$E$28/30 -> 6.110365e+08 | N89: =N52*$E$28/30 -> 6.110365e+08 | O89: =O52*$E$28/30 -> 6.110365e+08 | P89: =P52*$E$28/30 -> 6.2842038e+08 | Q89: =Q52*$E$28/30 -> 6.2842038e+08 | S89: =Q89 -> 6.2842038e+08
B90: Impuestos x Pagar | E90: =E42 -> 40077000 | F90: =F42 -> 14350080 | G90: =G42 -> 1791700 | H90: =H42 -> 25570584 | I90: =I42 -> 24496645 | J90: =J42 -> 22513416 | K90: =K42 -> 23325495 | L90: =L42 -> 19229474 | M90: =M69*$E$31 -> 2.5932201e+08 | N90: =N69*$E$31 -> 2.9129678e+08 | O90: =O69*$E$31 -> 3.2327188e+08 | P90: =P69*$E$31 -> 3.4936363e+08 | Q90: =Q69*$E$31 -> 3.813394e+08 | S90: =Q90 -> 3.813394e+08
B91: Obligaciones Laborales | E91: =E43 -> 333178000 | F91: =F43 -> 344307623 | G91: =G43 -> 241683051 | H91: =H43 -> 236353731 | I91: =I43 -> 271532869 | J91: =J43 -> 320296862 | K91: =K43 -> 247533920 | L91: =L43 -> 265675229 | M91: =L91 -> 265675229 | N91: =M91 -> 265675229 | O91: =N91 -> 265675229 | P91: =O91 -> 265675229 | Q91: =P91 -> 265675229 | S91: =Q91 -> 265675229
B92: Total Pasivos Corrientes | E92: =SUM(E88:E91) -> 998069000 | F92: =SUM(F88:F91) -> 933569405 | G92: =SUM(G88:G91) -> 838622147 | H92: =SUM(H88:H91) -> 937151860 | I92: =SUM(I88:I91) -> 972434747 | J92: =SUM(J88:J91) -> 944711095 | K92: =SUM(K88:K91) -> 837754268 | L92: =SUM(L88:L91) -> 793220202 | ... Q92: =SUM(Q88:Q91) -> 4.0005054e+09 | S92: =Q92 -> 4.0005054e+09
B94: CxP Socios/Terceros (pasivo no corriente) | E94: =E41 -> 2654919000 | F94: =F41 -> 2645015181 | G94: =G41 -> 2622128056 | H94: =H41 -> 2643128881 | I94: =I41 -> 2648455481 | J94: =J41 -> 2642649181 | K94: =K41 -> 2641566481 | L94: =L41 -> 2641787281 | M94: =L94 -> 2641787281 | N94: =M94 -> 2641787281 | O94: =N94 -> 2641787281 | P94: =O94 -> 2641787281 | Q94: =P94 -> 2641787281 | S94: =Q94 -> 2641787281
B95: Total Pasivos No Corrientes | E95: =E94 -> 2654919000 | F95: =F94 -> 2645015181 | G95: =G94 -> 2622128056 | H95: =H94 -> 2643128881 | I95: =I94 -> 2648455481 | J95: =J94 -> 2642649181 | K95: =K94 -> 2641566481 | L95: =L94 -> 2641787281 | ... Q95: =Q94 -> 2641787281 | S95: =Q95 -> 2641787281
B96: TOTAL PASIVOS | E96: =E92+E95 -> 3652988000 | F96: =F92+F95 -> 3578584586 | G96: =G92+G95 -> 3460750203 | H96: =H92+H95 -> 3580280741 | I96: =I92+I95 -> 3620890228 | J96: =J92+J95 -> 3587360276 | K96: =K92+K95 -> 3479320749 | L96: =L92+L95 -> 3435007483 | ... Q96: =Q92+Q95 -> 6.6422927e+09 | S96: =Q96 -> 6.6422927e+09
B98: PATRIMONIO
B99: Capital Social + Superávit | E99: =E45 -> 1210339000 | F99: =F45 -> 1210339000 | G99: =G45 -> 1210339000 | H99: =H45 -> 1210339000 | I99: =I45 -> 1210339000 | J99: =J45 -> 1210339000 | K99: =K45 -> 1210339000 | L99: =L45 -> 1210339000 | M99: =M149 -> 1210339000 | N99: =N149 -> 1210339000 | O99: =O149 -> 1210339000 | P99: =P149 -> 1210339000 | Q99: =Q149 -> 1210339000 | S99: =Q99 -> 1210339000
B100: Utilidades Acumuladas | E100: =E46 -> 1214593000 | F100: =F46 -> 1278078168 | G100: =G46 -> 1332127083 | H100: =H46 -> 1294189077 | I100: =I46 -> 1294895280 | J100: =J46 -> 1403270248 | K100: =K46 -> 1436613897 | L100: =L46 -> 1461320949 | M100: =M155 -> 1.942919e+09 | N100: =N155 -> 2.4838987e+09 | O100: =O155 -> 3.0842608e+09 | P100: =P155 -> 3.7330789e+09 | Q100: =Q155 -> 4.4412807e+09 | S100: =Q100 -> 4.4412807e+09
B101: TOTAL PATRIMONIO | E101: =E99+E100 -> 2424932000 | F101: =SUM(F99:F100) -> 2488417168 | G101: =SUM(G99:G100) -> 2542466083 | H101: =SUM(H99:H100) -> 2504528077 | I101: =SUM(I99:I100) -> 2505234280 | J101: =J99+J100 -> 2613609248 | K101: =K99+K100 -> 2646952897 | L101: =L99+L100 -> 2671659949 | M101: =M99+M100 -> 3.153258e+09 | N101: =N99+N100 -> 3.6942377e+09 | O101: =O99+O100 -> 4.2945998e+09 | P101: =P99+P100 -> 4.9434179e+09 | Q101: =Q99+Q100 -> 5.6516197e+09 | S101: =Q101 -> 5.6516197e+09
B103: TOTAL PASIVO + PATRIMONIO | E103: =E96+E101 -> 6077920000 | F103: =SUM(F96,F101) -> 6067001754 | G103: =SUM(G96,G101) -> 6003216286 | H103: =SUM(H96,H101) -> 6084808818 | I103: =SUM(I96,I101) -> 6126124508 | J103: =J96+J101 -> 6200969524 | K103: =K96+K101 -> 6126273646 | L103: =L96+L101 -> 6106667432 | M103: =M96+M101 -> 9.6561494e+09 | N103: =N96+N101 -> 1.0229104e+10 | O103: =O96+O101 -> 1.0861441e+10 | P103: =P96+P101 -> 1.1553735e+10 | Q103: =Q96+Q101 -> 1.2293912e+10 | S103: =Q103 -> 1.2293912e+10
B105: Verificación Balance (Activos - Pasivos+Patrimonio) | E105: =ROUND(E85-E103,0) -> 0 | F105: =IF(ABS(F85-F103)<=2,0,ROUND(F85-F103,0)) -> 0 | G105: =IF(ABS(G85-G103)<=2,0,ROUND(G85-G103,0)) -> 0 | H105: =IF(ABS(H85-H103)<=2,0,ROUND(H85-H103,0)) -> 0 | I105: =IF(ABS(I85-I103)<=2,0,ROUND(I85-I103,0)) -> 0 | J105: =IF(ABS(J85-J103)<=5,0,ROUND(J85-J103,0)) -> 0 | K105: =IF(ABS(K85-K103)<=5,0,ROUND(K85-K103,0)) -> 0 | L105: =IF(ABS(L85-L103)<=5,0,ROUND(L85-L103,0)) -> 0 | M105: =IF(ABS(M85-M103)<=5,0,ROUND(M85-M103,0)) -> -2697293365 | N105: =IF(ABS(N85-N103)<=5,0,ROUND(N85-N103,0)) -> -2697293365 | O105: =IF(ABS(O85-O103)<=5,0,ROUND(O85-O103,0)) -> -2697293365 | P105: =IF(ABS(P85-P103)<=5,0,ROUND(P85-P103,0)) -> -2697293365 | Q105: =IF(ABS(Q85-Q103)<=5,0,ROUND(Q85-Q103,0)) -> -2697293365 | S105: =IF(ABS(S85-S103)<=5,0,ROUND(S85-S103,0)) -> -2697293365
B107: Capital de Trabajo — Balance y cuentas operativas (COP)
B109: Activos Corrientes Operativos
B110: CxC Clientes | E110: =E79 -> 1833296000 | F110: =F79 -> 1590540829 | G110: =G79 -> 1797557189 | H110: =H79 -> 1690589814 | I110: =I79 -> 1612589704 | J110: =J79 -> 1675346692 | K110: =K79 -> 1799431102 | L110: =L79 -> 1688457915 | ... Q110: =Q79 -> 5430005000 | S110: =Q110 -> 5430005000
B111: Inversiones | E111: =E80 -> 92028000 | F111: =F80 -> 92548595 | G111: =G80 -> 93008823 | H111: =H80 -> 93705293 | I111: =I80 -> 94574157 | J111: =J80 -> 175907394 | K111: =K80 -> 77569331 | L111: =L80 -> 78270032 | ... Q111: =Q80 -> 94574157 | S111: =Q111 -> 94574157
B112: Otros Deudores | E112: =E81 -> 3301925000 | F112: =F81 -> 3331745751 | G112: =G81 -> 3359507781 | H112: =H81 -> 3397894998 | I112: =I81 -> 3433020955 | J112: =J81 -> 3468917579 | K112: =K81 -> 3497856336 | L112: =L81 -> 3529697045 | ... Q112: =Q81 -> 3433020955 | S112: =Q112 -> 3433020955
B113: Total Activos Corrientes Op. | E113: =SUM(E110:E112) -> 5227249000 | F113: =SUM(F110:F112) -> 5014835175 | G113: =SUM(G110:G112) -> 5250073793 | H113: =SUM(H110:H112) -> 5182190105 | I113: =SUM(I110:I112) -> 5140184816 | J113: =SUM(J110:J112) -> 5320171665 | K113: =SUM(K110:K112) -> 5374856769 | L113: =SUM(L110:L112) -> 5296424992 | ... Q113: =SUM(Q110:Q112) -> 8957600112 | S113: =Q113 -> 8957600112
B115: Pasivos Corrientes Operativos
B116: CxP Proveedores | E116: =E89 -> 544703000 | F116: =F89 -> 502128241 | G116: =G89 -> 493782297 | H116: =H89 -> 571037565 | I116: =I89 -> 563841763 | J116: =J89 -> 502311050 | K116: =K89 -> 483390906 | L116: =L89 -> 403760304 | ... Q116: =Q89 -> 6.2842038e+08 | S116: =Q116 -> 6.2842038e+08
B117: Impuestos x Pagar | E117: =E90 -> 40077000 | F117: =F90 -> 14350080 | G117: =G90 -> 1791700 | H117: =H90 -> 25570584 | I117: =I90 -> 24496645 | J117: =J90 -> 22513416 | K117: =K90 -> 23325495 | L117: =L90 -> 19229474 | ... Q117: =Q90 -> 3.813394e+08 | S117: =Q117 -> 3.813394e+08
B118: Total Pasivos Corrientes Op. | E118: =SUM(E116:E117) -> 584780000 | F118: =SUM(F116:F117) -> 516478321 | G118: =SUM(G116:G117) -> 495573997 | H118: =SUM(H116:H117) -> 596608149 | I118: =SUM(I116:I117) -> 588338408 | J118: =SUM(J116:J117) -> 524824466 | K118: =SUM(K116:K117) -> 506716401 | L118: =SUM(L116:L117) -> 422989778 | ... Q118: =SUM(Q116:Q117) -> 1.0097598e+09 | S118: =Q118 -> 1.0097598e+09
B119: Capital de Trabajo Neto (incl. inversiones y otros deudores) | C119: =G119-F119 -> 256142942 | E119: =E113-E118 -> 4642469000 | F119: =F113-F118 -> 4498356854 | G119: =G113-G118 -> 4754499796 | H119: =H113-H118 -> 4585581956 | I119: =I113-I118 -> 4551846408 | J119: =J113-J118 -> 4795347199 | K119: =K113-K118 -> 4868140368 | L119: =L113-L118 -> 4873435214 | ... Q119: =Q113-Q118 -> 7.9478403e+09 | S119: =Q119 -> 7.9478403e+09
B121: Schedule PP&E / Activos Fijos (COP)
B123: PP&E Inicio de Periodo | E123: =E83 -> 209212000 | F123: =E126 -> 209212000 | G123: =F126 -> 216571954 | H123: =G126 -> 222840954 | I123: =H126 -> 223130002 | J123: =I126 -> 3433020955 | K123: =J126 -> 225975514 | L123: =K126 -> 225975514 | M123: =L126 -> 2.2956935e+08 | ... Q123: =P126 -> 2.4335561e+08 | S123: =F123 -> 209212000
B124: CapEx / Adiciones (Disposiciones) | E124: 0 | F124: =F126-F123-F125 -> 10846821 | G124: =G126-G123-G125 -> 9878532.6 | H124: 0 | I124: =I126-I123-I125 -> 3.2136098e+09 | J124: =J126-J123-J125 -> -3.1498284e+09 | K124: =K126-K123-K125 -> 3766258.6 | L124: =$E$30 -> 7360092 | M124: =$E$30 -> 7360092 | N124: =$E$30 -> 7360092 | O124: =$E$30 -> 7360092 | P124: =$E$30 -> 7360092 | Q124: =$E$30 -> 7360092 | S124: =SUM(F124:Q124) -> 1.3243353e+08
B125: (-) Depreciación | E125: 0 | F125: =-F123/$E$29 -> -3486866.7 | G125: =-G123/$E$29 -> -3609532.6 | H125: =-H123/$E$29 -> -3714015.9 | I125: =-I123/$E$29 -> -3718833.4 | J125: =-J123/$E$29 -> -57217016 | K125: =-K123/$E$29 -> -3766258.6 | L125: =-L123/$E$29 -> -3766258.6 | M125: =-M123/$E$29 -> -3826155.8 | ... Q125: =-Q123/$E$29 -> -4055926.8 | S125: =SUM(F125:Q125) -> -98988815
...

Sheet Consol. Pptos
B1: COCO Tecnologías — Consolidado Total de Presupuestos 2026
B2: Apila las 4 hojas fuente: Ppto Metas · Ppto Intnl · Ppto Consolidado · Datos Intnl. Valores linkeados a las hojas originales. | H2: Óptica | I2: Total COP | J2: Total USD
H3: Ppto Metas | I3: 16192037025 | J3: 4272305.3
B4: ▸ Salta a: | C4: 1. Ppto Metas | D4: 2. Ppto Intnl | E4: 3. Ppto Consolidado | F4: 4. Datos Intnl | H4: Ppto Intnl | I4: 1.2299661e+10 | J4: 3245293.1
H5: Ppto Consolidado | I5: 15238222885 | J5: 4020639.3
B7: 1. PPTO METAS — Escenario objetivo (incluye Enterprise CR 1M USD)
B9: Variables principales
B10: TRM | C10: =Inputs!$C$6 -> 3690 | D10: COP/USD
B11: MRR base abril asumido | C11: 800000000 | D11: COP
B12: Ingreso real enero | C12: 612247701 | D12: COP
B13: Ingreso real febrero | C13: 744218137 | D13: COP
B14: Ingreso real marzo | C14: 787041187 | D14: COP
B16: Metas 2026 (inputs USD) | C16: USD
B17: Ingreso acumulado (referencia) | C17: 2100000
B18: Churn (-) | C18: 315000
B19: Contracción (-) | C19: 42000
B20: One-off (imp. + interop.) | C20: 63000
B21: Logos nuevos (MRR) | C21: =SUM(C22:C26) -> 374000
B22: Siesa | C22: 50000
B23: Indigo | C23: 50000
B24: Weli | C24: 50000
B25: Menudeo | C25: 200000
B26: Clientes > 3mil citas | C26: 24000
B27: Innovación | C27: =SUM(C28:C31) -> 507000
B28: Campañas + bot 2.0 | C28: 300000
B29: COCO Pay | C29: 105000
B30: Cirugías | C30: 60000
B31: ChargeBee | C31: 42000
B32: Up/Cross Selling (NRR) | C32: =SUM(C33:C35) -> 220000
B33: Comfama | C33: 36000
B34: Maple | C34: 84000
B35: Otros | C35: 100000
B36: Enterprise (MRR) CR | C36: 1000000
B37: TOTAL | C37: =C17-C18-C19+C20+C21+C27+C32+C36 -> 3907000
B40: Proyección mensual COP — Ppto Metas
B41: Categoría | C41: Rubro | D41: Ene-26 | E41: 46079 | F41: 46107 | G41: Abr-26 | H41: 46168 | I41: 46199 | J41: 46229 | K41: Ago-26 | L41: 46291 | M41: 46321 | N41: 46352 | O41: Dic-26 | P41: Total 2026
B42: Actual | C42: Ingresos reales reportados | D42: =$C$12 -> 612247701 | E42: =$C$13 -> 744218137 | F42: =$C$14 -> 787041187 | G42: 0 | H42: 0 | I42: 0 | J42: 0 | K42: 0 | L42: 0 | M42: 0 | N42: 0 | O42: 0 | P42: =SUM(D42:O42) -> 2143507025
B43: Base recurrente | C43: MRR base (800M plano Abr-Dic) | D43: 0 | E43: 0 | F43: 0 | G43: =$C$11 -> 800000000 | H43: =$C$11 -> 800000000 | I43: =$C$11 -> 800000000 | J43: =$C$11 -> 800000000 | K43: =$C$11 -> 800000000 | L43: =$C$11 -> 800000000 | M43: =$C$11 -> 800000000 | N43: =$C$11 -> 800000000 | O43: =$C$11 -> 800000000 | P43: =SUM(D43:O43) -> 7200000000
B44: Logos nuevos (MRR) | C44: Subtotal logos nuevos | D44: =SUM(D45:D49) -> 0 | E44: =SUM(E45:E49) -> 0 | F44: =SUM(F45:F49) -> 0 | G44: =SUM(G45:G49) -> 30668000 | H44: =SUM(H45:H49) -> 61336000 | I44: =SUM(I45:I49) -> 92004000 | J44: =SUM(J45:J49) -> 122672000 | K44: =SUM(K45:K49) -> 153340000 | ... O44: =SUM(O45:O49) -> 276012000 | P44: =SUM(D44:O44) -> 1380060000
B45: Logos nuevos | C45: Siesa | D45: 0 | E45: 0 | F45: 0 | G45: =$C$22*$C$10*1/45 -> 4100000 | H45: =$C$22*$C$10*2/45 -> 8200000 | I45: =$C$22*$C$10*3/45 -> 12300000 | J45: =$C$22*$C$10*4/45 -> 16400000 | K45: =$C$22*$C$10*5/45 -> 20500000 | L45: =$C$22*$C$10*6/45 -> 24600000 | M45: =$C$22*$C$10*7/45 -> 28700000 | N45: =$C$22*$C$10*8/45 -> 32800000 | O45: =$C$22*$C$10*9/45 -> 36900000 | P45: =SUM(D45:O45) -> 184500000
B46: Logos nuevos | C46: Indigo | D46: 0 | E46: 0 | F46: 0 | G46: =$C$23*$C$10*1/45 -> 4100000 | H46: =$C$23*$C$10*2/45 -> 8200000 | I46: =$C$23*$C$10*3/45 -> 12300000 | J46: =$C$23*$C$10*4/45 -> 16400000 | K46: =$C$23*$C$10*5/45 -> 20500000 | L46: =$C$23*$C$10*6/45 -> 24600000 | M46: =$C$23*$C$10*7/45 -> 28700000 | N46: =$C$23*$C$10*8/45 -> 32800000 | O46: =$C$23*$C$10*9/45 -> 36900000 | P46: =SUM(D46:O46) -> 184500000
B47: Logos nuevos | C47: Weli | D47: 0 | E47: 0 | F47: 0 | G47: =$C$24*$C$10*1/45 -> 4100000 | H47: =$C$24*$C$10*2/45 -> 8200000 | I47: =$C$24*$C$10*3/45 -> 12300000 | J47: =$C$24*$C$10*4/45 -> 16400000 | K47: =$C$24*$C$10*5/45 -> 20500000 | L47: =$C$24*$C$10*6/45 -> 24600000 | M47: =$C$24*$C$10*7/45 -> 28700000 | N47: =$C$24*$C$10*8/45 -> 32800000 | O47: =$C$24*$C$10*9/45 -> 36900000 | P47: =SUM(D47:O47) -> 184500000
B48: Logos nuevos | C48: Menudeo | D48: 0 | E48: 0 | F48: 0 | G48: =$C$25*$C$10*1/45 -> 16400000 | H48: =$C$25*$C$10*2/45 -> 32800000 | I48: =$C$25*$C$10*3/45 -> 49200000 | J48: =$C$25*$C$10*4/45 -> 65600000 | K48: =$C$25*$C$10*5/45 -> 82000000 | L48: =$C$25*$C$10*6/45 -> 98400000 | M48: =$C$25*$C$10*7/45 -> 114800000 | N48: =$C$25*$C$10*8/45 -> 131200000 | O48: =$C$25*$C$10*9/45 -> 147600000 | P48: =SUM(D48:O48) -> 738000000
B49: Logos nuevos | C49: Clientes > 3mil citas | D49: 0 | E49: 0 | F49: 0 | G49: =$C$26*$C$10*1/45 -> 1968000 | H49: =$C$26*$C$10*2/45 -> 3936000 | I49: =$C$26*$C$10*3/45 -> 5904000 | J49: =$C$26*$C$10*4/45 -> 7872000 | K49: =$C$26*$C$10*5/45 -> 9840000 | L49: =$C$26*$C$10*6/45 -> 11808000 | M49: =$C$26*$C$10*7/45 -> 13776000 | N49: =$C$26*$C$10*8/45 -> 15744000 | O49: =$C$26*$C$10*9/45 -> 17712000 | P49: =SUM(D49:O49) -> 88560000
B50: One-off | C50: One-off (imp. + interop.) | D50: 0 | E50: 0 | F50: 0 | G50: =$C$20*$C$10*1/45 -> 5166000 | H50: =$C$20*$C$10*2/45 -> 10332000 | I50: =$C$20*$C$10*3/45 -> 15498000 | J50: =$C$20*$C$10*4/45 -> 20664000 | K50: =$C$20*$C$10*5/45 -> 25830000 | L50: =$C$20*$C$10*6/45 -> 30996000 | M50: =$C$20*$C$10*7/45 -> 36162000 | N50: =$C$20*$C$10*8/45 -> 41328000 | O50: =$C$20*$C$10*9/45 -> 46494000 | P50: =SUM(D50:O50) -> 232470000
B51: Innovación | C51: Subtotal innovación | D51: =SUM(D52:D55) -> 0 | E51: =SUM(E52:E55) -> 0 | F51: =SUM(F52:F55) -> 0 | G51: =SUM(G52:G55) -> 0 | H51: =SUM(H52:H55) -> 0 | I51: =SUM(I52:I55) -> 66815357 | J51: =SUM(J52:J55) -> 1.3363071e+08 | K51: =SUM(K52:K55) -> 2.0044607e+08 | ... O51: =SUM(O52:O55) -> 467707500 | P51: =SUM(D51:O51) -> 1870830000
B52: Innovación | C52: Campañas + bot 2.0 | D52: 0 | E52: 0 | F52: 0 | G52: 0 | H52: 0 | I52: =$C$28*$C$10*1/28 -> 39535714 | J52: =$C$28*$C$10*2/28 -> 79071429 | K52: =$C$28*$C$10*3/28 -> 1.1860714e+08 | L52: =$C$28*$C$10*4/28 -> 1.5814286e+08 | M52: =$C$28*$C$10*5/28 -> 1.9767857e+08 | N52: =$C$28*$C$10*6/28 -> 2.3721429e+08 | O52: =$C$28*$C$10*7/28 -> 276750000 | P52: =SUM(D52:O52) -> 1107000000
B53: Innovación | C53: COCO Pay | D53: 0 | E53: 0 | F53: 0 | G53: 0 | H53: 0 | I53: =$C$29*$C$10*1/28 -> 13837500 | J53: =$C$29*$C$10*2/28 -> 27675000 | K53: =$C$29*$C$10*3/28 -> 41512500 | L53: =$C$29*$C$10*4/28 -> 55350000 | M53: =$C$29*$C$10*5/28 -> 69187500 | N53: =$C$29*$C$10*6/28 -> 83025000 | O53: =$C$29*$C$10*7/28 -> 96862500 | P53: =SUM(D53:O53) -> 387450000
B54: Innovación | C54: Cirugías | D54: 0 | E54: 0 | F54: 0 | G54: 0 | H54: 0 | I54: =$C$30*$C$10*1/28 -> 7907142.9 | J54: =$C$30*$C$10*2/28 -> 15814286 | K54: =$C$30*$C$10*3/28 -> 23721429 | L54: =$C$30*$C$10*4/28 -> 31628571 | M54: =$C$30*$C$10*5/28 -> 39535714 | N54: =$C$30*$C$10*6/28 -> 47442857 | O54: =$C$30*$C$10*7/28 -> 55350000 | P54: =SUM(D54:O54) -> 221400000
B55: Innovación | C55: ChargeBee | D55: 0 | E55: 0 | F55: 0 | G55: 0 | H55: 0 | I55: =$C$31*$C$10*1/28 -> 5535000 | J55: =$C$31*$C$10*2/28 -> 11070000 | K55: =$C$31*$C$10*3/28 -> 16605000 | L55: =$C$31*$C$10*4/28 -> 22140000 | M55: =$C$31*$C$10*5/28 -> 27675000 | N55: =$C$31*$C$10*6/28 -> 33210000 | O55: =$C$31*$C$10*7/28 -> 38745000 | P55: =SUM(D55:O55) -> 154980000
B56: Up/Cross Selling (NRR) | C56: Subtotal up/cross selling | D56: =SUM(D57:D59) -> 0 | E56: =SUM(E57:E59) -> 0 | F56: =SUM(F57:F59) -> 0 | G56: =SUM(G57:G59) -> 18040000 | H56: =SUM(H57:H59) -> 36080000 | I56: =SUM(I57:I59) -> 54120000 | J56: =SUM(J57:J59) -> 72160000 | K56: =SUM(K57:K59) -> 90200000 | ... O56: =SUM(O57:O59) -> 162360000 | P56: =SUM(D56:O56) -> 811800000
B57: Up/Cross | C57: Comfama | D57: 0 | E57: 0 | F57: 0 | G57: =$C$33*$C$10*1/45 -> 2952000 | H57: =$C$33*$C$10*2/45 -> 5904000 | I57: =$C$33*$C$10*3/45 -> 8856000 | J57: =$C$33*$C$10*4/45 -> 11808000 | K57: =$C$33*$C$10*5/45 -> 14760000 | L57: =$C$33*$C$10*6/45 -> 17712000 | M57: =$C$33*$C$10*7/45 -> 20664000 | N57: =$C$33*$C$10*8/45 -> 23616000 | O57: =$C$33*$C$10*9/45 -> 26568000 | P57: =SUM(D57:O57) -> 132840000
B58: Up/Cross | C58: Maple | D58: 0 | E58: 0 | F58: 0 | G58: =$C$34*$C$10*1/45 -> 6888000 | H58: =$C$34*$C$10*2/45 -> 13776000 | I58: =$C$34*$C$10*3/45 -> 20664000 | J58: =$C$34*$C$10*4/45 -> 27552000 | K58: =$C$34*$C$10*5/45 -> 34440000 | L58: =$C$34*$C$10*6/45 -> 41328000 | M58: =$C$34*$C$10*7/45 -> 48216000 | N58: =$C$34*$C$10*8/45 -> 55104000 | O58: =$C$34*$C$10*9/45 -> 61992000 | P58: =SUM(D58:O58) -> 309960000
B59: Up/Cross | C59: Otros | D59: 0 | E59: 0 | F59: 0 | G59: =$C$35*$C$10*1/45 -> 8200000 | H59: =$C$35*$C$10*2/45 -> 16400000 | I59: =$C$35*$C$10*3/45 -> 24600000 | J59: =$C$35*$C$10*4/45 -> 32800000 | K59: =$C$35*$C$10*5/45 -> 41000000 | L59: =$C$35*$C$10*6/45 -> 49200000 | M59: =$C$35*$C$10*7/45 -> 57400000 | N59: =$C$35*$C$10*8/45 -> 65600000 | O59: =$C$35*$C$10*9/45 -> 73800000 | P59: =SUM(D59:O59) -> 369000000
B60: Enterprise | C60: Enterprise (MRR) CR | D60: 0 | E60: 0 | F60: 0 | G60: =$C$36*$C$10*1/45 -> 82000000 | H60: =$C$36*$C$10*2/45 -> 164000000 | I60: =$C$36*$C$10*3/45 -> 246000000 | J60: =$C$36*$C$10*4/45 -> 328000000 | K60: =$C$36*$C$10*5/45 -> 410000000 | L60: =$C$36*$C$10*6/45 -> 492000000 | M60: =$C$36*$C$10*7/45 -> 574000000 | N60: =$C$36*$C$10*8/45 -> 656000000 | O60: =$C$36*$C$10*9/45 -> 738000000 | P60: =SUM(D60:O60) -> 3690000000
B61: Ajustes | C61: Churn (-) | D61: 0 | E61: 0 | F61: 0 | G61: =-$C$18*$C$10*1/45 -> -25830000 | H61: =-$C$18*$C$10*2/45 -> -51660000 | I61: =-$C$18*$C$10*3/45 -> -77490000 | J61: =-$C$18*$C$10*4/45 -> -103320000 | K61: =-$C$18*$C$10*5/45 -> -129150000 | L61: =-$C$18*$C$10*6/45 -> -154980000 | M61: =-$C$18*$C$10*7/45 -> -180810000 | N61: =-$C$18*$C$10*8/45 -> -206640000 | O61: =-$C$18*$C$10*9/45 -> -232470000 | P61: =SUM(D61:O61) -> -1162350000
B62: Ajustes | C62: Contracción (-) | D62: 0 | E62: 0 | F62: 0 | G62: =-$C$19*$C$10*1/45 -> -3444000 | H62: =-$C$19*$C$10*2/45 -> -6888000 | I62: =-$C$19*$C$10*3/45 -> -10332000 | J62: =-$C$19*$C$10*4/45 -> -13776000 | K62: =-$C$19*$C$10*5/45 -> -17220000 | L62: =-$C$19*$C$10*6/45 -> -20664000 | M62: =-$C$19*$C$10*7/45 -> -24108000 | N62: =-$C$19*$C$10*8/45 -> -27552000 | O62: =-$C$19*$C$10*9/45 -> -30996000 | P62: =SUM(D62:O62) -> -154980000
B63: Total | C63: Total ingresos | D63: =D42+D43+D44+D50+D51+D56+D60+D61+D62 -> 612247701 | E63: =E42+E43+E44+E50+E51+E56+E60+E61+E62 -> 744218137 | F63: =F42+F43+F44+F50+F51+F56+F60+F61+F62 -> 787041187 | G63: =G42+G43+G44+G50+G51+G56+G60+G61+G62 -> 906600000 | H63: =H42+H43+H44+H50+H51+H56+H60+H61+H62 -> 1013200000 | I63: =I42+I43+I44+I50+I51+I56+I60+I61+I62 -> 1.1866154e+09 | J63: =J42+J43+J44+J50+J51+J56+J60+J61+J62 -> 1.3600307e+09 | K63: =K42+K43+K44+K50+K51+K56+K60+K61+K62 -> 1.5334461e+09 | ... O63: =O42+O43+O44+O50+O51+O56+O60+O61+O62 -> 2227107500 | P63: =SUM(D63:O63) -> 16011337025
B65: Proyección mensual USD equivalente — Ppto Metas
B66: Categoría | C66: Rubro | D66: Ene-26 | E66: 46079 | F66: 46107 | G66: Abr-26 | H66: 46168 | I66: 46199 | J66: 46229 | K66: Ago-26 | L66: 46291 | M66: 46321 | N66: 46352 | O66: Dic-26 | P66: Total 2026
B92: 2. PPTO INTNL — Proyección con embudo USD ponderado por probabilidad
B94: Variables principales | G94: Supuestos USD por trimestre | H94: Monto USD | I94: Probabilidad | J94: Distribución | L94: Supuestos COP | M94: Monto | N94: Unidad | O94: Distribución
B95: TRM | C95: =Inputs!$C$6 -> 3690 | D95: COP/USD | E95: Variable editable para convertir USD a COP. | G95: Embudo MRR Q2 | H95: 13569 | I95: 0.95 | J95: Equitativa Abr-Jun | L95: OCR mayo | M95: 16200000 | N95: COP | O95: Inicio en mayo.
B96: Probabilidad Q2 | C96: 0.95 | D96: % | E96: Aplica a embudo y cross-selling del Q2. | G96: Embudo one-off Q2 | H96: 17504 | I96: 0.95 | J96: Equitativa Abr-Jun | L96: OCR diciembre | M96: 54000000 | N96: COP | O96: Crecimiento lineal hasta diciembre.
B97: Probabilidad Q3 | C97: 0.3 | D97: % | E97: Aplica a embudo y cross-selling del Q3. | G97: Embudo MRR Q3 | H97: 58173 | I97: 0.3 | J97: Equitativa Jul-Sep | L97: Campañas Q3 | M97: 85000000 | N97: COP | O97: Equitativa Jul-Sep.
B98: Probabilidad Q4 | C98: 0.3 | D98: % | E98: Aplica al embudo del Q4. | G98: Embudo one-off Q3 | H98: 87624 | I98: 0.3 | J98: Equitativa Jul-Sep | L98: Campañas Q4 | M98: 191000000 | N98: COP | O98: Equitativa Oct-Dic.
B99: One-off facturado marzo a restar | C99: 108666880 | D99: COP | G99: Embudo MRR Q4 | H99: 140577 | I99: 0.3 | J99: Equitativa Oct-Dic | L99: Ingresos reales enero | M99: 612247701 | N99: COP | O99: Dato suministrado por el usuario.
B100: Ingreso real marzo reportado | C100: 787041187 | D100: COP | G100: Embudo one-off Q4 | H100: 171076 | I100: 0.3 | J100: Equitativa Oct-Dic | L100: Ingresos reales febrero | M100: 744218137 | N100: COP | O100: Dato suministrado por el usuario.
B101: MRR mínimo estimado abril | C101: 678374307 | D101: COP | G101: Cross-selling MRR Q2 | H101: 3567 | I101: 0.95 | J101: Equitativa Abr-Jun
G102: Cross-selling one-off Q2 | H102: 3125 | I102: 0.95 | J102: Equitativa Abr-Jun
G103: Cross-selling MRR Q3 | H103: 1500 | I103: 0.3 | J103: Equitativa Jul-Sep
G104: Cross-selling one-off Q3 | H104: 0 | I104: 0.3 | J104: Equitativa Jul-Sep
G105: Upselling MRR | H105: 0 | I105: N/A | J105: Sin ingresos incluidos.
G106: Upselling one-off | H106: 0 | I106: N/A | J106: Sin ingresos incluidos.
B108: Proyección mensual COP — Ppto Intnl
B109: Categoría | C109: Rubro | D109: Ene-26 | E109: 46079 | F109: 46107 | G109: Abr-26 | H109: 46168 | I109: 46199 | J109: 46229 | K109: Ago-26 | L109: 46291 | M109: 46321 | N109: 46352 | O109: Dic-26 | P109: Total 2026
B110: Actual | C110: Ingresos reales reportados | D110: =$M$99 -> 612247701 | E110: =$M$100 -> 744218137 | F110: =$C$100 -> 787041187 | G110: 0 | H110: 0 | I110: 0 | J110: 0 | K110: 0 | L110: 0 | M110: 0 | N110: 0 | O110: 0 | P110: =SUM(D110:O110) -> 2143507025
B111: Base recurrente | C111: MRR base mínimo estimado | D111: 0 | E111: 0 | F111: 0 | G111: =$C$101 -> 678374307 | H111: =$C$101 -> 678374307 | I111: =$C$101 -> 678374307 | J111: =$C$101 -> 678374307 | K111: =$C$101 -> 678374307 | L111: =$C$101 -> 678374307 | M111: =$C$101 -> 678374307 | N111: =$C$101 -> 678374307 | O111: =$C$101 -> 678374307 | P111: =SUM(D111:O111) -> 6105368763
B112: Internacional | C112: MRR internacional | D112: 0 | E112: 0 | F112: 0 | G112: 0 | H112: 0 | I112: =$C$236*$C$95 -> 15376230 | J112: =$C$237*$C$95 -> 15376230 | K112: =$C$238*$C$95 -> 450180000 | L112: =$C$239*$C$95 -> 450180000 | M112: =$C$240*$C$95 -> 450180000 | N112: =$C$241*$C$95 -> 450180000 | O112: =$C$242*$C$95 -> 450180000 | P112: =SUM(D112:O112) -> 2281652460
B113: Internacional | C113: One-off internacional | D113: 0 | E113: 0 | F113: 0 | G113: 0 | H113: =$D$235*$C$95 -> 479700000 | I113: 0 | J113: 0 | K113: 0 | L113: 0 | M113: 0 | N113: 0 | O113: 0 | P113: =SUM(D113:O113) -> 479700000
B114: Embudo USD | C114: Embudo MRR ponderado | D114: 0 | E114: 0 | F114: 0 | G114: =$H$95*$I$95*$C$95/3 -> 15855376 | H114: =$H$95*$I$95*$C$95/3 -> 15855376 | I114: =$H$95*$I$95*$C$95/3 -> 15855376 | J114: =$H$97*$I$97*$C$95/3 -> 21465837 | K114: =$H$97*$I$97*$C$95/3 -> 21465837 | L114: =$H$97*$I$97*$C$95/3 -> 21465837 | M114: =$H$99*$I$99*$C$95/3 -> 51872913 | N114: =$H$99*$I$99*$C$95/3 -> 51872913 | O114: =$H$99*$I$99*$C$95/3 -> 51872913 | P114: =SUM(D114:O114) -> 2.6758238e+08
B115: Embudo USD | C115: Embudo one-off ponderado | D115: 0 | E115: 0 | F115: 0 | G115: =$H$96*$I$96*$C$95/3 -> 20453424 | H115: =$H$96*$I$96*$C$95/3 -> 20453424 | I115: =$H$96*$I$96*$C$95/3 -> 20453424 | J115: =$H$98*$I$98*$C$95/3 -> 32333256 | K115: =$H$98*$I$98*$C$95/3 -> 32333256 | L115: =$H$98*$I$98*$C$95/3 -> 32333256 | M115: =$H$100*$I$100*$C$95/3 -> 63127044 | N115: =$H$100*$I$100*$C$95/3 -> 63127044 | O115: =$H$100*$I$100*$C$95/3 -> 63127044 | P115: =SUM(D115:O115) -> 347741172
B116: Cross-selling USD | C116: Cross-selling MRR ponderado | D116: 0 | E116: 0 | F116: 0 | G116: =$H$101*$I$101*$C$95/3 -> 4168039.5 | H116: =$H$101*$I$101*$C$95/3 -> 4168039.5 | I116: =$H$101*$I$101*$C$95/3 -> 4168039.5 | J116: =$H$103*$I$103*$C$95/3 -> 553500 | K116: =$H$103*$I$103*$C$95/3 -> 553500 | L116: =$H$103*$I$103*$C$95/3 -> 553500 | M116: 0 | N116: 0 | O116: 0 | P116: =SUM(D116:O116) -> 14164618
B117: Cross-selling USD | C117: Cross-selling one-off ponderado | D117: 0 | E117: 0 | F117: 0 | G117: =$H$102*$I$102*$C$95/3 -> 3651562.5 | H117: =$H$102*$I$102*$C$95/3 -> 3651562.5 | I117: =$H$102*$I$102*$C$95/3 -> 3651562.5 | J117: =$H$104*$I$104*$C$95/3 -> 0 | K117: =$H$104*$I$104*$C$95/3 -> 0 | L117: =$H$104*$I$104*$C$95/3 -> 0 | M117: 0 | N117: 0 | O117: 0 | P117: =SUM(D117:O117) -> 10954688
B118: Upselling USD | C118: Upselling MRR ponderado | D118: 0 | E118: 0 | F118: 0 | G118: 0 | H118: 0 | I118: 0 | J118: 0 | K118: 0 | L118: 0 | M118: 0 | N118: 0 | O118: 0 | P118: =SUM(D118:O118) -> 0
B119: Upselling USD | C119: Upselling one-off ponderado | D119: 0 | E119: 0 | F119: 0 | G119: 0 | H119: 0 | I119: 0 | J119: 0 | K119: 0 | L119: 0 | M119: 0 | N119: 0 | O119: 0 | P119: =SUM(D119:O119) -> 0
B120: COP | C120: OCR | D120: 0 | E120: 0 | F120: 0 | G120: 0 | H120: =$M$95+(COLUMN()-COLUMN($H$120))*($M$96-$M$95)/7 -> 16200000 | I120: =$M$95+(COLUMN()-COLUMN($H$120))*($M$96-$M$95)/7 -> 21600000 | J120: =$M$95+(COLUMN()-COLUMN($H$120))*($M$96-$M$95)/7 -> 27000000 | K120: =$M$95+(COLUMN()-COLUMN($H$120))*($M$96-$M$95)/7 -> 32400000 | L120: =$M$95+(COLUMN()-COLUMN($H$120))*($M$96-$M$95)/7 -> 37800000 | M120: =$M$95+(COLUMN()-COLUMN($H$120))*($M$96-$M$95)/7 -> 43200000 | N120: =$M$95+(COLUMN()-COLUMN($H$120))*($M$96-$M$95)/7 -> 48600000 | O120: =$M$96 -> 54000000 | P120: =SUM(D120:O120) -> 280800000
B121: COP | C121: Campañas | D121: 0 | E121: 0 | F121: 0 | G121: 0 | H121: 0 | I121: 0 | J121: =$M$97/3 -> 28333333 | K121: =$M$97/3 -> 28333333 | L121: =$M$97/3 -> 28333333 | M121: =$M$98/3 -> 63666667 | N121: =$M$98/3 -> 63666667 | O121: =$M$98/3 -> 63666667 | P121: =SUM(D121:O121) -> 276000000
B122: Total | C122: Total ingresos | D122: =SUM(D110:D121) -> 612247701 | E122: =SUM(E110:E121) -> 744218137 | F122: =SUM(F110:F121) -> 787041187 | G122: =SUM(G110:G121) -> 7.2250271e+08 | H122: =SUM(H110:H121) -> 1.2184027e+09 | I122: =SUM(I110:I121) -> 7.5947894e+08 | J122: =SUM(J110:J121) -> 8.0343646e+08 | K122: =SUM(K110:K121) -> 1.2436402e+09 | ... O122: =SUM(O110:O121) -> 1.3612209e+09 | P122: =SUM(D122:O122) -> 1.2207471e+10
B126: Proyección mensual USD equivalente — Ppto Intnl
B127: Categoría | C127: Rubro | D127: Ene-26 | E127: 46079 | F127: 46107 | G127: Abr-26 | H127: 46168 | I127: 46199 | J127: 46229 | K127: Ago-26 | L127: 46291 | M127: 46321 | N127: 46352 | O127: Dic-26 | P127: Total 2026
B145: 3. PPTO CONSOLIDADO — MRR base + Metas (sin Enterprise) + Internacional
B147: Variables principales
B148: TRM | C148: =Inputs!$C$6 -> 3690 | D148: COP/USD
B149: MRR base abril asumido | C149: 800000000 | D149: COP
B150: Ingreso real enero | C150: 612247701 | D150: COP
B151: Ingreso real febrero | C151: 744218137 | D151: COP
B152: Ingreso real marzo | C152: 787041187 | D152: COP
B153: Ingreso real abril | C153: 750867662 | D153: COP
B154: Metas 2026 (inputs USD, sin Enterprise) | C154: USD
...

Sheet Informe Accionista
B2: COCO Tecnologías — Informe de Resultados Ene-Jul 2026 | L2: TRM Real / Ajustado: | M2: 3690
B3: Todas las cifras en USD. Presupuesto original Enero valorado a TRM 4,000 COP/USD (versión entregada en su momento). Real y presupuesto ajustado valorados a TRM 3,690 COP/USD. | L3: TRM Ppto Original Enero: | M3: 4000
B5: 1. RESUMEN EJECUTIVO — Acumulado Ene-Jul 2026 (USD) | L5: TRM: 3,690
C7: Ppto Ene-Jul | D7: Real | E7: Diferencia | F7: % Cumpl.
B8: Ingresos | C8: =SUM(C65:I65) -> 2462707 | D8: =SUM('Modelo Base'!F51:L51)/$M$2 -> 1396269.2 | E8: =D8-C8 -> -1066437.8 | F8: =IF(C8=0,0,D8/C8) -> 0.56696521
B9: Utilidad bruta | C9: =SUM(C65:I65)-SUM(C66:I66) -> 1683173 | D9: =SUM('Modelo Base'!F53:L53)/$M$2 -> 734311.64 | E9: =D9-C9 -> -948861.36 | F9: =IF(C9=0,0,D9/C9) -> 0.43626629
B10: EBITDA | C10: =C9-SUM(C68:I68)-SUM(C69:I69) -> 1070288 | D10: =SUM('Modelo Base'!F59:L59)/$M$2 -> 74806.554 | E10: =D10-C10 -> -995481.45 | F10: =IF(C10=0,0,D10/ABS(C10)) -> 0.069893855
B11: Utilidad neta | C11: =C10+SUM(C71:I71)-SUM(C72:I72)-SUM(C73:I73) -> 685267 | D11: =SUM('Modelo Base'!F70:L70)/$M$2 -> 66864.032 | E11: =D11-C11 -> -618402.97 | F11: =IF(C11=0,0,D11/ABS(C11)) -> 0.097573693
B12: Margen EBITDA | C12: =IF(C8=0,0,C10/C8) -> 0.43459819 | D12: =IF(D8=0,0,D10/D8) -> 0.053576026 | E12: =D12-C12 -> -0.38102216
B13: Margen neto | C13: =IF(C8=0,0,C11/C8) -> 0.27825762 | D13: =IF(D8=0,0,D11/D8) -> 0.047887637 | E13: =D13-C13 -> -0.23036999
B16: 2. CUMPLIMIENTO ACUMULADO vs PRESUPUESTO ORIGINAL ENERO (USD) | L16: TRM: 3,690
B17: Línea | C17: Ene | D17: Ene-Feb | E17: Ene-Mar | F17: Ene-Abr | G17: Ene-May | H17: Ene-Jun | I17: YTD (Ene-Jul)
B18: Ingresos | C18: =IF(C65=0,0,C30/C65) -> 0.89093596 | D18: =IF(SUM(C65:D65)=0,0,SUM(C30:D30)/SUM(C65:D65)) -> 0.68005527 | E18: =IF(SUM(C65:E65)=0,0,SUM(C30:E30)/SUM(C65:E65)) -> 0.62009092 | F18: =IF(SUM(C65:F65)=0,0,SUM(C30:F30)/SUM(C65:F65)) -> 0.60524203 | G18: =IF(SUM(C65:G65)=0,0,SUM(C30:G30)/SUM(C65:G65)) -> 0.5934866 | H18: =IF(SUM(C65:H65)=0,0,SUM(C30:H30)/SUM(C65:H65)) -> 0.58421101 | I18: =IF(SUM(C65:I65)=0,0,SUM(C30:I30)/SUM(C65:I65)) -> 0.56696521
B19: Utilidad bruta | C19: =IF(C65-C66=0,0,C32/(C65-C66)) -> 1.3527039 | D19: =IF(SUM(C65:D65)-SUM(C66:D66)=0,0,SUM(C32:D32)/(SUM(C65:D65)-SUM(C66:D66))) -> 0.66049498 | E19: =IF(SUM(C65:E65)-SUM(C66:E66)=0,0,SUM(C32:E32)/(SUM(C65:E65)-SUM(C66:E66))) -> 0.49731593 | F19: =IF(SUM(C65:F65)-SUM(C66:F66)=0,0,SUM(C32:F32)/(SUM(C65:F65)-SUM(C66:F66))) -> 0.47080754 | G19: =IF(SUM(C67:G67)=0,0,SUM(C32:G32)/ABS(SUM(C67:G67))) -> 0.46232538 | H19: =IF(SUM(C67:H67)=0,0,SUM(C32:H32)/ABS(SUM(C67:H67))) -> 0.45312671 | I19: =IF(SUM(C67:I67)=0,0,SUM(C32:I32)/ABS(SUM(C67:I67))) -> 0.43626629
B20: EBITDA | C20: =IF((C65-C66-C68-C69)=0,0,C37/ABS(C65-C66-C68-C69)) -> 1.4950411 | D20: =IF((SUM(C65:D65)-SUM(C66:D66)-SUM(C68:D68)-SUM(C69:D69))=0,0,SUM(C37:D37)/ABS(SUM(C65:D65)-SUM(C66:D66)-SUM(C68:D68)-SUM(C69:D69))) -> 0.22048252 | E20: =IF((SUM(C65:E65)-SUM(C66:E66)-SUM(C68:E68)-SUM(C69:E69))=0,0,SUM(C37:E37)/ABS(SUM(C65:E65)-SUM(C66:E66)-SUM(C68:E68)-SUM(C69:E69))) -> 0.074812117 | F20: =IF((SUM(C65:F65)-SUM(C66:F66)-SUM(C68:F68)-SUM(C69:F69))=0,0,SUM(C37:F37)/ABS(SUM(C65:F65)-SUM(C66:F66)-SUM(C68:F68)-SUM(C69:F69))) -> 0.053467049 | G20: =IF(SUM(C70:G70)=0,0,SUM(C37:G37)/ABS(SUM(C70:G70))) -> 0.081445042 | H20: =IF(SUM(C70:H70)=0,0,SUM(C37:H37)/ABS(SUM(C70:H70))) -> 0.075874676 | I20: =IF(SUM(C70:I70)=0,0,SUM(C37:I37)/ABS(SUM(C70:I70))) -> 0.069893855
B21: Utilidad neta | C21: =IF(C74=0,0,C41/ABS(C74)) -> 1.2372172 | D21: =IF(SUM(C74:D74)=0,0,SUM(C41:D41)/ABS(SUM(C74:D74))) -> 0.36903067 | E21: =IF(SUM(C74:E74)=0,0,SUM(C41:E41)/ABS(SUM(C74:E74))) -> 0.10090253 | F21: =IF(SUM(C74:F74)=0,0,SUM(C41:F41)/ABS(SUM(C74:F74))) -> 0.068615052 | G21: =IF(SUM(C74:G74)=0,0,SUM(C41:G41)/ABS(SUM(C74:G74))) -> 0.11386051 | H21: =IF(SUM(C74:H74)=0,0,SUM(C41:H41)/ABS(SUM(C74:H74))) -> 0.1068518 | I21: =IF(SUM(C74:I74)=0,0,SUM(C41:I41)/ABS(SUM(C74:I74))) -> 0.097573693
B25: 3. P&L MENSUAL 2026 — REAL ENE-JUL + PROYECCIÓN AGO-DIC (USD) | L25: TRM: 3,690
B26: Real Ene-Abr + proyección May-Dic actualizada del Modelo Base, valorado en USD a TRM 3,690.
B28: Línea | C28: Ene | D28: Feb | E28: Mar | F28: Abr | G28: May | H28: Jun | I28: Jul | J28: Ago | K28: Sep | L28: Oct | M28: Nov | N28: Dic | O28: Total 2026 | P28: YTD real Ene-Jul
B29: (Verde: real · Amarillo: proyectado)
B30: Ingresos | C30: ='Modelo Base'!F51/$M$2 -> 165920.79 | D30: ='Modelo Base'!G51/$M$2 -> 201685.13 | E30: ='Modelo Base'!H51/$M$2 -> 213290.29 | F30: ='Modelo Base'!I51/$M$2 -> 203487.17 | G30: ='Modelo Base'!J51/$M$2 -> 223987.74 | H30: ='Modelo Base'!K51/$M$2 -> 203645.88 | I30: ='Modelo Base'!L51/$M$2 -> 184252.18 | J30: ='Modelo Base'!M51/$M$2 -> 426456.93 | ... N30: ='Modelo Base'!Q51/$M$2 -> 525552.17 | O30: =SUM(C30:N30) -> 3776291.9 | P30: =SUM(C30:I30) -> 1396269.2
B31: Costo de ventas | C31: ='Modelo Base'!F52/$M$2 -> 64643.847 | D31: ='Modelo Base'!G52/$M$2 -> 93037.613 | E31: ='Modelo Base'!H52/$M$2 -> 123479.46 | F31: ='Modelo Base'!I52/$M$2 -> 102784.17 | G31: ='Modelo Base'!J52/$M$2 -> 96333.475 | H31: ='Modelo Base'!K52/$M$2 -> 94438.376 | I31: ='Modelo Base'!L52/$M$2 -> 87240.607 | J31: ='Modelo Base'!M52/$M$2 -> 95534.163 | ... N31: ='Modelo Base'!Q52/$M$2 -> 98252.092 | O31: =SUM(C31:N31) -> 1145064.2 | P31: =SUM(C31:I31) -> 661957.55
B32: Utilidad bruta | C32: ='Modelo Base'!F53/$M$2 -> 101276.94 | D32: ='Modelo Base'!G53/$M$2 -> 108647.52 | E32: ='Modelo Base'!H53/$M$2 -> 89810.836 | F32: ='Modelo Base'!I53/$M$2 -> 100703 | G32: ='Modelo Base'!J53/$M$2 -> 127654.26 | H32: ='Modelo Base'!K53/$M$2 -> 109207.51 | I32: ='Modelo Base'!L53/$M$2 -> 97011.576 | J32: ='Modelo Base'!M53/$M$2 -> 330922.77 | ... N32: ='Modelo Base'!Q53/$M$2 -> 427300.08 | O32: =SUM(C32:N32) -> 2631227.7 | P32: =SUM(C32:I32) -> 734311.64
B33: Margen bruto | C33: =IF(C30=0,0,C32/C30) -> 0.61039332 | D33: =IF(D30=0,0,D32/D30) -> 0.5386987 | E33: =IF(E30=0,0,E32/E30) -> 0.42107324 | F33: =IF(F30=0,0,F32/F30) -> 0.49488623 | G33: =IF(G30=0,0,G32/G30) -> 0.5699163 | H33: =IF(H30=0,0,H32/H30) -> 0.5362618 | I33: =IF(I30=0,0,I32/I30) -> 0.52651521 | J33: =IF(J30=0,0,J32/J30) -> 0.77598169 | ... P33: =IF(P30=0,0,P32/P30) -> 0.52590979
B34: Gastos admin | C34: ='Modelo Base'!F56/$M$2 -> 26754.047 | D34: ='Modelo Base'!G56/$M$2 -> 28626.957 | E34: ='Modelo Base'!H56/$M$2 -> 38431.4 | F34: ='Modelo Base'!I56/$M$2 -> 30970.43 | G34: ='Modelo Base'!J56/$M$2 -> 31655.508 | H34: ='Modelo Base'!K56/$M$2 -> 30430.54 | I34: ='Modelo Base'!L56/$M$2 -> 29250.066 | J34: ='Modelo Base'!M56/$M$2 -> 36693.761 | ... N34: ='Modelo Base'!Q56/$M$2 -> 36693.761 | O34: =SUM(C34:N34) -> 399587.76 | P34: =SUM(C34:I34) -> 216118.95
B35: Gastos ventas | C35: ='Modelo Base'!F57/$M$2 -> 35664.027 | D35: ='Modelo Base'!G57/$M$2 -> 47054.798 | E35: ='Modelo Base'!H57/$M$2 -> 37836.254 | F35: ='Modelo Base'!I57/$M$2 -> 35254.855 | G35: ='Modelo Base'!J57/$M$2 -> 32583.527 | H35: ='Modelo Base'!K57/$M$2 -> 39784.136 | I35: ='Modelo Base'!L57/$M$2 -> 31913.614 | J35: ='Modelo Base'!M57/$M$2 -> 62569.927 | ... N35: ='Modelo Base'!Q57/$M$2 -> 64407.701 | O35: =SUM(C35:N35) -> 576616.39 | P35: =SUM(C35:I35) -> 260091.21
B36: Gastos op/proyectos | C36: ='Modelo Base'!F58/$M$2 -> 19894.269 | D36: ='Modelo Base'!G58/$M$2 -> 20463.317 | E36: ='Modelo Base'!H58/$M$2 -> 19571.04 | F36: ='Modelo Base'!I58/$M$2 -> 33166.535 | G36: ='Modelo Base'!J58/$M$2 -> 32789.353 | H36: ='Modelo Base'!K58/$M$2 -> 29514.379 | I36: ='Modelo Base'!L58/$M$2 -> 27896.036 | J36: ='Modelo Base'!M58/$M$2 -> 30630.147 | ... N36: ='Modelo Base'!Q58/$M$2 -> 30630.147 | O36: =SUM(C36:N36) -> 336445.66 | P36: =SUM(C36:I36) -> 183294.93
B37: EBITDA | C37: ='Modelo Base'!F59/$M$2 -> 18964.596 | D37: ='Modelo Base'!G59/$M$2 -> 12502.448 | E37: ='Modelo Base'!H59/$M$2 -> -6027.8572 | F37: ='Modelo Base'!I59/$M$2 -> 1311.1794 | G37: ='Modelo Base'!J59/$M$2 -> 30625.874 | H37: ='Modelo Base'!K59/$M$2 -> 9478.4539 | I37: ='Modelo Base'!L59/$M$2 -> 7951.8596 | J37: ='Modelo Base'!M59/$M$2 -> 201028.93 | ... N37: ='Modelo Base'!Q59/$M$2 -> 295568.47 | O37: =SUM(C37:N37) -> 1318577.9 | P37: =SUM(C37:I37) -> 74806.554
B38: Margen EBITDA | C38: =IF(C30=0,0,C37/C30) -> 0.1142991 | D38: =IF(D30=0,0,D37/D30) -> 0.061989932 | E38: =IF(E30=0,0,E37/E30) -> -0.028261282 | F38: =IF(F30=0,0,F37/F30) -> 0.0064435482 | G38: =IF(G30=0,0,G37/G30) -> 0.13673014 | H38: =IF(H30=0,0,H37/H30) -> 0.046543803 | I38: =IF(I30=0,0,I37/I30) -> 0.043157479 | J38: =IF(J30=0,0,J37/J30) -> 0.47139328 | ... P38: =IF(P30=0,0,P37/P30) -> 0.053576026
B39: UAI | C39: ='Modelo Base'!F67/$M$2 -> 17204.742 | D39: ='Modelo Base'!G67/$M$2 -> 14647.402 | E39: ='Modelo Base'!H67/$M$2 -> -10281.303 | F39: ='Modelo Base'!I67/$M$2 -> 191.38293 | G39: ='Modelo Base'!J67/$M$2 -> 29369.91 | H39: ='Modelo Base'!K67/$M$2 -> 9036.2195 | I39: ='Modelo Base'!L67/$M$2 -> 6695.678 | J39: ='Modelo Base'!M67/$M$2 -> 200791.34 | ... N39: ='Modelo Base'!Q67/$M$2 -> 295268.61 | O39: =SUM(C39:N39) -> 1309290.4 | P39: =SUM(C39:I39) -> 66864.032
B40: Impuestos | C40: ='Modelo Base'!F69/$M$2 -> 0 | D40: ='Modelo Base'!G69/$M$2 -> 0 | E40: ='Modelo Base'!H69/$M$2 -> 0 | F40: ='Modelo Base'!I69/$M$2 -> 0 | G40: ='Modelo Base'!J69/$M$2 -> 0 | H40: ='Modelo Base'!K69/$M$2 -> 0 | I40: ='Modelo Base'!L69/$M$2 -> 0 | J40: ='Modelo Base'!M69/$M$2 -> 70276.969 | ... N40: ='Modelo Base'!Q69/$M$2 -> 103344.01 | O40: =SUM(C40:N40) -> 434849.24 | P40: =SUM(C40:I40) -> 0
B41: Utilidad neta | C41: ='Modelo Base'!F70/$M$2 -> 17204.742 | D41: ='Modelo Base'!G70/$M$2 -> 14647.402 | E41: ='Modelo Base'!H70/$M$2 -> -10281.303 | F41: ='Modelo Base'!I70/$M$2 -> 191.38293 | G41: ='Modelo Base'!J70/$M$2 -> 29369.91 | H41: ='Modelo Base'!K70/$M$2 -> 9036.2195 | I41: ='Modelo Base'!L70/$M$2 -> 6695.678 | J41: ='Modelo Base'!M70/$M$2 -> 130514.37 | ... N41: ='Modelo Base'!Q70/$M$2 -> 191924.59 | O41: =SUM(C41:N41) -> 874441.2 | P41: =SUM(C41:I41) -> 66864.032
B42: Margen neto | C42: =IF(C30=0,0,C41/C30) -> 0.1036925 | D42: =IF(D30=0,0,D41/D30) -> 0.072625098 | E42: =IF(E30=0,0,E41/E30) -> -0.048203331 | F42: =IF(F30=0,0,F41/F30) -> 0.00094051593 | G42: =IF(G30=0,0,G41/G30) -> 0.13112285 | H42: =IF(H30=0,0,H41/H30) -> 0.044372218 | I42: =IF(I30=0,0,I41/I30) -> 0.036339749 | J42: =IF(J30=0,0,J41/J30) -> 0.3060435 | ... P42: =IF(P30=0,0,P41/P30) -> 0.047887637
B44: 4. PRESUPUESTO NUEVO DE INGRESOS — Consolidado rubro por rubro en USD | L44: TRM: 3,690
B45: Presupuesto consolidado de ingresos 2026 (versión actualizada) desglosado por rubro: MRR base, logos nuevos, innovación, up/cross selling, internacional y ajustes. Cifras en USD a TRM 3,690 (vinculada a Inputs!C6). Datos fuente: hoja 'Consol. Pptos'. | L45: TRM aplicada: | M45: =Inputs!$C$6 -> 3690
B47: Rubro de ingreso | C47: Ene | D47: Feb | E47: Mar | F47: Abr | G47: May | H47: Jun | I47: Jul | J47: Ago | K47: Sep | L47: Oct | M47: Nov | N47: Dic | O47: Total 2026
B48: Ingresos reales reportados | C48: ='Consol. Pptos'!D206 -> 165920.79 | D48: ='Consol. Pptos'!E206 -> 201685.13 | E48: ='Consol. Pptos'!F206 -> 213290.29 | F48: ='Consol. Pptos'!G206 -> 203487.17 | G48: ='Consol. Pptos'!H206 -> 0 | H48: ='Consol. Pptos'!I206 -> 0 | I48: ='Consol. Pptos'!J206 -> 0 | J48: ='Consol. Pptos'!K206 -> 0 | ... O48: ='Consol. Pptos'!P206 -> 784383.38
B49: MRR base | C49: ='Consol. Pptos'!D207 -> 0 | D49: ='Consol. Pptos'!E207 -> 0 | E49: ='Consol. Pptos'!F207 -> 0 | F49: ='Consol. Pptos'!G207 -> 0 | G49: ='Consol. Pptos'!H207 -> 216802.17 | H49: ='Consol. Pptos'!I207 -> 216802.17 | I49: ='Consol. Pptos'!J207 -> 216802.17 | J49: ='Consol. Pptos'!K207 -> 216802.17 | ... O49: ='Consol. Pptos'!P207 -> 1734417.3
B50: Logos nuevos (MRR) | C50: ='Consol. Pptos'!D208 -> 0 | D50: ='Consol. Pptos'!E208 -> 0 | E50: ='Consol. Pptos'!F208 -> 0 | F50: ='Consol. Pptos'!G208 -> 0 | G50: ='Consol. Pptos'!H208 -> 16622.222 | H50: ='Consol. Pptos'!I208 -> 24933.333 | I50: ='Consol. Pptos'!J208 -> 33244.444 | J50: ='Consol. Pptos'!K208 -> 41555.556 | ... O50: ='Consol. Pptos'!P208 -> 365688.89
B51: One-off (implementación / interop.) | C51: ='Consol. Pptos'!D214 -> 0 | D51: ='Consol. Pptos'!E214 -> 0 | E51: ='Consol. Pptos'!F214 -> 0 | F51: ='Consol. Pptos'!G214 -> 0 | G51: ='Consol. Pptos'!H214 -> 2800 | H51: ='Consol. Pptos'!I214 -> 4200 | I51: ='Consol. Pptos'!J214 -> 5600 | J51: ='Consol. Pptos'!K214 -> 7000 | ... O51: ='Consol. Pptos'!P214 -> 61600
B52: Innovación | C52: ='Consol. Pptos'!D215 -> 0 | D52: ='Consol. Pptos'!E215 -> 0 | E52: ='Consol. Pptos'!F215 -> 0 | F52: ='Consol. Pptos'!G215 -> 0 | G52: ='Consol. Pptos'!H215 -> 0 | H52: ='Consol. Pptos'!I215 -> 18107.143 | I52: ='Consol. Pptos'!J215 -> 36214.286 | J52: ='Consol. Pptos'!K215 -> 54321.429 | ... O52: ='Consol. Pptos'!P215 -> 507000
B53: Up/Cross selling (NRR) | C53: ='Consol. Pptos'!D220 -> 0 | D53: ='Consol. Pptos'!E220 -> 0 | E53: ='Consol. Pptos'!F220 -> 0 | F53: ='Consol. Pptos'!G220 -> 0 | G53: ='Consol. Pptos'!H220 -> 9777.7778 | H53: ='Consol. Pptos'!I220 -> 14666.667 | I53: ='Consol. Pptos'!J220 -> 19555.556 | J53: ='Consol. Pptos'!K220 -> 24444.444 | ... O53: ='Consol. Pptos'!P220 -> 215111.11
B54: MRR Internacional | C54: ='Consol. Pptos'!D224 -> 0 | D54: ='Consol. Pptos'!E224 -> 0 | E54: ='Consol. Pptos'!F224 -> 0 | F54: ='Consol. Pptos'!G224 -> 0 | G54: ='Consol. Pptos'!H224 -> 0 | H54: ='Consol. Pptos'!I224 -> 4167 | I54: ='Consol. Pptos'!J224 -> 4167 | J54: ='Consol. Pptos'!K224 -> 122000 | ... O54: ='Consol. Pptos'!P224 -> 618334
B55: One-off Internacional | C55: ='Consol. Pptos'!D225 -> 0 | D55: ='Consol. Pptos'!E225 -> 0 | E55: ='Consol. Pptos'!F225 -> 0 | F55: ='Consol. Pptos'!G225 -> 0 | G55: ='Consol. Pptos'!H225 -> 130000 | H55: ='Consol. Pptos'!I225 -> 0 | I55: ='Consol. Pptos'!J225 -> 0 | J55: ='Consol. Pptos'!K225 -> 0 | ... O55: ='Consol. Pptos'!P225 -> 130000
B56: Churn (-) | C56: ='Consol. Pptos'!D243 -> 0 | D56: ='Consol. Pptos'!E243 -> 0 | E56: ='Consol. Pptos'!F243 -> 0 | F56: ='Consol. Pptos'!G243 -> 0 | G56: ='Consol. Pptos'!H243 -> 0 | H56: ='Consol. Pptos'!I243 -> 0 | I56: ='Consol. Pptos'!J243 -> 0 | J56: ='Consol. Pptos'!K243 -> 0 | ... L56: ='Consol. Pptos'!M243 -> 0 | M56: ='Consol. Pptos'!N226 -> -56000 | N56: ='Consol. Pptos'!O226 -> -63000 | O56: ='Consol. Pptos'!P226 -> -308000
B57: Contracción (-) | C57: ='Consol. Pptos'!D244 -> 0 | D57: ='Consol. Pptos'!E244 -> 0 | E57: ='Consol. Pptos'!F244 -> 0 | F57: ='Consol. Pptos'!G244 -> 0 | G57: ='Consol. Pptos'!H244 -> 0 | H57: ='Consol. Pptos'!I244 -> 0 | I57: ='Consol. Pptos'!J244 -> 0 | J57: ='Consol. Pptos'!K244 -> 0 | ... L57: ='Consol. Pptos'!M244 -> 0 | M57: ='Consol. Pptos'!N227 -> -7466.6667 | N57: ='Consol. Pptos'!O227 -> -8400 | O57: ='Consol. Pptos'!P227 -> -41066.667
B58: Total ingresos consolidado | C58: ='Consol. Pptos'!D228 -> 165920.79 | D58: ='Consol. Pptos'!E228 -> 201685.13 | E58: ='Consol. Pptos'!F228 -> 213290.29 | F58: ='Consol. Pptos'!G228 -> 203487.17 | G58: ='Consol. Pptos'!H228 -> 360135.5 | H58: ='Consol. Pptos'!I228 -> 259076.31 | I58: ='Consol. Pptos'!J228 -> 283850.12 | J58: ='Consol. Pptos'!K228 -> 426456.93 | ... O58: ='Consol. Pptos'!P228 -> 4067468.1
B61: 5. PRESUPUESTO ORIGINAL ENERO 2026 — P&L Completo en USD (referencia) | L61: TRM original: 4,000
B62: Versión original del presupuesto presentado en enero. Esta es la base histórica contra la cual se mide el desempeño en la sección 4.
B64: Línea | C64: Ene | D64: Feb | E64: Mar | F64: Abr | G64: May | H64: Jun | I64: Jul | J64: Ago | K64: Sep | L64: Oct | M64: Nov | N64: Dic | O64: Total 2026
B65: Ingresos | C65: 186232 | D65: 354321 | E65: 396239 | F65: 359191 | G65: 403080 | H65: 375559 | I65: 388085 | J65: 383589 | K65: 424263 | L65: 419954 | M65: 423217 | N65: 441996 | O65: =SUM(C65:N65) -> 4555726
B66: Costo de ventas | C66: 111362 | D66: 111362 | E66: 111362 | F66: 111362 | G66: 111362 | H66: 111362 | I66: 111362 | J66: 111362 | K66: 111362 | L66: 111362 | M66: 111362 | N66: 111362 | O66: =SUM(C66:N66) -> 1336344
B67: Utilidad bruta | C67: =C65-C66 -> 74870 | D67: =D65-D66 -> 242959 | E67: =E65-E66 -> 284877 | F67: =F65-F66 -> 247829 | G67: =G65-G66 -> 291718 | H67: =H65-H66 -> 264197 | I67: =I65-I66 -> 276723 | J67: =J65-J66 -> 272227 | ... N67: =N65-N66 -> 330634 | O67: =SUM(C67:N67) -> 3219382
B68: Gastos admin | C68: 33545 | D68: 33545 | E68: 33545 | F68: 33545 | G68: 33545 | H68: 33545 | I68: 33545 | J68: 33545 | K68: 33545 | L68: 33545 | M68: 33545 | N68: 33545 | O68: =SUM(C68:N68) -> 402540
B69: Gastos ventas | C69: 54010 | D69: 54010 | E69: 54010 | F69: 54010 | G69: 54010 | H69: 54010 | I69: 54010 | J69: 54010 | K69: 54010 | L69: 54010 | M69: 54010 | N69: 54010 | O69: =SUM(C69:N69) -> 648120
B70: EBITDA | C70: =C67-C68-C69 -> -12685 | D70: =D67-D68-D69 -> 155404 | E70: =E67-E68-E69 -> 197322 | F70: =F67-F68-F69 -> 160274 | G70: =G67-G68-G69 -> 204163 | H70: =H67-H68-H69 -> 176642 | I70: =I67-I68-I69 -> 189168 | J70: =J67-J68-J69 -> 184672 | ... N70: =N67-N68-N69 -> 243079 | O70: =SUM(C70:N70) -> 2168722
B71: Ingresos no operacionales | C71: 794 | D71: 794 | E71: 794 | F71: 794 | G71: 794 | H71: 794 | I71: 794 | J71: 794 | K71: 794 | L71: 794 | M71: 794 | N71: 794 | O71: =SUM(C71:N71) -> 9528
B72: Gastos no operacionales | C72: 2015 | D72: 2015 | E72: 2015 | F72: 2015 | G72: 2015 | H72: 2015 | I72: 2015 | J72: 2015 | K72: 2015 | L72: 2015 | M72: 2015 | N72: 2015 | O72: =SUM(C72:N72) -> 24180
B73: Impuestos | C73: 0 | D73: 53964 | E73: 68635 | F73: 55668 | G73: 71029 | H73: 61397 | I73: 65781 | J73: 64208 | K73: 78444 | L73: 76935 | M73: 78077 | N73: 84650 | O73: =SUM(C73:N73) -> 758788
B74: Utilidad neta | C74: =C70+C71-C72-C73 -> -13906 | D74: =D70+D71-D72-D73 -> 100219 | E74: =E70+E71-E72-E73 -> 127466 | F74: =F70+F71-F72-F73 -> 103385 | G74: =G70+G71-G72-G73 -> 131913 | H74: =H70+H71-H72-H73 -> 114024 | I74: =I70+I71-I72-I73 -> 122166 | J74: =J70+J71-J72-J73 -> 119243 | ... N74: =N70+N71-N72-N73 -> 157208 | O74: =SUM(C74:N74) -> 1395282
B76: Equivalencia: presupuesto original Enero valorado a la tasa actual (3,690 COP/USD)
B77: El presupuesto original Enero fue construido a TRM 4,000. A continuación se muestra cómo cambian las cifras anuales si se revaluaran a la tasa actual de 3,690 (las mismas COP a una tasa menor producen más USD).
B79: Línea | C79: Ppto Enero @ 4,000 | D79: Ppto Enero @ 3,690 | E79: Diferencia $ | F79: Diferencia %
B80: Ingresos | C80: =SUM(C65:N65) -> 4555726 | D80: =C80*$M$3/$M$2 -> 4938456.4 | E80: =D80-C80 -> 382730.37 | F80: =IF(C80=0,0,E80/C80) -> 0.08401084
B81: Utilidad bruta | C81: =SUM(C65:N65)-SUM(C66:N66) -> 3219382 | D81: =C81*$M$3/$M$2 -> 3489845 | E81: =D81-C81 -> 270462.99 | F81: =IF(C81=0,0,E81/C81) -> 0.08401084
B82: EBITDA | C82: =C81-SUM(C68:N68)-SUM(C69:N69) -> 2168722 | D82: =C82*$M$3/$M$2 -> 2350918.2 | E82: =D82-C82 -> 182196.16 | F82: =IF(C82=0,0,E82/C82) -> 0.08401084
B83: Utilidad neta | C83: =C82+SUM(C71:N71)-SUM(C72:N72)-SUM(C73:N73) -> 1395282 | D83: =C83*$M$3/$M$2 -> 1512500.8 | E83: =D83-C83 -> 117218.81 | F83: =IF(C83=0,0,E83/C83) -> 0.08401084
B94: COCO Tecnologías — Informe de Resultados Ene-Jul 2026 (COP) | L94: TRM Real / Ajustado: | M94: =M2 -> 3690
B95: Todas las cifras en COP. Presupuesto original Enero convertido a pesos con TRM 4,000 COP/USD. Real y presupuesto ajustado convertidos con TRM 3,690 COP/USD. | L95: TRM Ppto Original Enero: | M95: =M3 -> 4000
B97: 1. RESUMEN EJECUTIVO — Acumulado Ene-Jul 2026 (COP) | L97: TRM: 3,690
C99: Ppto Ene-Jul | D99: Real | E99: Diferencia | F99: % Cumpl.
B100: Ingresos | C100: =C8*$M$95 -> 9850828000 | D100: =D8*$M$94 -> 5152233299 | E100: =D100-C100 -> -4698594701 | F100: =IF(C100=0,0,D100/C100) -> 0.5230254
B101: Utilidad bruta | C101: =C9*$M$95 -> 6732692000 | D101: =D9*$M$94 -> 2709609952 | E101: =D101-C101 -> -4023082048 | F101: =IF(C101=0,0,D101/C101) -> 0.40245565
B102: EBITDA | C102: =C10*$M$95 -> 4281152000 | D102: =D10*$M$94 -> 276036184 | E102: =D102-C102 -> -4005115816 | F102: =IF(C102=0,0,D102/ABS(C102)) -> 0.064477081
B103: Utilidad neta | C103: =C11*$M$95 -> 2741068000 | D103: =D11*$M$94 -> 2.4672828e+08 | E103: =D103-C103 -> -2494339722 | F103: =IF(C103=0,0,D103/ABS(C103)) -> 0.090011732
B104: Margen EBITDA | C104: =IF(C100=0,0,C102/C100) -> 0.43459819 | D104: =IF(D100=0,0,D102/D100) -> 0.053576026 | E104: =D104-C104 -> -0.38102216
B105: Margen neto | C105: =IF(C100=0,0,C103/C100) -> 0.27825762 | D105: =IF(D100=0,0,D103/D100) -> 0.047887637 | E105: =D105-C105 -> -0.23036999
B108: 2. CUMPLIMIENTO ACUMULADO vs PRESUPUESTO ORIGINAL ENERO (COP) | L108: TRM: 3,690
B109: Línea | C109: Ene | D109: Ene-Feb | E109: Ene-Mar | F109: Ene-Abr | G109: Ene-May | H109: Ene-Jun | I109: YTD (Ene-Jul)
B110: Ingresos | C110: =IF(SUM($C$65:C65)=0,0,SUM($C122:C122)/(SUM($C$65:C65)*$M$95)) -> 0.82188843 | D110: =IF(SUM($C$65:D65)=0,0,SUM($C122:D122)/(SUM($C$65:D65)*$M$95)) -> 0.62735099 | E110: =IF(SUM($C$65:E65)=0,0,SUM($C122:E122)/(SUM($C$65:E65)*$M$95)) -> 0.57203387 | F110: =IF(SUM($C$65:F65)=0,0,SUM($C122:F122)/(SUM($C$65:F65)*$M$95)) -> 0.55833577 | G110: =IF(SUM($C$65:G65)=0,0,SUM($C122:G122)/(SUM($C$65:G65)*$M$95)) -> 0.54749139 | H110: =IF(SUM($C$65:H65)=0,0,SUM($C122:H122)/(SUM($C$65:H65)*$M$95)) -> 0.53893465 | I110: =IF(SUM($C$65:I65)=0,0,SUM($C122:I122)/(SUM($C$65:I65)*$M$95)) -> 0.5230254
B111: Utilidad bruta | C111: =IF(SUM($C$67:C67)=0,0,SUM($C124:C124)/(SUM($C$67:C67)*$M$95)) -> 1.2478693 | D111: =IF(SUM($C$67:D67)=0,0,SUM($C124:D124)/(SUM($C$67:D67)*$M$95)) -> 0.60930662 | E111: =IF(SUM($C$67:E67)=0,0,SUM($C124:E124)/(SUM($C$67:E67)*$M$95)) -> 0.45877395 | F111: =IF(SUM($C$67:F67)=0,0,SUM($C124:F124)/(SUM($C$67:F67)*$M$95)) -> 0.43431996 | G111: =IF(SUM($C$67:G67)=0,0,SUM($C124:G124)/(SUM($C$67:G67)*$M$95)) -> 0.42649517 | H111: =IF(SUM($C$67:H67)=0,0,SUM($C124:H124)/(SUM($C$67:H67)*$M$95)) -> 0.41800939 | I111: =IF(SUM($C$67:I67)=0,0,SUM($C124:I124)/(SUM($C$67:I67)*$M$95)) -> 0.40245565
B112: EBITDA | C112: =IF(SUM($C$70:C70)=0,0,SUM($C129:C129)/ABS(SUM($C$70:C70)*$M$95)) -> 1.3791754 | D112: =IF(SUM($C$70:D70)=0,0,SUM($C129:D129)/ABS(SUM($C$70:D70)*$M$95)) -> 0.20339512 | E112: =IF(SUM($C$70:E70)=0,0,SUM($C129:E129)/ABS(SUM($C$70:E70)*$M$95)) -> 0.069014178 | F112: =IF(SUM($C$70:F70)=0,0,SUM($C129:F129)/ABS(SUM($C$70:F70)*$M$95)) -> 0.049323352 | G112: =IF(SUM($C$70:G70)=0,0,SUM($C129:G129)/ABS(SUM($C$70:G70)*$M$95)) -> 0.075133051 | H112: =IF(SUM($C$70:H70)=0,0,SUM($C129:H129)/ABS(SUM($C$70:H70)*$M$95)) -> 0.069994388 | I112: =IF(SUM($C$70:I70)=0,0,SUM($C129:I129)/ABS(SUM($C$70:I70)*$M$95)) -> 0.064477081
B113: Utilidad neta | C113: =IF(SUM($C$74:C74)=0,0,SUM($C133:C133)/ABS(SUM($C$74:C74)*$M$95)) -> 1.1413328 | D113: =IF(SUM($C$74:D74)=0,0,SUM($C133:D133)/ABS(SUM($C$74:D74)*$M$95)) -> 0.34043079 | E113: =IF(SUM($C$74:E74)=0,0,SUM($C133:E133)/ABS(SUM($C$74:E74)*$M$95)) -> 0.093082582 | F113: =IF(SUM($C$74:F74)=0,0,SUM($C133:F133)/ABS(SUM($C$74:F74)*$M$95)) -> 0.063297386 | G113: =IF(SUM($C$74:G74)=0,0,SUM($C133:G133)/ABS(SUM($C$74:G74)*$M$95)) -> 0.10503632 | H113: =IF(SUM($C$74:H74)=0,0,SUM($C133:H133)/ABS(SUM($C$74:H74)*$M$95)) -> 0.098570783 | I113: =IF(SUM($C$74:I74)=0,0,SUM($C133:I133)/ABS(SUM($C$74:I74)*$M$95)) -> 0.090011732
B117: 3. P&L MENSUAL 2026 — REAL ENE-JUL + PROYECCIÓN AGO-DIC (COP) | L117: TRM: 3,690
B118: Real Ene-Abr + proyección May-Dic actualizada del Modelo Base, valorado en COP a TRM 3,690.
B120: Línea | C120: Ene | D120: Feb | E120: Mar | F120: Abr | G120: May | H120: Jun | I120: Jul | J120: Ago | K120: Sep | L120: Oct | M120: Nov | N120: Dic | O120: Total 2026 | P120: YTD real Ene-Jul
B121: (Verde: real · Amarillo: proyectado)
B122: Ingresos | C122: ='Modelo Base'!F51 -> 612247701 | D122: ='Modelo Base'!G51 -> 744218137 | E122: ='Modelo Base'!H51 -> 787041187 | F122: ='Modelo Base'!I51 -> 750867662 | G122: ='Modelo Base'!J51 -> 826514746 | H122: ='Modelo Base'!K51 -> 751453314 | I122: ='Modelo Base'!L51 -> 679890552 | J122: ='Modelo Base'!M51 -> 1.5736261e+09 | ... N122: ='Modelo Base'!Q51 -> 1939287500 | O122: =SUM(C122:N122) -> 1.3934517e+10 | P122: =SUM(C122:I122) -> 5152233299
B123: Costo de ventas | C123: ='Modelo Base'!F52 -> 238535794 | D123: ='Modelo Base'!G52 -> 343308791 | E123: ='Modelo Base'!H52 -> 455639201 | F123: ='Modelo Base'!I52 -> 379273594 | G123: ='Modelo Base'!J52 -> 355470523 | H123: ='Modelo Base'!K52 -> 348477606 | I123: ='Modelo Base'!L52 -> 321917838 | J123: ='Modelo Base'!M52 -> 3.5252106e+08 | ... N123: ='Modelo Base'!Q52 -> 3.6255022e+08 | O123: =SUM(C123:N123) -> 4.225287e+09 | P123: =SUM(C123:I123) -> 2442623347
B124: Utilidad bruta | C124: ='Modelo Base'!F53 -> 373711907 | D124: ='Modelo Base'!G53 -> 400909346 | E124: ='Modelo Base'!H53 -> 331401986 | F124: ='Modelo Base'!I53 -> 371594068 | G124: ='Modelo Base'!J53 -> 471044223 | H124: ='Modelo Base'!K53 -> 402975708 | I124: ='Modelo Base'!L53 -> 357972714 | J124: ='Modelo Base'!M53 -> 1.221105e+09 | ... N124: ='Modelo Base'!Q53 -> 1.5767373e+09 | O124: =SUM(C124:N124) -> 9.7092303e+09 | P124: =SUM(C124:I124) -> 2709609952
B125: Margen bruto | C125: =IF(C122=0,0,C124/C122) -> 0.61039332 | D125: =IF(D122=0,0,D124/D122) -> 0.5386987 | E125: =IF(E122=0,0,E124/E122) -> 0.42107324 | F125: =IF(F122=0,0,F124/F122) -> 0.49488623 | G125: =IF(G122=0,0,G124/G122) -> 0.5699163 | H125: =IF(H122=0,0,H124/H122) -> 0.5362618 | I125: =IF(I122=0,0,I124/I122) -> 0.52651521 | J125: =IF(J122=0,0,J124/J122) -> 0.77598169 | ... P125: =IF(P122=0,0,P124/P122) -> 0.52590979
B126: Gastos admin | C126: ='Modelo Base'!F56 -> 98722435 | D126: ='Modelo Base'!G56 -> 105633472 | E126: ='Modelo Base'!H56 -> 141811865 | F126: ='Modelo Base'!I56 -> 114280887 | G126: ='Modelo Base'!J56 -> 116808824 | H126: ='Modelo Base'!K56 -> 112288693 | I126: ='Modelo Base'!L56 -> 107932742 | J126: ='Modelo Base'!M56 -> 1.3539998e+08 | ... N126: ='Modelo Base'!Q56 -> 1.3539998e+08 | O126: =SUM(C126:N126) -> 1.4744788e+09 | P126: =SUM(C126:I126) -> 797478918
B127: Gastos ventas | C127: ='Modelo Base'!F57 -> 131600259 | D127: ='Modelo Base'!G57 -> 173632204 | E127: ='Modelo Base'!H57 -> 139615776 | F127: ='Modelo Base'!I57 -> 130090415 | G127: ='Modelo Base'!J57 -> 120233213 | H127: ='Modelo Base'!K57 -> 146803460 | I127: ='Modelo Base'!L57 -> 117761236 | J127: ='Modelo Base'!M57 -> 2.3088303e+08 | ... N127: ='Modelo Base'!Q57 -> 2.3766442e+08 | O127: =SUM(C127:N127) -> 2.1277145e+09 | P127: =SUM(C127:I127) -> 959736563
B128: Gastos op/proyectos | C128: ='Modelo Base'!F58 -> 73409852 | D128: ='Modelo Base'!G58 -> 75509638 | E128: ='Modelo Base'!H58 -> 72217138 | F128: ='Modelo Base'!I58 -> 122384514 | G128: ='Modelo Base'!J58 -> 120992711 | H128: ='Modelo Base'!K58 -> 108908060 | I128: ='Modelo Base'!L58 -> 102936374 | J128: ='Modelo Base'!M58 -> 1.1302524e+08 | ... N128: ='Modelo Base'!Q58 -> 1.1302524e+08 | O128: =SUM(C128:N128) -> 1.2414845e+09 | P128: =SUM(C128:I128) -> 676358287
B129: EBITDA | C129: ='Modelo Base'!F59 -> 69979361 | D129: ='Modelo Base'!G59 -> 46134032 | E129: ='Modelo Base'!H59 -> -22242793 | F129: ='Modelo Base'!I59 -> 4838252 | G129: ='Modelo Base'!J59 -> 113009475 | H129: ='Modelo Base'!K59 -> 34975495 | I129: ='Modelo Base'!L59 -> 29342362 | J129: ='Modelo Base'!M59 -> 7.4179676e+08 | ... N129: ='Modelo Base'!Q59 -> 1090647643 | O129: =SUM(C129:N129) -> 4.8655525e+09 | P129: =SUM(C129:I129) -> 276036184
B130: Margen EBITDA | C130: =IF(C122=0,0,C129/C122) -> 0.1142991 | D130: =IF(D122=0,0,D129/D122) -> 0.061989932 | E130: =IF(E122=0,0,E129/E122) -> -0.028261282 | F130: =IF(F122=0,0,F129/F122) -> 0.0064435482 | G130: =IF(G122=0,0,G129/G122) -> 0.13673014 | H130: =IF(H122=0,0,H129/H122) -> 0.046543803 | I130: =IF(I122=0,0,I129/I122) -> 0.043157479 | J130: =IF(J122=0,0,J129/J122) -> 0.47139328 | ... P130: =IF(P122=0,0,P129/P122) -> 0.053576026
B131: UAI | C131: ='Modelo Base'!F67 -> 63485497 | D131: ='Modelo Base'!G67 -> 54048915 | E131: ='Modelo Base'!H67 -> -37938007 | F131: ='Modelo Base'!I67 -> 706203 | G131: ='Modelo Base'!J67 -> 108374968 | H131: ='Modelo Base'!K67 -> 33343650 | I131: ='Modelo Base'!L67 -> 24707052 | J131: ='Modelo Base'!M67 -> 7.4092004e+08 | ... N131: ='Modelo Base'!Q67 -> 1.0895412e+09 | O131: =SUM(C131:N131) -> 4.8312817e+09 | P131: =SUM(C131:I131) -> 246728278
B132: Impuestos | C132: ='Modelo Base'!F69 -> 0 | D132: ='Modelo Base'!G69 -> 0 | E132: ='Modelo Base'!H69 -> 0 | F132: ='Modelo Base'!I69 -> 0 | G132: ='Modelo Base'!J69 -> 0 | H132: ='Modelo Base'!K69 -> 0 | I132: ='Modelo Base'!L69 -> 0 | J132: ='Modelo Base'!M69 -> 2.5932201e+08 | ... N132: ='Modelo Base'!Q69 -> 3.813394e+08 | O132: =SUM(C132:N132) -> 1.6045937e+09 | P132: =SUM(C132:I132) -> 0
B133: Utilidad neta | C133: ='Modelo Base'!F70 -> 63485497 | D133: ='Modelo Base'!G70 -> 54048915 | E133: ='Modelo Base'!H70 -> -37938007 | F133: ='Modelo Base'!I70 -> 706203 | G133: ='Modelo Base'!J70 -> 108374968 | H133: ='Modelo Base'!K70 -> 33343650 | I133: ='Modelo Base'!L70 -> 24707052 | J133: ='Modelo Base'!M70 -> 4.8159803e+08 | ... N133: ='Modelo Base'!Q70 -> 7.0820175e+08 | O133: =SUM(C133:N133) -> 3.226688e+09 | P133: =SUM(C133:I133) -> 246728278
B134: Margen neto | C134: =IF(C122=0,0,C133/C122) -> 0.1036925 | D134: =IF(D122=0,0,D133/D122) -> 0.072625098 | E134: =IF(E122=0,0,E133/E122) -> -0.048203331 | F134: =IF(F122=0,0,F133/F122) -> 0.00094051593 | G134: =IF(G122=0,0,G133/G122) -> 0.13112285 | H134: =IF(H122=0,0,H133/H122) -> 0.044372218 | I134: =IF(I122=0,0,I133/I122) -> 0.036339749 | J134: =IF(J122=0,0,J133/J122) -> 0.3060435 | ... P134: =IF(P122=0,0,P133/P122) -> 0.047887637
...

Sheet Consolidado 
C1: ABRIL | H1: Mayo | M1: Junio
B2: Estado de Resultados Consolidado por Subsidiaria | C2: USA | D2: PERU | E2: COSTA RICA | F2: COLOMBIA | G2: CONSOLIDADO | H2: USA | I2: PERU | J2: COSTA RICA | K2: COLOMBIA | L2: CONSOLIDADO | M2: USA | N2: PERU | O2: COSTA RICA | P2: COLOMBIA | Q2: CONSOLIDADO
B3: Estado de Resultados | C3: USD | D3: USD/PEN | E3: USD/USD | F3: COP/USD | G3: TOTAL USD | H3: USD | I3: USD/PEN | J3: USD/USD | K3: COP/USD | L3: TOTAL USD | M3: USD | N3: USD/PEN | O3: USD/USD | P3: COP/USD | Q3: TOTAL USD
D4: 0.29044438 | E4: 1 | F4: 3617.5187 | I4: 0.29112082 | J4: 1 | K4: 3714.021 | N4: 0.29368576 | O4: 1 | P4: 3505.2683
A6: 417005 | B6: Ingresos Ordinarios | C6: 17616.15 | D6: =10291.03*D4 -> 2988.9718 | E6: 0 | F6: =(3092211433-197836746)/F4 -> 800099.45 | G6: =SUM(C6:F6) -> 820704.57 | H6: 9716.45 | I6: =2813.98*I4 -> 819.20815 | J6: 0 | K6: =826514745/K4 -> 222539.06 | L6: =SUM(H6:K6) -> 233074.72 | M6: 5664.45 | N6: =6202.25*N4 -> 1821.5125 | P6: =751453313.77/P4 -> 214378.26 | Q6: =SUM(M6:P6) -> 221864.22
A7: 420505 | B7: Otros Ingresos | E7: 0 | F7: =4795548/F4 -> 1325.6457 | G7: =SUM(C7:F7) -> 1325.6457 | H7: 0 | I7: 0 | J7: 0 | K7: =1366337/K4 -> 367.88618 | L7: =SUM(H7:K7) -> 367.88618 | M7: 0 | N7: 0 | O7: 0 | P7: =3920248.31/P4 -> 1118.3875 | Q7: =SUM(M7:P7) -> 1118.3875
A9: 613005 | B9: Costo del servicio | F9: =1416757380/F4 -> 391637.89 | G9: =SUM(C9:F9) -> 391637.89 | H9: 0 | I9: =15383.22*I4 -> 4478.3755 | J9: 0 | K9: =355470522.84/K4 -> 95710.424 | L9: =SUM(H9:K9) -> 100188.8 | M9: 0 | N9: 0 | O9: 0 | P9: =348477606.57/P4 -> 99415.387 | Q9: =SUM(M9:P9) -> 99415.387
A11: 51 | B11: Administracion | C11: -46372.59 | E11: -17320.22 | F11: =460448659/F4 -> 127283.01 | G11: =C11+D22+E11+F11 -> 70573.178 | H11: 21616.02 | I11: 0 | J11: 57.8 | K11: =116808823.84/K4 -> 31450.771 | L11: =H11+I22+J11+K11 -> 59194.222 | M11: 25433.27 | N11: 0 | O11: 71.99 | P11: =112288693.6/P4 -> 32034.265 | Q11: =M11+N22+O11+P11 -> 59705.889
A12: 52 | B12: Ventas | F12: =574938654/F4 -> 158931.77 | G12: =SUM(C12:F12) -> 158931.77 | H12: 4000 | I12: 0 | J12: 1300 | K12: =120233213.2/K4 -> 32372.788 | L12: =SUM(H12:K12) -> 37672.788 | M12: 2535 | N12: 0 | O12: 2550 | P12: =146803459.79/P4 -> 41880.805 | Q12: =SUM(M12:P12) -> 46965.805
A13: 75 | B13: Operacion | F13: =343521142/F4 -> 94960.434 | G13: =SUM(C13:F13) -> 94960.434 | H13: 7500 | I13: 0 | J13: 0 | K13: =120992711/K4 -> 32577.283 | L13: =SUM(H13:K13) -> 40077.283 | M13: 0 | N13: 0 | O13: 0 | P13: =108908060.06/P4 -> 31069.821 | Q13: =SUM(M13:P13) -> 31069.821
A15: 530505 | B15: Gastos financieros | D15: =-318.95*D4 -> -92.637235 | E15: 267.92 | F15: =23201792/F4 -> 6413.7311 | G15: =SUM(C15:F15) -> 6589.0139 | H15: 0 | I15: =111*I4 -> 32.31441 | J15: 36 | K15: =6000847.89/K4 -> 1615.7281 | L15: =SUM(H15:K15) -> 1684.0425 | M15: 0 | N15: =40.75*N4 -> 11.967695 | O15: 50 | P15: =5552093.3/P4 -> 1583.9282 | Q15: =SUM(M15:P15) -> 1645.8959
A17: 360501 | B17: Utilidad | C17: =C6+C11 -> -28756.44 | D17: =D6-D15 -> 3081.6091 | E17: =E6+E7+E11+E15 -> -17052.3 | F17: =F6+F7-F9-F11-F12-F13-F15 -> 22198.257 | G17: =C17+D17+E17+F17 -> -20528.874 | H17: =H6+H7-H9-H11-H12-H13-H15 -> -23399.57 | I17: =I6+I7-I9-I11-I12-I13-I15 -> -3691.4818 | J17: =J6+J7-J9-J11-J12-J13-J15 -> -1393.8 | K17: =K6+K7-K9-K11-K12-K13-K15 -> 29179.955 | L17: =H17+I17+J17+K17 -> 695.1028 | M17: =M6+M7-M9-M11-M12-M13-M15 -> -22303.82 | N17: =N6+N7-N9-N11-N12-N13-N15 -> 1809.5448 | O17: =O6+O7-O9-O11-O12-O13-O15 -> -2671.99 | P17: =P6+P7-P9-P11-P12-P13-P15 -> 9512.4383 | Q17: =M17+N17+O17+P17 -> -13653.827
B19: PROINNOVATE — Perú | D19: PROINNOVATE | I19: PROINNOVATE | N19: PROINNOVATE | Q19: PROINNOVATE
B20: Ingresos / desembolsos | D20: =79069.02*D4 -> 22965.152 | I20: 0 | N20: 1380.84 | Q20: =D20+I20+N20 -> 24345.992
B22: Gastos asociados | D22: =24042.4*D4 -> 6982.98 | I22: =20849.18*I4 -> 6069.6303 | N22: =7376.47*N4 -> 2166.3642 | Q22: =D22+I22+N22 -> 15218.974
B23: Resultado neto | D23: =D20-D22 -> 15982.173 | I23: =I20-I22 -> -6069.6303 | N23: =N20-N22 -> -785.52417 | Q23: =D23+I23+N23 -> 9127.0181
B28: P&G CONSOLIDADO — ACUMULADO A JUNIO 2026 (USD)
B29: Período: 1 de enero al 30 de junio de 2026 | Sin balance general
B32: Tasa promedio junio 2026 (moneda local por USD) | C32: 1 | D32: =1/$N$4 -> 3.405 | E32: 1 | F32: =$P$4 -> 3505.2683
C33: USD/USD | D33: PEN/USD | E33: USD/USD | F33: COP/USD
B34: Concepto | C34: Estados Unidos (USD) | D34: Perú (USD) | E34: Costa Rica (USD) | F34: Colombia (USD) | G34: Consolidado (USD) | H34: %
B35: Servicios de software / ingresos brutos | C35: 32997.05 | D35: =15930.57/$D$32 -> 4678.5815 | E35: 0 | F35: =4903610738/$F$32 -> 1398925.9 | G35: =SUM(C35:F35) -> 1436601.6
B36: Devoluciones | C36: 0 | D36: 0 | E36: 0 | F36: =-431267991/$F$32 -> -123034.23 | G36: =SUM(C36:F36) -> -123034.23
B37: Ingresos operacionales netos | C37: =SUM(C35:C36) -> 32997.05 | D37: =SUM(D35:D36) -> 4678.5815 | E37: =SUM(E35:E36) -> 0 | F37: =SUM(F35:F36) -> 1275891.7 | G37: =SUM(G35:G36) -> 1313567.3 | H37: =G37/$G$37 -> 1
B38: Costo del servicio | C38: 0 | D38: 0 | E38: 0 | F38: =2120705509/$F$32 -> 605005.18 | G38: =SUM(C38:F38) -> 605005.18 | H38: =G38/$G$37 -> 0.46058178
B39: Utilidad bruta | C39: =C37-C38 -> 32997.05 | D39: =D37-D38 -> 4678.5815 | E39: =E37-E38 -> 0 | F39: =F37-F38 -> 670886.51 | G39: =G37-G38 -> 708562.14 | H39: =G39/$G$37 -> 0.53941822
B40: Gastos de administración | C40: 30735.95 | D40: =5446.95/$D$32 -> 1599.6916 | E40: 21792.38 | F40: =689546176/$F$32 -> 196717.09 | G40: =SUM(C40:F40) -> 250845.11 | H40: =G40/$G$37 -> 0.19096479
B41: Gastos de ventas | C41: 25215.98 | D41: 0 | E41: 0 | F41: =841975327/$F$32 -> 240202.82 | G41: =SUM(C41:F41) -> 265418.8 | H41: =G41/$G$37 -> 0.20205953
B42: Gastos de operación / proyectos | C42: 11500 | D42: =57192.5/$D$32 -> 16796.623 | E42: 0 | F42: =573421913/$F$32 -> 163588.59 | G42: =SUM(C42:F42) -> 191885.22 | H42: =G42/$G$37 -> 0.14607947
B43: Resultado de la operación | C43: =C39-C40-C41-C42 -> -34454.88 | D43: =D39-D40-D41-D42 -> -13717.733 | E43: =E39-E40-E41-E42 -> -21792.38 | F43: =F39-F40-F41-F42 -> 70378.013 | G43: =G39-G40-G41-G42 -> 413.02073 | H43: =G43/$G$37 -> 0.00031442677
B44: Ingresos no operacionales | C44: 0 | D44: 0 | E44: 0 | F44: =10082136/$F$32 -> 2876.2808 | G44: =SUM(C44:F44) -> 2876.2808 | H44: =G44/$G$37 -> 0.0021896714
B45: Gastos financieros | C45: 15 | D45: =903.21/$D$32 -> 265.25991 | E45: 206 | F45: =34754732/$F$32 -> 9914.999 | G45: =SUM(C45:F45) -> 10401.259 | H45: =G45/$G$37 -> 0.0079183295
B46: Ajuste de redondeo del estado fuente | C46: 0 | D46: 0 | E46: 0 | F46: =-1/$F$32 -> -0.00028528486 | G46: =SUM(C46:F46) -> -0.00028528486 | H46: =G46/$G$37 -> -2.1718328e-10
B47: Resultado antes de impuestos | C47: =C43+C44-C45+C46 -> -34469.88 | D47: =D43+D44-D45+D46 -> -13982.993 | E47: =E43+E44-E45+E46 -> -21998.38 | F47: =F43+F44-F45+F46 -> 63339.295 | G47: =G43+G44-G45+G46 -> -7111.9577 | H47: =G47/$G$37 -> -0.0054142316
B48: Impuesto de renta | C48: 0 | D48: 0 | E48: 0 | F48: 0 | G48: =SUM(C48:F48) -> 0 | H48: =G48/$G$37 -> 0
B49: UTILIDAD / (PÉRDIDA) NETA | C49: =C47-C48 -> -34469.88 | D49: =D47-D48 -> -13982.993 | E49: =E47-E48 -> -21998.38 | F49: =F47-F48 -> 63339.295 | G49: =G47-G48 -> -7111.9577 | H49: =G49/$G$37 -> -0.0054142316
B51: NOTAS Y CRITERIOS DEL P&G CONSOLIDADO
B52: 1. Período | C52: Cifras acumuladas del 1 de enero al 30 de junio de 2026.
B53: 2. Tasas de conversión | C53: Estados Unidos y Costa Rica: 1.0000 USD/USD; Perú: 3.4050 PEN/USD; Colombia: 3,505.2683 COP/USD.
B54: 3. Estados Unidos | C54: Clasificación gerencial en base caja. Administración incluye nómina, impuestos, seguros, telecomunicaciones, software, equipos/oficina y servicios profesionales.
B55: 4. Gastos de ventas USA | C55: Incluye marketing, eventos, comidas de negocio, viajes, comisiones, regalos a clientes y representación.
B56: 5. Operación / proyectos USA | C56: Incluye Vitally por USD 7,500 y Georgia Tech Online por USD 4,000.
B57: 6. Exclusiones USA | C57: Se excluyen transferencias a Perú y Costa Rica, pagos de Mercury Credit, depósitos reembolsables, transacciones fallidas, cashbacks e ingresos de Stripe.
B58: 7. Perú | C58: La cuenta 5110 se clasificó como administración; cuentas 5210, 5235, 5255 y 5295 como operación/proyectos; cuenta 5305 como gasto financiero.
B59: 8. Costa Rica | C59: La cuenta 51 se clasificó como administración y la cuenta 53 como gasto financiero. No se reportaron ingresos operacionales ni costo del servicio.
B60: 9. Colombia | C60: Se utilizó el Estado de Resultados acumulado a junio. Se mantuvo un ajuste de redondeo de COP 1 para conciliar la utilidad reportada.
B61: 10. Revisión pendiente | C61: Validar antes del cierre definitivo la capitalización de equipos, el tratamiento del pago IRS y la naturaleza contable de Georgia Tech.
B63: DETALLE GASTOS ESTADOS UNIDOS — ACUMULADO A JUNIO 2026
B64: Grupo consolidado | C64: USD | D64: Tratamiento
B65: Gastos de administración | C65: =$C$40 -> 30735.95 | D65: Nómina, impuestos, seguros, telecom, software, oficina y servicios profesionales
B66: Gastos de ventas | C66: =$C$41 -> 25215.98 | D66: Marketing, eventos, comidas, viajes, comisiones y representación
B67: Gastos de operación / proyectos | C67: =$C$42 -> 11500 | D67: Vitally y Georgia Tech Online
B68: Gastos financieros | C68: =$C$45 -> 15 | D68: Comisión por transferencia internacional
B69: TOTAL GASTOS USA | C69: =SUM(C65:C68) -> 67466.93
B75: P&G CONSOLIDADO — ACUMULADO A JUNIO 2026 (USD)
B76: Período: 1 de enero al 30 de junio de 2026 |
B77: Tasa promedio junio 2026 (moneda local por USD) | C77: 1 | D77: 3.405 | E77: 1 | F77: 3505.2683
C78: USD/USD | D78: PEN/USD | E78: USD/USD | F78: COP/USD
B79: Concepto | C79: Estados Unidos (USD) | D79: Perú (USD) | E79: Costa Rica (USD) | F79: Colombia (USD) | G79: Consolidado (USD)
B80: Servicios de software / ingresos brutos | C80: 32997.05 | D80: 4678.5815 | E80: 0 | F80: 1398925.9 | G80: 1436601.6
B81: Devoluciones | C81: 0 | D81: 0 | E81: 0 | F81: -123034.23 | G81: -123034.23
B82: Ingresos operacionales netos | C82: 32997.05 | D82: 4678.5815 | E82: 0 | F82: 1275891.7 | G82: 1313567.3
B83: Costo del servicio | C83: 0 | D83: 0 | E83: 0 | F83: 605005.18 | G83: 605005.18
B84: Utilidad bruta | C84: 32997.05 | D84: 4678.5815 | E84: 0 | F84: 670886.51 | G84: 708562.14
B85: Gastos de administración | C85: 30735.95 | D85: 1599.6916 | E85: 21792.38 | F85: 196717.09 | G85: 250845.11
B86: Gastos de ventas | C86: 25215.98 | D86: 0 | E86: 0 | F86: 240202.82 | G86: 265418.8
B87: Gastos de operación / proyectos | C87: 11500 | D87: 16796.623 | E87: 0 | F87: 163588.59 | G87: 191885.22
B88: Resultado de la operación | C88: -34454.88 | D88: -13717.733 | E88: -21792.38 | F88: 70378.013 | G88: 413.02073
B89: Ingresos no operacionales | C89: 0 | D89: 0 | E89: 0 | F89: 2876.2808 | G89: 2876.2808
B90: Gastos financieros | C90: 15 | D90: 265.25991 | E90: 206 | F90: 9914.999 | G90: 10401.259
B91: Resultado antes de impuestos | C91: -34469.88 | D91: -13982.993 | E91: -21998.38 | F91: 63339.295 | G91: -7111.9577
... B93: UTILIDAD / (PÉRDIDA) NETA | C93: -34469.88 | D93: -13982.993 | E93: -21998.38 | F93: 63339.295 | G93: -7111.9577
B100: Concepto | C100: Movimiento (USD miles) | D100: Aumento | E100: Disminución | F100: Total
B101: Utilidad bruta | C101: =ROUND($G$39/1000,0) -> 709 | D101: 0 | E101: 0 | F101: =$G$84 -> 708562.14
B102: Gastos administración | C102: =-ROUND($G$40/1000,0) -> -251 | D102: 0 | E102: =$G$85 -> 250845.11 | F102: 0
B103: Gastos ventas | C103: =-ROUND($G$41/1000,0) -> -265 | D103: 0 | E103: =$G$87 -> 191885.22 | F103: 0
B104: Operación / proyectos | C104: =-ROUND($G$42/1000,0) -> -192 | D104: 0 | E104: =$G$88 -> 413.02073 | F104: 0
B105: Otros ingresos | C105: =ROUND($G$44/1000,0) -> 3 | D105: 0 | E105: =$G$89 -> 2876.2808 | F105: 0
B106: Gastos financieros | C106: =-ROUND($G$45/1000,0) -> -10 | D106: =$G$91 -> -7111.9577 | E106: 0 | F106: 0
B107: Utilidad neta | C107: =ROUND($G$49/1000,0) -> -7 | D107: 0 | E107: =$G$92 -> 0 | F107: 0
B108: Utilidad neta | C108: 0 | D108: 0 | E108: 0 | F108: =$G$96 -> 0
B140: PUENTE A UTILIDAD NETA — ACUMULADO A JUNIO 2026
B141: P&G consolidado | USD | Cifras aproximadas en miles
C143: $709K | E143: ($251K) | G143: ($265K) | I143: ($192K) | K143: +$3K | M143: ($10K) | O143: ($7K)
C157: UTILIDAD BRUTA | E157: GASTOS ADMIN. | G157: GASTOS VENTAS | I157: OPERACIÓN / PROYECTOS | K157: OTROS INGRESOS | M157: GASTOS FINANCIEROS | O157: UTILIDAD NETA
C161: ■ Positivo | E161: ■ Gastos / disminuciones | I161: ■ Otros ingresos | M161: Fuente: P&G consolidado a junio 2026

Sheet Dashboard Gráficos
A1: DASHBOARD FINANCIERO 2026
A2: Modelo Base | COP millones | Reales Ene-Jul 2026 (EF julio) · proyección Ago-Dic | X2: Métrica | Y2: =TEXT(DATE(2026,COLUMN()-COLUMN($X$2),1),"mmm-aa") -> ene-26 | Z2: =TEXT(DATE(2026,COLUMN()-COLUMN($X$2),1),"mmm-aa") -> feb-26 | AA2: =TEXT(DATE(2026,COLUMN()-COLUMN($X$2),1),"mmm-aa") -> mar-26 | AB2: =TEXT(DATE(2026,COLUMN()-COLUMN($X$2),1),"mmm-aa") -> abr-26 | AC2: =TEXT(DATE(2026,COLUMN()-COLUMN($X$2),1),"mmm-aa") -> may-26 | AD2: =TEXT(DATE(2026,COLUMN()-COLUMN($X$2),1),"mmm-aa") -> jun-26 | AE2: =TEXT(DATE(2026,COLUMN()-COLUMN($X$2),1),"mmm-aa") -> jul-26 | AF2: =TEXT(DATE(2026,COLUMN()-COLUMN($X$2),1),"mmm-aa") -> ago-26 | ... AJ2: =TEXT(DATE(2026,COLUMN()-COLUMN($X$2),1),"mmm-aa") -> dic-26
X3: Ingresos | Y3: ='Modelo Base'!F192/1000000 -> 612.2477 | Z3: ='Modelo Base'!G192/1000000 -> 744.21814 | AA3: ='Modelo Base'!H192/1000000 -> 787.04119 | AB3: ='Modelo Base'!I192/1000000 -> 750.86766 | AC3: ='Modelo Base'!J192/1000000 -> 826.51475 | AD3: ='Modelo Base'!K192/1000000 -> 751.45331 | AE3: ='Modelo Base'!L192/1000000 -> 679.89055 | AF3: ='Modelo Base'!M192/1000000 -> 1573.6261 | ... AJ3: ='Modelo Base'!Q192/1000000 -> 1939.2875
A4: INGRESOS 2026 (COP MM) | D4: EBITDA 2026 (COP MM) | G4: MARGEN EBITDA (%) | J4: UTILIDAD NETA (COP MM) | M4: CAJA FINAL DIC (COP MM) | P4: DÉFICIT MÁXIMO (COP MM) | X4: EBITDA | Y4: ='Modelo Base'!F193/1000000 -> 69.979361 | Z4: ='Modelo Base'!G193/1000000 -> 46.134032 | AA4: ='Modelo Base'!H193/1000000 -> -22.242793 | AB4: ='Modelo Base'!I193/1000000 -> 4.838252 | AC4: ='Modelo Base'!J193/1000000 -> 113.00947 | AD4: ='Modelo Base'!K193/1000000 -> 34.975495 | AE4: ='Modelo Base'!L193/1000000 -> 29.342362 | AF4: ='Modelo Base'!M193/1000000 -> 741.79676 | ... AJ4: ='Modelo Base'!Q193/1000000 -> 1090.6476
A5: ='Modelo Base'!S192/1000000 -> 13934.517 | D5: ='Modelo Base'!S193/1000000 -> 4865.5525 | G5: =IF('Modelo Base'!S192=0,0,'Modelo Base'!S193/'Modelo Base'!S192) -> 0.34917266 | J5: ='Modelo Base'!S196/1000000 -> 3226.688 | M5: ='Modelo Base'!Q186/1000000 -> -17.640842 | P5: ='Modelo Base'!S452/1000000 -> 1849.4543 | X5: Utilidad Neta | Y5: ='Modelo Base'!F196/1000000 -> 63.485497 | Z5: ='Modelo Base'!G196/1000000 -> 54.048915 | AA5: ='Modelo Base'!H196/1000000 -> -37.938007 | AB5: ='Modelo Base'!I196/1000000 -> 0.706203 | AC5: ='Modelo Base'!J196/1000000 -> 108.37497 | AD5: ='Modelo Base'!K196/1000000 -> 33.34365 | AE5: ='Modelo Base'!L196/1000000 -> 24.707052 | AF5: ='Modelo Base'!M196/1000000 -> 481.59803 | ... AJ5: ='Modelo Base'!Q196/1000000 -> 708.20175
A8: RESULTADOS Y RENTABILIDAD | X8: Métrica | Y8: =TEXT(DATE(2026,COLUMN()-COLUMN($X$2),1),"mmm-aa") -> ene-26 | Z8: =TEXT(DATE(2026,COLUMN()-COLUMN($X$2),1),"mmm-aa") -> feb-26 | AA8: =TEXT(DATE(2026,COLUMN()-COLUMN($X$2),1),"mmm-aa") -> mar-26 | AB8: =TEXT(DATE(2026,COLUMN()-COLUMN($X$2),1),"mmm-aa") -> abr-26 | AC8: =TEXT(DATE(2026,COLUMN()-COLUMN($X$2),1),"mmm-aa") -> may-26 | AD8: =TEXT(DATE(2026,COLUMN()-COLUMN($X$2),1),"mmm-aa") -> jun-26 | AE8: =TEXT(DATE(2026,COLUMN()-COLUMN($X$2),1),"mmm-aa") -> jul-26 | AF8: =TEXT(DATE(2026,COLUMN()-COLUMN($X$2),1),"mmm-aa") -> ago-26 | ... AJ8: =TEXT(DATE(2026,COLUMN()-COLUMN($X$2),1),"mmm-aa") -> dic-26
X9: Margen Bruto | Y9: ='Modelo Base'!F54 -> 0.61039332 | Z9: ='Modelo Base'!G54 -> 0.5386987 | AA9: ='Modelo Base'!H54 -> 0.42107324 | AB9: ='Modelo Base'!I54 -> 0.49488623 | AC9: ='Modelo Base'!J54 -> 0.5699163 | AD9: ='Modelo Base'!K54 -> 0.5362618 | AE9: ='Modelo Base'!L54 -> 0.52651521 | AF9: ='Modelo Base'!M54 -> 0.77598169 | ... AJ9: ='Modelo Base'!Q54 -> 0.81304978
X10: Margen EBITDA | Y10: ='Modelo Base'!F194 -> 0.1142991 | Z10: ='Modelo Base'!G194 -> 0.061989932 | AA10: ='Modelo Base'!H194 -> -0.028261282 | AB10: ='Modelo Base'!I194 -> 0.0064435482 | AC10: ='Modelo Base'!J194 -> 0.13673014 | AD10: ='Modelo Base'!K194 -> 0.046543803 | AE10: ='Modelo Base'!L194 -> 0.043157479 | AF10: ='Modelo Base'!M194 -> 0.47139328 | ... AJ10: ='Modelo Base'!Q194 -> 0.56239606
X11: Margen Neto | Y11: ='Modelo Base'!F197 -> 0.1036925 | Z11: ='Modelo Base'!G197 -> 0.072625098 | AA11: ='Modelo Base'!H197 -> -0.048203331 | AB11: ='Modelo Base'!I197 -> 0.00094051593 | AC11: ='Modelo Base'!J197 -> 0.13112285 | AD11: ='Modelo Base'!K197 -> 0.044372218 | AE11: ='Modelo Base'!L197 -> 0.036339749 | AF11: ='Modelo Base'!M197 -> 0.3060435 | ... AJ11: ='Modelo Base'!Q197 -> 0.36518657
X14: Métrica | Y14: =TEXT(DATE(2026,COLUMN()-COLUMN($X$2),1),"mmm-aa") -> ene-26 | Z14: =TEXT(DATE(2026,COLUMN()-COLUMN($X$2),1),"mmm-aa") -> feb-26 | AA14: =TEXT(DATE(2026,COLUMN()-COLUMN($X$2),1),"mmm-aa") -> mar-26 | AB14: =TEXT(DATE(2026,COLUMN()-COLUMN($X$2),1),"mmm-aa") -> abr-26 | AC14: =TEXT(DATE(2026,COLUMN()-COLUMN($X$2),1),"mmm-aa") -> may-26 | AD14: =TEXT(DATE(2026,COLUMN()-COLUMN($X$2),1),"mmm-aa") -> jun-26 | AE14: =TEXT(DATE(2026,COLUMN()-COLUMN($X$2),1),"mmm-aa") -> jul-26 | AF14: =TEXT(DATE(2026,COLUMN()-COLUMN($X$2),1),"mmm-aa") -> ago-26 | ... AJ14: =TEXT(DATE(2026,COLUMN()-COLUMN($X$2),1),"mmm-aa") -> dic-26
X15: Operativo | Y15: ='Modelo Base'!F200/1000000 -> 254.49508 | Z15: ='Modelo Base'!G200/1000000 -> -267.33079 | AA15: ='Modelo Base'!H200/1000000 -> 51.916596 | AB15: ='Modelo Base'!I200/1000000 -> 89.724697 | AC15: ='Modelo Base'!J200/1000000 -> 39.321054 | AD15: ='Modelo Base'!K200/1000000 -> -105.08257 | AE15: ='Modelo Base'!L200/1000000 -> 55.719875 | AF15: ='Modelo Base'!M200/1000000 -> -1784.9022 | ... AJ15: ='Modelo Base'!Q200/1000000 -> 488.27045
X16: Inversión | Y16: ='Modelo Base'!F201/1000000 -> -7.880549 | Z16: ='Modelo Base'!G201/1000000 -> -6.729228 | AA16: ='Modelo Base'!H201/1000000 -> -0.985518 | AB16: ='Modelo Base'!I201/1000000 -> -3213.6098 | AC16: ='Modelo Base'!J201/1000000 -> 3149.8284 | AD16: ='Modelo Base'!K201/1000000 -> -3.7662586 | AE16: ='Modelo Base'!L201/1000000 -> -7.360092 | AF16: ='Modelo Base'!M201/1000000 -> -7.360092 | ... AJ16: ='Modelo Base'!Q201/1000000 -> -7.360092
X17: Financiamiento | Y17: ='Modelo Base'!F202/1000000 -> -17.231358 | Z17: ='Modelo Base'!G202/1000000 -> 5.694513 | AA17: ='Modelo Base'!H202/1000000 -> 23.825706 | AB17: ='Modelo Base'!I202/1000000 -> -649.70875 | AC17: ='Modelo Base'!J202/1000000 -> 643.92264 | AD17: ='Modelo Base'!K202/1000000 -> -17.16852 | AE17: ='Modelo Base'!L202/1000000 -> 21.272048 | AF17: ='Modelo Base'!M202/1000000 -> 2620.5152 | ... AJ17: ='Modelo Base'!Q202/1000000 -> 0
X18: Cambio Neto | Y18: ='Modelo Base'!F203/1000000 -> 229.38317 | Z18: ='Modelo Base'!G203/1000000 -> -268.3655 | AA18: ='Modelo Base'!H203/1000000 -> 74.756784 | AB18: ='Modelo Base'!I203/1000000 -> -3773.5938 | AC18: ='Modelo Base'!J203/1000000 -> 3833.0721 | AD18: ='Modelo Base'!K203/1000000 -> -126.01735 | AE18: ='Modelo Base'!L203/1000000 -> 69.631831 | AF18: ='Modelo Base'!M203/1000000 -> 828.25298 | ... AJ18: ='Modelo Base'!Q203/1000000 -> 480.91036
X21: Métrica | Y21: =TEXT(DATE(2026,COLUMN()-COLUMN($X$2),1),"mmm-aa") -> ene-26 | Z21: =TEXT(DATE(2026,COLUMN()-COLUMN($X$2),1),"mmm-aa") -> feb-26 | AA21: =TEXT(DATE(2026,COLUMN()-COLUMN($X$2),1),"mmm-aa") -> mar-26 | AB21: =TEXT(DATE(2026,COLUMN()-COLUMN($X$2),1),"mmm-aa") -> abr-26 | AC21: =TEXT(DATE(2026,COLUMN()-COLUMN($X$2),1),"mmm-aa") -> may-26 | AD21: =TEXT(DATE(2026,COLUMN()-COLUMN($X$2),1),"mmm-aa") -> jun-26 | AE21: =TEXT(DATE(2026,COLUMN()-COLUMN($X$2),1),"mmm-aa") -> jul-26 | AF21: =TEXT(DATE(2026,COLUMN()-COLUMN($X$2),1),"mmm-aa") -> ago-26 | ... AJ21: =TEXT(DATE(2026,COLUMN()-COLUMN($X$2),1),"mmm-aa") -> dic-26
X22: Caja Final | Y22: ='Modelo Base'!F186/1000000 -> 460.84217 | Z22: ='Modelo Base'!G186/1000000 -> 157.22912 | AA22: ='Modelo Base'!H186/1000000 -> 195.05832 | AB22: ='Modelo Base'!I186/1000000 -> 357.75716 | AC22: ='Modelo Base'!J186/1000000 -> 244.82235 | AD22: ='Modelo Base'!K186/1000000 -> 115.44136 | AE22: ='Modelo Base'!L186/1000000 -> 174.26693 | AF22: ='Modelo Base'!M186/1000000 -> -1617.9953 | ... AJ22: ='Modelo Base'!Q186/1000000 -> -17.640842
X23: Caja Mínima | Y23: ='Modelo Base'!F183/1000000 -> 231.459 | Z23: ='Modelo Base'!G183/1000000 -> 231.459 | AA23: ='Modelo Base'!H183/1000000 -> 231.459 | AB23: ='Modelo Base'!I183/1000000 -> 231.459 | AC23: ='Modelo Base'!J183/1000000 -> 231.459 | AD23: ='Modelo Base'!K183/1000000 -> 231.459 | AE23: ='Modelo Base'!L183/1000000 -> 231.459 | AF23: ='Modelo Base'!M183/1000000 -> 231.459 | ... AJ23: ='Modelo Base'!Q183/1000000 -> 231.459
X26: Escenario | Y26: =TEXT(DATE(2026,COLUMN()-COLUMN($X$26),1),"mmm-aa") -> ene-26 | Z26: =TEXT(DATE(2026,COLUMN()-COLUMN($X$26),1),"mmm-aa") -> feb-26 | AA26: =TEXT(DATE(2026,COLUMN()-COLUMN($X$26),1),"mmm-aa") -> mar-26 | AB26: =TEXT(DATE(2026,COLUMN()-COLUMN($X$26),1),"mmm-aa") -> abr-26 | AC26: =TEXT(DATE(2026,COLUMN()-COLUMN($X$26),1),"mmm-aa") -> may-26 | AD26: =TEXT(DATE(2026,COLUMN()-COLUMN($X$26),1),"mmm-aa") -> jun-26 | AE26: =TEXT(DATE(2026,COLUMN()-COLUMN($X$26),1),"mmm-aa") -> jul-26 | AF26: =TEXT(DATE(2026,COLUMN()-COLUMN($X$26),1),"mmm-aa") -> ago-26 | ... AJ26: =TEXT(DATE(2026,COLUMN()-COLUMN($X$26),1),"mmm-aa") -> dic-26
X27: Optimista | Y27: ='Modelo Base'!F21/1000000 -> 612.2477 | Z27: ='Modelo Base'!G21/1000000 -> 744.21814 | AA27: ='Modelo Base'!H21/1000000 -> 787.04119 | AB27: ='Modelo Base'!I21/1000000 -> 750.86766 | AC27: ='Modelo Base'!J21/1000000 -> 1013.2 | AD27: ='Modelo Base'!K21/1000000 -> 1186.6154 | AE27: ='Modelo Base'!L21/1000000 -> 1360.0307 | AF27: ='Modelo Base'!M21/1000000 -> 1533.4461 | ... AJ27: ='Modelo Base'!Q21/1000000 -> 2227.1075
X28: Conservador | Y28: ='Modelo Base'!F22/1000000 -> 612.2477 | Z28: ='Modelo Base'!G22/1000000 -> 744.21814 | AA28: ='Modelo Base'!H22/1000000 -> 787.04119 | AB28: ='Modelo Base'!I22/1000000 -> 750.86766 | AC28: ='Modelo Base'!J22/1000000 -> 1218.4027 | AD28: ='Modelo Base'!K22/1000000 -> 759.47894 | AE28: ='Modelo Base'!L22/1000000 -> 803.43646 | AF28: ='Modelo Base'!M22/1000000 -> 1243.6402 | ... AJ28: ='Modelo Base'!Q22/1000000 -> 1361.2209
X29: Base | Y29: ='Modelo Base'!F23/1000000 -> 612.2477 | Z29: ='Modelo Base'!G23/1000000 -> 744.21814 | AA29: ='Modelo Base'!H23/1000000 -> 787.04119 | AB29: ='Modelo Base'!I23/1000000 -> 750.86766 | AC29: ='Modelo Base'!J23/1000000 -> 826.51475 | AD29: ='Modelo Base'!K23/1000000 -> 751.45331 | AE29: ='Modelo Base'!L23/1000000 -> 1047.4069 | AF29: ='Modelo Base'!M23/1000000 -> 1573.6261 | ... AJ29: ='Modelo Base'!Q23/1000000 -> 1939.2875
X32: Métrica | Y32: =TEXT(DATE(2026,COLUMN()-COLUMN($X$32),1),"mmm-aa") -> ene-26 | Z32: =TEXT(DATE(2026,COLUMN()-COLUMN($X$32),1),"mmm-aa") -> feb-26 | AA32: =TEXT(DATE(2026,COLUMN()-COLUMN($X$32),1),"mmm-aa") -> mar-26 | AB32: =TEXT(DATE(2026,COLUMN()-COLUMN($X$32),1),"mmm-aa") -> abr-26 | AC32: =TEXT(DATE(2026,COLUMN()-COLUMN($X$32),1),"mmm-aa") -> may-26 | AD32: =TEXT(DATE(2026,COLUMN()-COLUMN($X$32),1),"mmm-aa") -> jun-26 | AE32: =TEXT(DATE(2026,COLUMN()-COLUMN($X$32),1),"mmm-aa") -> jul-26 | AF32: =TEXT(DATE(2026,COLUMN()-COLUMN($X$32),1),"mmm-aa") -> ago-26 | ... AJ32: =TEXT(DATE(2026,COLUMN()-COLUMN($X$32),1),"mmm-aa") -> dic-26
X33: DSO | Y33: ='Modelo Base'!F228 -> 83.883618 | Z33: ='Modelo Base'!G228 -> 68.288406 | AA33: ='Modelo Base'!H228 -> 66.479628 | AB33: ='Modelo Base'!I228 -> 65.987251 | AC33: ='Modelo Base'!J228 -> 59.671102 | AD33: ='Modelo Base'!K228 -> 69.361151 | AE33: ='Modelo Base'!L228 -> 76.951114 | AF33: ='Modelo Base'!M228 -> 58.094591 | ... AJ33: ='Modelo Base'!Q228 -> 82.020178
X34: DPO | Y34: ='Modelo Base'!F229 -> 9.6145609 | Z34: ='Modelo Base'!G229 -> 7.6089761 | AA34: ='Modelo Base'!H229 -> 6.7670345 | AB34: ='Modelo Base'!I229 -> 8.5724443 | AC34: ='Modelo Base'!J229 -> 8.9523557 | AD34: ='Modelo Base'!K229 -> 7.8811541 | AE34: ='Modelo Base'!L229 -> 8.762755 | AF34: ='Modelo Base'!M229 -> 120.40241 | ... AJ34: ='Modelo Base'!Q229 -> 225.49183
X35: CCC | Y35: ='Modelo Base'!F230 -> 74.269057 | Z35: ='Modelo Base'!G230 -> 60.67943 | AA35: ='Modelo Base'!H230 -> 59.712593 | AB35: ='Modelo Base'!I230 -> 57.414807 | AC35: ='Modelo Base'!J230 -> 50.718747 | AD35: ='Modelo Base'!K230 -> 61.479997 | AE35: ='Modelo Base'!L230 -> 68.188359 | AF35: ='Modelo Base'!M230 -> -62.307816 | ... AJ35: ='Modelo Base'!Q230 -> -143.47165
X38: Métrica | Y38: =TEXT(DATE(2026,COLUMN()-COLUMN($X$38),1),"mmm-aa") -> ene-26 | Z38: =TEXT(DATE(2026,COLUMN()-COLUMN($X$38),1),"mmm-aa") -> feb-26 | AA38: =TEXT(DATE(2026,COLUMN()-COLUMN($X$38),1),"mmm-aa") -> mar-26 | AB38: =TEXT(DATE(2026,COLUMN()-COLUMN($X$38),1),"mmm-aa") -> abr-26 | AC38: =TEXT(DATE(2026,COLUMN()-COLUMN($X$38),1),"mmm-aa") -> may-26 | AD38: =TEXT(DATE(2026,COLUMN()-COLUMN($X$38),1),"mmm-aa") -> jun-26 | AE38: =TEXT(DATE(2026,COLUMN()-COLUMN($X$38),1),"mmm-aa") -> jul-26 | AF38: =TEXT(DATE(2026,COLUMN()-COLUMN($X$38),1),"mmm-aa") -> ago-26 | ... AJ38: =TEXT(DATE(2026,COLUMN()-COLUMN($X$38),1),"mmm-aa") -> dic-26
X39: Deuda Financiera | Y39: ='Modelo Base'!F133/1000000 -> 72.783461 | Z39: ='Modelo Base'!G133/1000000 -> 101.3651 | AA39: ='Modelo Base'!H133/1000000 -> 104.18998 | AB39: ='Modelo Base'!I133/1000000 -> 112.56347 | AC39: ='Modelo Base'!J133/1000000 -> 99.589767 | AD39: ='Modelo Base'!K133/1000000 -> 83.503947 | AE39: ='Modelo Base'!L133/1000000 -> 83.503947 | AF39: ='Modelo Base'!M133/1000000 -> 83.503947 | ... AJ39: ='Modelo Base'!Q133/1000000 -> 83.503947
X40: CxP Coco Delaware | Y40: ='Modelo Base'!F144/1000000 -> 0 | Z40: ='Modelo Base'!G144/1000000 -> 0 | AA40: ='Modelo Base'!H144/1000000 -> 0 | AB40: ='Modelo Base'!I144/1000000 -> 0 | AC40: ='Modelo Base'!J144/1000000 -> 2642.6492 | AD40: ='Modelo Base'!K144/1000000 -> 2641.5665 | AE40: ='Modelo Base'!L144/1000000 -> 2641.5665 | AF40: ='Modelo Base'!M144/1000000 -> 2641.5665 | ... AJ40: ='Modelo Base'!Q144/1000000 -> 2641.5665
X41: Deuda Total | Y41: =('Modelo Base'!F133+'Modelo Base'!F144)/1000000 -> 72.783461 | Z41: =('Modelo Base'!G133+'Modelo Base'!G144)/1000000 -> 101.3651 | AA41: =('Modelo Base'!H133+'Modelo Base'!H144)/1000000 -> 104.18998 | AB41: =('Modelo Base'!I133+'Modelo Base'!I144)/1000000 -> 112.56347 | AC41: =('Modelo Base'!J133+'Modelo Base'!J144)/1000000 -> 2742.2389 | AD41: =('Modelo Base'!K133+'Modelo Base'!K144)/1000000 -> 2725.0704 | AE41: =('Modelo Base'!L133+'Modelo Base'!L144)/1000000 -> 2725.0704 | AF41: =('Modelo Base'!M133+'Modelo Base'!M144)/1000000 -> 2725.0704 | ... AJ41: =('Modelo Base'!Q133+'Modelo Base'!Q144)/1000000 -> 2725.0704
X44: Métrica | Y44: =TEXT(DATE(2026,COLUMN()-COLUMN($X$44),1),"mmm-aa") -> ene-26 | Z44: =TEXT(DATE(2026,COLUMN()-COLUMN($X$44),1),"mmm-aa") -> feb-26 | AA44: =TEXT(DATE(2026,COLUMN()-COLUMN($X$44),1),"mmm-aa") -> mar-26 | AB44: =TEXT(DATE(2026,COLUMN()-COLUMN($X$44),1),"mmm-aa") -> abr-26 | AC44: =TEXT(DATE(2026,COLUMN()-COLUMN($X$44),1),"mmm-aa") -> may-26 | AD44: =TEXT(DATE(2026,COLUMN()-COLUMN($X$44),1),"mmm-aa") -> jun-26 | AE44: =TEXT(DATE(2026,COLUMN()-COLUMN($X$44),1),"mmm-aa") -> jul-26 | AF44: =TEXT(DATE(2026,COLUMN()-COLUMN($X$44),1),"mmm-aa") -> ago-26 | ... AJ44: =TEXT(DATE(2026,COLUMN()-COLUMN($X$44),1),"mmm-aa") -> dic-26
X45: Cuentas por Cobrar | Y45: ='Modelo Base'!F210/1000000 -> 1590.5408 | Z45: ='Modelo Base'!G210/1000000 -> 1797.5572 | AA45: ='Modelo Base'!H210/1000000 -> 1690.5898 | AB45: ='Modelo Base'!I210/1000000 -> 1612.5897 | AC45: ='Modelo Base'!J210/1000000 -> 1675.3467 | AD45: ='Modelo Base'!K210/1000000 -> 1799.4311 | AE45: ='Modelo Base'!L210/1000000 -> 1688.4579 | AF45: ='Modelo Base'!M210/1000000 -> 4406.153 | ... AJ45: ='Modelo Base'!Q210/1000000 -> 5430.005
X46: Cuentas por Pagar | Y46: ='Modelo Base'!F211/1000000 -> 502.12824 | Z46: ='Modelo Base'!G211/1000000 -> 493.7823 | AA46: ='Modelo Base'!H211/1000000 -> 571.03756 | AB46: ='Modelo Base'!I211/1000000 -> 563.84176 | AC46: ='Modelo Base'!J211/1000000 -> 502.31105 | AD46: ='Modelo Base'!K211/1000000 -> 483.39091 | AE46: ='Modelo Base'!L211/1000000 -> 403.7603 | AF46: ='Modelo Base'!M211/1000000 -> 611.0365 | ... AJ46: ='Modelo Base'!Q211/1000000 -> 628.42038
X47: Impuestos por Pagar | Y47: ='Modelo Base'!F212/1000000 -> 14.35008 | Z47: ='Modelo Base'!G212/1000000 -> 1.7917 | AA47: ='Modelo Base'!H212/1000000 -> 25.570584 | AB47: ='Modelo Base'!I212/1000000 -> 24.496645 | AC47: ='Modelo Base'!J212/1000000 -> 22.513416 | AD47: ='Modelo Base'!K212/1000000 -> 23.325495 | AE47: ='Modelo Base'!L212/1000000 -> 19.229474 | AF47: ='Modelo Base'!M212/1000000 -> 259.32201 | ... AJ47: ='Modelo Base'!Q212/1000000 -> 381.3394
A48: CAJA, ESCENARIOS Y EFICIENCIA | X48: Capital de Trabajo Neto | Y48: ='Modelo Base'!F213/1000000 -> 1074.0625 | Z48: ='Modelo Base'!G213/1000000 -> 1301.9832 | AA48: ='Modelo Base'!H213/1000000 -> 1093.9817 | AB48: ='Modelo Base'!I213/1000000 -> 1024.2513 | AC48: ='Modelo Base'!J213/1000000 -> 1150.5222 | AD48: ='Modelo Base'!K213/1000000 -> 1292.7147 | AE48: ='Modelo Base'!L213/1000000 -> 1265.4681 | AF48: ='Modelo Base'!M213/1000000 -> 3535.7945 | ... AJ48: ='Modelo Base'!Q213/1000000 -> 4420.2452
X51: Métrica | Y51: =TEXT(DATE(2026,COLUMN()-COLUMN($X$51),1),"mmm-aa") -> ene-26 | Z51: =TEXT(DATE(2026,COLUMN()-COLUMN($X$51),1),"mmm-aa") -> feb-26 | AA51: =TEXT(DATE(2026,COLUMN()-COLUMN($X$51),1),"mmm-aa") -> mar-26 | AB51: =TEXT(DATE(2026,COLUMN()-COLUMN($X$51),1),"mmm-aa") -> abr-26 | AC51: =TEXT(DATE(2026,COLUMN()-COLUMN($X$51),1),"mmm-aa") -> may-26 | AD51: =TEXT(DATE(2026,COLUMN()-COLUMN($X$51),1),"mmm-aa") -> jun-26 | AE51: =TEXT(DATE(2026,COLUMN()-COLUMN($X$51),1),"mmm-aa") -> jul-26 | AF51: =TEXT(DATE(2026,COLUMN()-COLUMN($X$51),1),"mmm-aa") -> ago-26 | ... AJ51: =TEXT(DATE(2026,COLUMN()-COLUMN($X$51),1),"mmm-aa") -> dic-26
X52: Margen EBITDA | Y52: ='Modelo Base'!F194 -> 0.1142991 | Z52: ='Modelo Base'!G194 -> 0.061989932 | AA52: ='Modelo Base'!H194 -> -0.028261282 | AB52: ='Modelo Base'!I194 -> 0.0064435482 | AC52: ='Modelo Base'!J194 -> 0.13673014 | AD52: ='Modelo Base'!K194 -> 0.046543803 | AE52: ='Modelo Base'!L194 -> 0.043157479 | AF52: ='Modelo Base'!M194 -> 0.47139328 | ... AJ52: ='Modelo Base'!Q194 -> 0.56239606
X53: Margen Neto | Y53: ='Modelo Base'!F197 -> 0.1036925 | Z53: ='Modelo Base'!G197 -> 0.072625098 | AA53: ='Modelo Base'!H197 -> -0.048203331 | AB53: ='Modelo Base'!I197 -> 0.00094051593 | AC53: ='Modelo Base'!J197 -> 0.13112285 | AD53: ='Modelo Base'!K197 -> 0.044372218 | AE53: ='Modelo Base'!L197 -> 0.036339749 | AF53: ='Modelo Base'!M197 -> 0.3060435 | ... AJ53: ='Modelo Base'!Q197 -> 0.36518657
X56: Métrica | Y56: =TEXT(DATE(2026,COLUMN()-COLUMN($X$56),1),"mmm-aa") -> ene-26 | Z56: =TEXT(DATE(2026,COLUMN()-COLUMN($X$56),1),"mmm-aa") -> feb-26 | AA56: =TEXT(DATE(2026,COLUMN()-COLUMN($X$56),1),"mmm-aa") -> mar-26 | AB56: =TEXT(DATE(2026,COLUMN()-COLUMN($X$56),1),"mmm-aa") -> abr-26 | AC56: =TEXT(DATE(2026,COLUMN()-COLUMN($X$56),1),"mmm-aa") -> may-26 | AD56: =TEXT(DATE(2026,COLUMN()-COLUMN($X$56),1),"mmm-aa") -> jun-26 | AE56: =TEXT(DATE(2026,COLUMN()-COLUMN($X$56),1),"mmm-aa") -> jul-26 | AF56: =TEXT(DATE(2026,COLUMN()-COLUMN($X$56),1),"mmm-aa") -> ago-26 | ... AJ56: =TEXT(DATE(2026,COLUMN()-COLUMN($X$56),1),"mmm-aa") -> dic-26
X57: Flujo Operativo | Y57: ='Modelo Base'!F200/1000000 -> 254.49508 | Z57: ='Modelo Base'!G200/1000000 -> -267.33079 | AA57: ='Modelo Base'!H200/1000000 -> 51.916596 | AB57: ='Modelo Base'!I200/1000000 -> 89.724697 | AC57: ='Modelo Base'!J200/1000000 -> 39.321054 | AD57: ='Modelo Base'!K200/1000000 -> -105.08257 | AE57: ='Modelo Base'!L200/1000000 -> 55.719875 | AF57: ='Modelo Base'!M200/1000000 -> -1784.9022 | ... AJ57: ='Modelo Base'!Q200/1000000 -> 488.27045
X58: Cambio Neto de Caja | Y58: ='Modelo Base'!F203/1000000 -> 229.38317 | Z58: ='Modelo Base'!G203/1000000 -> -268.3655 | AA58: ='Modelo Base'!H203/1000000 -> 74.756784 | AB58: ='Modelo Base'!I203/1000000 -> -3773.5938 | AC58: ='Modelo Base'!J203/1000000 -> 3833.0721 | AD58: ='Modelo Base'!K203/1000000 -> -126.01735 | AE58: ='Modelo Base'!L203/1000000 -> 69.631831 | AF58: ='Modelo Base'!M203/1000000 -> 828.25298 | ... AJ58: ='Modelo Base'!Q203/1000000 -> 480.91036
X61: Métrica | Y61: =TEXT(DATE(2026,COLUMN()-COLUMN($X$61),1),"mmm-aa") -> ene-26 | Z61: =TEXT(DATE(2026,COLUMN()-COLUMN($X$61),1),"mmm-aa") -> feb-26 | AA61: =TEXT(DATE(2026,COLUMN()-COLUMN($X$61),1),"mmm-aa") -> mar-26 | AB61: =TEXT(DATE(2026,COLUMN()-COLUMN($X$61),1),"mmm-aa") -> abr-26 | AC61: =TEXT(DATE(2026,COLUMN()-COLUMN($X$61),1),"mmm-aa") -> may-26 | AD61: =TEXT(DATE(2026,COLUMN()-COLUMN($X$61),1),"mmm-aa") -> jun-26 | AE61: =TEXT(DATE(2026,COLUMN()-COLUMN($X$61),1),"mmm-aa") -> jul-26 | AF61: =TEXT(DATE(2026,COLUMN()-COLUMN($X$61),1),"mmm-aa") -> ago-26 | ... AJ61: =TEXT(DATE(2026,COLUMN()-COLUMN($X$61),1),"mmm-aa") -> dic-26
X62: Inversión | Y62: ='Modelo Base'!F201/1000000 -> -7.880549 | Z62: ='Modelo Base'!G201/1000000 -> -6.729228 | AA62: ='Modelo Base'!H201/1000000 -> -0.985518 | AB62: ='Modelo Base'!I201/1000000 -> -3213.6098 | AC62: ='Modelo Base'!J201/1000000 -> 3149.8284 | AD62: ='Modelo Base'!K201/1000000 -> -3.7662586 | AE62: ='Modelo Base'!L201/1000000 -> -7.360092 | AF62: ='Modelo Base'!M201/1000000 -> -7.360092 | ... AJ62: ='Modelo Base'!Q201/1000000 -> -7.360092
X63: Financiamiento | Y63: ='Modelo Base'!F202/1000000 -> -17.231358 | Z63: ='Modelo Base'!G202/1000000 -> 5.694513 | AA63: ='Modelo Base'!H202/1000000 -> 23.825706 | AB63: ='Modelo Base'!I202/1000000 -> -649.70875 | AC63: ='Modelo Base'!J202/1000000 -> 643.92264 | AD63: ='Modelo Base'!K202/1000000 -> -17.16852 | AE63: ='Modelo Base'!L202/1000000 -> 21.272048 | AF63: ='Modelo Base'!M202/1000000 -> 2620.5152 | ... AJ63: ='Modelo Base'!Q202/1000000 -> 0
X66: Métrica | Y66: =TEXT(DATE(2026,COLUMN()-COLUMN($X$66),1),"mmm-aa") -> ene-26 | Z66: =TEXT(DATE(2026,COLUMN()-COLUMN($X$66),1),"mmm-aa") -> feb-26 | AA66: =TEXT(DATE(2026,COLUMN()-COLUMN($X$66),1),"mmm-aa") -> mar-26 | AB66: =TEXT(DATE(2026,COLUMN()-COLUMN($X$66),1),"mmm-aa") -> abr-26 | AC66: =TEXT(DATE(2026,COLUMN()-COLUMN($X$66),1),"mmm-aa") -> may-26 | AD66: =TEXT(DATE(2026,COLUMN()-COLUMN($X$66),1),"mmm-aa") -> jun-26 | AE66: =TEXT(DATE(2026,COLUMN()-COLUMN($X$66),1),"mmm-aa") -> jul-26 | AF66: =TEXT(DATE(2026,COLUMN()-COLUMN($X$66),1),"mmm-aa") -> ago-26 | ... AJ66: =TEXT(DATE(2026,COLUMN()-COLUMN($X$66),1),"mmm-aa") -> dic-26
X67: Ciclo de Conversión | Y67: ='Modelo Base'!F230 -> 74.269057 | Z67: ='Modelo Base'!G230 -> 60.67943 | AA67: ='Modelo Base'!H230 -> 59.712593 | AB67: ='Modelo Base'!I230 -> 57.414807 | AC67: ='Modelo Base'!J230 -> 50.718747 | AD67: ='Modelo Base'!K230 -> 61.479997 | AE67: ='Modelo Base'!L230 -> 68.188359 | AF67: ='Modelo Base'!M230 -> -62.307816 | ... AJ67: ='Modelo Base'!Q230 -> -143.47165
X70: Métrica | Y70: =TEXT(DATE(2026,COLUMN()-COLUMN($X$70),1),"mmm-aa") -> ene-26 | Z70: =TEXT(DATE(2026,COLUMN()-COLUMN($X$70),1),"mmm-aa") -> feb-26 | AA70: =TEXT(DATE(2026,COLUMN()-COLUMN($X$70),1),"mmm-aa") -> mar-26 | AB70: =TEXT(DATE(2026,COLUMN()-COLUMN($X$70),1),"mmm-aa") -> abr-26 | AC70: =TEXT(DATE(2026,COLUMN()-COLUMN($X$70),1),"mmm-aa") -> may-26 | AD70: =TEXT(DATE(2026,COLUMN()-COLUMN($X$70),1),"mmm-aa") -> jun-26 | AE70: =TEXT(DATE(2026,COLUMN()-COLUMN($X$70),1),"mmm-aa") -> jul-26 | AF70: =TEXT(DATE(2026,COLUMN()-COLUMN($X$70),1),"mmm-aa") -> ago-26 | ... AJ70: =TEXT(DATE(2026,COLUMN()-COLUMN($X$70),1),"mmm-aa") -> dic-26
X71: Deuda Total | Y71: =('Modelo Base'!F133+'Modelo Base'!F144)/1000000 -> 72.783461 | Z71: =('Modelo Base'!G133+'Modelo Base'!G144)/1000000 -> 101.3651 | AA71: =('Modelo Base'!H133+'Modelo Base'!H144)/1000000 -> 104.18998 | AB71: =('Modelo Base'!I133+'Modelo Base'!I144)/1000000 -> 112.56347 | AC71: =('Modelo Base'!J133+'Modelo Base'!J144)/1000000 -> 2742.2389 | AD71: =('Modelo Base'!K133+'Modelo Base'!K144)/1000000 -> 2725.0704 | AE71: =('Modelo Base'!L133+'Modelo Base'!L144)/1000000 -> 2725.0704 | AF71: =('Modelo Base'!M133+'Modelo Base'!M144)/1000000 -> 2725.0704 | ... AJ71: =('Modelo Base'!Q133+'Modelo Base'!Q144)/1000000 -> 2725.0704
X74: Métrica | Y74: =TEXT(DATE(2026,COLUMN()-COLUMN($X$74),1),"mmm-aa") -> ene-26 | Z74: =TEXT(DATE(2026,COLUMN()-COLUMN($X$74),1),"mmm-aa") -> feb-26 | AA74: =TEXT(DATE(2026,COLUMN()-COLUMN($X$74),1),"mmm-aa") -> mar-26 | AB74: =TEXT(DATE(2026,COLUMN()-COLUMN($X$74),1),"mmm-aa") -> abr-26 | AC74: =TEXT(DATE(2026,COLUMN()-COLUMN($X$74),1),"mmm-aa") -> may-26 | AD74: =TEXT(DATE(2026,COLUMN()-COLUMN($X$74),1),"mmm-aa") -> jun-26 | AE74: =TEXT(DATE(2026,COLUMN()-COLUMN($X$74),1),"mmm-aa") -> jul-26 | AF74: =TEXT(DATE(2026,COLUMN()-COLUMN($X$74),1),"mmm-aa") -> ago-26 | ... AJ74: =TEXT(DATE(2026,COLUMN()-COLUMN($X$74),1),"mmm-aa") -> dic-26
X75: Impuestos por Pagar | Y75: ='Modelo Base'!F212/1000000 -> 14.35008 | Z75: ='Modelo Base'!G212/1000000 -> 1.7917 | AA75: ='Modelo Base'!H212/1000000 -> 25.570584 | AB75: ='Modelo Base'!I212/1000000 -> 24.496645 | AC75: ='Modelo Base'!J212/1000000 -> 22.513416 | AD75: ='Modelo Base'!K212/1000000 -> 23.325495 | AE75: ='Modelo Base'!L212/1000000 -> 19.229474 | AF75: ='Modelo Base'!M212/1000000 -> 259.32201 | ... AJ75: ='Modelo Base'!Q212/1000000 -> 381.3394
X78: Métrica | Y78: =TEXT(DATE(2026,COLUMN()-COLUMN($X$78),1),"mmm-aa") -> ene-26 | Z78: =TEXT(DATE(2026,COLUMN()-COLUMN($X$78),1),"mmm-aa") -> feb-26 | AA78: =TEXT(DATE(2026,COLUMN()-COLUMN($X$78),1),"mmm-aa") -> mar-26 | AB78: =TEXT(DATE(2026,COLUMN()-COLUMN($X$78),1),"mmm-aa") -> abr-26 | AC78: =TEXT(DATE(2026,COLUMN()-COLUMN($X$78),1),"mmm-aa") -> may-26 | AD78: =TEXT(DATE(2026,COLUMN()-COLUMN($X$78),1),"mmm-aa") -> jun-26 | AE78: =TEXT(DATE(2026,COLUMN()-COLUMN($X$78),1),"mmm-aa") -> jul-26 | AF78: =TEXT(DATE(2026,COLUMN()-COLUMN($X$78),1),"mmm-aa") -> ago-26 | ... AJ78: =TEXT(DATE(2026,COLUMN()-COLUMN($X$78),1),"mmm-aa") -> dic-26
X79: Capital de Trabajo Neto | Y79: ='Modelo Base'!F213/1000000 -> 1074.0625 | Z79: ='Modelo Base'!G213/1000000 -> 1301.9832 | AA79: ='Modelo Base'!H213/1000000 -> 1093.9817 | AB79: ='Modelo Base'!I213/1000000 -> 1024.2513 | AC79: ='Modelo Base'!J213/1000000 -> 1150.5222 | AD79: ='Modelo Base'!K213/1000000 -> 1292.7147 | AE79: ='Modelo Base'!L213/1000000 -> 1265.4681 | AF79: ='Modelo Base'!M213/1000000 -> 3535.7945 | ... AJ79: ='Modelo Base'!Q213/1000000 -> 4420.2452
X82: Métrica | Y82: =TEXT(DATE(2026,COLUMN()-COLUMN($X$82),1),"mmm-aa") -> ene-26 | Z82: =TEXT(DATE(2026,COLUMN()-COLUMN($X$82),1),"mmm-aa") -> feb-26 | AA82: =TEXT(DATE(2026,COLUMN()-COLUMN($X$82),1),"mmm-aa") -> mar-26 | AB82: =TEXT(DATE(2026,COLUMN()-COLUMN($X$82),1),"mmm-aa") -> abr-26 | AC82: =TEXT(DATE(2026,COLUMN()-COLUMN($X$82),1),"mmm-aa") -> may-26 | AD82: =TEXT(DATE(2026,COLUMN()-COLUMN($X$82),1),"mmm-aa") -> jun-26 | AE82: =TEXT(DATE(2026,COLUMN()-COLUMN($X$82),1),"mmm-aa") -> jul-26 | AF82: =TEXT(DATE(2026,COLUMN()-COLUMN($X$82),1),"mmm-aa") -> ago-26 | ... AJ82: =TEXT(DATE(2026,COLUMN()-COLUMN($X$82),1),"mmm-aa") -> dic-26
X83: EBITDA | Y83: ='Modelo Base'!F193/1000000 -> 69.979361 | Z83: ='Modelo Base'!G193/1000000 -> 46.134032 | AA83: ='Modelo Base'!H193/1000000 -> -22.242793 | AB83: ='Modelo Base'!I193/1000000 -> 4.838252 | AC83: ='Modelo Base'!J193/1000000 -> 113.00947 | AD83: ='Modelo Base'!K193/1000000 -> 34.975495 | AE83: ='Modelo Base'!L193/1000000 -> 29.342362 | AF83: ='Modelo Base'!M193/1000000 -> 741.79676 | ... AJ83: ='Modelo Base'!Q193/1000000 -> 1090.6476
X84: Utilidad Neta | Y84: ='Modelo Base'!F196/1000000 -> 63.485497 | Z84: ='Modelo Base'!G196/1000000 -> 54.048915 | AA84: ='Modelo Base'!H196/1000000 -> -37.938007 | AB84: ='Modelo Base'!I196/1000000 -> 0.706203 | AC84: ='Modelo Base'!J196/1000000 -> 108.37497 | AD84: ='Modelo Base'!K196/1000000 -> 33.34365 | AE84: ='Modelo Base'!L196/1000000 -> 24.707052 | AF84: ='Modelo Base'!M196/1000000 -> 481.59803 | ... AJ84: ='Modelo Base'!Q196/1000000 -> 708.20175
X87: Métrica | Y87: =TEXT(DATE(2026,COLUMN()-COLUMN($X$87),1),"mmm-aa") -> ene-26 | Z87: =TEXT(DATE(2026,COLUMN()-COLUMN($X$87),1),"mmm-aa") -> feb-26 | AA87: =TEXT(DATE(2026,COLUMN()-COLUMN($X$87),1),"mmm-aa") -> mar-26 | AB87: =TEXT(DATE(2026,COLUMN()-COLUMN($X$87),1),"mmm-aa") -> abr-26 | AC87: =TEXT(DATE(2026,COLUMN()-COLUMN($X$87),1),"mmm-aa") -> may-26 | AD87: =TEXT(DATE(2026,COLUMN()-COLUMN($X$87),1),"mmm-aa") -> jun-26 | AE87: =TEXT(DATE(2026,COLUMN()-COLUMN($X$87),1),"mmm-aa") -> jul-26 | AF87: =TEXT(DATE(2026,COLUMN()-COLUMN($X$87),1),"mmm-aa") -> ago-26 | ... AJ87: =TEXT(DATE(2026,COLUMN()-COLUMN($X$87),1),"mmm-aa") -> dic-26
X88: Intereses Totales | Y88: ='Modelo Base'!F138/1000000 -> 0.63706025 | Z88: ='Modelo Base'!G138/1000000 -> 0.725619 | AA88: ='Modelo Base'!H138/1000000 -> 0.8564795 | AB88: ='Modelo Base'!I138/1000000 -> 0.90313937 | AC88: ='Modelo Base'!J138/1000000 -> 0.93802892 | AD88: ='Modelo Base'!K138/1000000 -> 0.82991473 | AE88: ='Modelo Base'!L138/1000000 -> 0.69586622 | AF88: ='Modelo Base'!M138/1000000 -> 0.69586622 | ... AJ88: ='Modelo Base'!Q138/1000000 -> 0.69586622
X92: Métrica / Unidad | Y92: =Y$2 -> ene-26 | Z92: =Z$2 -> feb-26 | AA92: =AA$2 -> mar-26 | AB92: =AB$2 -> abr-26 | AC92: =AC$2 -> may-26 | AD92: =AD$2 -> jun-26 | AE92: =AE$2 -> jul-26 | AF92: =AF$2 -> ago-26 | ... AJ92: =AJ$2 -> dic-26
X93: Margen Bruto (%) | Y93: ='Modelo Base'!F54 -> 0.61039332 | Z93: ='Modelo Base'!G54 -> 0.5386987 | AA93: ='Modelo Base'!H54 -> 0.42107324 | AB93: ='Modelo Base'!I54 -> 0.49488623 | AC93: ='Modelo Base'!J54 -> 0.5699163 | AD93: ='Modelo Base'!K54 -> 0.5362618 | AE93: ='Modelo Base'!L54 -> 0.52651521 | AF93: ='Modelo Base'!M54 -> 0.77598169 | ... AJ93: ='Modelo Base'!Q54 -> 0.81304978
X96: Métrica / Unidad | Y96: =Y$2 -> ene-26 | Z96: =Z$2 -> feb-26 | AA96: =AA$2 -> mar-26 | AB96: =AB$2 -> abr-26 | AC96: =AC$2 -> may-26 | AD96: =AD$2 -> jun-26 | AE96: =AE$2 -> jul-26 | AF96: =AF$2 -> ago-26 | ... AJ96: =AJ$2 -> dic-26
X97: Costo de Ventas (COP MM) | Y97: ='Modelo Base'!F52/1000000 -> 238.53579 | Z97: ='Modelo Base'!G52/1000000 -> 343.30879 | AA97: ='Modelo Base'!H52/1000000 -> 455.6392 | AB97: ='Modelo Base'!I52/1000000 -> 379.27359 | AC97: ='Modelo Base'!J52/1000000 -> 355.47052 | AD97: ='Modelo Base'!K52/1000000 -> 348.47761 | AE97: ='Modelo Base'!L52/1000000 -> 321.91784 | AF97: ='Modelo Base'!M52/1000000 -> 352.52106 | ... AJ97: ='Modelo Base'!Q52/1000000 -> 362.55022
X98: Opex Total (COP MM) | Y98: =SUM('Modelo Base'!F56:F58)/1000000 -> 303.73255 | Z98: =SUM('Modelo Base'!G56:G58)/1000000 -> 354.77531 | AA98: =SUM('Modelo Base'!H56:H58)/1000000 -> 353.64478 | AB98: =SUM('Modelo Base'!I56:I58)/1000000 -> 366.75582 | AC98: =SUM('Modelo Base'!J56:J58)/1000000 -> 358.03475 | AD98: =SUM('Modelo Base'!K56:K58)/1000000 -> 368.00021 | AE98: =SUM('Modelo Base'!L56:L58)/1000000 -> 328.63035 | AF98: =SUM('Modelo Base'!M56:M58)/1000000 -> 479.30825 | ... AJ98: =SUM('Modelo Base'!Q56:Q58)/1000000 -> 486.08964
X102: Métrica / Unidad | Y102: =Y$2 -> ene-26 | Z102: =Z$2 -> feb-26 | AA102: =AA$2 -> mar-26 | AB102: =AB$2 -> abr-26 | AC102: =AC$2 -> may-26 | AD102: =AD$2 -> jun-26 | AE102: =AE$2 -> jul-26 | AF102: =AF$2 -> ago-26 | ... AJ102: =AJ$2 -> dic-26
X103: Déficit vs Caja Mínima (COP MM) | Y103: ='Modelo Base'!F452/1000000 -> 0 | Z103: ='Modelo Base'!G452/1000000 -> 74.229878 | AA103: ='Modelo Base'!H452/1000000 -> 36.400677 | AB103: ='Modelo Base'!I452/1000000 -> 0 | AC103: ='Modelo Base'!J452/1000000 -> 0 | AD103: ='Modelo Base'!K452/1000000 -> 116.01764 | AE103: ='Modelo Base'!L452/1000000 -> 57.192074 | AF103: ='Modelo Base'!M452/1000000 -> 1849.4543 | ... AJ103: ='Modelo Base'!Q452/1000000 -> 249.09984
X106: Métrica / Unidad | Y106: =Y$2 -> ene-26 | Z106: =Z$2 -> feb-26 | AA106: =AA$2 -> mar-26 | AB106: =AB$2 -> abr-26 | AC106: =AC$2 -> may-26 | AD106: =AD$2 -> jun-26 | AE106: =AE$2 -> jul-26 | AF106: =AF$2 -> ago-26 | ... AJ106: =AJ$2 -> dic-26
A107: DEUDA Y CAPITAL DE TRABAJO | X107: Activos Corrientes Op. (COP MM) | Y107: ='Modelo Base'!F113/1000000 -> 5014.8352 | Z107: ='Modelo Base'!G113/1000000 -> 5250.0738 | AA107: ='Modelo Base'!H113/1000000 -> 5182.1901 | AB107: ='Modelo Base'!I113/1000000 -> 5140.1848 | AC107: ='Modelo Base'!J113/1000000 -> 5320.1717 | AD107: ='Modelo Base'!K113/1000000 -> 5374.8568 | AE107: ='Modelo Base'!L113/1000000 -> 5296.425 | AF107: ='Modelo Base'!M113/1000000 -> 7933.7481 | ... AJ107: ='Modelo Base'!Q113/1000000 -> 8957.6001
