Workbook

Sheet Diccionario
A1: Diccionario de indicadores — Dashboard Ejecutivo COCO Tecnologías
A2: Catálogo único de variables. 'Origen=COCO' viene de tu archivo; 'Origen=Claude' son inputs base que las fórmulas requieren y conviene validar.
A3: ID | B3: Categoría | C3: Código indicador | D3: Nombre visible | E3: Tipo | F3: Fórmula / regla de cálculo | G3: Unidad | H3: Responsable carga | I3: Fuente sugerida | J3: Frecuencia | K3: Desglose (segmento / detalle) | L3: Origen | M3: Comentario | N3: periodicidad
A4: 1 | B4: Control | C4: periodo | D4: Periodo | E4: Dimensión | F4: Mes de reporte en formato AAAA-MM | G4: AAAA-MM | H4: Cada área | I4: Plantilla | J4: Mensual | L4: COCO | M4: Debe existir en todas las filas | N4: Mensual
A5: 2 | B5: Control | C5: pais | D5: País | E5: Dimensión | F5: País donde se genera la métrica | G5: Texto | H5: Cada área | I5: Plantilla | J5: Mensual | K5: Colombia / México / EE.UU. / Otros | L5: COCO | N5: Mensual
A6: 3 | B6: Control | C6: compania | D6: Compañía | E6: Dimensión | F6: Entidad legal o unidad de negocio | G6: Texto | H6: Finanzas | I6: Contabilidad | J6: Mensual | K6: Coco Colombia / Coco LLC / Coco Global | L6: COCO | N6: Mensual
A7: 4 | B7: Control | C7: moneda | D7: Moneda | E7: Dimensión | F7: Moneda original del dato reportado | G7: COP/USD | H7: Cada área | I7: Plantilla | J7: Mensual | K7: COP / USD | L7: COCO | M7: No mezclar monedas sin identificar | N7: Mensual
A8: 5 | B8: Control | C8: escenario | D8: Escenario | E8: Dimensión | F8: Tipo de dato reportado | G8: Texto | H8: Finanzas | I8: Plantilla | J8: Mensual | K8: Real / Budget / Forecast | L8: COCO | M8: Permite comparar real vs ppto vs forecast | N8: Mensual
A9: 7 | B9: Finanzas | C9: ingresos_one_off | D9: Ingresos one-off | E9: Input | F9: Facturación no recurrente | G9: COP/USD | H9: Ventas | I9: Facturación / contab. | J9: Mensual | K9: detalle: Implementación / Interoperabilidad / Integración / Proyectos | L9: COCO | M9: Separar de ingresos recurrentes | N9: Mensual
A10: 10 | B10: Finanzas | C10: margen_bruto | D10: Margen bruto | E10: KPI | F10: ingresos_totales - costo_directo | G10: COP/USD | H10: Finanzas | I10: Contabilidad | J10: Mensual | L10: COCO | M10: Indicador clave de escalabilidad | N10: Mensual
A11: 11 | B11: Finanzas | C11: margen_bruto_pct | D11: Margen bruto % | E11: KPI | F11: margen_bruto / ingresos_totales | G11: % | H11: Finanzas | I11: Contabilidad | J11: Mensual | L11: COCO | M11: Meta a definir con CEO | N11: Mensual
A12: 12 | B12: Finanzas | C12: gastos_totales | D12: Gastos operativos totales | E12: Input/KPI | F12: Σ gastos por área | G12: COP/USD | H12: Finanzas | I12: Contabilidad | J12: Mensual | L12: COCO | M12: Opex. Puede cargarse agregado o por área. Distinto de 'egresos_totales' | N12: Mensual
A13: 15 | B13: Finanzas | C13: egresos_totales | D13: Egresos totales | E13: Input/KPI | F13: Σ de todas las salidas del periodo (costos + gastos + financieros) | G13: COP/USD | H13: Finanzas | I13: Contabilidad | J13: Mensual | L13: COCO | M13: P&L: Ingresos - Egresos = Utilidad neta | N13: Mensual
A14: 17 | B14: Finanzas | C14: utilidad_neta | D14: Utilidad neta | E14: KPI | F14: ingresos_totales - egresos_totales | G14: COP/USD | H14: Finanzas | I14: Contabilidad | J14: Mensual | L14: COCO | M14: Resultado del P&L del periodo | N14: Mensual
A15: 13 | B15: Finanzas | C15: ebitda | D15: EBITDA | E15: KPI | F15: margen_bruto - gastos_totales | G15: COP/USD | H15: Finanzas | I15: Contabilidad | J15: Mensual | L15: COCO | M15: Métrica central del comité | N15: Mensual
A16: 14 | B16: Finanzas | C16: margen_ebitda | D16: Margen EBITDA | E16: KPI | F16: ebitda / ingresos_totales | G16: % | H16: Finanzas | I16: Contabilidad | J16: Mensual | L16: COCO | M16: Comparar contra presupuesto | N16: Mensual
A17: 16 | B17: Finanzas | C17: cobros_periodo | D17: Cobros del periodo | E17: Input | F17: Dinero efectivamente recibido de clientes | G17: COP/USD | H17: Tesorería | I17: Bancos / cartera | J17: Mensual | L17: COCO | M17: Distinto a facturación | N17: Mensual
A18: 18 | B18: Finanzas | C18: burn_rate_neto | D18: Burn rate neto | E18: KPI | F18: pagos_periodo - cobros_periodo | G18: COP/USD | H18: Finanzas | I18: Tesorería | J18: Mensual | L18: COCO | M18: Negativo = consume caja | N18: Mensual
A19: 19 | B19: Finanzas | C19: runway_meses | D19: Runway | E19: KPI | F19: caja_disponible / burn_rate_neto | G19: Meses | H19: Finanzas | I19: Tesorería | J19: Mensual | L19: COCO | M19: Solo si burn_rate_neto > 0 | N19: Mensual
A20: 21 | B20: Finanzas | C20: ppto_vs_real_ingresos | D20: Ingresos real vs presupuesto | E20: KPI | F20: (ingresos_totales Real / ingresos_totales Budget) - 1 | G20: % | H20: Finanzas | I20: Presupuesto | J20: Mensual | L20: COCO | M20: Se deriva del campo 'escenario' | N20: Mensual
A21: 22 | B21: Finanzas | C21: ppto_vs_real_gastos | D21: Gastos real vs presupuesto | E21: KPI | F21: (gastos_totales Real / gastos_totales Budget) - 1 | G21: % | H21: Finanzas | I21: Presupuesto | J21: Mensual | L21: COCO | M21: Se deriva del campo 'escenario' | N21: Mensual
... A26: 36 | B26: Ventas | C26: pipeline_ponderado | D26: Pipeline ponderado | E26: KPI | F26: Σ (valor_oportunidad * prob_cierre) | G26: COP/USD | H26: Ventas | I26: CRM | J26: Semanal/mensual | L26: COCO | M26: Más útil que pipeline bruto | N26: Mensual
A27: 37 | B27: Ventas | C27: ventas_cerradas | D27: Ventas cerradas | E27: Input | F27: Valor contratos ganados en el periodo | G27: COP/USD | H27: Ventas | I27: CRM / contratos | J27: Mensual | K27: detalle: Recurrente / One-off | L27: COCO | M27: Separar recurrente vs one-off | N27: Mensual
A28: 41 | B28: Ventas | C28: ticket_promedio | D28: Ticket promedio | E28: KPI | F28: ventas_cerradas / deals_ganados | G28: COP/USD | H28: Ventas | I28: CRM / contratos | J28: Mensual | L28: COCO | M28: Medir también por país | N28: Mensual
A29: 42 | B29: Ventas | C29: forecast_comercial | D29: Forecast comercial | E29: Input/KPI | F29: Σ (oport. con cierre esperado * prob_cierre) | G29: COP/USD | H29: Ventas | I29: CRM | J29: Semanal/mensual | L29: COCO | M29: Anticipa ingresos | N29: Mensual
A30: 43 | B30: Marketing | C30: gasto_marketing_total | D30: Gasto marketing total | E30: Input | F30: Gasto total de marketing (pauta total) | G30: COP/USD | H30: Marketing | I30: Marketing | J30: Mensual | L30: COCO | M30: Necesario para CAC. Revisar = pauta total | N30: Mensual
A31: 44 | B31: Marketing | C31: leads_generados | D31: Leads generados | E31: Input | F31: Nº de leads nuevos | G31: Número | H31: Marketing | I31: CRM / formularios | J31: Mensual | K31: detalle: por canal (opcional) | L31: COCO | M31: Separar por canal si es posible | N31: Mensual
A32: 49 | B32: Marketing | C32: cac_fully_loaded | D32: CAC fully loaded | E32: KPI | F32: (gasto_ventas_comercial + gasto_marketing_total) / clientes_nuevos | G32: COP/USD | H32: Comercial/Mktg | I32: Contab. / CRM | J32: Trimestral | L32: COCO | M32: Incluye ventas + mktg. Revisión trimestral (Andrés) | N32: Trimestral
A33: 50 | B33: Marketing | C33: ltv | D33: LTV | E33: KPI | F33: (arpa * margen_bruto_pct) / churn_ingresos_pct | G33: COP/USD | H33: Comercial/Mktg | I33: Facturación / CRM | J33: Trimestral | K33: detalle: Mercadeo (s/ingreso, churn clientes) | Financiero TTM (margen 51%, churn ingresos) | L33: COCO | M33: Vista Financiera: hoja Calc_LTV_Fin, margen editable, churn TTM | N33: Trimestral
A34: 51 | B34: Marketing | C34: ltv_cac | D34: LTV / CAC | E34: KPI | F34: ltv / cac_fully_loaded | G34: Veces | H34: Comercial/Mktg | I34: Dashboard | J34: Trimestral | K34: detalle: Mercadeo | Financiero | L34: COCO | M34: Eficiencia comercial. Difiere según vista del LTV | N34: Trimestral
A35: 52 | B35: Marketing | C35: cac_payback_meses | D35: Payback CAC | E35: KPI | F35: cac_fully_loaded / (arpa * margen_bruto_pct) | G35: Meses | H35: Comercial/Mktg | I35: Dashboard | J35: Trimestral | K35: detalle: Mercadeo (s/margen) | Financiero (c/margen) | L35: COCO | M35: Dos vistas. Revisión trimestral (Andrés) | N35: Trimestral
A36: 53 | B36: Customer Success | C36: clientes_inicio | D36: Clientes iniciales | E36: Input | F36: Clientes activos al inicio del periodo | G36: Número | H36: Comercial | I36: CRM / facturación | J36: Mensual | L36: COCO | M36: Base para churn | N36: Mensual
A37: 54 | B37: Customer Success | C37: clientes_nuevos | D37: Clientes nuevos | E37: Input | F37: Clientes ganados en el periodo | G37: Número | H37: Comercial | I37: CRM | J37: Mensual | L37: COCO | M37: Reconcilia con ventas | N37: Mensual
A38: 56 | B38: Customer Success | C38: clientes_final | D38: Clientes finales | E38: KPI | F38: clientes_inicio + clientes_nuevos - clientes_perdidos | G38: Número | H38: Comercial | I38: CRM | J38: Mensual | L38: COCO | M38: Base al cierre | N38: Mensual
A39: 57 | B39: Customer Success | C39: churn_clientes_pct | D39: Churn de clientes | E39: KPI | F39: clientes_perdidos / clientes_inicio | G39: % | H39: Comercial | I39: CRM | J39: Mensual | L39: COCO | M39: Complementa churn de ingresos | N39: Mensual
A40: 58 | B40: Customer Success | C40: clientes_en_riesgo | D40: Clientes en riesgo | E40: Input | F40: Clientes con prob. de churn según CS | G40: Número | H40: Comercial | I40: CRM / health score | J40: Mensual | L40: COCO | M40: Métrica accionable | N40: Mensual
A41: 59 | B41: Customer Success | C41: clientes_riesgo_pct | D41: % clientes en riesgo | E41: KPI | F41: clientes_en_riesgo / clientes_final | G41: % | H41: Comercial | I41: CRM | J41: Mensual | L41: COCO | M41: Alerta temprana | N41: Mensual
A42: 60 | B42: Customer Success | C42: nps | D42: NPS | E42: Input | F42: Resultado de encuesta de recomendación | G42: % | H42: CS | I42: Encuestas | J42: Mensual/trim. | K42: detalle: Promotores / Pasivos / Detractores | L42: COCO | M42: S8. Histórico completo lo envía CS | N42: Mensual
A43: 67 | B43: Internacional | C43: ingresos_internacionales | D43: Ingresos internacionales | E43: KPI | F43: Σ ingresos_totales donde país≠Colombia | G43: COP/USD | H43: Finanzas | I43: Facturación | J43: Mensual | K43: segmento: por país | L43: COCO | M43: Clave para ronda | N43: Mensual
A44: 68 | B44: Internacional | C44: mrr_internacional | D44: MRR internacional | E44: KPI | F44: Σ mrr_final donde país≠Colombia | G44: COP/USD | H44: Finanzas/Intl | I44: Facturación / CRM | J44: Mensual | K44: segmento: por país | L44: COCO | N44: Mensual
A45: 69 | B45: Internacional | C45: pipeline_internacional | D45: Pipeline internacional | E45: KPI | F45: Σ pipeline_total donde país≠Colombia | G45: COP/USD | H45: Ventas/Intl | I45: CRM | J45: Semanal/mensual | K45: segmento: por país | L45: COCO | M45: Tracción internacional | N45: Mensual
A46: 70 | B46: Internacional | C46: clientes_internacionales | D46: Clientes internacionales | E46: KPI | F46: Σ clientes_final donde país≠Colombia | G46: Número | H46: CS/Intl | I46: CRM / facturación | J46: Mensual | K46: segmento: por país | L46: COCO | N46: Mensual
A47: 101 | B47: Contabilidad | C47: new_mrr | D47: Nuevas ventas MRR | E47: Input | F47: MRR de clientes nuevos del periodo | G47: COP/USD | H47: Contabilidad | I47: Contabilidad | J47: Mensual (serie 13m) | L47: COCO | M47: Componente del MRR bridge | N47: Mensual
A48: 102 | B48: Contabilidad | C48: expansion_mrr | D48: Expansión MRR | E48: Input | F48: Incremento de MRR de clientes existentes | G48: COP/USD | H48: Contabilidad | I48: Contabilidad | J48: Mensual (serie 13m) | L48: COCO | M48: Componente del MRR bridge | N48: Mensual
A49: 103 | B49: Contabilidad | C49: reactivacion_mrr | D49: Rescatadas MRR | E49: Input | F49: MRR de clientes recuperados | G49: COP/USD | H49: Contabilidad | I49: Contabilidad | J49: Mensual (serie 13m) | L49: COCO | M49: Componente del MRR bridge | N49: Mensual
A50: 104 | B50: Contabilidad | C50: contraction_mrr | D50: Contracción MRR | E50: Input | F50: Reducción de MRR de clientes existentes | G50: COP/USD | H50: Contabilidad | I50: Contabilidad | J50: Mensual (serie 13m) | L50: COCO | M50: Componente del MRR bridge | N50: Mensual
A51: 105 | B51: Contabilidad | C51: churned_mrr | D51: Churned MRR | E51: Input | F51: MRR perdido por clientes que se van | G51: COP/USD | H51: Contabilidad | I51: Contabilidad | J51: Mensual (serie 13m) | L51: COCO | M51: Componente del MRR bridge | N51: Mensual
A52: 106 | B52: Contabilidad | C52: retained_mrr | D52: Retenidas MRR | E52: Input | F52: MRR retenido del periodo anterior | G52: COP/USD | H52: Contabilidad | I52: Contabilidad | J52: Mensual (serie 13m) | L52: COCO | M52: Componente del MRR bridge | N52: Mensual
A53: 107 | B53: Contabilidad | C53: churn_mrr_mensual | D53: Churn MRR mensual | E53: KPI | F53: churned_mrr / mrr_inicio | G53: % | H53: Contabilidad | I53: Contabilidad | J53: Mensual (serie 13m) | L53: COCO | M53: Churn de ingresos mes a mes | N53: Mensual
A54: 108 | B54: Customer Success | C54: clientes_retirados | D54: Clientes retirados | E54: Input | F54: Nº de clientes que se retiran en el periodo | G54: Número | H54: Comercial | I54: CRM | J54: Mensual | L54: COCO | M54: Igual a clientes_perdidos | N54: Mensual
A55: 120 | B55: Contabilidad | C55: cartera_total | D55: Cartera total | E55: Input | F55: Saldo total de cartera por cobrar | G55: COP/USD | H55: Contabilidad | I55: Contabilidad | J55: Mensual (serie 13m + último mes) | L55: COCO | N55: Mensual
A56: 121 | B56: Contabilidad | C56: cartera_vencida | D56: Cartera vencida | E56: Input | F56: Cartera con plazo vencido | G56: COP/USD | H56: Contabilidad | I56: Contabilidad | J56: Mensual (serie 13m + último mes) | L56: COCO | N56: Mensual
A57: 122 | B57: Contabilidad | C57: cartera_sana | D57: Cartera sana | E57: KPI | F57: cartera_total - cartera_vencida | G57: COP/USD | H57: Contabilidad | I57: Contabilidad | J57: Mensual (serie 13m + último mes) | L57: COCO | N57: Mensual
A58: 123 | B58: Contabilidad | C58: cartera_vencida_cliente | D58: Cartera vencida por cliente | E58: Input | F58: Cartera vencida atribuida a cada cliente | G58: COP/USD | H58: Contabilidad | I58: Contabilidad | J58: Mensual | K58: detalle: 7 principales + 'Otros' | L58: COCO | M58: Para gráfico de torta | N58: Mensual
A59: 124 | B59: Contabilidad | C59: liquidez_total | D59: Liquidez total | E59: Input | F59: Saldo disponible por cuenta principal | G59: COP/USD | H59: Tesorería | I59: Bancos | J59: Mensual | K59: detalle: cuenta bancaria | L59: COCO | M59: Por cuentas principales | N59: Mensual
A60: 130 | B60: Contabilidad | C60: dso | D60: DSO | E60: KPI | F60: cartera_total / facturacion_periodo * 30 | G60: Días | H60: Contabilidad | I60: Contabilidad | J60: Mensual (evol. 12m + proy.) | L60: COCO | M60: Días de cartera | N60: Mensual
A61: 131 | B61: Contabilidad | C61: dpo | D61: DPO | E61: KPI | F61: cuentas_x_pagar / costo_directo * 30 | G61: Días | H61: Contabilidad | I61: Contabilidad | J61: Mensual (evol. 12m + proy.) | L61: COCO | M61: Días de pago a proveedores | N61: Mensual
A62: 132 | B62: Contabilidad | C62: ccc | D62: CCC | E62: KPI | F62: dso - dpo (+ días de inventario) | G62: Días | H62: Contabilidad | I62: Contabilidad | J62: Mensual (evol. 12m + proy.) | L62: COCO | M62: Ciclo de conversión de efectivo | N62: Mensual
A63: 140 | B63: Contabilidad | C63: gasto_area | D63: Costos y gastos por área | E63: Input | F63: Gasto del periodo por gran área | G63: COP/USD | H63: Contabilidad | I63: Contabilidad | J63: Mensual (serie 13m) | K63: detalle: Administración / Comercial / Proveedores / TI / Financieros | L63: COCO | M63: CONSOLIDADO: usar 'detalle' para el área | N63: Mensual
A64: 141 | B64: Contabilidad | C64: gasto_admin | D64: Gastos administrativos | E64: Input | F64: Gasto administrativo por concepto | G64: COP/USD | H64: Contabilidad | I64: Contabilidad | J64: Mensual (serie 13m) | K64: detalle: Diversos / Viajes / Servicios / Seguros / Arrendamientos / Honorarios / Personal | L64: COCO | M64: CONSOLIDADO: usar 'detalle' para el concepto | N64: Mensual
A65: 142 | B65: Contabilidad | C65: costo_operacion | D65: Costos de operación | E65: Input | F65: Costo de operación por concepto | G65: COP/USD | H65: Contabilidad | I65: Contabilidad | J65: Mensual (serie 13m) | K65: detalle: Viajes / Mantenimientos / Servicios / Honorarios / Personal | L65: COCO | M65: CONSOLIDADO: usar 'detalle' para el concepto | N65: Mensual
A66: 143 | B66: Contabilidad | C66: costo_proveedor | D66: Costos de proveedores | E66: Input | F66: Costo por proveedor tecnológico | G66: COP/USD | H66: Contabilidad | I66: Contabilidad | J66: Mensual (serie 13m) | K66: detalle: B2Chat / AWS / Infobip / IVA / Otros | L66: COCO | M66: CONSOLIDADO: usar 'detalle' para el proveedor | N66: Mensual
A67: 144 | B67: Contabilidad | C67: costo_proveedor_ventas_pct | D67: Costos de proveedores / ventas % | E67: KPI | F67: Σ costo_proveedor / ingresos_totales | G67: % | H67: Contabilidad | I67: Contabilidad | J67: Mensual (serie 13m) | L67: COCO | N67: Mensual
A68: 145 | B68: Contabilidad | C68: salario_area_pct | D68: Salarios por área % | E68: KPI | F68: nómina_área / nómina_total | G68: % | H68: Contabilidad | I68: Contabilidad | J68: Mensual (últimos 2 meses) | K68: detalle: Desarrollo / Operaciones / Comercial / Administrativo | L68: COCO | M68: Gráfico de torta | N68: Mensual
A69: 150 | B69: Contabilidad | C69: distribucion_clientes | D69: Distribución de clientes | E69: Input/KPI | F69: Nº o % de clientes por tipo de ingreso | G69: Número/% | H69: Comercial | I69: CRM / facturación | J69: Mensual | K69: detalle: Recurrente / No recurrente | L69: COCO | N69: Mensual
A70: 160 | B70: Financiero | C70: escenarios_fin | D70: Escenarios financieros | E70: KPI | F70: Proyección por escenario (Real/Budget/Forecast) | G70: COP/USD | H70: Finanzas | I70: Modelo financiero | J70: Mensual | K70: detalle: definir vistas con Andrés | L70: COCO | M70: ALCANCE A DEFINIR — vino suelto en el archivo | N70: Mensual
A71: 125 | B71: Contabilidad | C71: cartera_cobro_legal | D71: Cartera en cobro legal | E71: Input | F71: Saldo de cartera en proceso jurídico | G71: COP/USD | H71: Contabilidad | I71: Contabilidad | J71: Mensual | L71: COCO | M71: Subconjunto de la cartera vencida | N71: Mensual
A72: 133 | B72: Contabilidad | C72: indice_morosidad | D72: Índice de morosidad | E72: KPI | F72: cartera_vencida / cartera_total | G72: % | H72: Contabilidad | I72: Contabilidad | J72: Mensual | L72: COCO | M72: Meta: excelente < 5% | N72: Mensual
A73: 134 | B73: Contabilidad | C73: cartera_mayor_60_pct | D73: % Cartera mayor a 60 días | E73: KPI | F73: cartera_>60d / cartera_total | G73: % | H73: Contabilidad | I73: Contabilidad | J73: Mensual | L73: COCO | M73: Meta: excelente < 5% | N73: Mensual
A74: 135 | B74: Contabilidad | C74: cartera_arr_pct | D74: Cartera como % de ARR | E74: KPI | F74: cartera_total / arr | G74: % | H74: Contabilidad | I74: Contabilidad | J74: Mensual | L74: COCO | M74: Meta: excelente < 12% | N74: Mensual
A75: 136 | B75: Contabilidad | C75: concentracion_cartera | D75: Concentración de cartera | E75: KPI | F75: cartera top cliente(s) / cartera_total | G75: % | H75: Contabilidad | I75: Contabilidad | J75: Mensual | L75: COCO | M75: Meta: excelente < 15% | N75: Mensual
A76: 137 | B76: Contabilidad | C76: write_off_ratio | D76: Write-off ratio (castigo real) | E76: KPI | F76: cartera_castigada / ventas | G76: % | H76: Contabilidad | I76: Contabilidad | J76: Mensual | L76: COCO | M76: Meta: excelente < 1% | N76: Mensual
A77: 8 | B77: Finanzas | C77: ingresos_no_recurrentes | D77: Ingresos no recurrentes | E77: Input | F77: Ingresos variables / one-off del periodo | G77: COP/USD | H77: Finanzas | I77: Facturación | J77: Mensual | L77: COCO | M77: Serie S5 | N77: Mensual
A78: 146 | B78: Contabilidad | C78: gasto_desarrollo | D78: Gastos de Desarrollo | E78: Input | F78: Gasto del área de desarrollo por concepto | G78: COP/USD | H78: Contabilidad | I78: Contabilidad | J78: Mensual (serie) | K78: detalle: Personal / Honorarios / Servicios / Viajes | L78: COCO | M78: Zoom S15 | N78: Mensual
A79: 147 | B79: Contabilidad | C79: gasto_comercial | D79: Gastos Comercial | E79: Input | F79: Gasto del área comercial por concepto | G79: COP/USD | H79: Contabilidad | I79: Contabilidad | J79: Mensual (serie) | K79: detalle: Personal / Honorario / Seguros / Servicios / Viajes / Diversos | L79: COCO | M79: Zoom S13 | N79: Mensual
A80: 170 | B80: Ventas | C80: distribucion_facturacion_tamano | D80: Distribución facturación por tamaño | E80: KPI | F80: % de facturación por tamaño de cliente | G80: % | H80: Comercial | I80: CRM / facturación | J80: Mensual (serie) | K80: detalle: Grandes / Medianos / Pequeños | L80: COCO | M80: S9 | N80: Mensual
A81: 171 | B81: Finanzas | C81: distribucion_ingresos | D81: Distribución de ingresos por tipo | E81: KPI | F81: % de ingresos por tipo | G81: % | H81: Finanzas | I81: Contabilidad | J81: Anual | K81: detalle: Recurrente / Variable / Implementaciones / Internacional | L81: COCO | M81: S4 (pie por año) | N81: Mensual
A82: 201 | B82: Finanzas | C82: mrr_inicio | D82: MRR inicio | E82: Input | F82: MRR al inicio del periodo | G82: COP/USD | H82: Finanzas | I82: Facturación / CRM | J82: Mensual | L82: Claude | M82: Requerido por GRR, churn, bridge | N82: Mensual
A83: 202 | B83: Finanzas | C83: mrr_final | D83: MRR final | E83: Input | F83: MRR al cierre del periodo | G83: COP/USD | H83: Finanzas | I83: Facturación / CRM | J83: Mensual | L83: Claude | M83: Requerido por ARR, ARPA, MRR intl | N83: Mensual
A84: 203 | B84: Finanzas | C84: ingresos_recurrentes | D84: Ingresos recurrentes | E84: Input | F84: Ingreso recurrente reconocido en el periodo | G84: COP/USD | H84: Finanzas | I84: Facturación | J84: Mensual | L84: Claude | M84: ≈ MRR reconocido del mes | N84: Mensual
A85: 204 | B85: Finanzas | C85: ingresos_totales | D85: Ingresos totales | E85: KPI | F85: ingresos_recurrentes + ingresos_one_off | G85: COP/USD | H85: Finanzas | I85: Contabilidad | J85: Mensual | L85: Claude | M85: Base de muchos KPIs | N85: Mensual
A86: 205 | B86: Finanzas | C86: costo_directo | D86: Costo directo | E86: Input | F86: Costo directo de servicio (COGS) | G86: COP/USD | H86: Finanzas | I86: Contabilidad | J86: Mensual | L86: Claude | M86: Requerido por margen bruto | N86: Mensual
A87: 206 | B87: Finanzas | C87: caja_disponible | D87: Caja disponible | E87: Input | F87: Saldo de caja al cierre | G87: COP/USD | H87: Tesorería | I87: Bancos | J87: Mensual | L87: Claude | M87: Requerido por runway | N87: Mensual
A88: 207 | B88: Finanzas | C88: pagos_periodo | D88: Pagos del periodo | E88: Input | F88: Dinero efectivamente pagado en el periodo | G88: COP/USD | H88: Tesorería | I88: Bancos | J88: Mensual | L88: Claude | M88: Requerido por burn rate | N88: Mensual
A89: 208 | B89: Finanzas | C89: facturacion_periodo | D89: Facturación del periodo | E89: Input | F89: Dinero efectivamente facturado | G89: COP/USD | H89: Facturación | I89: Facturación | J89: Mensual | L89: Claude | M89: Requerido por DSO / cartera | N89: Mensual
A90: 209 | B90: Customer Success | C90: clientes_perdidos | D90: Clientes perdidos | E90: Input | F90: Clientes que se retiran en el periodo | G90: Número | H90: Comercial | I90: CRM | J90: Mensual | L90: Claude | M90: Igual a clientes_retirados; requerido por churn | N90: Mensual
A91: 210 | B91: Ventas | C91: deals_ganados | D91: Deals ganados | E91: Input | F91: Nº de oportunidades ganadas | G91: Número | H91: Ventas | I91: CRM | J91: Mensual | L91: Claude | M91: Requerido por ticket promedio | N91: Mensual
A92: 211 | B92: Ventas | C92: gasto_ventas_comercial | D92: Gasto comercial (ventas) | E92: Input | F92: Gasto del área comercial para adquisición | G92: COP/USD | H92: Comercial | I92: Contabilidad | J92: Mensual | L92: Claude | M92: Requerido por CAC fully loaded | N92: Mensual
A93: 212 | B93: SaaS / Revenue | C93: churn_ingresos_pct | D93: Churn de ingresos % | E93: KPI | F93: churned_mrr / mrr_inicio | G93: % | H93: Finanzas | I93: Contabilidad | J93: Mensual | L93: Claude | M93: Requerido por LTV | N93: Mensual
A94: 213 | B94: P&G oficial | C94: pyg_ingresos_operacionales | D94: P&G · Ingresos operacionales netos | E94: Input | F94: Servicio de software − devoluciones | G94: COP/USD | H94: Finanzas | I94: Estados financieros / Contabilidad | J94: Mensual | K94: pais / compañía | L94: COCO | M94: Ingreso operacional neto del P&G oficial mensual | N94: Mensual
A95: 214 | B95: P&G oficial | C95: pyg_servicio_software | D95: P&G · Servicio de software | E95: Input | F95: Facturación bruta por servicio de software | G95: COP | H95: Finanzas | I95: Estados financieros / Contabilidad | J95: Mensual | K95: pais / compañía | L95: COCO | M95: Antes de devoluciones | N95: Mensual
A96: 215 | B96: P&G oficial | C96: pyg_devoluciones | D96: P&G · Devoluciones en ventas | E96: Input | F96: Devoluciones del periodo (valor negativo) | G96: COP | H96: Finanzas | I96: Estados financieros / Contabilidad | J96: Mensual | K96: pais / compañía | L96: COCO | M96: Resta de ingresos | N96: Mensual
A97: 216 | B97: P&G oficial | C97: pyg_costo_ventas | D97: P&G · Costo de ventas | E97: Input | F97: Costo directo del servicio | G97: COP/USD | H97: Finanzas | I97: Estados financieros / Contabilidad | J97: Mensual | K97: pais / compañía | L97: COCO | M97: COGS del P&G oficial | N97: Mensual
A98: 217 | B98: P&G oficial | C98: pyg_utilidad_bruta | D98: P&G · Utilidad bruta | E98: KPI | F98: ingresos_operacionales − costo_ventas | G98: COP | H98: Finanzas | I98: Estados financieros / Contabilidad | J98: Mensual | K98: pais / compañía | L98: COCO | M98: Margen bruto del P&G oficial | N98: Mensual
A99: 218 | B99: P&G oficial | C99: pyg_gasto_administracion | D99: P&G · Gastos de administración | E99: Input | F99: Gastos operacionales de administración | G99: COP/USD | H99: Finanzas | I99: Estados financieros / Contabilidad | J99: Mensual | K99: pais / compañía | L99: COCO | M99: Línea del P&G oficial | N99: Mensual
A100: 219 | B100: P&G oficial | C100: pyg_gasto_proyectos | D100: P&G · Gastos operación/proyectos | E100: Input | F100: Gastos operacionales / proyectos reclasificados | G100: COP/USD | H100: Finanzas | I100: Estados financieros / Contabilidad | J100: Mensual | K100: pais / compañía | L100: COCO | M100: Línea del P&G oficial | N100: Mensual
A101: 220 | B101: P&G oficial | C101: pyg_gasto_ventas | D101: P&G · Gastos de ventas | E101: Input | F101: Gastos operacionales de ventas | G101: COP/USD | H101: Finanzas | I101: Estados financieros / Contabilidad | J101: Mensual | K101: pais / compañía | L101: COCO | M101: Línea del P&G oficial | N101: Mensual
A102: 221 | B102: P&G oficial | C102: pyg_utilidad_operativa | D102: P&G · Utilidad operativa | E102: KPI | F102: utilidad_bruta − gastos operacionales | G102: COP | H102: Finanzas | I102: Estados financieros / Contabilidad | J102: Mensual | K102: pais / compañía | L102: COCO | M102: Base de EBITDA junio | N102: Mensual
A103: 222 | B103: P&G oficial | C103: pyg_ingresos_no_operacionales | D103: P&G · Ingresos no operacionales | E103: Input | F103: Ingresos financieros / otros no operacionales | G103: COP/USD | H103: Finanzas | I103: Estados financieros / Contabilidad | J103: Mensual | K103: pais / compañía | L103: COCO | M103: Línea del P&G oficial | N103: Mensual
A104: 223 | B104: P&G oficial | C104: pyg_gastos_financieros | D104: P&G · Gastos financieros | E104: Input | F104: Gastos no operacionales / financieros | G104: COP/USD | H104: Finanzas | I104: Estados financieros / Contabilidad | J104: Mensual | K104: pais / compañía | L104: COCO | M104: Línea del P&G oficial | N104: Mensual
...

Sheet BD_Indicadores
A1: BD_Indicadores — tabla de hechos (formato largo). 1 fila = 1 indicador en 1 periodo y dimensiones.
A2: AAAA-MM | B2: lista | C2: lista | D2: lista | E2: lista | F2: lista (Diccionario) | G2: p.ej. Medianos | H2: p.ej. AWS / Comercial | I2: número | J2: COP/USD/%/… | K2: opcional | L2: lista (Diccionario)
A3: periodo | B3: pais | C3: compania | D3: moneda | E3: escenario | F3: codigo_indicador | G3: segmento | H3: detalle | I3: valor | J3: unidad | K3: comentario | L3: area | M3: area_responsable | N3: periodicidad
A4: 2024-01 | B4: Colombia | C4: Coco Colombia | D4: COP | E4: Real | F4: ingresos_totales | I4: 430000000 | J4: COP | L4: =IFERROR(INDEX(Diccionario!$B:$B,MATCH(F4,Diccionario!$C:$C,0)),"") | M4: =IFERROR(INDEX(Diccionario!$H:$H,MATCH(F4,Diccionario!$C:$C,0)),"") | N4: =IFERROR(INDEX(Diccionario!$N:$N,MATCH(F4,Diccionario!$C:$C,0)),"")
A5: 2024-01 | B5: Colombia | C5: Coco Colombia | D5: COP | E5: Real | F5: egresos_totales | I5: 547000000 | J5: COP | L5: =IFERROR(INDEX(Diccionario!$B:$B,MATCH(F5,Diccionario!$C:$C,0)),"") | M5: =IFERROR(INDEX(Diccionario!$H:$H,MATCH(F5,Diccionario!$C:$C,0)),"") | N5: =IFERROR(INDEX(Diccionario!$N:$N,MATCH(F5,Diccionario!$C:$C,0)),"")
A6: 2024-01 | B6: Colombia | C6: Coco Colombia | D6: COP | E6: Real | F6: utilidad_neta | I6: -117000000 | J6: COP | K6: Derivado: ingresos - egresos | L6: =IFERROR(INDEX(Diccionario!$B:$B,MATCH(F6,Diccionario!$C:$C,0)),"") | M6: =IFERROR(INDEX(Diccionario!$H:$H,MATCH(F6,Diccionario!$C:$C,0)),"") | N6: =IFERROR(INDEX(Diccionario!$N:$N,MATCH(F6,Diccionario!$C:$C,0)),"")
A7: 2024-02 | B7: Colombia | C7: Coco Colombia | D7: COP | E7: Real | F7: ingresos_totales | I7: 692000000 | J7: COP | L7: =IFERROR(INDEX(Diccionario!$B:$B,MATCH(F7,Diccionario!$C:$C,0)),"") | M7: =IFERROR(INDEX(Diccionario!$H:$H,MATCH(F7,Diccionario!$C:$C,0)),"") | N7: =IFERROR(INDEX(Diccionario!$N:$N,MATCH(F7,Diccionario!$C:$C,0)),"")
A8: 2024-02 | B8: Colombia | C8: Coco Colombia | D8: COP | E8: Real | F8: egresos_totales | I8: 515000000 | J8: COP | L8: =IFERROR(INDEX(Diccionario!$B:$B,MATCH(F8,Diccionario!$C:$C,0)),"") | M8: =IFERROR(INDEX(Diccionario!$H:$H,MATCH(F8,Diccionario!$C:$C,0)),"") | N8: =IFERROR(INDEX(Diccionario!$N:$N,MATCH(F8,Diccionario!$C:$C,0)),"")
A9: 2024-02 | B9: Colombia | C9: Coco Colombia | D9: COP | E9: Real | F9: utilidad_neta | I9: 177000000 | J9: COP | K9: Derivado: ingresos - egresos | L9: =IFERROR(INDEX(Diccionario!$B:$B,MATCH(F9,Diccionario!$C:$C,0)),"") | M9: =IFERROR(INDEX(Diccionario!$H:$H,MATCH(F9,Diccionario!$C:$C,0)),"") | N9: =IFERROR(INDEX(Diccionario!$N:$N,MATCH(F9,Diccionario!$C:$C,0)),"")
A10: 2024-03 | B10: Colombia | C10: Coco Colombia | D10: COP | E10: Real | F10: ingresos_totales | I10: 582000000 | J10: COP | L10: =IFERROR(INDEX(Diccionario!$B:$B,MATCH(F10,Diccionario!$C:$C,0)),"") | M10: =IFERROR(INDEX(Diccionario!$H:$H,MATCH(F10,Diccionario!$C:$C,0)),"") | N10: =IFERROR(INDEX(Diccionario!$N:$N,MATCH(F10,Diccionario!$C:$C,0)),"")
A11: 2024-03 | B11: Colombia | C11: Coco Colombia | D11: COP | E11: Real | F11: egresos_totales | I11: 571000000 | J11: COP | L11: =IFERROR(INDEX(Diccionario!$B:$B,MATCH(F11,Diccionario!$C:$C,0)),"") | M11: =IFERROR(INDEX(Diccionario!$H:$H,MATCH(F11,Diccionario!$C:$C,0)),"") | N11: =IFERROR(INDEX(Diccionario!$N:$N,MATCH(F11,Diccionario!$C:$C,0)),"")
A12: 2024-03 | B12: Colombia | C12: Coco Colombia | D12: COP | E12: Real | F12: utilidad_neta | I12: 11000000 | J12: COP | K12: Derivado: ingresos - egresos | L12: =IFERROR(INDEX(Diccionario!$B:$B,MATCH(F12,Diccionario!$C:$C,0)),"") | M12: =IFERROR(INDEX(Diccionario!$H:$H,MATCH(F12,Diccionario!$C:$C,0)),"") | N12: =IFERROR(INDEX(Diccionario!$N:$N,MATCH(F12,Diccionario!$C:$C,0)),"")
A13: 2024-04 | B13: Colombia | C13: Coco Colombia | D13: COP | E13: Real | F13: ingresos_totales | I13: 578000000 | J13: COP | L13: =IFERROR(INDEX(Diccionario!$B:$B,MATCH(F13,Diccionario!$C:$C,0)),"") | M13: =IFERROR(INDEX(Diccionario!$H:$H,MATCH(F13,Diccionario!$C:$C,0)),"") | N13: =IFERROR(INDEX(Diccionario!$N:$N,MATCH(F13,Diccionario!$C:$C,0)),"")
A14: 2024-04 | B14: Colombia | C14: Coco Colombia | D14: COP | E14: Real | F14: egresos_totales | I14: 573000000 | J14: COP | L14: =IFERROR(INDEX(Diccionario!$B:$B,MATCH(F14,Diccionario!$C:$C,0)),"") | M14: =IFERROR(INDEX(Diccionario!$H:$H,MATCH(F14,Diccionario!$C:$C,0)),"") | N14: =IFERROR(INDEX(Diccionario!$N:$N,MATCH(F14,Diccionario!$C:$C,0)),"")
A15: 2024-04 | B15: Colombia | C15: Coco Colombia | D15: COP | E15: Real | F15: utilidad_neta | I15: 5000000 | J15: COP | K15: Derivado: ingresos - egresos | L15: =IFERROR(INDEX(Diccionario!$B:$B,MATCH(F15,Diccionario!$C:$C,0)),"") | M15: =IFERROR(INDEX(Diccionario!$H:$H,MATCH(F15,Diccionario!$C:$C,0)),"") | N15: =IFERROR(INDEX(Diccionario!$N:$N,MATCH(F15,Diccionario!$C:$C,0)),"")
A16: 2024-05 | B16: Colombia | C16: Coco Colombia | D16: COP | E16: Real | F16: ingresos_totales | I16: 679000000 | J16: COP | L16: =IFERROR(INDEX(Diccionario!$B:$B,MATCH(F16,Diccionario!$C:$C,0)),"") | M16: =IFERROR(INDEX(Diccionario!$H:$H,MATCH(F16,Diccionario!$C:$C,0)),"") | N16: =IFERROR(INDEX(Diccionario!$N:$N,MATCH(F16,Diccionario!$C:$C,0)),"")
A17: 2024-05 | B17: Colombia | C17: Coco Colombia | D17: COP | E17: Real | F17: egresos_totales | I17: 574000000 | J17: COP | L17: =IFERROR(INDEX(Diccionario!$B:$B,MATCH(F17,Diccionario!$C:$C,0)),"") | M17: =IFERROR(INDEX(Diccionario!$H:$H,MATCH(F17,Diccionario!$C:$C,0)),"") | N17: =IFERROR(INDEX(Diccionario!$N:$N,MATCH(F17,Diccionario!$C:$C,0)),"")
A18: 2024-05 | B18: Colombia | C18: Coco Colombia | D18: COP | E18: Real | F18: utilidad_neta | I18: 105000000 | J18: COP | K18: Derivado: ingresos - egresos | L18: =IFERROR(INDEX(Diccionario!$B:$B,MATCH(F18,Diccionario!$C:$C,0)),"") | M18: =IFERROR(INDEX(Diccionario!$H:$H,MATCH(F18,Diccionario!$C:$C,0)),"") | N18: =IFERROR(INDEX(Diccionario!$N:$N,MATCH(F18,Diccionario!$C:$C,0)),"")
A19: 2024-06 | B19: Colombia | C19: Coco Colombia | D19: COP | E19: Real | F19: ingresos_totales | I19: 684000000 | J19: COP | L19: =IFERROR(INDEX(Diccionario!$B:$B,MATCH(F19,Diccionario!$C:$C,0)),"") | M19: =IFERROR(INDEX(Diccionario!$H:$H,MATCH(F19,Diccionario!$C:$C,0)),"") | N19: =IFERROR(INDEX(Diccionario!$N:$N,MATCH(F19,Diccionario!$C:$C,0)),"")
A20: 2024-06 | B20: Colombia | C20: Coco Colombia | D20: COP | E20: Real | F20: egresos_totales | I20: 611000000 | J20: COP | L20: =IFERROR(INDEX(Diccionario!$B:$B,MATCH(F20,Diccionario!$C:$C,0)),"") | M20: =IFERROR(INDEX(Diccionario!$H:$H,MATCH(F20,Diccionario!$C:$C,0)),"") | N20: =IFERROR(INDEX(Diccionario!$N:$N,MATCH(F20,Diccionario!$C:$C,0)),"")
A21: 2024-06 | B21: Colombia | C21: Coco Colombia | D21: COP | E21: Real | F21: utilidad_neta | I21: 73000000 | J21: COP | K21: Derivado: ingresos - egresos | L21: =IFERROR(INDEX(Diccionario!$B:$B,MATCH(F21,Diccionario!$C:$C,0)),"") | M21: =IFERROR(INDEX(Diccionario!$H:$H,MATCH(F21,Diccionario!$C:$C,0)),"") | N21: =IFERROR(INDEX(Diccionario!$N:$N,MATCH(F21,Diccionario!$C:$C,0)),"")
A22: 2024-07 | B22: Colombia | C22: Coco Colombia | D22: COP | E22: Real | F22: ingresos_totales | I22: 642000000 | J22: COP | L22: =IFERROR(INDEX(Diccionario!$B:$B,MATCH(F22,Diccionario!$C:$C,0)),"") | M22: =IFERROR(INDEX(Diccionario!$H:$H,MATCH(F22,Diccionario!$C:$C,0)),"") | N22: =IFERROR(INDEX(Diccionario!$N:$N,MATCH(F22,Diccionario!$C:$C,0)),"")
A23: 2024-07 | B23: Colombia | C23: Coco Colombia | D23: COP | E23: Real | F23: egresos_totales | I23: 555000000 | J23: COP | L23: =IFERROR(INDEX(Diccionario!$B:$B,MATCH(F23,Diccionario!$C:$C,0)),"") | M23: =IFERROR(INDEX(Diccionario!$H:$H,MATCH(F23,Diccionario!$C:$C,0)),"") | N23: =IFERROR(INDEX(Diccionario!$N:$N,MATCH(F23,Diccionario!$C:$C,0)),"")
A24: 2024-07 | B24: Colombia | C24: Coco Colombia | D24: COP | E24: Real | F24: utilidad_neta | I24: 87000000 | J24: COP | K24: Derivado: ingresos - egresos | L24: =IFERROR(INDEX(Diccionario!$B:$B,MATCH(F24,Diccionario!$C:$C,0)),"") | M24: =IFERROR(INDEX(Diccionario!$H:$H,MATCH(F24,Diccionario!$C:$C,0)),"") | N24: =IFERROR(INDEX(Diccionario!$N:$N,MATCH(F24,Diccionario!$C:$C,0)),"")
A25: 2024-08 | B25: Colombia | C25: Coco Colombia | D25: COP | E25: Real | F25: ingresos_totales | I25: 675000000 | J25: COP | L25: =IFERROR(INDEX(Diccionario!$B:$B,MATCH(F25,Diccionario!$C:$C,0)),"") | M25: =IFERROR(INDEX(Diccionario!$H:$H,MATCH(F25,Diccionario!$C:$C,0)),"") | N25: =IFERROR(INDEX(Diccionario!$N:$N,MATCH(F25,Diccionario!$C:$C,0)),"")
A26: 2024-08 | B26: Colombia | C26: Coco Colombia | D26: COP | E26: Real | F26: egresos_totales | I26: 638000000 | J26: COP | L26: =IFERROR(INDEX(Diccionario!$B:$B,MATCH(F26,Diccionario!$C:$C,0)),"") | M26: =IFERROR(INDEX(Diccionario!$H:$H,MATCH(F26,Diccionario!$C:$C,0)),"") | N26: =IFERROR(INDEX(Diccionario!$N:$N,MATCH(F26,Diccionario!$C:$C,0)),"")
A27: 2024-08 | B27: Colombia | C27: Coco Colombia | D27: COP | E27: Real | F27: utilidad_neta | I27: 37000000 | J27: COP | K27: Derivado: ingresos - egresos | L27: =IFERROR(INDEX(Diccionario!$B:$B,MATCH(F27,Diccionario!$C:$C,0)),"") | M27: =IFERROR(INDEX(Diccionario!$H:$H,MATCH(F27,Diccionario!$C:$C,0)),"") | N27: =IFERROR(INDEX(Diccionario!$N:$N,MATCH(F27,Diccionario!$C:$C,0)),"")
A28: 2024-09 | B28: Colombia | C28: Coco Colombia | D28: COP | E28: Real | F28: ingresos_totales | I28: 663000000 | J28: COP | L28: =IFERROR(INDEX(Diccionario!$B:$B,MATCH(F28,Diccionario!$C:$C,0)),"") | M28: =IFERROR(INDEX(Diccionario!$H:$H,MATCH(F28,Diccionario!$C:$C,0)),"") | N28: =IFERROR(INDEX(Diccionario!$N:$N,MATCH(F28,Diccionario!$C:$C,0)),"")
A29: 2024-09 | B29: Colombia | C29: Coco Colombia | D29: COP | E29: Real | F29: egresos_totales | I29: 679000000 | J29: COP | L29: =IFERROR(INDEX(Diccionario!$B:$B,MATCH(F29,Diccionario!$C:$C,0)),"") | M29: =IFERROR(INDEX(Diccionario!$H:$H,MATCH(F29,Diccionario!$C:$C,0)),"") | N29: =IFERROR(INDEX(Diccionario!$N:$N,MATCH(F29,Diccionario!$C:$C,0)),"")
A30: 2024-09 | B30: Colombia | C30: Coco Colombia | D30: COP | E30: Real | F30: utilidad_neta | I30: -16000000 | J30: COP | K30: Derivado: ingresos - egresos | L30: =IFERROR(INDEX(Diccionario!$B:$B,MATCH(F30,Diccionario!$C:$C,0)),"") | M30: =IFERROR(INDEX(Diccionario!$H:$H,MATCH(F30,Diccionario!$C:$C,0)),"") | N30: =IFERROR(INDEX(Diccionario!$N:$N,MATCH(F30,Diccionario!$C:$C,0)),"")
A31: 2024-10 | B31: Colombia | C31: Coco Colombia | D31: COP | E31: Real | F31: ingresos_totales | I31: 672000000 | J31: COP | L31: =IFERROR(INDEX(Diccionario!$B:$B,MATCH(F31,Diccionario!$C:$C,0)),"") | M31: =IFERROR(INDEX(Diccionario!$H:$H,MATCH(F31,Diccionario!$C:$C,0)),"") | N31: =IFERROR(INDEX(Diccionario!$N:$N,MATCH(F31,Diccionario!$C:$C,0)),"")
A32: 2024-10 | B32: Colombia | C32: Coco Colombia | D32: COP | E32: Real | F32: egresos_totales | I32: 716000000 | J32: COP | L32: =IFERROR(INDEX(Diccionario!$B:$B,MATCH(F32,Diccionario!$C:$C,0)),"") | M32: =IFERROR(INDEX(Diccionario!$H:$H,MATCH(F32,Diccionario!$C:$C,0)),"") | N32: =IFERROR(INDEX(Diccionario!$N:$N,MATCH(F32,Diccionario!$C:$C,0)),"")
A33: 2024-10 | B33: Colombia | C33: Coco Colombia | D33: COP | E33: Real | F33: utilidad_neta | I33: -44000000 | J33: COP | K33: Derivado: ingresos - egresos | L33: =IFERROR(INDEX(Diccionario!$B:$B,MATCH(F33,Diccionario!$C:$C,0)),"") | M33: =IFERROR(INDEX(Diccionario!$H:$H,MATCH(F33,Diccionario!$C:$C,0)),"") | N33: =IFERROR(INDEX(Diccionario!$N:$N,MATCH(F33,Diccionario!$C:$C,0)),"")
A34: 2024-11 | B34: Colombia | C34: Coco Colombia | D34: COP | E34: Real | F34: ingresos_totales | I34: 761000000 | J34: COP | L34: =IFERROR(INDEX(Diccionario!$B:$B,MATCH(F34,Diccionario!$C:$C,0)),"") | M34: =IFERROR(INDEX(Diccionario!$H:$H,MATCH(F34,Diccionario!$C:$C,0)),"") | N34: =IFERROR(INDEX(Diccionario!$N:$N,MATCH(F34,Diccionario!$C:$C,0)),"")
A35: 2024-11 | B35: Colombia | C35: Coco Colombia | D35: COP | E35: Real | F35: egresos_totales | I35: 740000000 | J35: COP | L35: =IFERROR(INDEX(Diccionario!$B:$B,MATCH(F35,Diccionario!$C:$C,0)),"") | M35: =IFERROR(INDEX(Diccionario!$H:$H,MATCH(F35,Diccionario!$C:$C,0)),"") | N35: =IFERROR(INDEX(Diccionario!$N:$N,MATCH(F35,Diccionario!$C:$C,0)),"")
A36: 2024-11 | B36: Colombia | C36: Coco Colombia | D36: COP | E36: Real | F36: utilidad_neta | I36: 21000000 | J36: COP | K36: Derivado: ingresos - egresos | L36: =IFERROR(INDEX(Diccionario!$B:$B,MATCH(F36,Diccionario!$C:$C,0)),"") | M36: =IFERROR(INDEX(Diccionario!$H:$H,MATCH(F36,Diccionario!$C:$C,0)),"") | N36: =IFERROR(INDEX(Diccionario!$N:$N,MATCH(F36,Diccionario!$C:$C,0)),"")
A37: 2024-12 | B37: Colombia | C37: Coco Colombia | D37: COP | E37: Real | F37: ingresos_totales | I37: 1279000000 | J37: COP | L37: =IFERROR(INDEX(Diccionario!$B:$B,MATCH(F37,Diccionario!$C:$C,0)),"") | M37: =IFERROR(INDEX(Diccionario!$H:$H,MATCH(F37,Diccionario!$C:$C,0)),"") | N37: =IFERROR(INDEX(Diccionario!$N:$N,MATCH(F37,Diccionario!$C:$C,0)),"")
A38: 2024-12 | B38: Colombia | C38: Coco Colombia | D38: COP | E38: Real | F38: egresos_totales | I38: 810000000 | J38: COP | L38: =IFERROR(INDEX(Diccionario!$B:$B,MATCH(F38,Diccionario!$C:$C,0)),"") | M38: =IFERROR(INDEX(Diccionario!$H:$H,MATCH(F38,Diccionario!$C:$C,0)),"") | N38: =IFERROR(INDEX(Diccionario!$N:$N,MATCH(F38,Diccionario!$C:$C,0)),"")
A39: 2024-12 | B39: Colombia | C39: Coco Colombia | D39: COP | E39: Real | F39: utilidad_neta | I39: 469000000 | J39: COP | K39: Derivado: ingresos - egresos | L39: =IFERROR(INDEX(Diccionario!$B:$B,MATCH(F39,Diccionario!$C:$C,0)),"") | M39: =IFERROR(INDEX(Diccionario!$H:$H,MATCH(F39,Diccionario!$C:$C,0)),"") | N39: =IFERROR(INDEX(Diccionario!$N:$N,MATCH(F39,Diccionario!$C:$C,0)),"")
A40: 2025-01 | B40: Colombia | C40: Coco Colombia | D40: COP | E40: Real | F40: ingresos_totales | I40: 504000000 | J40: COP | L40: =IFERROR(INDEX(Diccionario!$B:$B,MATCH(F40,Diccionario!$C:$C,0)),"") | M40: =IFERROR(INDEX(Diccionario!$H:$H,MATCH(F40,Diccionario!$C:$C,0)),"") | N40: =IFERROR(INDEX(Diccionario!$N:$N,MATCH(F40,Diccionario!$C:$C,0)),"")
A41: 2025-01 | B41: Colombia | C41: Coco Colombia | D41: COP | E41: Real | F41: egresos_totales | I41: 694000000 | J41: COP | L41: =IFERROR(INDEX(Diccionario!$B:$B,MATCH(F41,Diccionario!$C:$C,0)),"") | M41: =IFERROR(INDEX(Diccionario!$H:$H,MATCH(F41,Diccionario!$C:$C,0)),"") | N41: =IFERROR(INDEX(Diccionario!$N:$N,MATCH(F41,Diccionario!$C:$C,0)),"")
A42: 2025-01 | B42: Colombia | C42: Coco Colombia | D42: COP | E42: Real | F42: utilidad_neta | I42: -190000000 | J42: COP | K42: Derivado: ingresos - egresos | L42: =IFERROR(INDEX(Diccionario!$B:$B,MATCH(F42,Diccionario!$C:$C,0)),"") | M42: =IFERROR(INDEX(Diccionario!$H:$H,MATCH(F42,Diccionario!$C:$C,0)),"") | N42: =IFERROR(INDEX(Diccionario!$N:$N,MATCH(F42,Diccionario!$C:$C,0)),"")
A43: 2025-02 | B43: Colombia | C43: Coco Colombia | D43: COP | E43: Real | F43: ingresos_totales | I43: 564000000 | J43: COP | L43: =IFERROR(INDEX(Diccionario!$B:$B,MATCH(F43,Diccionario!$C:$C,0)),"") | M43: =IFERROR(INDEX(Diccionario!$H:$H,MATCH(F43,Diccionario!$C:$C,0)),"") | N43: =IFERROR(INDEX(Diccionario!$N:$N,MATCH(F43,Diccionario!$C:$C,0)),"")
A44: 2025-02 | B44: Colombia | C44: Coco Colombia | D44: COP | E44: Real | F44: egresos_totales | I44: 688000000 | J44: COP | L44: =IFERROR(INDEX(Diccionario!$B:$B,MATCH(F44,Diccionario!$C:$C,0)),"") | M44: =IFERROR(INDEX(Diccionario!$H:$H,MATCH(F44,Diccionario!$C:$C,0)),"") | N44: =IFERROR(INDEX(Diccionario!$N:$N,MATCH(F44,Diccionario!$C:$C,0)),"")
A45: 2025-02 | B45: Colombia | C45: Coco Colombia | D45: COP | E45: Real | F45: utilidad_neta | I45: -124000000 | J45: COP | K45: Derivado: ingresos - egresos | L45: =IFERROR(INDEX(Diccionario!$B:$B,MATCH(F45,Diccionario!$C:$C,0)),"") | M45: =IFERROR(INDEX(Diccionario!$H:$H,MATCH(F45,Diccionario!$C:$C,0)),"") | N45: =IFERROR(INDEX(Diccionario!$N:$N,MATCH(F45,Diccionario!$C:$C,0)),"")
A46: 2025-03 | B46: Colombia | C46: Coco Colombia | D46: COP | E46: Real | F46: ingresos_totales | I46: 695000000 | J46: COP | L46: =IFERROR(INDEX(Diccionario!$B:$B,MATCH(F46,Diccionario!$C:$C,0)),"") | M46: =IFERROR(INDEX(Diccionario!$H:$H,MATCH(F46,Diccionario!$C:$C,0)),"") | N46: =IFERROR(INDEX(Diccionario!$N:$N,MATCH(F46,Diccionario!$C:$C,0)),"")
A47: 2025-03 | B47: Colombia | C47: Coco Colombia | D47: COP | E47: Real | F47: egresos_totales | I47: 809000000 | J47: COP | L47: =IFERROR(INDEX(Diccionario!$B:$B,MATCH(F47,Diccionario!$C:$C,0)),"") | M47: =IFERROR(INDEX(Diccionario!$H:$H,MATCH(F47,Diccionario!$C:$C,0)),"") | N47: =IFERROR(INDEX(Diccionario!$N:$N,MATCH(F47,Diccionario!$C:$C,0)),"")
A48: 2025-03 | B48: Colombia | C48: Coco Colombia | D48: COP | E48: Real | F48: utilidad_neta | I48: -114000000 | J48: COP | K48: Derivado: ingresos - egresos | L48: =IFERROR(INDEX(Diccionario!$B:$B,MATCH(F48,Diccionario!$C:$C,0)),"") | M48: =IFERROR(INDEX(Diccionario!$H:$H,MATCH(F48,Diccionario!$C:$C,0)),"") | N48: =IFERROR(INDEX(Diccionario!$N:$N,MATCH(F48,Diccionario!$C:$C,0)),"")
A49: 2025-04 | B49: Colombia | C49: Coco Colombia | D49: COP | E49: Real | F49: ingresos_totales | I49: 578000000 | J49: COP | L49: =IFERROR(INDEX(Diccionario!$B:$B,MATCH(F49,Diccionario!$C:$C,0)),"") | M49: =IFERROR(INDEX(Diccionario!$H:$H,MATCH(F49,Diccionario!$C:$C,0)),"") | N49: =IFERROR(INDEX(Diccionario!$N:$N,MATCH(F49,Diccionario!$C:$C,0)),"")
A50: 2025-04 | B50: Colombia | C50: Coco Colombia | D50: COP | E50: Real | F50: egresos_totales | I50: 766600000 | J50: COP | L50: =IFERROR(INDEX(Diccionario!$B:$B,MATCH(F50,Diccionario!$C:$C,0)),"") | M50: =IFERROR(INDEX(Diccionario!$H:$H,MATCH(F50,Diccionario!$C:$C,0)),"") | N50: =IFERROR(INDEX(Diccionario!$N:$N,MATCH(F50,Diccionario!$C:$C,0)),"")
A51: 2025-04 | B51: Colombia | C51: Coco Colombia | D51: COP | E51: Real | F51: utilidad_neta | I51: -188600000 | J51: COP | K51: Derivado: ingresos - egresos | L51: =IFERROR(INDEX(Diccionario!$B:$B,MATCH(F51,Diccionario!$C:$C,0)),"") | M51: =IFERROR(INDEX(Diccionario!$H:$H,MATCH(F51,Diccionario!$C:$C,0)),"") | N51: =IFERROR(INDEX(Diccionario!$N:$N,MATCH(F51,Diccionario!$C:$C,0)),"")
A52: 2025-05 | B52: Colombia | C52: Coco Colombia | D52: COP | E52: Real | F52: ingresos_totales | I52: 716000000 | J52: COP | L52: =IFERROR(INDEX(Diccionario!$B:$B,MATCH(F52,Diccionario!$C:$C,0)),"") | M52: =IFERROR(INDEX(Diccionario!$H:$H,MATCH(F52,Diccionario!$C:$C,0)),"") | N52: =IFERROR(INDEX(Diccionario!$N:$N,MATCH(F52,Diccionario!$C:$C,0)),"")
A53: 2025-05 | B53: Colombia | C53: Coco Colombia | D53: COP | E53: Real | F53: egresos_totales | I53: 729000000 | J53: COP | L53: =IFERROR(INDEX(Diccionario!$B:$B,MATCH(F53,Diccionario!$C:$C,0)),"") | M53: =IFERROR(INDEX(Diccionario!$H:$H,MATCH(F53,Diccionario!$C:$C,0)),"") | N53: =IFERROR(INDEX(Diccionario!$N:$N,MATCH(F53,Diccionario!$C:$C,0)),"")
A54: 2025-05 | B54: Colombia | C54: Coco Colombia | D54: COP | E54: Real | F54: utilidad_neta | I54: -13000000 | J54: COP | K54: Derivado: ingresos - egresos | L54: =IFERROR(INDEX(Diccionario!$B:$B,MATCH(F54,Diccionario!$C:$C,0)),"") | M54: =IFERROR(INDEX(Diccionario!$H:$H,MATCH(F54,Diccionario!$C:$C,0)),"") | N54: =IFERROR(INDEX(Diccionario!$N:$N,MATCH(F54,Diccionario!$C:$C,0)),"")
A55: 2025-06 | B55: Colombia | C55: Coco Colombia | D55: COP | E55: Real | F55: ingresos_totales | I55: 610000000 | J55: COP | L55: =IFERROR(INDEX(Diccionario!$B:$B,MATCH(F55,Diccionario!$C:$C,0)),"") | M55: =IFERROR(INDEX(Diccionario!$H:$H,MATCH(F55,Diccionario!$C:$C,0)),"") | N55: =IFERROR(INDEX(Diccionario!$N:$N,MATCH(F55,Diccionario!$C:$C,0)),"")
A56: 2025-06 | B56: Colombia | C56: Coco Colombia | D56: COP | E56: Real | F56: egresos_totales | I56: 636000000 | J56: COP | L56: =IFERROR(INDEX(Diccionario!$B:$B,MATCH(F56,Diccionario!$C:$C,0)),"") | M56: =IFERROR(INDEX(Diccionario!$H:$H,MATCH(F56,Diccionario!$C:$C,0)),"") | N56: =IFERROR(INDEX(Diccionario!$N:$N,MATCH(F56,Diccionario!$C:$C,0)),"")
A57: 2025-06 | B57: Colombia | C57: Coco Colombia | D57: COP | E57: Real | F57: utilidad_neta | I57: -26000000 | J57: COP | K57: Derivado: ingresos - egresos | L57: =IFERROR(INDEX(Diccionario!$B:$B,MATCH(F57,Diccionario!$C:$C,0)),"") | M57: =IFERROR(INDEX(Diccionario!$H:$H,MATCH(F57,Diccionario!$C:$C,0)),"") | N57: =IFERROR(INDEX(Diccionario!$N:$N,MATCH(F57,Diccionario!$C:$C,0)),"")
A58: 2025-07 | B58: Colombia | C58: Coco Colombia | D58: COP | E58: Real | F58: ingresos_totales | I58: 648000000 | J58: COP | L58: =IFERROR(INDEX(Diccionario!$B:$B,MATCH(F58,Diccionario!$C:$C,0)),"") | M58: =IFERROR(INDEX(Diccionario!$H:$H,MATCH(F58,Diccionario!$C:$C,0)),"") | N58: =IFERROR(INDEX(Diccionario!$N:$N,MATCH(F58,Diccionario!$C:$C,0)),"")
A59: 2025-07 | B59: Colombia | C59: Coco Colombia | D59: COP | E59: Real | F59: egresos_totales | I59: 884000000 | J59: COP | L59: =IFERROR(INDEX(Diccionario!$B:$B,MATCH(F59,Diccionario!$C:$C,0)),"") | M59: =IFERROR(INDEX(Diccionario!$H:$H,MATCH(F59,Diccionario!$C:$C,0)),"") | N59: =IFERROR(INDEX(Diccionario!$N:$N,MATCH(F59,Diccionario!$C:$C,0)),"")
A60: 2025-07 | B60: Colombia | C60: Coco Colombia | D60: COP | E60: Real | F60: utilidad_neta | I60: -236000000 | J60: COP | K60: Derivado: ingresos - egresos | L60: =IFERROR(INDEX(Diccionario!$B:$B,MATCH(F60,Diccionario!$C:$C,0)),"") | M60: =IFERROR(INDEX(Diccionario!$H:$H,MATCH(F60,Diccionario!$C:$C,0)),"") | N60: =IFERROR(INDEX(Diccionario!$N:$N,MATCH(F60,Diccionario!$C:$C,0)),"")
A61: 2025-08 | B61: Colombia | C61: Coco Colombia | D61: COP | E61: Real | F61: ingresos_totales | I61: 634000000 | J61: COP | L61: =IFERROR(INDEX(Diccionario!$B:$B,MATCH(F61,Diccionario!$C:$C,0)),"") | M61: =IFERROR(INDEX(Diccionario!$H:$H,MATCH(F61,Diccionario!$C:$C,0)),"") | N61: =IFERROR(INDEX(Diccionario!$N:$N,MATCH(F61,Diccionario!$C:$C,0)),"")
A62: 2025-08 | B62: Colombia | C62: Coco Colombia | D62: COP | E62: Real | F62: egresos_totales | I62: 673000000 | J62: COP | L62: =IFERROR(INDEX(Diccionario!$B:$B,MATCH(F62,Diccionario!$C:$C,0)),"") | M62: =IFERROR(INDEX(Diccionario!$H:$H,MATCH(F62,Diccionario!$C:$C,0)),"") | N62: =IFERROR(INDEX(Diccionario!$N:$N,MATCH(F62,Diccionario!$C:$C,0)),"")
A63: 2025-08 | B63: Colombia | C63: Coco Colombia | D63: COP | E63: Real | F63: utilidad_neta | I63: -39000000 | J63: COP | K63: Derivado: ingresos - egresos | L63: =IFERROR(INDEX(Diccionario!$B:$B,MATCH(F63,Diccionario!$C:$C,0)),"") | M63: =IFERROR(INDEX(Diccionario!$H:$H,MATCH(F63,Diccionario!$C:$C,0)),"") | N63: =IFERROR(INDEX(Diccionario!$N:$N,MATCH(F63,Diccionario!$C:$C,0)),"")
A64: 2025-09 | B64: Colombia | C64: Coco Colombia | D64: COP | E64: Real | F64: ingresos_totales | I64: 758000000 | J64: COP | L64: =IFERROR(INDEX(Diccionario!$B:$B,MATCH(F64,Diccionario!$C:$C,0)),"") | M64: =IFERROR(INDEX(Diccionario!$H:$H,MATCH(F64,Diccionario!$C:$C,0)),"") | N64: =IFERROR(INDEX(Diccionario!$N:$N,MATCH(F64,Diccionario!$C:$C,0)),"")
A65: 2025-09 | B65: Colombia | C65: Coco Colombia | D65: COP | E65: Real | F65: egresos_totales | I65: 708000000 | J65: COP | L65: =IFERROR(INDEX(Diccionario!$B:$B,MATCH(F65,Diccionario!$C:$C,0)),"") | M65: =IFERROR(INDEX(Diccionario!$H:$H,MATCH(F65,Diccionario!$C:$C,0)),"") | N65: =IFERROR(INDEX(Diccionario!$N:$N,MATCH(F65,Diccionario!$C:$C,0)),"")
A66: 2025-09 | B66: Colombia | C66: Coco Colombia | D66: COP | E66: Real | F66: utilidad_neta | I66: 50000000 | J66: COP | K66: Derivado: ingresos - egresos | L66: =IFERROR(INDEX(Diccionario!$B:$B,MATCH(F66,Diccionario!$C:$C,0)),"") | M66: =IFERROR(INDEX(Diccionario!$H:$H,MATCH(F66,Diccionario!$C:$C,0)),"") | N66: =IFERROR(INDEX(Diccionario!$N:$N,MATCH(F66,Diccionario!$C:$C,0)),"")
A67: 2025-10 | B67: Colombia | C67: Coco Colombia | D67: COP | E67: Real | F67: ingresos_totales | I67: 691000000 | J67: COP | L67: =IFERROR(INDEX(Diccionario!$B:$B,MATCH(F67,Diccionario!$C:$C,0)),"") | M67: =IFERROR(INDEX(Diccionario!$H:$H,MATCH(F67,Diccionario!$C:$C,0)),"") | N67: =IFERROR(INDEX(Diccionario!$N:$N,MATCH(F67,Diccionario!$C:$C,0)),"")
A68: 2025-10 | B68: Colombia | C68: Coco Colombia | D68: COP | E68: Real | F68: egresos_totales | I68: 778000000 | J68: COP | L68: =IFERROR(INDEX(Diccionario!$B:$B,MATCH(F68,Diccionario!$C:$C,0)),"") | M68: =IFERROR(INDEX(Diccionario!$H:$H,MATCH(F68,Diccionario!$C:$C,0)),"") | N68: =IFERROR(INDEX(Diccionario!$N:$N,MATCH(F68,Diccionario!$C:$C,0)),"")
A69: 2025-10 | B69: Colombia | C69: Coco Colombia | D69: COP | E69: Real | F69: utilidad_neta | I69: -87000000 | J69: COP | K69: Derivado: ingresos - egresos | L69: =IFERROR(INDEX(Diccionario!$B:$B,MATCH(F69,Diccionario!$C:$C,0)),"") | M69: =IFERROR(INDEX(Diccionario!$H:$H,MATCH(F69,Diccionario!$C:$C,0)),"") | N69: =IFERROR(INDEX(Diccionario!$N:$N,MATCH(F69,Diccionario!$C:$C,0)),"")
A70: 2025-11 | B70: Colombia | C70: Coco Colombia | D70: COP | E70: Real | F70: ingresos_totales | I70: 700000000 | J70: COP | L70: =IFERROR(INDEX(Diccionario!$B:$B,MATCH(F70,Diccionario!$C:$C,0)),"") | M70: =IFERROR(INDEX(Diccionario!$H:$H,MATCH(F70,Diccionario!$C:$C,0)),"") | N70: =IFERROR(INDEX(Diccionario!$N:$N,MATCH(F70,Diccionario!$C:$C,0)),"")
A71: 2025-11 | B71: Colombia | C71: Coco Colombia | D71: COP | E71: Real | F71: egresos_totales | I71: 739000000 | J71: COP | L71: =IFERROR(INDEX(Diccionario!$B:$B,MATCH(F71,Diccionario!$C:$C,0)),"") | M71: =IFERROR(INDEX(Diccionario!$H:$H,MATCH(F71,Diccionario!$C:$C,0)),"") | N71: =IFERROR(INDEX(Diccionario!$N:$N,MATCH(F71,Diccionario!$C:$C,0)),"")
A72: 2025-11 | B72: Colombia | C72: Coco Colombia | D72: COP | E72: Real | F72: utilidad_neta | I72: -39000000 | J72: COP | K72: Derivado: ingresos - egresos | L72: =IFERROR(INDEX(Diccionario!$B:$B,MATCH(F72,Diccionario!$C:$C,0)),"") | M72: =IFERROR(INDEX(Diccionario!$H:$H,MATCH(F72,Diccionario!$C:$C,0)),"") | N72: =IFERROR(INDEX(Diccionario!$N:$N,MATCH(F72,Diccionario!$C:$C,0)),"")
A73: 2025-12 | B73: Colombia | C73: Coco Colombia | D73: COP | E73: Real | F73: ingresos_totales | I73: 765000000 | J73: COP | L73: =IFERROR(INDEX(Diccionario!$B:$B,MATCH(F73,Diccionario!$C:$C,0)),"") | M73: =IFERROR(INDEX(Diccionario!$H:$H,MATCH(F73,Diccionario!$C:$C,0)),"") | N73: =IFERROR(INDEX(Diccionario!$N:$N,MATCH(F73,Diccionario!$C:$C,0)),"")
A74: 2025-12 | B74: Colombia | C74: Coco Colombia | D74: COP | E74: Real | F74: egresos_totales | I74: 718000000 | J74: COP | L74: =IFERROR(INDEX(Diccionario!$B:$B,MATCH(F74,Diccionario!$C:$C,0)),"") | M74: =IFERROR(INDEX(Diccionario!$H:$H,MATCH(F74,Diccionario!$C:$C,0)),"") | N74: =IFERROR(INDEX(Diccionario!$N:$N,MATCH(F74,Diccionario!$C:$C,0)),"")
A75: 2025-12 | B75: Colombia | C75: Coco Colombia | D75: COP | E75: Real | F75: utilidad_neta | I75: 47000000 | J75: COP | K75: Derivado: ingresos - egresos | L75: =IFERROR(INDEX(Diccionario!$B:$B,MATCH(F75,Diccionario!$C:$C,0)),"") | M75: =IFERROR(INDEX(Diccionario!$H:$H,MATCH(F75,Diccionario!$C:$C,0)),"") | N75: =IFERROR(INDEX(Diccionario!$N:$N,MATCH(F75,Diccionario!$C:$C,0)),"")
A76: 2026-01 | B76: Colombia | C76: Coco Colombia | D76: COP | E76: Real | F76: ingresos_totales | I76: 612247701 | J76: COP | K76: Ajustado al cierre oficial (PDF Estados Financieros Junio 2026); serie mensual del Modelo, suma = 4.472.342.747 | L76: =IFERROR(INDEX(Diccionario!$B:$B,MATCH(F76,Diccionario!$C:$C,0)),"") | M76: =IFERROR(INDEX(Diccionario!$H:$H,MATCH(F76,Diccionario!$C:$C,0)),"") | N76: =IFERROR(INDEX(Diccionario!$N:$N,MATCH(F76,Diccionario!$C:$C,0)),"")
A77: 2026-01 | B77: Colombia | C77: Coco Colombia | D77: COP | E77: Real | F77: egresos_totales | I77: 542000000 | J77: COP | L77: =IFERROR(INDEX(Diccionario!$B:$B,MATCH(F77,Diccionario!$C:$C,0)),"") | M77: =IFERROR(INDEX(Diccionario!$H:$H,MATCH(F77,Diccionario!$C:$C,0)),"") | N77: =IFERROR(INDEX(Diccionario!$N:$N,MATCH(F77,Diccionario!$C:$C,0)),"")
A78: 2026-01 | B78: Colombia | C78: Coco Colombia | D78: COP | E78: Real | F78: utilidad_neta | I78: 91000000 | J78: COP | K78: Derivado: ingresos - egresos | L78: =IFERROR(INDEX(Diccionario!$B:$B,MATCH(F78,Diccionario!$C:$C,0)),"") | M78: =IFERROR(INDEX(Diccionario!$H:$H,MATCH(F78,Diccionario!$C:$C,0)),"") | N78: =IFERROR(INDEX(Diccionario!$N:$N,MATCH(F78,Diccionario!$C:$C,0)),"")
A79: 2026-02 | B79: Colombia | C79: Coco Colombia | D79: COP | E79: Real | F79: ingresos_totales | I79: 744218137 | J79: COP | K79: Ajustado al cierre oficial (PDF Estados Financieros Junio 2026); serie mensual del Modelo, suma = 4.472.342.747 | L79: =IFERROR(INDEX(Diccionario!$B:$B,MATCH(F79,Diccionario!$C:$C,0)),"") | M79: =IFERROR(INDEX(Diccionario!$H:$H,MATCH(F79,Diccionario!$C:$C,0)),"") | N79: =IFERROR(INDEX(Diccionario!$N:$N,MATCH(F79,Diccionario!$C:$C,0)),"")
A80: 2026-02 | B80: Colombia | C80: Coco Colombia | D80: COP | E80: Real | F80: egresos_totales | I80: 684000000 | J80: COP | L80: =IFERROR(INDEX(Diccionario!$B:$B,MATCH(F80,Diccionario!$C:$C,0)),"") | M80: =IFERROR(INDEX(Diccionario!$H:$H,MATCH(F80,Diccionario!$C:$C,0)),"") | N80: =IFERROR(INDEX(Diccionario!$N:$N,MATCH(F80,Diccionario!$C:$C,0)),"")
A81: 2026-02 | B81: Colombia | C81: Coco Colombia | D81: COP | E81: Real | F81: utilidad_neta | I81: 60000000 | J81: COP | K81: Derivado: ingresos - egresos | L81: =IFERROR(INDEX(Diccionario!$B:$B,MATCH(F81,Diccionario!$C:$C,0)),"") | M81: =IFERROR(INDEX(Diccionario!$H:$H,MATCH(F81,Diccionario!$C:$C,0)),"") | N81: =IFERROR(INDEX(Diccionario!$N:$N,MATCH(F81,Diccionario!$C:$C,0)),"")
A82: 2026-03 | B82: Colombia | C82: Coco Colombia | D82: COP | E82: Real | F82: ingresos_totales | I82: 787041187 | J82: COP | K82: Ajustado al cierre oficial (PDF Estados Financieros Junio 2026); serie mensual del Modelo, suma = 4.472.342.747 | L82: =IFERROR(INDEX(Diccionario!$B:$B,MATCH(F82,Diccionario!$C:$C,0)),"") | M82: =IFERROR(INDEX(Diccionario!$H:$H,MATCH(F82,Diccionario!$C:$C,0)),"") | N82: =IFERROR(INDEX(Diccionario!$N:$N,MATCH(F82,Diccionario!$C:$C,0)),"")
A83: 2026-03 | B83: Colombia | C83: Coco Colombia | D83: COP | E83: Real | F83: egresos_totales | I83: 806000000 | J83: COP | L83: =IFERROR(INDEX(Diccionario!$B:$B,MATCH(F83,Diccionario!$C:$C,0)),"") | M83: =IFERROR(INDEX(Diccionario!$H:$H,MATCH(F83,Diccionario!$C:$C,0)),"") | N83: =IFERROR(INDEX(Diccionario!$N:$N,MATCH(F83,Diccionario!$C:$C,0)),"")
A84: 2026-03 | B84: Colombia | C84: Coco Colombia | D84: COP | E84: Real | F84: utilidad_neta | I84: -37000000 | J84: COP | K84: Derivado: ingresos - egresos | L84: =IFERROR(INDEX(Diccionario!$B:$B,MATCH(F84,Diccionario!$C:$C,0)),"") | M84: =IFERROR(INDEX(Diccionario!$H:$H,MATCH(F84,Diccionario!$C:$C,0)),"") | N84: =IFERROR(INDEX(Diccionario!$N:$N,MATCH(F84,Diccionario!$C:$C,0)),"")
A85: 2026-04 | B85: Colombia | C85: Coco Colombia | D85: COP | E85: Real | F85: ingresos_totales | I85: 750867662 | J85: COP | K85: Ajustado al cierre oficial (PDF Estados Financieros Junio 2026); serie mensual del Modelo, suma = 4.472.342.747 | L85: =IFERROR(INDEX(Diccionario!$B:$B,MATCH(F85,Diccionario!$C:$C,0)),"") | M85: =IFERROR(INDEX(Diccionario!$H:$H,MATCH(F85,Diccionario!$C:$C,0)),"") | N85: =IFERROR(INDEX(Diccionario!$N:$N,MATCH(F85,Diccionario!$C:$C,0)),"")
A86: 2026-04 | B86: Colombia | C86: Coco Colombia | D86: COP | E86: Real | F86: egresos_totales | I86: 755000000 | J86: COP | L86: =IFERROR(INDEX(Diccionario!$B:$B,MATCH(F86,Diccionario!$C:$C,0)),"") | M86: =IFERROR(INDEX(Diccionario!$H:$H,MATCH(F86,Diccionario!$C:$C,0)),"") | N86: =IFERROR(INDEX(Diccionario!$N:$N,MATCH(F86,Diccionario!$C:$C,0)),"")
A87: 2026-04 | B87: Colombia | C87: Coco Colombia | D87: COP | E87: Real | F87: utilidad_neta | I87: -1000000 | J87: COP | K87: Derivado: ingresos - egresos | L87: =IFERROR(INDEX(Diccionario!$B:$B,MATCH(F87,Diccionario!$C:$C,0)),"") | M87: =IFERROR(INDEX(Diccionario!$H:$H,MATCH(F87,Diccionario!$C:$C,0)),"") | N87: =IFERROR(INDEX(Diccionario!$N:$N,MATCH(F87,Diccionario!$C:$C,0)),"")
A88: 2026-05 | B88: Colombia | C88: Coco Colombia | D88: COP | E88: Real | F88: ingresos_totales | I88: 826514746 | J88: COP | K88: Ajustado al cierre oficial (PDF Estados Financieros Junio 2026); serie mensual del Modelo, suma = 4.472.342.747 | L88: =IFERROR(INDEX(Diccionario!$B:$B,MATCH(F88,Diccionario!$C:$C,0)),"") | M88: =IFERROR(INDEX(Diccionario!$H:$H,MATCH(F88,Diccionario!$C:$C,0)),"") | N88: =IFERROR(INDEX(Diccionario!$N:$N,MATCH(F88,Diccionario!$C:$C,0)),"")
A89: 2026-05 | B89: Colombia | C89: Coco Colombia | D89: COP | E89: Real | F89: egresos_totales | I89: 720000000 | J89: COP | L89: =IFERROR(INDEX(Diccionario!$B:$B,MATCH(F89,Diccionario!$C:$C,0)),"") | M89: =IFERROR(INDEX(Diccionario!$H:$H,MATCH(F89,Diccionario!$C:$C,0)),"") | N89: =IFERROR(INDEX(Diccionario!$N:$N,MATCH(F89,Diccionario!$C:$C,0)),"")
A90: 2026-05 | B90: Colombia | C90: Coco Colombia | D90: COP | E90: Real | F90: utilidad_neta | I90: 92000000 | J90: COP | K90: Derivado: ingresos - egresos | L90: =IFERROR(INDEX(Diccionario!$B:$B,MATCH(F90,Diccionario!$C:$C,0)),"") | M90: =IFERROR(INDEX(Diccionario!$H:$H,MATCH(F90,Diccionario!$C:$C,0)),"") | N90: =IFERROR(INDEX(Diccionario!$N:$N,MATCH(F90,Diccionario!$C:$C,0)),"")
A91: 2025-06 | B91: Colombia | C91: Coco Colombia | D91: COP | E91: Real | F91: ebitda | I91: 154028000 | J91: COP | L91: =IFERROR(INDEX(Diccionario!$B:$B,MATCH(F91,Diccionario!$C:$C,0)),"") | M91: =IFERROR(INDEX(Diccionario!$H:$H,MATCH(F91,Diccionario!$C:$C,0)),"") | N91: =IFERROR(INDEX(Diccionario!$N:$N,MATCH(F91,Diccionario!$C:$C,0)),"")
A92: 2025-07 | B92: Colombia | C92: Coco Colombia | D92: COP | E92: Real | F92: ebitda | I92: 210623000 | J92: COP | L92: =IFERROR(INDEX(Diccionario!$B:$B,MATCH(F92,Diccionario!$C:$C,0)),"") | M92: =IFERROR(INDEX(Diccionario!$H:$H,MATCH(F92,Diccionario!$C:$C,0)),"") | N92: =IFERROR(INDEX(Diccionario!$N:$N,MATCH(F92,Diccionario!$C:$C,0)),"")
A93: 2025-08 | B93: Colombia | C93: Coco Colombia | D93: COP | E93: Real | F93: ebitda | I93: 219976000 | J93: COP | L93: =IFERROR(INDEX(Diccionario!$B:$B,MATCH(F93,Diccionario!$C:$C,0)),"") | M93: =IFERROR(INDEX(Diccionario!$H:$H,MATCH(F93,Diccionario!$C:$C,0)),"") | N93: =IFERROR(INDEX(Diccionario!$N:$N,MATCH(F93,Diccionario!$C:$C,0)),"")
A94: 2025-09 | B94: Colombia | C94: Coco Colombia | D94: COP | E94: Real | F94: ebitda | I94: 207986000 | J94: COP | L94: =IFERROR(INDEX(Diccionario!$B:$B,MATCH(F94,Diccionario!$C:$C,0)),"") | M94: =IFERROR(INDEX(Diccionario!$H:$H,MATCH(F94,Diccionario!$C:$C,0)),"") | N94: =IFERROR(INDEX(Diccionario!$N:$N,MATCH(F94,Diccionario!$C:$C,0)),"")
A95: 2025-10 | B95: Colombia | C95: Coco Colombia | D95: COP | E95: Real | F95: ebitda | I95: 230467000 | J95: COP | L95: =IFERROR(INDEX(Diccionario!$B:$B,MATCH(F95,Diccionario!$C:$C,0)),"") | M95: =IFERROR(INDEX(Diccionario!$H:$H,MATCH(F95,Diccionario!$C:$C,0)),"") | N95: =IFERROR(INDEX(Diccionario!$N:$N,MATCH(F95,Diccionario!$C:$C,0)),"")
A96: 2025-11 | B96: Colombia | C96: Coco Colombia | D96: COP | E96: Real | F96: ebitda | I96: 240545000 | J96: COP | L96: =IFERROR(INDEX(Diccionario!$B:$B,MATCH(F96,Diccionario!$C:$C,0)),"") | M96: =IFERROR(INDEX(Diccionario!$H:$H,MATCH(F96,Diccionario!$C:$C,0)),"") | N96: =IFERROR(INDEX(Diccionario!$N:$N,MATCH(F96,Diccionario!$C:$C,0)),"")
A97: 2025-12 | B97: Colombia | C97: Coco Colombia | D97: COP | E97: Real | F97: ebitda | I97: 231501000 | J97: COP | L97: =IFERROR(INDEX(Diccionario!$B:$B,MATCH(F97,Diccionario!$C:$C,0)),"") | M97: =IFERROR(INDEX(Diccionario!$H:$H,MATCH(F97,Diccionario!$C:$C,0)),"") | N97: =IFERROR(INDEX(Diccionario!$N:$N,MATCH(F97,Diccionario!$C:$C,0)),"")
A98: 2026-01 | B98: Colombia | C98: Coco Colombia | D98: COP | E98: Real | F98: ebitda | I98: 207987000 | J98: COP | L98: =IFERROR(INDEX(Diccionario!$B:$B,MATCH(F98,Diccionario!$C:$C,0)),"") | M98: =IFERROR(INDEX(Diccionario!$H:$H,MATCH(F98,Diccionario!$C:$C,0)),"") | N98: =IFERROR(INDEX(Diccionario!$N:$N,MATCH(F98,Diccionario!$C:$C,0)),"")
A99: 2026-02 | B99: Colombia | C99: Coco Colombia | D99: COP | E99: Real | F99: ebitda | I99: 191717000 | J99: COP | L99: =IFERROR(INDEX(Diccionario!$B:$B,MATCH(F99,Diccionario!$C:$C,0)),"") | M99: =IFERROR(INDEX(Diccionario!$H:$H,MATCH(F99,Diccionario!$C:$C,0)),"") | N99: =IFERROR(INDEX(Diccionario!$N:$N,MATCH(F99,Diccionario!$C:$C,0)),"")
A100: 2026-03 | B100: Colombia | C100: Coco Colombia | D100: COP | E100: Real | F100: ebitda | I100: 201750000 | J100: COP | L100: =IFERROR(INDEX(Diccionario!$B:$B,MATCH(F100,Diccionario!$C:$C,0)),"") | M100: =IFERROR(INDEX(Diccionario!$H:$H,MATCH(F100,Diccionario!$C:$C,0)),"") | N100: =IFERROR(INDEX(Diccionario!$N:$N,MATCH(F100,Diccionario!$C:$C,0)),"")
...

Sheet TRM
A1: TRM mensual (COP por USD) — derivada de ingresos COP / ingresos USD
A2: El dashboard convierte a USD dividiendo el valor COP entre la TRM del periodo. Editable.
A3: periodo | B3: trm_cop_usd | C3: fuente | D3: trm_promedio_mercado
A4: 2024-01 | B4: 4420 | C4: Ingresos COP/USD | D4: 3915.2
A5: 2024-02 | B5: 4420 | C5: Ingresos COP/USD | D5: 3931.44
A6: 2024-03 | B6: 4420 | C6: Ingresos COP/USD | D6: 3899.34
A7: 2024-04 | B7: 4420 | C7: Ingresos COP/USD | D7: 3867.98
A8: 2024-05 | B8: 4420 | C8: Ingresos COP/USD | D8: 3869.1
A9: 2024-06 | B9: 4420 | C9: Ingresos COP/USD | D9: 4042.8
A10: 2024-07 | B10: 4420 | C10: Ingresos COP/USD | D10: 4036.92
A11: 2024-08 | B11: 4420 | C11: Ingresos COP/USD | D11: 4065.55
A12: 2024-09 | B12: 4420 | C12: Ingresos COP/USD | D12: 4182.51
A13: 2024-10 | B13: 4420 | C13: Ingresos COP/USD | D13: 4249.47
A14: 2024-11 | B14: 4420 | C14: Ingresos COP/USD | D14: 4408.65
A15: 2024-12 | B15: 4420 | C15: Ingresos COP/USD | D15: 4385.15
... A33: 2026-06 | B33: 4170 | C33: Ingresos COP/USD | D33: 3571.44
A34: 2023-07 | C34: TRM promedio mensual (mercado) | D34: 4069.23
A35: 2023-08 | C35: TRM promedio mensual (mercado) | D35: 4070.73
A36: 2023-09 | C36: TRM promedio mensual (mercado) | D36: 4004.52
A37: 2023-10 | C37: TRM promedio mensual (mercado) | D37: 4222.43
A38: 2023-11 | C38: TRM promedio mensual (mercado) | D38: 4038.8
A39: 2023-12 | C39: TRM promedio mensual (mercado) | D39: 3948.21
A40: 2026-07 | B40: 3505.2683 | C40: Base previa/impl?cita para convertir Colombia julio

Sheet TRM_Peru
A1: Tasa de cambio Perú — promedio mensual 2026 (S/ por US$)
A2: Fuente: BCRP (promedio del periodo). Julio = promedio del mes hasta la fecha (días hábiles 1–9 jul, provisional).
A4: periodo | B4: par | C4: tc_pen_usd | D4: factor_usd_pen | E4: fuente
A5: 2026-01 | B5: PEN/USD | C5: 3.357 | D5: 0.297885 | E5: BCRP promedio mensual
A6: 2026-02 | B6: PEN/USD | C6: 3.357 | D6: 0.297885 | E6: BCRP promedio mensual
A7: 2026-03 | B7: PEN/USD | C7: 3.447 | D7: 0.290107 | E7: BCRP promedio mensual
A8: 2026-04 | B8: PEN/USD | C8: 3.443 | D8: 0.290444 | E8: BCRP promedio mensual
A9: 2026-05 | B9: PEN/USD | C9: 3.435 | D9: 0.291121 | E9: BCRP promedio mensual
A10: 2026-06 | B10: PEN/USD | C10: 3.405 | D10: 0.293686 | E10: BCRP promedio mensual
A11: 2026-07* | B11: PEN/USD | C11: 3.405 | D11: 0.293686 | E11: Promedio hasta 9-jul (provisional)

Sheet Calc_LTV_Fin
A1: LTV financiero (margen bruto + churn de ingresos TTM)
A2: Cambia solo la celda amarilla (margen bruto) y LTV / payback / LTV:CAC se recalculan. Ventana TTM jun-2025 a may-2026.
A4: Margen bruto (EDITABLE) | B4: 0.51 | C4: Source: Contabilidad, may-2026
A5: ARPA mensual prom. (TTM) | B5: 8307111 | C5: Prom. ARPU mercadeo TTM
A6: Churn de ingresos mensual (TTM) | B6: 0.0102 | C6: Σchurned / Σmrr_inicio (MRR bridge)
A7: Churn de clientes mensual (TTM) | B7: 0.0117 | C7: Account Churn mercadeo (comparativo)
A8: CAC prom. trimestral (TTM) | B8: 64935810 | C8: Prom. CAC mercadeo en la ventana
A10: RESULTADOS
A11: LTV financiero (COP) | B11: =B5*B4/B6
A12: Payback financiero (meses) | B12: =B8/(B5*B4)
A13: LTV:CAC financiero (veces) | B13: =B11/B8

Sheet Analisis_Churn
A1: Análisis de Churn — Informe Contabilidad mayo 2026
A2: Valor de churn en USD. Definición de la cifra (MRR perdido vs. valor de contrato) a confirmar. Total churn = 40.131 USD.
A4: 1. Churn por razón de retiro
A5: Razón | B5: Valor USD | C5: % del total
A6: Cambio de gerente | B6: 3689 | C6: 0.0919
A7: Interoperabilidad | B7: 1381 | C7: 0.0344
A8: No agrega valor | B8: 18462 | C8: 0.46
A9: Piloto no exitoso | B9: 558 | C9: 0.0139
A10: Presupuesto | B10: 16040 | C10: 0.3997
A11: Total | B11: 40131 | C11: 1
A13: 2. Churn por factor
A14: Factor | B14: Valor USD | C14: % del total
A15: Externo | B15: 19436 | C15: 0.4843
A16: Interno | B16: 20694 | C16: 0.5157
A17: Total | B17: 40131 | C17: 1
A19: 3. Churn por tamaño de cliente
A20: Tamaño | B20: Valor USD | C20: Comparativo 'Enero'
A21: Grande | B21: 28116 | C21: 0
A22: Mediano | B22: 8720 | C22: 14164
A23: Pequeño | B23: 3294 | C23: 1731
A24: Total | B24: 40131 | C24: 15895
A26: 4. Notas y hallazgos (CS)
A27: • Salud Total representa el 40% del churn.
A28: • No gastar esfuerzo comercial en clientes con < 3.000 citas mensuales o consultorios particulares.
A29: • El churn de B2C debe medirse aparte del agendamiento.
A30: • Producto: estabilización del bot en Q1.
A31: • Campañas y mejoras para Q3.

Sheet Analisis_Reconciliacion
A1: Facturación Contable vs Ejecutada — mayo 2026 (S2)
A3: Concepto | B3: Contable (COP) | C3: Ejecutada (COP) | D3: Contable (USD) | E3: Ejecutada (USD)
A4: Ingresos operativos | B4: 826514745 | C4: 812464793 | D4: 223987.74 | E4: 220180.16
A5: Otros ingresos | B5: 1366337 | C5: 1366337 | D5: 370.28103 | E5: 370.28103
A6: Egresos | B6: 713505270 | C6: 713505270 | D6: 193361.86 | E6: 193361.86
A7: Financieros | B7: 6000847 | C7: 6000847 | D7: 1626.2458 | E7: 1626.2458
A8: Utilidad | B8: 108374965 | C8: 94325013 | D8: 29369.909 | E8: 25562.334

Sheet CATALOGOS
A1: area | B1: codigo_indicador | D1: paises | E1: escenarios | F1: monedas | G1: companias
A2: Finanzas | B2: ingresos_totales | D2: Colombia | E2: Real | F2: COP | G2: Coco Colombia
A3: Finanzas | B3: ingresos_recurrentes | D3: EE.UU. | E3: Presupuesto | F3: USD | G3: Coco LLC
A4: Finanzas | B4: ingresos_no_recurrentes | D4: Perú | E4: Modelo | G4: Coco Perú
A5: Finanzas | B5: costo_proveedor_ventas_pct | D5: Costa Rica | G5: Coco Costa Rica
A6: Finanzas | B6: ebitda | D6: Consolidado | G6: Coco Consolidado
A7: Finanzas | B7: utilidad_neta | D7: Otros
A8: Finanzas | B8: egresos_totales
A9: Finanzas | B9: burn_rate_neto
A10: Finanzas | B10: runway_meses
A11: Ingresos_MRR | B11: mrr_final
A12: Ingresos_MRR | B12: arr
A13: Ingresos_MRR | B13: arpa
A14: Ingresos_MRR | B14: retained_mrr
A15: Ingresos_MRR | B15: new_mrr
A16: Ingresos_MRR | B16: expansion_mrr
A17: Ingresos_MRR | B17: reactivacion_mrr
A18: Ingresos_MRR | B18: contraction_mrr
A19: Ingresos_MRR | B19: churned_mrr
... A66: Internacional | B66: clientes_internacionales

Sheet LOG
A1: timestamp | B1: usuario | C1: accion | D1: area | E1: hoja | F1: filas_afectadas | G1: detalle
A2: 2026-08-12T14:53:01 | B2: Codex | C2: actualizacion_bd_local | D2: Finanzas | E2: BD_MAESTRA_COCO | F2: 84 | G2: EEFF julio 2026: soporte contable, P&G Colombia mensual, bloque internacional y candidatos intercompa??a.
A3: 2026-08-12T14:55:03 | B3: Codex | C3: correccion_actualizacion_bd_local | D3: Finanzas | E3: BD_MAESTRA_COCO | F3: 84 | G3: Correcci?n: julio Colombia derivado solo con filas COP locales, excluyendo conversiones USD.
C4: Actualizaci?n final julio 2026 | G4: Base maestra actualizada con Colombia, EE.UU., Per? y Costa Rica julio; consolidado USD recalculado; CR julio agregado desde Julio 2026 CR.xlsx.
A5: 2026-08-12T17:09 | B5: Codex | C5: organizacion_base_datos | D5: Finanzas/BI | E5: BD_MAESTRA_COCO | F5: 1261 | G5: Se agregan capas BD_PYG_OFICIAL, BD_GASTOS_HOMOLOGADOS, MAP_DASHBOARD_GASTOS, BD_GASTOS_DASHBOARD_BRIDGE y DB_CHECKS_ORGANIZACION.
A6: 2026-08-12T17:11 | B6: Codex | C6: ajuste_organizacion_base | D6: Finanzas/BI | E6: BD_MAESTRA_COCO | F6: 129 | G6: Se agrega BD_GASTOS_RESUMEN_MENSUAL y se corrigen checks normalizados de cobertura julio.

Sheet Pipeline_Comercial
A1: cliente | B1: comercial | C1: tipo | D1: prob | E1: mes | F1: mrr_cop | G1: impl_cop | H1: citas | I1: valor_cop | J1: ponderado_cop

Sheet MAP_DASHBOARD_GASTOS
A1: codigo_comun | B1: rubro_comun | C1: categoria_comun | D1: indicador_dashboard | E1: detalle_dashboard | F1: area_dashboard | G1: usar_en_grafica | H1: criterio | I1: estado_mapeo
A2: PL-O-010 | B2: Gastos de personal | C2: Gastos de administraci?n | D2: gasto_admin | E2: Personal | F2: Administracion | G2: SI | H2: Administracion: personal, n?mina y beneficios | I2: Aprobado
A3: PL-O-020 | B3: Honorarios y servicios profesionales | C3: Gastos de administraci?n | D3: gasto_admin | E3: Honorarios | F3: Administracion | G3: SI | H3: Servicios profesionales administrativos | I3: Aprobado
A4: PL-O-030 | B4: Impuestos y contribuciones | C4: Gastos de administraci?n | D4: gasto_admin | E4: Diversos | F4: Administracion | G4: SI | H4: Impuestos administrativos no financieros | I4: Aprobado
A5: PL-O-040 | B5: Arrendamientos | C5: Gastos de administraci?n | D5: gasto_admin | E5: Arrendamiento | F5: Administracion | G5: SI | H5: Arrendamientos administrativos | I5: Aprobado
A6: PL-O-050 | B6: Seguros | C6: Gastos de administraci?n | D6: gasto_admin | E6: Seguros | F6: Administracion | G6: SI | H6: P?lizas y seguros | I6: Aprobado
A7: PL-O-060 | B7: Tecnolog?a y procesamiento de datos | C7: Gastos de administraci?n | D7: gasto_admin | E7: Servicios | F7: Administracion | G7: SI | H7: Servicios tecnol?gicos administrativos | I7: Aprobado
A8: PL-O-070 | B8: Telecomunicaciones | C8: Gastos de administraci?n | D8: gasto_admin | E8: Servicios | F8: Administracion | G8: SI | H8: Telecomunicaciones y conectividad | I8: Aprobado
A9: PL-O-080 | B9: Correo y mensajer?a | C9: Gastos de administraci?n | D9: gasto_admin | E9: Servicios | F9: Administracion | G9: SI | H9: Mensajer?a y correo | I9: Aprobado
A10: PL-O-090 | B10: Viajes y representaci?n | C10: Gastos de administraci?n | D10: gasto_admin | E10: Viajes | F10: Administracion | G10: SI | H10: Viajes y representaci?n | I10: Aprobado
A11: PL-O-100 | B11: Otros servicios administrativos | C11: Gastos de administraci?n | D11: gasto_admin | E11: Servicios | F11: Administracion | G11: SI | H11: Servicios administrativos no clasificados | I11: Revisar
A12: PL-O-110 | B12: Suministros y oficina | C12: Gastos de administraci?n | D12: gasto_admin | E12: Diversos | F12: Administracion | G12: SI | H12: Suministros/oficina | I12: Aprobado
... A21: PL-F-010 | B21: Gastos financieros | C21: Gastos financieros | D21: gasto_area | E21: Financieros | F21: Financieros | G21: SI | H21: Costos financieros separados | I21: Aprobado

Sheet BD_GASTOS_HOMOLOGADOS
A1: periodo | B1: pais | C1: entidad | D1: moneda | E1: codigo_comun | F1: categoria | G1: rubro_comun | H1: subrubro | I1: tercero_detalle | J1: saldo_inicial | K1: debitos | L1: creditos | M1: saldo_final_fuente | N1: saldo_presentacion_ytd | O1: movimiento_mes | P1: fuente_archivo | Q1: referencia | R1: confianza | S1: revisar | T1: fundamento
A2: 2026-04 | B2: Costa Rica | C2: CR | D2: USD | E2: PL-O-010 | F2: Gastos de administración | G2: Gastos de personal | H2: Sueldos | I2: NARANJO BUSTOS MARIAM | J2: 3600 | K2: 1200 | L2: 0 | M2: 4800 | N2: 4800 | O2: 1200 | P2: Abril 2026 CR.xlsx | Q2: Fila 28 | R2: Alta | S2: NO | T2: Remuneración laboral
A3: 2026-04 | B3: Costa Rica | C3: CR | D3: USD | E3: PL-O-090 | F3: Gastos de administración | G3: Viajes y representación | H3: Viáticos | J3: 900 | K3: 300 | L3: 0 | M3: 1200 | N3: 1200 | O3: 300 | P3: Abril 2026 CR.xlsx | Q3: Fila 30 | R3: Alta | S3: NO | T3: Viáticos administrativos
A4: 2026-04 | B4: Costa Rica | C4: CR | D4: USD | E4: PL-O-010 | F4: Gastos de administración | G4: Gastos de personal | H4: Prestaciones sociales | I4: NARANJO BUSTOS MARIAM | J4: 1212.37 | K4: 400 | L4: 0 | M4: 1612.37 | N4: 1612.37 | O4: 400 | P4: Abril 2026 CR.xlsx | Q4: Fila 32 | R4: Alta | S4: NO | T4: Prestaciones laborales
A5: 2026-04 | B5: Costa Rica | C5: CR | D5: USD | E5: PL-O-020 | F5: Gastos de administración | G5: Honorarios y servicios profesionales | H5: Asesoría jurídica | I5: MUÑOZ CHACON FRANCISCO JAVIER | J5: 270.35 | K5: 0 | L5: 0 | M5: 270.35 | N5: 270.35 | O5: 0 | P5: Abril 2026 CR.xlsx | Q5: Fila 35 | R5: Alta | S5: NO | T5: Servicio profesional jurídico
A6: 2026-04 | B6: Costa Rica | C6: CR | D6: USD | E6: PL-O-030 | F6: Gastos de administración | G6: Impuestos y contribuciones | H6: Industria, comercio y otros | I6: MINISTERIO DE HACIENDA | J6: 252.73 | K6: 0 | L6: 0 | M6: 252.73 | N6: 252.73 | O6: 0 | P6: Abril 2026 CR.xlsx | Q6: Fila 38 | R6: Alta | S6: NO | T6: Impuestos no asociados a renta
A7: 2026-04 | B7: Costa Rica | C7: CR | D7: USD | E7: PL-O-030 | F7: Gastos de administración | G7: Impuestos y contribuciones | H7: Industria, comercio y otros | I7: MINISTERIO DE HACIENDA | J7: 26.55 | K7: 115.64 | L7: 0 | M7: 142.19 | N7: 142.19 | O7: 115.64 | P7: Abril 2026 CR.xlsx | Q7: Fila 39 | R7: Alta | S7: NO | T7: Impuestos no asociados a renta
A8: 2026-04 | B8: Costa Rica | C8: CR | D8: USD | E8: PL-O-030 | F8: Gastos de administración | G8: Impuestos y contribuciones | H8: Contribuciones y afiliaciones | I8: MINISTERIO DE SALUD | J8: 64.79 | K8: 0 | L8: 0 | M8: 64.79 | N8: 64.79 | O8: 0 | P8: Abril 2026 CR.xlsx | Q8: Fila 42 | R8: Alta | S8: NO | T8: Contribuciones
A9: 2026-04 | B9: Costa Rica | C9: CR | D9: USD | E9: PL-O-050 | F9: Gastos de administración | G9: Seguros | H9: Otros seguros | I9: RADIOGRAFICA COSTARRICENSE SA | J9: 0 | K9: 9205.72 | L9: 0 | M9: 9205.72 | N9: 9205.72 | O9: 9205.72 | P9: Abril 2026 CR.xlsx | Q9: Fila 45 | R9: Media | S9: SI | T9: Cuenta fuente de seguros con descripción genérica
A10: 2026-04 | B10: Costa Rica | C10: CR | D10: USD | E10: PL-O-050 | F10: Gastos de administración | G10: Seguros | H10: Otros seguros | I10: SEGUROS INS | J10: 70.81 | K10: 0 | L10: 0 | M10: 70.81 | N10: 70.81 | O10: 0 | P10: Abril 2026 CR.xlsx | Q10: Fila 46 | R10: Media | S10: SI | T10: Cuenta fuente de seguros con descripción genérica
A11: 2026-04 | B11: Costa Rica | C11: CR | D11: USD | E11: PL-O-060 | F11: Gastos de administración | G11: Tecnología y procesamiento de datos | H11: Plataformas y software | I11: CAJA COSTARRICENSE DE SEGURO SOCIAL | J11: 0 | K11: 57.71 | L11: 0 | M11: 57.71 | N11: 57.71 | O11: 57.71 | P11: Abril 2026 CR.xlsx | Q11: Fila 49 | R11: Alta | S11: SI | T11: Revisar proveedores de telecomunicaciones registrados aquí
A12: 2026-04 | B12: Costa Rica | C12: CR | D12: USD | E12: PL-O-110 | F12: Gastos de administración | G12: Suministros y oficina | H12: Útiles, papelería y fotocopias | I12: FERRETERIA EPA S.A. | J12: 39.61 | K12: 0 | L12: 0 | M12: 39.61 | N12: 39.61 | O12: 0 | P12: Abril 2026 CR.xlsx | Q12: Fila 52 | R12: Alta | S12: NO | T12: Suministros de oficina
A13: 2026-04 | B13: Costa Rica | C13: CR | D13: USD | E13: PL-O-110 | F13: Gastos de administración | G13: Suministros y oficina | H13: Útiles, papelería y fotocopias | I13: ISTORE SAN PEDRO | J13: 74.31 | K13: 0 | L13: 0 | M13: 74.31 | N13: 74.31 | O13: 0 | P13: Abril 2026 CR.xlsx | Q13: Fila 53 | R13: Alta | S13: NO | T13: Suministros de oficina
A14: 2026-04 | B14: Costa Rica | C14: CR | D14: USD | E14: PL-O-110 | F14: Gastos de administración | G14: Suministros y oficina | H14: Útiles, papelería y fotocopias | I14: MUNDO TECNOLOGIA | J14: 15 | K14: 0 | L14: 0 | M14: 15 | N14: 15 | O14: 0 | P14: Abril 2026 CR.xlsx | Q14: Fila 54 | R14: Alta | S14: NO | T14: Suministros de oficina
A15: 2026-04 | B15: Costa Rica | C15: CR | D15: USD | E15: PL-O-110 | F15: Gastos de administración | G15: Suministros y oficina | H15: Útiles, papelería y fotocopias | I15: REGISTRO NACIONAL REPUBLICA DE COSTA RICA | J15: 7 | K15: 0 | L15: 0 | M15: 7 | N15: 7 | O15: 0 | P15: Abril 2026 CR.xlsx | Q15: Fila 55 | R15: Alta | S15: NO | T15: Suministros de oficina
... A100: 2026-01 | B100: Costa Rica | C100: CR | D100: USD | E100: PL-O-010 | F100: Gastos de administración | G100: Gastos de personal | H100: Sueldos | I100: NARANJO BUSTOS MARIAM | J100: 0 | K100: 1200 | L100: 0 | M100: 1200 | N100: 1200 | O100: 1200 | P100: Enero 2026 CR.xlsx | Q100: Fila 28 | R100: Alta | S100: NO | T100: Remuneración laboral
A101: 2026-01 | B101: Costa Rica | C101: CR | D101: USD | E101: PL-O-090 | F101: Gastos de administración | G101: Viajes y representación | H101: Viáticos | J101: 0 | K101: 300 | L101: 0 | M101: 300 | N101: 300 | O101: 300 | P101: Enero 2026 CR.xlsx | Q101: Fila 30 | R101: Alta | S101: NO | T101: Viáticos administrativos
A102: 2026-01 | B102: Costa Rica | C102: CR | D102: USD | E102: PL-O-010 | F102: Gastos de administración | G102: Gastos de personal | H102: Prestaciones sociales | I102: NARANJO BUSTOS MARIAM | J102: 0 | K102: 400 | L102: 0 | M102: 400 | N102: 400 | O102: 400 | P102: Enero 2026 CR.xlsx | Q102: Fila 32 | R102: Alta | S102: NO | T102: Prestaciones laborales
A103: 2026-01 | B103: Costa Rica | C103: CR | D103: USD | E103: PL-O-030 | F103: Gastos de administración | G103: Impuestos y contribuciones | H103: Industria, comercio y otros | I103: MINISTERIO DE HACIENDA | J103: 0 | K103: 240.73 | L103: 0 | M103: 240.73 | N103: 240.73 | O103: 240.73 | P103: Enero 2026 CR.xlsx | Q103: Fila 35 | R103: Alta | S103: NO | T103: Impuestos no asociados a renta
A104: 2026-01 | B104: Costa Rica | C104: CR | D104: USD | E104: PL-O-110 | F104: Gastos de administración | G104: Suministros y oficina | H104: Útiles, papelería y fotocopias | I104: MUNDO TECNOLOGIA | J104: 0 | K104: 15 | L104: 0 | M104: 15 | N104: 15 | O104: 15 | P104: Enero 2026 CR.xlsx | Q104: Fila 38 | R104: Alta | S104: NO | T104: Suministros de oficina
A105: 2026-01 | B105: Costa Rica | C105: CR | D105: USD | E105: PL-O-110 | F105: Gastos de administración | G105: Suministros y oficina | H105: Útiles, papelería y fotocopias | I105: REGISTRO NACIONAL REPUBLICA DE COSTA RICA | J105: 0 | K105: 7 | L105: 0 | M105: 7 | N105: 7 | O105: 7 | P105: Enero 2026 CR.xlsx | Q105: Fila 39 | R105: Alta | S105: NO | T105: Suministros de oficina
A106: 2026-01 | B106: Costa Rica | C106: CR | D106: USD | E106: PL-F-010 | F106: Gastos financieros | G106: Gastos financieros | H106: Gastos bancarios | I106: BAC CREDOMATIC | J106: 0 | K106: 20 | L106: 0 | M106: 20 | N106: 20 | O106: 20 | P106: Enero 2026 CR.xlsx | Q106: Fila 43 | R106: Alta | S106: NO | T106: Costo financiero bancario
A107: 2026-01 | B107: Peru | C107: PERU | D107: PEN | E107: PL-S-010 | F107: Gastos de ventas | G107: Honorarios comerciales y técnicos | H107: Otros honorarios | I107: HONORARIOS OTROS CONCEPTOS | J107: 0 | K107: 2127 | L107: 0 | M107: 2127 | N107: 2127 | O107: 2127 | P107: Enero 2026 PERU.xlsx | Q107: Fila 34 | R107: Media | S107: SI | T107: Cuenta genérica de honorarios de ventas
A108: 2026-01 | B108: Peru | C108: PERU | D108: PEN | E108: PL-F-010 | F108: Gastos financieros | G108: Gastos financieros | H108: Gastos bancarios | I108: GASTOS BANCARIOS | J108: 0 | K108: 11.06 | L108: 0 | M108: 11.06 | N108: 11.06 | O108: 11.06 | P108: Enero 2026 PERU.xlsx | Q108: Fila 37 | R108: Alta | S108: NO | T108: Costo financiero bancario
A109: 2026-01 | B109: Peru | C109: PERU | D109: PEN | E109: PL-F-010 | F109: Gastos financieros | G109: Gastos financieros | H109: Gastos bancarios | I109: IVA | J109: 0 | K109: 1.65 | L109: 0 | M109: 1.65 | N109: 1.65 | O109: 1.65 | P109: Enero 2026 PERU.xlsx | Q109: Fila 38 | R109: Alta | S109: NO | T109: Costo financiero bancario
A110: 2026-01 | B110: Peru | C110: PERU | D110: PEN | E110: PL-F-010 | F110: Gastos financieros | G110: Gastos financieros | H110: Gastos bancarios | I110: CUOTA MANEJO | J110: 0 | K110: 80 | L110: 0 | M110: 80 | N110: 80 | O110: 80 | P110: Enero 2026 PERU.xlsx | Q110: Fila 39 | R110: Alta | S110: NO | T110: Costo financiero bancario
A111: 2026-01 | B111: Estados Unidos | C111: USA | D111: USD | E111: PL-R-010 | F111: Ingresos operacionales | G111: Ingresos por servicios | H111: Software y agendamiento | I111: PRESTADORA DE SERVICIOS DE SALUD PREVENTIS SA | J111: 0 | K111: 0 | L111: 2830.35 | M111: -2830.35 | N111: 2830.35 | O111: 2830.35 | P111: Enero 2026 USA.xlsx | Q111: Fila 63 | R111: Alta | S111: NO | T111: Ingreso operacional principal
A112: 2026-01 | B112: Estados Unidos | C112: USA | D112: USD | E112: PL-R-010 | F112: Ingresos operacionales | G112: Ingresos por servicios | H112: Software y agendamiento | I112: SERVICIOS HOSPITALARIOS BRISAS SA | J112: 0 | K112: 0 | L112: 300 | M112: -300 | N112: 300 | O112: 300 | P112: Enero 2026 USA.xlsx | Q112: Fila 64 | R112: Alta | S112: NO | T112: Ingreso operacional principal
A113: 2026-01 | B113: Estados Unidos | C113: USA | D113: USD | E113: PL-R-010 | F113: Ingresos operacionales | G113: Ingresos por servicios | H113: Software y agendamiento | I113: ACOSTA BORBON ALEJANDRO | J113: 0 | K113: 0 | L113: 217 | M113: -217 | N113: 217 | O113: 217 | P113: Enero 2026 USA.xlsx | Q113: Fila 65 | R113: Alta | S113: NO | T113: Ingreso operacional principal
... A133: 2026-02 | B133: Costa Rica | C133: CR | D133: USD | E133: PL-O-010 | F133: Gastos de administración | G133: Gastos de personal | H133: Sueldos | I133: NARANJO BUSTOS MARIAM | J133: 2400 | K133: 1200 | L133: 0 | M133: 3600 | N133: 3600 | O133: 1200 | P133: Febrero 2026 CR.xlsx | Q133: Fila 28 | R133: Alta | S133: NO | T133: Remuneración laboral
A134: 2026-02 | B134: Costa Rica | C134: CR | D134: USD | E134: PL-O-090 | F134: Gastos de administración | G134: Viajes y representación | H134: Viáticos | J134: 600 | K134: 300 | L134: 0 | M134: 900 | N134: 900 | O134: 300 | P134: Febrero 2026 CR.xlsx | Q134: Fila 30 | R134: Alta | S134: NO | T134: Viáticos administrativos
A135: 2026-02 | B135: Costa Rica | C135: CR | D135: USD | E135: PL-O-010 | F135: Gastos de administración | G135: Gastos de personal | H135: Prestaciones sociales | I135: NARANJO BUSTOS MARIAM | J135: 812.37 | K135: 400 | L135: 0 | M135: 1212.37 | N135: 1212.37 | O135: 400 | P135: Febrero 2026 CR.xlsx | Q135: Fila 32 | R135: Alta | S135: NO | T135: Prestaciones laborales
A136: 2026-02 | B136: Costa Rica | C136: CR | D136: USD | E136: PL-O-020 | F136: Gastos de administración | G136: Honorarios y servicios profesionales | H136: Asesoría jurídica | I136: MUÑOZ CHACON FRANCISCO JAVIER | J136: 222.59 | K136: 47.76 | L136: 0 | M136: 270.35 | N136: 270.35 | O136: 47.76 | P136: Febrero 2026 CR.xlsx | Q136: Fila 35 | R136: Alta | S136: NO | T136: Servicio profesional jurídico
A137: 2026-02 | B137: Costa Rica | C137: CR | D137: USD | E137: PL-O-030 | F137: Gastos de administración | G137: Impuestos y contribuciones | H137: Industria, comercio y otros | I137: MINISTERIO DE HACIENDA | J137: 240.73 | K137: 12 | L137: 0 | M137: 252.73 | N137: 252.73 | O137: 12 | P137: Febrero 2026 CR.xlsx | Q137: Fila 38 | R137: Alta | S137: NO | T137: Impuestos no asociados a renta
A138: 2026-02 | B138: Costa Rica | C138: CR | D138: USD | E138: PL-O-030 | F138: Gastos de administración | G138: Impuestos y contribuciones | H138: Industria, comercio y otros | I138: MINISTERIO DE HACIENDA | J138: 0 | K138: 26.55 | L138: 0 | M138: 26.55 | N138: 26.55 | O138: 26.55 | P138: Febrero 2026 CR.xlsx | Q138: Fila 39 | R138: Alta | S138: NO | T138: Impuestos no asociados a renta
A139: 2026-02 | B139: Costa Rica | C139: CR | D139: USD | E139: PL-O-030 | F139: Gastos de administración | G139: Impuestos y contribuciones | H139: Contribuciones y afiliaciones | I139: MINISTERIO DE SALUD | J139: 0 | K139: 64.79 | L139: 0 | M139: 64.79 | N139: 64.79 | O139: 64.79 | P139: Febrero 2026 CR.xlsx | Q139: Fila 42 | R139: Alta | S139: NO | T139: Contribuciones
A140: 2026-02 | B140: Costa Rica | C140: CR | D140: USD | E140: PL-O-050 | F140: Gastos de administración | G140: Seguros | H140: Otros seguros | I140: SEGUROS INS | J140: 0 | K140: 70.81 | L140: 0 | M140: 70.81 | N140: 70.81 | O140: 70.81 | P140: Febrero 2026 CR.xlsx | Q140: Fila 45 | R140: Media | S140: SI | T140: Cuenta fuente de seguros con descripción genérica
A141: 2026-02 | B141: Costa Rica | C141: CR | D141: USD | E141: PL-O-110 | F141: Gastos de administración | G141: Suministros y oficina | H141: Útiles, papelería y fotocopias | I141: FERRETERIA EPA S.A. | J141: 0 | K141: 39.61 | L141: 0 | M141: 39.61 | N141: 39.61 | O141: 39.61 | P141: Febrero 2026 CR.xlsx | Q141: Fila 48 | R141: Alta | S141: NO | T141: Suministros de oficina
A142: 2026-02 | B142: Costa Rica | C142: CR | D142: USD | E142: PL-O-110 | F142: Gastos de administración | G142: Suministros y oficina | H142: Útiles, papelería y fotocopias | I142: ISTORE SAN PEDRO | J142: 0 | K142: 74.31 | L142: 0 | M142: 74.31 | N142: 74.31 | O142: 74.31 | P142: Febrero 2026 CR.xlsx | Q142: Fila 49 | R142: Alta | S142: NO | T142: Suministros de oficina
A143: 2026-02 | B143: Costa Rica | C143: CR | D143: USD | E143: PL-O-110 | F143: Gastos de administración | G143: Suministros y oficina | H143: Útiles, papelería y fotocopias | I143: MUNDO TECNOLOGIA | J143: 15 | K143: 0 | L143: 0 | M143: 15 | N143: 15 | O143: 0 | P143: Febrero 2026 CR.xlsx | Q143: Fila 50 | R143: Alta | S143: NO | T143: Suministros de oficina
A144: 2026-02 | B144: Costa Rica | C144: CR | D144: USD | E144: PL-O-110 | F144: Gastos de administración | G144: Suministros y oficina | H144: Útiles, papelería y fotocopias | I144: REGISTRO NACIONAL REPUBLICA DE COSTA RICA | J144: 7 | K144: 0 | L144: 0 | M144: 7 | N144: 7 | O144: 0 | P144: Febrero 2026 CR.xlsx | Q144: Fila 51 | R144: Alta | S144: NO | T144: Suministros de oficina
A145: 2026-02 | B145: Costa Rica | C145: CR | D145: USD | E145: PL-F-010 | F145: Gastos financieros | G145: Gastos financieros | H145: Gastos bancarios | I145: BAC CREDOMATIC | J145: 50 | K145: 30 | L145: 0 | M145: 80 | N145: 80 | O145: 30 | P145: Febrero 2026 CR.xlsx | Q145: Fila 55 | R145: Alta | S145: NO | T145: Costo financiero bancario
A146: 2026-02 | B146: Peru | C146: PERU | D146: PEN | E146: PL-R-010 | F146: Ingresos operacionales | G146: Ingresos por servicios | H146: Software y agendamiento | I146: AGENDAMIENTO EN LA NUBE | J146: 0 | K146: 0 | L146: 2784.7 | M146: -2784.7 | N146: 2784.7 | O146: 2784.7 | P146: Febrero 2026 PERU.xlsx | Q146: Fila 40 | R146: Alta | S146: NO | T146: Ingreso operacional principal
... A309: 2026-06 | B309: Costa Rica | C309: CR | D309: USD | E309: PL-O-010 | F309: Gastos de administración | G309: Gastos de personal | H309: Sueldos | I309: NARANJO BUSTOS MARIAM | J309: 5400 | K309: 1850 | L309: 0 | M309: 7250 | N309: 7250 | O309: 1850 | P309: Junio 2026 CR.xlsx | Q309: Fila 28 | R309: Alta | S309: NO | T309: Remuneración laboral
A310: 2026-06 | B310: Costa Rica | C310: CR | D310: USD | E310: PL-O-090 | F310: Gastos de administración | G310: Viajes y representación | H310: Viáticos | J310: 1500 | K310: 300 | L310: 0 | M310: 1800 | N310: 1800 | O310: 300 | P310: Junio 2026 CR.xlsx | Q310: Fila 30 | R310: Alta | S310: NO | T310: Viáticos administrativos
A311: 2026-06 | B311: Costa Rica | C311: CR | D311: USD | E311: PL-O-010 | F311: Gastos de administración | G311: Gastos de personal | H311: Prestaciones sociales | I311: NARANJO BUSTOS MARIAM | J311: 2012.37 | K311: 400 | L311: 0 | M311: 2412.37 | N311: 2412.37 | O311: 400 | P311: Junio 2026 CR.xlsx | Q311: Fila 32 | R311: Alta | S311: NO | T311: Prestaciones laborales
A312: 2026-06 | B312: Costa Rica | C312: CR | D312: USD | E312: PL-O-020 | F312: Gastos de administración | G312: Honorarios y servicios profesionales | H312: Asesoría jurídica | I312: MUÑOZ CHACON FRANCISCO JAVIER | J312: 270.35 | K312: 0 | L312: 0 | M312: 270.35 | N312: 270.35 | O312: 0 | P312: Junio 2026 CR.xlsx | Q312: Fila 35 | R312: Alta | S312: NO | T312: Servicio profesional jurídico
A313: 2026-06 | B313: Costa Rica | C313: CR | D313: USD | E313: PL-O-030 | F313: Gastos de administración | G313: Impuestos y contribuciones | H313: Industria, comercio y otros | I313: MINISTERIO DE HACIENDA | J313: 252.73 | K313: 0 | L313: 0 | M313: 252.73 | N313: 252.73 | O313: 0 | P313: Junio 2026 CR.xlsx | Q313: Fila 38 | R313: Alta | S313: NO | T313: Impuestos no asociados a renta
A314: 2026-06 | B314: Costa Rica | C314: CR | D314: USD | E314: PL-O-030 | F314: Gastos de administración | G314: Impuestos y contribuciones | H314: Industria, comercio y otros | I314: MINISTERIO DE HACIENDA | J314: 142.19 | K314: 0 | L314: 0 | M314: 142.19 | N314: 142.19 | O314: 0 | P314: Junio 2026 CR.xlsx | Q314: Fila 39 | R314: Alta | S314: NO | T314: Impuestos no asociados a renta
A315: 2026-06 | B315: Costa Rica | C315: CR | D315: USD | E315: PL-O-030 | F315: Gastos de administración | G315: Impuestos y contribuciones | H315: Contribuciones y afiliaciones | I315: MINISTERIO DE SALUD | J315: 64.79 | K315: 0 | L315: 0 | M315: 64.79 | N315: 64.79 | O315: 0 | P315: Junio 2026 CR.xlsx | Q315: Fila 42 | R315: Alta | S315: NO | T315: Contribuciones
A316: 2026-06 | B316: Costa Rica | C316: CR | D316: USD | E316: PL-O-050 | F316: Gastos de administración | G316: Seguros | H316: Otros seguros | I316: RADIOGRAFICA COSTARRICENSE SA | J316: 9205.72 | K316: 0 | L316: 0 | M316: 9205.72 | N316: 9205.72 | O316: 0 | P316: Junio 2026 CR.xlsx | Q316: Fila 45 | R316: Media | S316: SI | T316: Cuenta fuente de seguros con descripción genérica
A317: 2026-06 | B317: Costa Rica | C317: CR | D317: USD | E317: PL-O-050 | F317: Gastos de administración | G317: Seguros | H317: Otros seguros | I317: SEGUROS INS | J317: 70.81 | K317: 0 | L317: 0 | M317: 70.81 | N317: 70.81 | O317: 0 | P317: Junio 2026 CR.xlsx | Q317: Fila 46 | R317: Media | S317: SI | T317: Cuenta fuente de seguros con descripción genérica
A318: 2026-06 | B318: Costa Rica | C318: CR | D318: USD | E318: PL-O-060 | F318: Gastos de administración | G318: Tecnología y procesamiento de datos | H318: Plataformas y software | I318: CAJA COSTARRICENSE DE SEGURO SOCIAL | J318: 115.51 | K318: 0 | L318: 0 | M318: 115.51 | N318: 115.51 | O318: 0 | P318: Junio 2026 CR.xlsx | Q318: Fila 49 | R318: Alta | S318: SI | T318: Revisar proveedores de telecomunicaciones registrados aquí
A319: 2026-06 | B319: Costa Rica | C319: CR | D319: USD | E319: PL-O-060 | F319: Gastos de administración | G319: Tecnología y procesamiento de datos | H319: Plataformas y software | I319: GTI SA | J319: 0 | K319: 34.3 | L319: 0 | M319: 34.3 | N319: 34.3 | O319: 34.3 | P319: Junio 2026 CR.xlsx | Q319: Fila 50 | R319: Alta | S319: SI | T319: Revisar proveedores de telecomunicaciones registrados aquí
A320: 2026-06 | B320: Costa Rica | C320: CR | D320: USD | E320: PL-O-110 | F320: Gastos de administración | G320: Suministros y oficina | H320: Útiles, papelería y fotocopias | I320: ELECTRONICA STEREN DE COSTARICA SA | J320: 0 | K320: 37.69 | L320: 0 | M320: 37.69 | N320: 37.69 | O320: 37.69 | P320: Junio 2026 CR.xlsx | Q320: Fila 53 | R320: Alta | S320: NO | T320: Suministros de oficina
A321: 2026-06 | B321: Costa Rica | C321: CR | D321: USD | E321: PL-O-110 | F321: Gastos de administración | G321: Suministros y oficina | H321: Útiles, papelería y fotocopias | I321: FERRETERIA EPA S.A. | J321: 39.61 | K321: 0 | L321: 0 | M321: 39.61 | N321: 39.61 | O321: 0 | P321: Junio 2026 CR.xlsx | Q321: Fila 54 | R321: Alta | S321: NO | T321: Suministros de oficina
A322: 2026-06 | B322: Costa Rica | C322: CR | D322: USD | E322: PL-O-110 | F322: Gastos de administración | G322: Suministros y oficina | H322: Útiles, papelería y fotocopias | I322: ISTORE SAN PEDRO | J322: 74.31 | K322: 0 | L322: 0 | M322: 74.31 | N322: 74.31 | O322: 0 | P322: Junio 2026 CR.xlsx | Q322: Fila 55 | R322: Alta | S322: NO | T322: Suministros de oficina
... A450: 2026-03 | B450: Costa Rica | C450: CR | D450: USD | E450: PL-O-010 | F450: Gastos de administración | G450: Gastos de personal | H450: Sueldos | I450: NARANJO BUSTOS MARIAM | J450: 2400 | K450: 1200 | L450: 0 | M450: 3600 | N450: 3600 | O450: 1200 | P450: Marzo 2026 CR.xlsx | Q450: Fila 28 | R450: Alta | S450: NO | T450: Remuneración laboral
A451: 2026-03 | B451: Costa Rica | C451: CR | D451: USD | E451: PL-O-090 | F451: Gastos de administración | G451: Viajes y representación | H451: Viáticos | J451: 600 | K451: 300 | L451: 0 | M451: 900 | N451: 900 | O451: 300 | P451: Marzo 2026 CR.xlsx | Q451: Fila 30 | R451: Alta | S451: NO | T451: Viáticos administrativos
A452: 2026-03 | B452: Costa Rica | C452: CR | D452: USD | E452: PL-O-010 | F452: Gastos de administración | G452: Gastos de personal | H452: Prestaciones sociales | I452: NARANJO BUSTOS MARIAM | J452: 812.37 | K452: 400 | L452: 0 | M452: 1212.37 | N452: 1212.37 | O452: 400 | P452: Marzo 2026 CR.xlsx | Q452: Fila 32 | R452: Alta | S452: NO | T452: Prestaciones laborales
A453: 2026-03 | B453: Costa Rica | C453: CR | D453: USD | E453: PL-O-020 | F453: Gastos de administración | G453: Honorarios y servicios profesionales | H453: Asesoría jurídica | I453: MUÑOZ CHACON FRANCISCO JAVIER | J453: 222.59 | K453: 47.76 | L453: 0 | M453: 270.35 | N453: 270.35 | O453: 47.76 | P453: Marzo 2026 CR.xlsx | Q453: Fila 35 | R453: Alta | S453: NO | T453: Servicio profesional jurídico
A454: 2026-03 | B454: Costa Rica | C454: CR | D454: USD | E454: PL-O-030 | F454: Gastos de administración | G454: Impuestos y contribuciones | H454: Industria, comercio y otros | I454: MINISTERIO DE HACIENDA | J454: 240.73 | K454: 12 | L454: 0 | M454: 252.73 | N454: 252.73 | O454: 12 | P454: Marzo 2026 CR.xlsx | Q454: Fila 38 | R454: Alta | S454: NO | T454: Impuestos no asociados a renta
A455: 2026-03 | B455: Costa Rica | C455: CR | D455: USD | E455: PL-O-030 | F455: Gastos de administración | G455: Impuestos y contribuciones | H455: Industria, comercio y otros | I455: MINISTERIO DE HACIENDA | J455: 0 | K455: 26.55 | L455: 0 | M455: 26.55 | N455: 26.55 | O455: 26.55 | P455: Marzo 2026 CR.xlsx | Q455: Fila 39 | R455: Alta | S455: NO | T455: Impuestos no asociados a renta
A456: 2026-03 | B456: Costa Rica | C456: CR | D456: USD | E456: PL-O-030 | F456: Gastos de administración | G456: Impuestos y contribuciones | H456: Contribuciones y afiliaciones | I456: MINISTERIO DE SALUD | J456: 0 | K456: 64.79 | L456: 0 | M456: 64.79 | N456: 64.79 | O456: 64.79 | P456: Marzo 2026 CR.xlsx | Q456: Fila 42 | R456: Alta | S456: NO | T456: Contribuciones
A457: 2026-03 | B457: Costa Rica | C457: CR | D457: USD | E457: PL-O-050 | F457: Gastos de administración | G457: Seguros | H457: Otros seguros | I457: SEGUROS INS | J457: 0 | K457: 70.81 | L457: 0 | M457: 70.81 | N457: 70.81 | O457: 70.81 | P457: Marzo 2026 CR.xlsx | Q457: Fila 45 | R457: Media | S457: SI | T457: Cuenta fuente de seguros con descripción genérica
A458: 2026-03 | B458: Costa Rica | C458: CR | D458: USD | E458: PL-O-110 | F458: Gastos de administración | G458: Suministros y oficina | H458: Útiles, papelería y fotocopias | I458: FERRETERIA EPA S.A. | J458: 0 | K458: 39.61 | L458: 0 | M458: 39.61 | N458: 39.61 | O458: 39.61 | P458: Marzo 2026 CR.xlsx | Q458: Fila 48 | R458: Alta | S458: NO | T458: Suministros de oficina
A459: 2026-03 | B459: Costa Rica | C459: CR | D459: USD | E459: PL-O-110 | F459: Gastos de administración | G459: Suministros y oficina | H459: Útiles, papelería y fotocopias | I459: ISTORE SAN PEDRO | J459: 0 | K459: 74.31 | L459: 0 | M459: 74.31 | N459: 74.31 | O459: 74.31 | P459: Marzo 2026 CR.xlsx | Q459: Fila 49 | R459: Alta | S459: NO | T459: Suministros de oficina
A460: 2026-03 | B460: Costa Rica | C460: CR | D460: USD | E460: PL-O-110 | F460: Gastos de administración | G460: Suministros y oficina | H460: Útiles, papelería y fotocopias | I460: MUNDO TECNOLOGIA | J460: 15 | K460: 0 | L460: 0 | M460: 15 | N460: 15 | O460: 0 | P460: Marzo 2026 CR.xlsx | Q460: Fila 50 | R460: Alta | S460: NO | T460: Suministros de oficina
A461: 2026-03 | B461: Costa Rica | C461: CR | D461: USD | E461: PL-O-110 | F461: Gastos de administración | G461: Suministros y oficina | H461: Útiles, papelería y fotocopias | I461: REGISTRO NACIONAL REPUBLICA DE COSTA RICA | J461: 7 | K461: 0 | L461: 0 | M461: 7 | N461: 7 | O461: 0 | P461: Marzo 2026 CR.xlsx | Q461: Fila 51 | R461: Alta | S461: NO | T461: Suministros de oficina
A462: 2026-03 | B462: Costa Rica | C462: CR | D462: USD | E462: PL-F-010 | F462: Gastos financieros | G462: Gastos financieros | H462: Gastos bancarios | I462: BAC CREDOMATIC | J462: 50 | K462: 30 | L462: 0 | M462: 80 | N462: 80 | O462: 30 | P462: Marzo 2026 CR.xlsx | Q462: Fila 55 | R462: Alta | S462: NO | T462: Costo financiero bancario
A463: 2026-03 | B463: Peru | C463: PERU | D463: PEN | E463: PL-R-010 | F463: Ingresos operacionales | G463: Ingresos por servicios | H463: Software y agendamiento | I463: IMPLEMENTACION- EXCLUIDA | J463: -1808.92 | K463: 0 | L463: 0 | M463: -1808.92 | N463: 1808.92 | O463: 0 | P463: Marzo 2026 PERU.xlsx | Q463: Fila 41 | R463: Alta | S463: NO | T463: Ingreso operacional principal
... A526: 2026-05 | B526: Costa Rica | C526: CR | D526: USD | E526: PL-O-010 | F526: Gastos de administración | G526: Gastos de personal | H526: Sueldos | I526: NARANJO BUSTOS MARIAM | J526: 4800 | K526: 600 | L526: 0 | M526: 5400 | N526: 5400 | O526: 600 | P526: Mayo 2026 CR.xlsx | Q526: Fila 28 | R526: Alta | S526: NO | T526: Remuneración laboral
A527: 2026-05 | B527: Costa Rica | C527: CR | D527: USD | E527: PL-O-090 | F527: Gastos de administración | G527: Viajes y representación | H527: Viáticos | J527: 1200 | K527: 300 | L527: 0 | M527: 1500 | N527: 1500 | O527: 300 | P527: Mayo 2026 CR.xlsx | Q527: Fila 30 | R527: Alta | S527: NO | T527: Viáticos administrativos
A528: 2026-05 | B528: Costa Rica | C528: CR | D528: USD | E528: PL-O-010 | F528: Gastos de administración | G528: Gastos de personal | H528: Prestaciones sociales | I528: NARANJO BUSTOS MARIAM | J528: 1612.37 | K528: 400 | L528: 0 | M528: 2012.37 | N528: 2012.37 | O528: 400 | P528: Mayo 2026 CR.xlsx | Q528: Fila 32 | R528: Alta | S528: NO | T528: Prestaciones laborales
A529: 2026-05 | B529: Costa Rica | C529: CR | D529: USD | E529: PL-O-020 | F529: Gastos de administración | G529: Honorarios y servicios profesionales | H529: Asesoría jurídica | I529: MUÑOZ CHACON FRANCISCO JAVIER | J529: 270.35 | K529: 0 | L529: 0 | M529: 270.35 | N529: 270.35 | O529: 0 | P529: Mayo 2026 CR.xlsx | Q529: Fila 35 | R529: Alta | S529: NO | T529: Servicio profesional jurídico
A530: 2026-05 | B530: Costa Rica | C530: CR | D530: USD | E530: PL-O-030 | F530: Gastos de administración | G530: Impuestos y contribuciones | H530: Industria, comercio y otros | I530: MINISTERIO DE HACIENDA | J530: 252.73 | K530: 0 | L530: 0 | M530: 252.73 | N530: 252.73 | O530: 0 | P530: Mayo 2026 CR.xlsx | Q530: Fila 38 | R530: Alta | S530: NO | T530: Impuestos no asociados a renta
A531: 2026-05 | B531: Costa Rica | C531: CR | D531: USD | E531: PL-O-030 | F531: Gastos de administración | G531: Impuestos y contribuciones | H531: Industria, comercio y otros | I531: MINISTERIO DE HACIENDA | J531: 142.19 | K531: 0 | L531: 0 | M531: 142.19 | N531: 142.19 | O531: 0 | P531: Mayo 2026 CR.xlsx | Q531: Fila 39 | R531: Alta | S531: NO | T531: Impuestos no asociados a renta
A532: 2026-05 | B532: Costa Rica | C532: CR | D532: USD | E532: PL-O-030 | F532: Gastos de administración | G532: Impuestos y contribuciones | H532: Contribuciones y afiliaciones | I532: MINISTERIO DE SALUD | J532: 64.79 | K532: 0 | L532: 0 | M532: 64.79 | N532: 64.79 | O532: 0 | P532: Mayo 2026 CR.xlsx | Q532: Fila 42 | R532: Alta | S532: NO | T532: Contribuciones
A533: 2026-05 | B533: Costa Rica | C533: CR | D533: USD | E533: PL-O-050 | F533: Gastos de administración | G533: Seguros | H533: Otros seguros | I533: RADIOGRAFICA COSTARRICENSE SA | J533: 9205.72 | K533: 0 | L533: 0 | M533: 9205.72 | N533: 9205.72 | O533: 0 | P533: Mayo 2026 CR.xlsx | Q533: Fila 45 | R533: Media | S533: SI | T533: Cuenta fuente de seguros con descripción genérica
A534: 2026-05 | B534: Costa Rica | C534: CR | D534: USD | E534: PL-O-050 | F534: Gastos de administración | G534: Seguros | H534: Otros seguros | I534: SEGUROS INS | J534: 70.81 | K534: 0 | L534: 0 | M534: 70.81 | N534: 70.81 | O534: 0 | P534: Mayo 2026 CR.xlsx | Q534: Fila 46 | R534: Media | S534: SI | T534: Cuenta fuente de seguros con descripción genérica
A535: 2026-05 | B535: Costa Rica | C535: CR | D535: USD | E535: PL-O-060 | F535: Gastos de administración | G535: Tecnología y procesamiento de datos | H535: Plataformas y software | I535: CAJA COSTARRICENSE DE SEGURO SOCIAL | J535: 57.71 | K535: 57.8 | L535: 0 | M535: 115.51 | N535: 115.51 | O535: 57.8 | P535: Mayo 2026 CR.xlsx | Q535: Fila 49 | R535: Alta | S535: SI | T535: Revisar proveedores de telecomunicaciones registrados aquí
A536: 2026-05 | B536: Costa Rica | C536: CR | D536: USD | E536: PL-O-110 | F536: Gastos de administración | G536: Suministros y oficina | H536: Útiles, papelería y fotocopias | I536: FERRETERIA EPA S.A. | J536: 39.61 | K536: 0 | L536: 0 | M536: 39.61 | N536: 39.61 | O536: 0 | P536: Mayo 2026 CR.xlsx | Q536: Fila 52 | R536: Alta | S536: NO | T536: Suministros de oficina
A537: 2026-05 | B537: Costa Rica | C537: CR | D537: USD | E537: PL-O-110 | F537: Gastos de administración | G537: Suministros y oficina | H537: Útiles, papelería y fotocopias | I537: ISTORE SAN PEDRO | J537: 74.31 | K537: 0 | L537: 0 | M537: 74.31 | N537: 74.31 | O537: 0 | P537: Mayo 2026 CR.xlsx | Q537: Fila 53 | R537: Alta | S537: NO | T537: Suministros de oficina
A538: 2026-05 | B538: Costa Rica | C538: CR | D538: USD | E538: PL-O-110 | F538: Gastos de administración | G538: Suministros y oficina | H538: Útiles, papelería y fotocopias | I538: MUNDO TECNOLOGIA | J538: 15 | K538: 0 | L538: 0 | M538: 15 | N538: 15 | O538: 0 | P538: Mayo 2026 CR.xlsx | Q538: Fila 54 | R538: Alta | S538: NO | T538: Suministros de oficina
A539: 2026-05 | B539: Costa Rica | C539: CR | D539: USD | E539: PL-O-110 | F539: Gastos de administración | G539: Suministros y oficina | H539: Útiles, papelería y fotocopias | I539: REGISTRO NACIONAL REPUBLICA DE COSTA RICA | J539: 7 | K539: 0 | L539: 0 | M539: 7 | N539: 7 | O539: 0 | P539: Mayo 2026 CR.xlsx | Q539: Fila 55 | R539: Alta | S539: NO | T539: Suministros de oficina
... A644: 2026-05 | B644: Estados Unidos | C644: USA | D644: USD | E644: PL-F-010 | F644: Gastos financieros | G644: Gastos financieros | H644: Comisiones | I644: MERCURY LLC | J644: 0.9 | K644: 0 | L644: 0 | M644: 0.9 | N644: 0.9 | O644: 0 | P644: Mayo 2026 USA.xlsx | Q644: Fila 165 | R644: Alta | S644: NO | T644: Comisiones financieras
A645: 2026-07 | B645: Colombia | C645: COCO | D645: COP | E645: PL-R-010 | F645: Ingresos operacionales | G645: Ingresos por servicios | H645: Software de agendamiento | I645: Servicios de software de agendamiento | K645: 0 | L645: 0 | M645: 5615511389 | N645: 5615511389 | O645: 0 | P645: EF Julio COCO 2026.pdf | Q645: Pág. 2 / Nota 9 | R645: Alta | S645: NO | T645: Estado de resultados y Nota 9
A646: 2026-07 | B646: Colombia | C646: COCO | D646: COP | E646: PL-R-020 | F646: Deducciones de ingresos | G646: Devoluciones | H646: Devoluciones | I646: Devoluciones | K646: 0 | L646: 0 | M646: -463278090 | N646: -463278090 | O646: 0 | P646: EF Julio COCO 2026.pdf | Q646: Pág. 2 / Nota 9 | R646: Alta | S646: NO | T646: Estado de resultados y Nota 9
A647: 2026-07 | B647: Colombia | C647: COCO | D647: COP | E647: PL-C-010 | F647: Costo de ventas | G647: Costo de ventas | H647: Desarrollo de software | I647: Costo de ventas / desarrollo de software | K647: 0 | L647: 0 | M647: 2442623347 | N647: 2442623347 | O647: 0 | P647: EF Julio COCO 2026.pdf | Q647: Pág. 2 / Nota 10 | R647: Alta | S647: NO | T647: Estado de resultados y Nota 10
A648: 2026-07 | B648: Colombia | C648: COCO | D648: COP | E648: PL-G-900 | F648: Conciliaciones de resultados | G648: Conciliación utilidad bruta oficial | H648: Diferencia estado principal vs detalle | I648: Diferencia total ingresos ordinarios: estado oficial vs detalle | K648: 0 | L648: 0 | M648: -1 | N648: -1 | O648: 0 | P648: EF Julio COCO 2026.pdf | Q648: Pág. 2 - conciliación | R648: Alta | S648: NO | T648: Diferencia explícita de COP -1 para igualar el total oficial de ingresos ordinarios
A649: 2026-07 | B649: Colombia | C649: COCO | D649: COP | E649: PL-O-200 | F649: Gastos de administración | G649: Gastos de administración - COCO | H649: Total administración | I649: Gastos de administración | K649: 0 | L649: 0 | M649: 797478918 | N649: 797478918 | O649: 0 | P649: EF Julio COCO 2026.pdf | Q649: Pág. 2 / Nota 11 | R649: Alta | S649: NO | T649: Estado de resultados y Nota 11
A650: 2026-07 | B650: Colombia | C650: COCO | D650: COP | E650: PL-S-200 | F650: Gastos de ventas | G650: Gastos de ventas - COCO | H650: Total ventas | I650: Gastos de ventas | K650: 0 | L650: 0 | M650: 959736563 | N650: 959736563 | O650: 0 | P650: EF Julio COCO 2026.pdf | Q650: Pág. 2 / Nota 11 | R650: Alta | S650: NO | T650: Estado de resultados y Nota 11
A651: 2026-07 | B651: Colombia | C651: COCO | D651: COP | E651: PL-O-210 | F651: Otros gastos operacionales | G651: Gastos operacionales - COCO | H651: Total operativo | I651: Gastos operacionales | K651: 0 | L651: 0 | M651: 676358287 | N651: 676358287 | O651: 0 | P651: EF Julio COCO 2026.pdf | Q651: Pág. 2 / Nota 11 | R651: Alta | S651: NO | T651: Estado de resultados y Nota 11
A652: 2026-07 | B652: Colombia | C652: COCO | D652: COP | E652: PL-O-900 | F652: Conciliaciones de resultados | G652: Conciliación gastos operacionales | H652: Diferencia estado principal vs detalle | I652: Diferencia total gastos de operación: estado oficial vs detalle | K652: 0 | L652: 0 | M652: 1 | N652: 1 | O652: 0 | P652: EF Julio COCO 2026.pdf | Q652: Pág. 2 - conciliación | R652: Alta | S652: NO | T652: Diferencia explícita de COP 1 para igualar el total oficial de gastos de operación
A653: 2026-07 | B653: Colombia | C653: COCO | D653: COP | E653: PL-NO-010 | F653: Ingresos no operacionales | G653: Ingresos financieros | H653: Financieros | I653: Ingreso no operacional - financiero | K653: 0 | L653: 0 | M653: 10800447 | N653: 10800447 | O653: 0 | P653: EF Julio COCO 2026.pdf | Q653: Pág. 2 / Nota 12 | R653: Alta | S653: NO | T653: Estado de resultados y Nota 12
A654: 2026-07 | B654: Colombia | C654: COCO | D654: COP | E654: PL-F-010 | F654: Gastos financieros | G654: Gastos financieros | H654: Total gastos financieros | I654: Gastos financieros - total del estado | K654: 0 | L654: 0 | M654: 40108353 | N654: 40108353 | O654: 0 | P654: EF Julio COCO 2026.pdf | Q654: Pág. 2 / Nota 13 | R654: Alta | S654: SI | T654: El estado y la nota difieren por COP 1; se usa el estado
A655: 2026-07 | B655: Colombia | C655: COCO | D655: COP | E655: PL-T-010 | F655: Impuesto a las ganancias | G655: Impuesto de renta | H655: Impuesto de renta | I655: Impuesto de renta | K655: 0 | L655: 0 | M655: 0 | O655: 0 | P655: EF Julio COCO 2026.pdf | Q655: Pág. 2 | R655: Alta | S655: NO | T655: Estado de resultados
A656: 2026-07 | B656: Colombia | C656: COCO | D656: COP | E656: PL-N-900 | F656: Conciliaciones de resultados | G656: Conciliación resultado oficial | H656: Diferencia aritmética del estado principal | I656: Diferencia resultado calculado vs utilidad oficial | K656: 0 | L656: 0 | M656: 1 | N656: 1 | O656: 0 | P656: EF Julio COCO 2026.pdf | Q656: Pág. 2 - conciliación | R656: Alta | S656: NO | T656: Diferencia explícita de COP 1 para igualar la utilidad oficial publicada
A657: 2026-07 | B657: Costa Rica | C657: CR | D657: USD | E657: PL-R-010 | F657: Ingresos operacionales | G657: Ingresos por servicios | H657: Software y agendamiento | I657: CAJA COSTARRICENSE DE SEGURO SOCIAL | J657: 0 | K657: 0 | L657: 134104 | M657: -134104 | N657: 134104 | O657: 134104 | P657: Julio 2026 CR.xlsx | Q657: Fila 32 | R657: Alta | S657: NO | T657: Ingreso operacional principal
A658: 2026-07 | B658: Costa Rica | C658: CR | D658: USD | E658: PL-O-010 | F658: Gastos de administración | G658: Gastos de personal | H658: Sueldos | I658: NARANJO BUSTOS MARIAM | J658: 7250 | K658: 2230 | L658: 0 | M658: 9480 | N658: 9480 | O658: 2230 | P658: Julio 2026 CR.xlsx | Q658: Fila 37 | R658: Alta | S658: NO | T658: Remuneración laboral
...

Sheet BD_GASTOS_DASHBOARD_BRIDGE
A1: periodo | B1: pais | C1: entidad | D1: moneda | E1: codigo_comun | F1: rubro_comun | G1: indicador_dashboard | H1: detalle_dashboard | I1: area_dashboard | J1: valor_mes | K1: valor_ytd | L1: fuente | M1: calidad_mapeo | N1: nota
A2: 2026-04 | B2: Costa Rica | C2: CR | D2: USD | E2: PL-O-010 | F2: Gastos de personal | G2: gasto_admin | H2: Personal | I2: Administracion | J2: 1200 | K2: 4800 | L2: Abril 2026 CR.xlsx | M2: Aprobado | N2: Puente para redise?ar vistas de Costos & Gastos; no reemplaza P&G oficial.
A3: 2026-04 | B3: Costa Rica | C3: CR | D3: USD | E3: PL-O-090 | F3: Viajes y representación | G3: gasto_admin | H3: Viajes | I3: Administracion | J3: 300 | K3: 1200 | L3: Abril 2026 CR.xlsx | M3: Aprobado | N3: Puente para redise?ar vistas de Costos & Gastos; no reemplaza P&G oficial.
A4: 2026-04 | B4: Costa Rica | C4: CR | D4: USD | E4: PL-O-010 | F4: Gastos de personal | G4: gasto_admin | H4: Personal | I4: Administracion | J4: 400 | K4: 1612.37 | L4: Abril 2026 CR.xlsx | M4: Aprobado | N4: Puente para redise?ar vistas de Costos & Gastos; no reemplaza P&G oficial.
A5: 2026-04 | B5: Costa Rica | C5: CR | D5: USD | E5: PL-O-020 | F5: Honorarios y servicios profesionales | G5: gasto_admin | H5: Honorarios | I5: Administracion | J5: 0 | K5: 270.35 | L5: Abril 2026 CR.xlsx | M5: Aprobado | N5: Puente para redise?ar vistas de Costos & Gastos; no reemplaza P&G oficial.
A6: 2026-04 | B6: Costa Rica | C6: CR | D6: USD | E6: PL-O-030 | F6: Impuestos y contribuciones | G6: gasto_admin | H6: Diversos | I6: Administracion | J6: 0 | K6: 252.73 | L6: Abril 2026 CR.xlsx | M6: Aprobado | N6: Puente para redise?ar vistas de Costos & Gastos; no reemplaza P&G oficial.
A7: 2026-04 | B7: Costa Rica | C7: CR | D7: USD | E7: PL-O-030 | F7: Impuestos y contribuciones | G7: gasto_admin | H7: Diversos | I7: Administracion | J7: 115.64 | K7: 142.19 | L7: Abril 2026 CR.xlsx | M7: Aprobado | N7: Puente para redise?ar vistas de Costos & Gastos; no reemplaza P&G oficial.
A8: 2026-04 | B8: Costa Rica | C8: CR | D8: USD | E8: PL-O-030 | F8: Impuestos y contribuciones | G8: gasto_admin | H8: Diversos | I8: Administracion | J8: 0 | K8: 64.79 | L8: Abril 2026 CR.xlsx | M8: Aprobado | N8: Puente para redise?ar vistas de Costos & Gastos; no reemplaza P&G oficial.
A9: 2026-04 | B9: Costa Rica | C9: CR | D9: USD | E9: PL-O-050 | F9: Seguros | G9: gasto_admin | H9: Seguros | I9: Administracion | J9: 9205.72 | K9: 9205.72 | L9: Abril 2026 CR.xlsx | M9: Aprobado | N9: Puente para redise?ar vistas de Costos & Gastos; no reemplaza P&G oficial.
A10: 2026-04 | B10: Costa Rica | C10: CR | D10: USD | E10: PL-O-050 | F10: Seguros | G10: gasto_admin | H10: Seguros | I10: Administracion | J10: 0 | K10: 70.81 | L10: Abril 2026 CR.xlsx | M10: Aprobado | N10: Puente para redise?ar vistas de Costos & Gastos; no reemplaza P&G oficial.
A11: 2026-04 | B11: Costa Rica | C11: CR | D11: USD | E11: PL-O-060 | F11: Tecnología y procesamiento de datos | G11: gasto_admin | H11: Servicios | I11: Administracion | J11: 57.71 | K11: 57.71 | L11: Abril 2026 CR.xlsx | M11: Aprobado | N11: Puente para redise?ar vistas de Costos & Gastos; no reemplaza P&G oficial.
A12: 2026-04 | B12: Costa Rica | C12: CR | D12: USD | E12: PL-O-110 | F12: Suministros y oficina | G12: gasto_admin | H12: Diversos | I12: Administracion | J12: 0 | K12: 39.61 | L12: Abril 2026 CR.xlsx | M12: Aprobado | N12: Puente para redise?ar vistas de Costos & Gastos; no reemplaza P&G oficial.
A13: 2026-04 | B13: Costa Rica | C13: CR | D13: USD | E13: PL-O-110 | F13: Suministros y oficina | G13: gasto_admin | H13: Diversos | I13: Administracion | J13: 0 | K13: 74.31 | L13: Abril 2026 CR.xlsx | M13: Aprobado | N13: Puente para redise?ar vistas de Costos & Gastos; no reemplaza P&G oficial.
... A588: 2026-07 | B588: Costa Rica | C588: CR | D588: USD | E588: PL-F-010 | F588: Gastos financieros | G588: gasto_area | H588: Financieros | I588: Financieros | J588: 0 | K588: 6 | L588: Julio 2026 CR.xlsx | M588: Aprobado | N588: Puente para redise?ar vistas de Costos & Gastos; no reemplaza P&G oficial.

Sheet BD_GASTOS_RESUMEN_MENSUAL
A1: periodo | B1: pais | C1: entidad | D1: moneda | E1: indicador_dashboard | F1: detalle_dashboard | G1: area_dashboard | H1: valor_mes | I1: valor_ytd | J1: filas_fuente | K1: nota
A2: 2026-01 | B2: Costa Rica | C2: CR | D2: USD | E2: gasto_admin | F2: Diversos | G2: Administracion | H2: 262.73 | I2: 262.73 | J2: 3 | K2: Agregado desde BD_GASTOS_DASHBOARD_BRIDGE
A3: 2026-01 | B3: Costa Rica | C3: CR | D3: USD | E3: gasto_admin | F3: Personal | G3: Administracion | H3: 1600 | I3: 1600 | J3: 2 | K3: Agregado desde BD_GASTOS_DASHBOARD_BRIDGE
A4: 2026-01 | B4: Costa Rica | C4: CR | D4: USD | E4: gasto_admin | F4: Viajes | G4: Administracion | H4: 300 | I4: 300 | J4: 1 | K4: Agregado desde BD_GASTOS_DASHBOARD_BRIDGE
A5: 2026-01 | B5: Costa Rica | C5: CR | D5: USD | E5: gasto_area | F5: Financieros | G5: Financieros | H5: 20 | I5: 20 | J5: 1 | K5: Agregado desde BD_GASTOS_DASHBOARD_BRIDGE
A6: 2026-01 | B6: Estados Unidos | C6: USA | D6: USD | E6: gasto_admin | F6: Diversos | G6: Administracion | H6: 506.5 | I6: 506.5 | J6: 4 | K6: Agregado desde BD_GASTOS_DASHBOARD_BRIDGE
A7: 2026-01 | B7: Estados Unidos | C7: USA | D7: USD | E7: gasto_admin | F7: Honorarios | G7: Administracion | H7: 1500 | I7: 1500 | J7: 1 | K7: Agregado desde BD_GASTOS_DASHBOARD_BRIDGE
A8: 2026-01 | B8: Estados Unidos | C8: USA | D8: USD | E8: gasto_admin | F8: Personal | G8: Administracion | H8: 3550.43 | I8: 3550.43 | J8: 3 | K8: Agregado desde BD_GASTOS_DASHBOARD_BRIDGE
A9: 2026-01 | B9: Estados Unidos | C9: USA | D9: USD | E9: gasto_admin | F9: Servicios | G9: Administracion | H9: 281.34 | I9: 281.34 | J9: 4 | K9: Agregado desde BD_GASTOS_DASHBOARD_BRIDGE
A10: 2026-01 | B10: Estados Unidos | C10: USA | D10: USD | E10: gasto_area | F10: Financieros | G10: Financieros | H10: 75.9 | I10: 75.9 | J10: 2 | K10: Agregado desde BD_GASTOS_DASHBOARD_BRIDGE
A11: 2026-01 | B11: Estados Unidos | C11: USA | D11: USD | E11: gasto_comercial | F11: Servicios | G11: Comercial | H11: 648 | I11: 648 | J11: 1 | K11: Agregado desde BD_GASTOS_DASHBOARD_BRIDGE
A12: 2026-01 | B12: Peru | C12: PERU | D12: PEN | E12: gasto_area | F12: Financieros | G12: Financieros | H12: 92.71 | I12: 92.71 | J12: 3 | K12: Agregado desde BD_GASTOS_DASHBOARD_BRIDGE
A13: 2026-01 | B13: Peru | C13: PERU | D13: PEN | E13: gasto_comercial | F13: Honorarios | G13: Comercial | H13: 2127 | I13: 2127 | J13: 1 | K13: Agregado desde BD_GASTOS_DASHBOARD_BRIDGE
... A130: 2026-07 | B130: Peru | C130: PERU | D130: PEN | E130: gasto_comercial | F130: Viajes | G130: Comercial | H130: 7143.79 | I130: 14188.48 | J130: 24 | K130: Agregado desde BD_GASTOS_DASHBOARD_BRIDGE
