Workbook

Sheet LEEME
B2: COCO Tecnologías · Cockpit Financiero
B3: Plantilla de Burn & Runway · alimenta burn_runway.json
B5: Instrucciones
B6: 1. Diligencia solo las celdas en crema con texto azul. Lo gris está fijo y lo negro es fórmula.
B7: 2. NO cambies el texto de la columna 'Indicador' en RESUMEN ni en PROYECCION_KPIS: el tablero busca sus
B8: tarjetas por ese texto. Si lo reescribes, la tarjeta se queda vacía y nada avisa.
B9: 3. Las cifras van en COP millones (1.162,6 = mil ciento sesenta y dos millones), salvo donde la columna
B10: 'unidad' diga otra cosa. Es la escala del informe del modelo, no la del resto del tablero.
B11: 4. 'FCF' y 'Burn' son fórmula: FCF = CFO + CapEx, y Burn = el FCF cuando es negativo. No los escribas.
B12: 5. Un mes sin quema deja el runway vacío. No escribas 999 ni 0: el tablero muestra '—' y lo explica.
B13: 6. Esta pestaña convierte con SU PROPIA tasa, distinta a la del resto del tablero. El tablero lo advierte
B14: solo si la diferencia pasa de 0,5%, así que la celda 'TRM del informe' tiene que ser la de verdad.
... B28: Lo que esta plantilla NO trae: el puente de caja, la sensibilidad DSO y el flujo internacional. Se retiraron de la pestaña en agosto y siguen viviendo en el modelo.

Sheet CABECERA
B2: COCO Tecnologías · Cockpit Financiero
B3: Cabecera del informe
B5: Corte | C5: Julio 2026 | D5: Mes del informe, tal como debe leerse en el encabezado.
B6: Modelo de origen | C6: Modelo_COCO.xlsx | D6: Nombre del archivo del que salieron las cifras.
B7: TRM del informe | C7: 3505.27 | D7: La tasa con que ESTA pestaña convierte. El tablero avisa si difiere de la suya.
B8: TRM del presupuesto | C8: 3690 | D8: La que relaciona las columnas COP y USD de PRESUPUESTO.
B10: Lectura para accionistas | D10: Párrafo que abre la pestaña. Escríbelo como se lo dirías a la junta.
B11: Conclusión proyectada | D11: Cierra la pestaña, debajo de la tabla de presupuesto.

Sheet RESUMEN
B2: COCO Tecnologías · Cockpit Financiero
B3: Las tarjetas de caja y runway · NO cambies la columna Indicador
B5: Indicador (fijo) | C5: Valor | D5: Unidad | E5: Qué es
B6: Caja Colombia | D6: COP MM | E6: Efectivo y equivalentes del balance del mes.
B7: Caja EE.UU. (al cierre) | D7: USD k | E7: Saldo de caja en Estados Unidos, en miles de dólares.
B8: TRM aplicada (promedio del mes) | D8: COP / USD | E8: Tasa con que se convierte la caja de EE.UU.
B9: Caja total consolidada | D9: COP MM | E9: TARJETA 1. Colombia + EE.UU. convertida.
B10: FCF burn del mes | D10: COP MM/mes | E10: TARJETA 2. Flujo operativo + CapEx, en positivo si quema.
B11: Consumo neto de caja del mes | D11: COP MM | E11: TARJETA 3. Disminución real de bancos.
B12: Runway consolidado al burn del mes | D12: Meses | E12: TARJETA 4. Vacío o 'N/A' si el mes no tuvo quema.
B13: Runway promedio May-Jul | D13: Meses | E13: TARJETA 5. Cambia el rango del rótulo cada cierre.
B14: Runway promedio Ene-Jul | D14: Meses | E14: TARJETA 6. El rango largo del año.
B16: Los rótulos «Runway promedio May-Jul» y «Ene-Jul» llevan el rango dentro del texto: actualízalo cada cierre, el tablero lo lee de ahí.

Sheet MENSUAL
B2: COCO Tecnologías · Cockpit Financiero
B3: FCF y quema mes a mes · COP millones
B5: Mes | C5: CFO | D5: CapEx | E5: FCF | F5: Burn | G5: Cambio en caja | H5: Lectura del mes
B6: Ene-26 | E6: =IF(COUNT(C6:D6)=0,"",C6+D6) | F6: =IF(E6="","",MAX(0,-E6))
B7: Feb-26 | E7: =IF(COUNT(C7:D7)=0,"",C7+D7) | F7: =IF(E7="","",MAX(0,-E7))
B8: Mar-26 | E8: =IF(COUNT(C8:D8)=0,"",C8+D8) | F8: =IF(E8="","",MAX(0,-E8))
B9: Abr-26 | E9: =IF(COUNT(C9:D9)=0,"",C9+D9) | F9: =IF(E9="","",MAX(0,-E9))
B10: May-26 | E10: =IF(COUNT(C10:D10)=0,"",C10+D10) | F10: =IF(E10="","",MAX(0,-E10))
B11: Jun-26 | E11: =IF(COUNT(C11:D11)=0,"",C11+D11) | F11: =IF(E11="","",MAX(0,-E11))
B12: Jul-26 | E12: =IF(COUNT(C12:D12)=0,"",C12+D12) | F12: =IF(E12="","",MAX(0,-E12))
B14: CapEx va en negativo. FCF y Burn son fórmula: no los escribas. «Lectura del mes» es opcional y sale en el tooltip del gráfico.

Sheet PRESUPUESTO
B2: COCO Tecnologías · Cockpit Financiero
B3: Ingresos: presupuesto vs ejecutado · COP millones
B5: Mes | C5: Presupuesto COP | D5: Ejecutado COP | E5: Brecha COP | F5: Cumplimiento | G5: Ppto USD | H5: Ejec USD | I5: Brecha USD
B6: Ene-26 | E6: =IF(COUNT(C6:D6)<2,"",D6-C6) | F6: =IF(OR(C6="",C6=0,D6=""),"",D6/C6) | G6: =IF(OR(C6="",CABECERA!$C$8=0),"",C6/CABECERA!$C$8) | H6: =IF(OR(D6="",CABECERA!$C$8=0),"",D6/CABECERA!$C$8) | I6: =IF(OR(G6="",H6=""),"",H6-G6)
B7: Feb-26 | E7: =IF(COUNT(C7:D7)<2,"",D7-C7) | F7: =IF(OR(C7="",C7=0,D7=""),"",D7/C7) | G7: =IF(OR(C7="",CABECERA!$C$8=0),"",C7/CABECERA!$C$8) | H7: =IF(OR(D7="",CABECERA!$C$8=0),"",D7/CABECERA!$C$8) | I7: =IF(OR(G7="",H7=""),"",H7-G7)
B8: Mar-26 | E8: =IF(COUNT(C8:D8)<2,"",D8-C8) | F8: =IF(OR(C8="",C8=0,D8=""),"",D8/C8) | G8: =IF(OR(C8="",CABECERA!$C$8=0),"",C8/CABECERA!$C$8) | H8: =IF(OR(D8="",CABECERA!$C$8=0),"",D8/CABECERA!$C$8) | I8: =IF(OR(G8="",H8=""),"",H8-G8)
B9: Abr-26 | E9: =IF(COUNT(C9:D9)<2,"",D9-C9) | F9: =IF(OR(C9="",C9=0,D9=""),"",D9/C9) | G9: =IF(OR(C9="",CABECERA!$C$8=0),"",C9/CABECERA!$C$8) | H9: =IF(OR(D9="",CABECERA!$C$8=0),"",D9/CABECERA!$C$8) | I9: =IF(OR(G9="",H9=""),"",H9-G9)
B10: May-26 | E10: =IF(COUNT(C10:D10)<2,"",D10-C10) | F10: =IF(OR(C10="",C10=0,D10=""),"",D10/C10) | G10: =IF(OR(C10="",CABECERA!$C$8=0),"",C10/CABECERA!$C$8) | H10: =IF(OR(D10="",CABECERA!$C$8=0),"",D10/CABECERA!$C$8) | I10: =IF(OR(G10="",H10=""),"",H10-G10)
B11: Jun-26 | E11: =IF(COUNT(C11:D11)<2,"",D11-C11) | F11: =IF(OR(C11="",C11=0,D11=""),"",D11/C11) | G11: =IF(OR(C11="",CABECERA!$C$8=0),"",C11/CABECERA!$C$8) | H11: =IF(OR(D11="",CABECERA!$C$8=0),"",D11/CABECERA!$C$8) | I11: =IF(OR(G11="",H11=""),"",H11-G11)
B12: Jul-26 | E12: =IF(COUNT(C12:D12)<2,"",D12-C12) | F12: =IF(OR(C12="",C12=0,D12=""),"",D12/C12) | G12: =IF(OR(C12="",CABECERA!$C$8=0),"",C12/CABECERA!$C$8) | H12: =IF(OR(D12="",CABECERA!$C$8=0),"",D12/CABECERA!$C$8) | I12: =IF(OR(G12="",H12=""),"",H12-G12)
B13: Total Ene-Jul | C13: =SUM(C6:C12) -> 0 | D13: =SUM(D6:D12) -> 0 | E13: =SUM(E6:E12) -> 0 | F13: =IF(C13=0,"",D13/C13) | G13: =SUM(G6:G12) -> 0 | H13: =SUM(H6:H12) -> 0 | I13: =SUM(I6:I12) -> 0
B15: Las columnas en dólares se derivan de la TRM del presupuesto (CABECERA!C8). Si el modelo usó otra tasa, cámbiala allá, no aquí.

Sheet PROYECCION
B2: COCO Tecnologías · Cockpit Financiero
B3: Proyección con el presupuesto · COP millones
B5: Mes | C5: Ingresos | D5: Flujo del mes | E5: Caja al cierre | F5: Estado / explicación
B6: Ago-26
B7: Sep-26
B8: Oct-26
B9: Nov-26
B10: Dic-26
B12: «Estado» es la frase que el tablero muestra junto al mes. Di por qué, no solo «déficit»: en agosto 2026 el bache era el salto de capital de trabajo, no falta de caja.

Sheet PROYECCION_KPIS
B2: COCO Tecnologías · Cockpit Financiero
B3: KPIs de la proyección · NO cambies la columna Indicador
B5: Indicador (fijo) | C5: Valor | D5: Unidad | E5: Qué es
B6: Presupuesto anual de ingresos | D6: USD MM | E6: Ingresos 2026 del Modelo Base.
B7: Ingresos presupuestados del semestre restante | D7: USD MM | E7: Lo que falta del año.
B8: Runway hasta primer déficit | D8: Meses | E8: TARJETA 7. Meses de caja antes del primer mes en rojo.
B9: Déficit máximo proyectado | D9: COP MM | E9: El punto más bajo de la proyección.
B10: Caja proyectada a diciembre | D10: COP MM | E10: Cierre del año según el modelo.

Sheet INTERNACIONAL
B2: COCO Tecnologías · Cockpit Financiero
B3: Flujo de las filiales del mes · USD
B5: País | C5: Ingresos USD | D5: Egresos USD | E5: Neto USD | F5: Neto COP MM
B6: USA | E6: =IF(COUNT(C6:D6)=0,"",C6+D6) | F6: =IF(OR(E6="",CABECERA!$C$7=0),"",E6*CABECERA!$C$7/1000000)
B7: Perú | E7: =IF(COUNT(C7:D7)=0,"",C7+D7) | F7: =IF(OR(E7="",CABECERA!$C$7=0),"",E7*CABECERA!$C$7/1000000)
B8: Costa Rica | E8: =IF(COUNT(C8:D8)=0,"",C8+D8) | F8: =IF(OR(E8="",CABECERA!$C$7=0),"",E8*CABECERA!$C$7/1000000)
B9: Colombia | E9: =IF(COUNT(C9:D9)=0,"",C9+D9) | F9: =IF(OR(E9="",CABECERA!$C$7=0),"",E9*CABECERA!$C$7/1000000)
B11: Egresos en NEGATIVO. Si esta hoja queda vacía, el título de la pestaña pasa a decir «Burn & Runway · Colombia» en vez de «Consolidado (4 países)».
