Workbook

Sheet Diccionario
A1: Diccionario de indicadores — Dashboard Ejecutivo COCO Tecnologías
A2: Catálogo único de variables. 'Origen=COCO' viene de tu archivo; 'Origen=Claude' son inputs base que las fórmulas requieren y conviene validar.
A3: ID | B3: Categoría | C3: Código indicador | D3: Nombre visible | E3: Tipo | F3: Fórmula / regla de cálculo | G3: Unidad | H3: Responsable carga | I3: Fuente sugerida | J3: Frecuencia | K3: Desglose (segmento / detalle) | L3: Origen | M3: Comentario | N3: periodicidad
A4: 1 | B4: Control | C4: periodo | D4: Periodo | E4: Dimensión | F4: Mes de reporte en formato AAAA-MM | G4: AAAA-MM | H4: Cada área | I4: Plantilla | J4: Mensual | L4: COCO | M4: Debe existir en todas las filas | N4: Mensual
A5: 2 | B5: Control | C5: pais | D5: País | E5: Dimensión | F5: País donde se genera la métrica | G5: Texto | H5: Cada área | I5: Plantilla | J5: Mensual | K5: Colombia / México / EE.UU. / Otros | L5: COCO | N5: Mensual
A6: 3 | B6: Control | C6: compania | D6: Compañía | E6: Dimensión | F6: Entidad legal o unidad de negocio | G6: Texto | H6: Finanzas | I6: Contabilidad | J6: Mensual | K6: Coco Colombia / Coco LLC / Coco Global | L6: COCO | N6: Mensual
A7: 4 | B7: Control | C7: moneda | D7: Moneda | E7: Dimensión | F7: Moneda original del dato reportado | G7: COP/USD | H7: Cada área | I7: Plantilla | J7: Mensual | K7: COP / USD | L7: COCO | M7: No mezclar monedas sin identificar | N7: Mensual
A8: 5 | B8: Control | C8: escenario | D8: Escenario | E8: Dimensión | F8: Tipo de dato reportado | G8: Texto | H8: Finanzas | I8: Plantilla | J8: Mensual | K8: Real / Budget / Forecast | L8: COCO | M8: Permite comparar real vs ppto vs forecast | N8: Mensual
A9: 7 | B9: Finanzas | C9: ingresos_one_off | D9: Ingresos one-off | E9: Input | F9: Facturación no recurrente | G9: COP/USD | H9: Ventas | I9: Facturación / contab. | J9: Mensual | K9: detalle: Implementación / Interoperabilidad / Integración / Proyectos | L9: COCO | M9: Separar de ingresos recurrentes | N9: Mensual
A10: 10 | B10: Finanzas | C10: margen_bruto | D10: Margen bruto | E10: KPI | F10: ingresos_totales - costo_directo | G10: COP/USD | H10: Finanzas | I10: Contabilidad | J10: Mensual | L10: COCO | M10: Indicador clave de escalabilidad | N10: Mensual
A11: 11 | B11: Finanzas | C11: margen_bruto_pct | D11: Margen bruto % | E11: KPI | F11: margen_bruto / ingresos_totales | G11: % | H11: Finanzas | I11: Contabilidad | J11: Mensual | L11: COCO | M11: Meta a definir con CEO | N11: Mensual
A12: 12 | B12: Finanzas | C12: gastos_totales | D12: Gastos operativos totales | E12: Input/KPI | F12: Σ gastos por área | G12: COP/USD | H12: Finanzas | I12: Contabilidad | J12: Mensual | L12: COCO | M12: Opex. Puede cargarse agregado o por área. Distinto de 'egresos_totales' | N12: Mensual
A13: 15 | B13: Finanzas | C13: egresos_totales | D13: Egresos totales | E13: Input/KPI | F13: Σ de todas las salidas del periodo (costos + gastos + financieros) | G13: COP/USD | H13: Finanzas | I13: Contabilidad | J13: Mensual | L13: COCO | M13: P&L: Ingresos - Egresos = Utilidad neta | N13: Mensual
A14: 17 | B14: Finanzas | C14: utilidad_neta | D14: Utilidad neta | E14: KPI | F14: ingresos_totales - egresos_totales | G14: COP/USD | H14: Finanzas | I14: Contabilidad | J14: Mensual | L14: COCO | M14: Resultado del P&L del periodo | N14: Mensual
A15: 13 | B15: Finanzas | C15: ebitda | D15: EBITDA | E15: KPI | F15: margen_bruto - gastos_totales | G15: COP/USD | H15: Finanzas | I15: Contabilidad | J15: Mensual | L15: COCO | M15: Métrica central del comité | N15: Mensual
A16: 14 | B16: Finanzas | C16: margen_ebitda | D16: Margen EBITDA | E16: KPI | F16: ebitda / ingresos_totales | G16: % | H16: Finanzas | I16: Contabilidad | J16: Mensual | L16: COCO | M16: Comparar contra presupuesto | N16: Mensual
A17: 16 | B17: Finanzas | C17: cobros_periodo | D17: Cobros del periodo | E17: Input | F17: Dinero efectivamente recibido de clientes | G17: COP/USD | H17: Tesorería | I17: Bancos / cartera | J17: Mensual | L17: COCO | M17: Distinto a facturación | N17: Mensual
A18: 18 | B18: Finanzas | C18: burn_rate_neto | D18: Burn rate neto | E18: KPI | F18: pagos_periodo - cobros_periodo | G18: COP/USD | H18: Finanzas | I18: Tesorería | J18: Mensual | L18: COCO | M18: Negativo = consume caja | N18: Mensual
A19: 19 | B19: Finanzas | C19: runway_meses | D19: Runway | E19: KPI | F19: caja_disponible / burn_rate_neto | G19: Meses | H19: Finanzas | I19: Tesorería | J19: Mensual | L19: COCO | M19: Solo si burn_rate_neto > 0 | N19: Mensual
A20: 21 | B20: Finanzas | C20: ppto_vs_real_ingresos | D20: Ingresos real vs presupuesto | E20: KPI | F20: (ingresos_totales Real / ingresos_totales Budget) - 1 | G20: % | H20: Finanzas | I20: Presupuesto | J20: Mensual | L20: COCO | M20: Se deriva del campo 'escenario' | N20: Mensual
A21: 22 | B21: Finanzas | C21: ppto_vs_real_gastos | D21: Gastos real vs presupuesto | E21: KPI | F21: (gastos_totales Real / gastos_totales Budget) - 1 | G21: % | H21: Finanzas | I21: Presupuesto | J21: Mensual | L21: COCO | M21: Se deriva del campo 'escenario' | N21: Mensual
... A26: 36 | B26: Ventas | C26: pipeline_ponderado | D26: Pipeline ponderado | E26: KPI | F26: Σ (valor_oportunidad * prob_cierre) | G26: COP/USD | H26: Ventas | I26: CRM | J26: Semanal/mensual | L26: COCO | M26: Más útil que pipeline bruto | N26: Mensual
A27: 37 | B27: Ventas | C27: ventas_cerradas | D27: Ventas cerradas | E27: Input | F27: Valor contratos ganados en el periodo | G27: COP/USD | H27: Ventas | I27: CRM / contratos | J27: Mensual | K27: detalle: Recurrente / One-off | L27: COCO | M27: Separar recurrente vs one-off | N27: Mensual
A28: 41 | B28: Ventas | C28: ticket_promedio | D28: Ticket promedio | E28: KPI | F28: ventas_cerradas / deals_ganados | G28: COP/USD | H28: Ventas | I28: CRM / contratos | J28: Mensual | L28: COCO | M28: Medir también por país | N28: Mensual
A29: 42 | B29: Ventas | C29: forecast_comercial | D29: Forecast comercial | E29: Input/KPI | F29: Σ (oport. con cierre esperado * prob_cierre) | G29: COP/USD | H29: Ventas | I29: CRM | J29: Semanal/mensual | L29: COCO | M29: Anticipa ingresos | N29: Mensual
A30: 43 | B30: Marketing | C30: gasto_marketing_total | D30: Gasto marketing total | E30: Input | F30: Gasto total de marketing (pauta total) | G30: COP/USD | H30: Marketing | I30: Marketing | J30: Mensual | L30: COCO | M30: Necesario para CAC. Revisar = pauta total | N30: Mensual
A31: 44 | B31: Marketing | C31: leads_generados | D31: Leads generados | E31: Input | F31: Nº de leads nuevos | G31: Número | H31: Marketing | I31: CRM / formularios | J31: Mensual | K31: detalle: por canal (opcional) | L31: COCO | M31: Separar por canal si es posible | N31: Mensual
A32: 49 | B32: Marketing | C32: cac_fully_loaded | D32: CAC fully loaded | E32: KPI | F32: (gasto_ventas_comercial + gasto_marketing_total) / clientes_nuevos | G32: COP/USD | H32: Comercial/Mktg | I32: Contab. / CRM | J32: Trimestral | L32: COCO | M32: Incluye ventas + mktg. Revisión trimestral (Andrés) | N32: Trimestral
A33: 50 | B33: Marketing | C33: ltv | D33: LTV | E33: KPI | F33: (arpa * margen_bruto_pct) / churn_ingresos_pct | G33: COP/USD | H33: Comercial/Mktg | I33: Facturación / CRM | J33: Trimestral | K33: detalle: Mercadeo (s/ingreso, churn clientes) | Financiero TTM (margen 51%, churn ingresos) | L33: COCO | M33: Vista Financiera: hoja Calc_LTV_Fin, margen editable, churn TTM | N33: Trimestral
A34: 51 | B34: Marketing | C34: ltv_cac | D34: LTV / CAC | E34: KPI | F34: ltv / cac_fully_loaded | G34: Veces | H34: Comercial/Mktg | I34: Dashboard | J34: Trimestral | K34: detalle: Mercadeo | Financiero | L34: COCO | M34: Eficiencia comercial. Difiere según vista del LTV | N34: Trimestral
A35: 52 | B35: Marketing | C35: cac_payback_meses | D35: Payback CAC | E35: KPI | F35: cac_fully_loaded / (arpa * margen_bruto_pct) | G35: Meses | H35: Comercial/Mktg | I35: Dashboard | J35: Trimestral | K35: detalle: Mercadeo (s/margen) | Financiero (c/margen) | L35: COCO | M35: Dos vistas. Revisión trimestral (Andrés) | N35: Trimestral
A36: 53 | B36: Customer Success | C36: clientes_inicio | D36: Clientes iniciales | E36: Input | F36: Clientes activos al inicio del periodo | G36: Número | H36: Comercial | I36: CRM / facturación | J36: Mensual | L36: COCO | M36: Base para churn | N36: Mensual
A37: 54 | B37: Customer Success | C37: clientes_nuevos | D37: Clientes nuevos | E37: Input | F37: Clientes ganados en el periodo | G37: Número | H37: Comercial | I37: CRM | J37: Mensual | L37: COCO | M37: Reconcilia con ventas | N37: Mensual
A38: 56 | B38: Customer Success | C38: clientes_final | D38: Clientes finales | E38: KPI | F38: clientes_inicio + clientes_nuevos - clientes_perdidos | G38: Número | H38: Comercial | I38: CRM | J38: Mensual | L38: COCO | M38: Base al cierre | N38: Mensual
A39: 57 | B39: Customer Success | C39: churn_clientes_pct | D39: Churn de clientes | E39: KPI | F39: clientes_perdidos / clientes_inicio | G39: % | H39: Comercial | I39: CRM | J39: Mensual | L39: COCO | M39: Complementa churn de ingresos | N39: Mensual
A40: 58 | B40: Customer Success | C40: clientes_en_riesgo | D40: Clientes en riesgo | E40: Input | F40: Clientes con prob. de churn según CS | G40: Número | H40: Comercial | I40: CRM / health score | J40: Mensual | L40: COCO | M40: Métrica accionable | N40: Mensual
A41: 59 | B41: Customer Success | C41: clientes_riesgo_pct | D41: % clientes en riesgo | E41: KPI | F41: clientes_en_riesgo / clientes_final | G41: % | H41: Comercial | I41: CRM | J41: Mensual | L41: COCO | M41: Alerta temprana | N41: Mensual
A42: 60 | B42: Customer Success | C42: nps | D42: NPS | E42: Input | F42: Resultado de encuesta de recomendación | G42: % | H42: CS | I42: Encuestas | J42: Mensual/trim. | K42: detalle: Promotores / Pasivos / Detractores | L42: COCO | M42: S8. Histórico completo lo envía CS | N42: Mensual
A43: 67 | B43: Internacional | C43: ingresos_internacionales | D43: Ingresos internacionales | E43: KPI | F43: Σ ingresos_totales donde país≠Colombia | G43: COP/USD | H43: Finanzas | I43: Facturación | J43: Mensual | K43: segmento: por país | L43: COCO | M43: Clave para ronda | N43: Mensual
A44: 68 | B44: Internacional | C44: mrr_internacional | D44: MRR internacional | E44: KPI | F44: Σ mrr_final donde país≠Colombia | G44: COP/USD | H44: Finanzas/Intl | I44: Facturación / CRM | J44: Mensual | K44: segmento: por país | L44: COCO | N44: Mensual
A45: 69 | B45: Internacional | C45: pipeline_internacional | D45: Pipeline internacional | E45: KPI | F45: Σ pipeline_total donde país≠Colombia | G45: COP/USD | H45: Ventas/Intl | I45: CRM | J45: Semanal/mensual | K45: segmento: por país | L45: COCO | M45: Tracción internacional | N45: Mensual
A46: 70 | B46: Internacional | C46: clientes_internacionales | D46: Clientes internacionales | E46: KPI | F46: Σ clientes_final donde país≠Colombia | G46: Número | H46: CS/Intl | I46: CRM / facturación | J46: Mensual | K46: segmento: por país | L46: COCO | N46: Mensual
A47: 101 | B47: Contabilidad | C47: new_mrr | D47: Nuevas ventas MRR | E47: Input | F47: MRR de clientes nuevos del periodo | G47: COP/USD | H47: Contabilidad | I47: Contabilidad | J47: Mensual (serie 13m) | L47: COCO | M47: Componente del MRR bridge | N47: Mensual
A48: 102 | B48: Contabilidad | C48: expansion_mrr | D48: Expansión MRR | E48: Input | F48: Incremento de MRR de clientes existentes | G48: COP/USD | H48: Contabilidad | I48: Contabilidad | J48: Mensual (serie 13m) | L48: COCO | M48: Componente del MRR bridge | N48: Mensual
A49: 103 | B49: Contabilidad | C49: reactivacion_mrr | D49: Rescatadas MRR | E49: Input | F49: MRR de clientes recuperados | G49: COP/USD | H49: Contabilidad | I49: Contabilidad | J49: Mensual (serie 13m) | L49: COCO | M49: Componente del MRR bridge | N49: Mensual
A50: 104 | B50: Contabilidad | C50: contraction_mrr | D50: Contracción MRR | E50: Input | F50: Reducción de MRR de clientes existentes | G50: COP/USD | H50: Contabilidad | I50: Contabilidad | J50: Mensual (serie 13m) | L50: COCO | M50: Componente del MRR bridge | N50: Mensual
A51: 105 | B51: Contabilidad | C51: churned_mrr | D51: Churned MRR | E51: Input | F51: MRR perdido por clientes que se van | G51: COP/USD | H51: Contabilidad | I51: Contabilidad | J51: Mensual (serie 13m) | L51: COCO | M51: Componente del MRR bridge | N51: Mensual
A52: 106 | B52: Contabilidad | C52: retained_mrr | D52: Retenidas MRR | E52: Input | F52: MRR retenido del periodo anterior | G52: COP/USD | H52: Contabilidad | I52: Contabilidad | J52: Mensual (serie 13m) | L52: COCO | M52: Componente del MRR bridge | N52: Mensual
A53: 107 | B53: Contabilidad | C53: churn_mrr_mensual | D53: Churn MRR mensual | E53: KPI | F53: churned_mrr / mrr_inicio | G53: % | H53: Contabilidad | I53: Contabilidad | J53: Mensual (serie 13m) | L53: COCO | M53: Churn de ingresos mes a mes | N53: Mensual
A54: 108 | B54: Customer Success | C54: clientes_retirados | D54: Clientes retirados | E54: Input | F54: Nº de clientes que se retiran en el periodo | G54: Número | H54: Comercial | I54: CRM | J54: Mensual | L54: COCO | M54: Igual a clientes_perdidos | N54: Mensual
A55: 120 | B55: Contabilidad | C55: cartera_total | D55: Cartera total | E55: Input | F55: Saldo total de cartera por cobrar | G55: COP/USD | H55: Contabilidad | I55: Contabilidad | J55: Mensual (serie 13m + último mes) | L55: COCO | N55: Mensual
A56: 121 | B56: Contabilidad | C56: cartera_vencida | D56: Cartera vencida | E56: Input | F56: Cartera con plazo vencido | G56: COP/USD | H56: Contabilidad | I56: Contabilidad | J56: Mensual (serie 13m + último mes) | L56: COCO | N56: Mensual
A57: 122 | B57: Contabilidad | C57: cartera_sana | D57: Cartera sana | E57: KPI | F57: cartera_total - cartera_vencida | G57: COP/USD | H57: Contabilidad | I57: Contabilidad | J57: Mensual (serie 13m + último mes) | L57: COCO | N57: Mensual
A58: 123 | B58: Contabilidad | C58: cartera_vencida_cliente | D58: Cartera vencida por cliente | E58: Input | F58: Cartera vencida atribuida a cada cliente | G58: COP/USD | H58: Contabilidad | I58: Contabilidad | J58: Mensual | K58: detalle: 7 principales + 'Otros' | L58: COCO | M58: Para gráfico de torta | N58: Mensual
A59: 124 | B59: Contabilidad | C59: liquidez_total | D59: Liquidez total | E59: Input | F59: Saldo disponible por cuenta principal | G59: COP/USD | H59: Tesorería | I59: Bancos | J59: Mensual | K59: detalle: cuenta bancaria | L59: COCO | M59: Por cuentas principales | N59: Mensual
A60: 130 | B60: Contabilidad | C60: dso | D60: DSO | E60: KPI | F60: cartera_total / facturacion_periodo * 30 | G60: Días | H60: Contabilidad | I60: Contabilidad | J60: Mensual (evol. 12m + proy.) | L60: COCO | M60: Días de cartera | N60: Mensual
A61: 131 | B61: Contabilidad | C61: dpo | D61: DPO | E61: KPI | F61: cuentas_x_pagar / costo_directo * 30 | G61: Días | H61: Contabilidad | I61: Contabilidad | J61: Mensual (evol. 12m + proy.) | L61: COCO | M61: Días de pago a proveedores | N61: Mensual
A62: 132 | B62: Contabilidad | C62: ccc | D62: CCC | E62: KPI | F62: dso - dpo (+ días de inventario) | G62: Días | H62: Contabilidad | I62: Contabilidad | J62: Mensual (evol. 12m + proy.) | L62: COCO | M62: Ciclo de conversión de efectivo | N62: Mensual
A63: 140 | B63: Contabilidad | C63: gasto_area | D63: Costos y gastos por área | E63: Input | F63: Gasto del periodo por gran área | G63: COP/USD | H63: Contabilidad | I63: Contabilidad | J63: Mensual (serie 13m) | K63: detalle: Administración / Comercial / Proveedores / TI / Financieros | L63: COCO | M63: CONSOLIDADO: usar 'detalle' para el área | N63: Mensual
A64: 141 | B64: Contabilidad | C64: gasto_admin | D64: Gastos administrativos | E64: Input | F64: Gasto administrativo por concepto | G64: COP/USD | H64: Contabilidad | I64: Contabilidad | J64: Mensual (serie 13m) | K64: detalle: Diversos / Viajes / Servicios / Seguros / Arrendamientos / Honorarios / Personal | L64: COCO | M64: CONSOLIDADO: usar 'detalle' para el concepto | N64: Mensual
A65: 142 | B65: Contabilidad | C65: costo_operacion | D65: Costos de operación | E65: Input | F65: Costo de operación por concepto | G65: COP/USD | H65: Contabilidad | I65: Contabilidad | J65: Mensual (serie 13m) | K65: detalle: Viajes / Mantenimientos / Servicios / Honorarios / Personal | L65: COCO | M65: CONSOLIDADO: usar 'detalle' para el concepto | N65: Mensual
A66: 143 | B66: Contabilidad | C66: costo_proveedor | D66: Costos de proveedores | E66: Input | F66: Costo por proveedor tecnológico | G66: COP/USD | H66: Contabilidad | I66: Contabilidad | J66: Mensual (serie 13m) | K66: detalle: B2Chat / AWS / Infobip / IVA / Otros | L66: COCO | M66: CONSOLIDADO: usar 'detalle' para el proveedor | N66: Mensual
A67: 144 | B67: Contabilidad | C67: costo_proveedor_ventas_pct | D67: Costos de proveedores / ventas % | E67: KPI | F67: Σ costo_proveedor / ingresos_totales | G67: % | H67: Contabilidad | I67: Contabilidad | J67: Mensual (serie 13m) | L67: COCO | N67: Mensual
A68: 145 | B68: Contabilidad | C68: salario_area_pct | D68: Salarios por área % | E68: KPI | F68: nómina_área / nómina_total | G68: % | H68: Contabilidad | I68: Contabilidad | J68: Mensual (últimos 2 meses) | K68: detalle: Desarrollo / Operaciones / Comercial / Administrativo | L68: COCO | M68: Gráfico de torta | N68: Mensual
A69: 150 | B69: Contabilidad | C69: distribucion_clientes | D69: Distribución de clientes | E69: Input/KPI | F69: Nº o % de clientes por tipo de ingreso | G69: Número/% | H69: Comercial | I69: CRM / facturación | J69: Mensual | K69: detalle: Recurrente / No recurrente | L69: COCO | N69: Mensual
A70: 160 | B70: Financiero | C70: escenarios_fin | D70: Escenarios financieros | E70: KPI | F70: Proyección por escenario (Real/Budget/Forecast) | G70: COP/USD | H70: Finanzas | I70: Modelo financiero | J70: Mensual | K70: detalle: definir vistas con Andrés | L70: COCO | M70: ALCANCE A DEFINIR — vino suelto en el archivo | N70: Mensual
A71: 125 | B71: Contabilidad | C71: cartera_cobro_legal | D71: Cartera en cobro legal | E71: Input | F71: Saldo de cartera en proceso jurídico | G71: COP/USD | H71: Contabilidad | I71: Contabilidad | J71: Mensual | L71: COCO | M71: Subconjunto de la cartera vencida | N71: Mensual
A72: 133 | B72: Contabilidad | C72: indice_morosidad | D72: Índice de morosidad | E72: KPI | F72: cartera_vencida / cartera_total | G72: % | H72: Contabilidad | I72: Contabilidad | J72: Mensual | L72: COCO | M72: Meta: excelente < 5% | N72: Mensual
A73: 134 | B73: Contabilidad | C73: cartera_mayor_60_pct | D73: % Cartera mayor a 60 días | E73: KPI | F73: cartera_>60d / cartera_total | G73: % | H73: Contabilidad | I73: Contabilidad | J73: Mensual | L73: COCO | M73: Meta: excelente < 5% | N73: Mensual
A74: 135 | B74: Contabilidad | C74: cartera_arr_pct | D74: Cartera como % de ARR | E74: KPI | F74: cartera_total / arr | G74: % | H74: Contabilidad | I74: Contabilidad | J74: Mensual | L74: COCO | M74: Meta: excelente < 12% | N74: Mensual
A75: 136 | B75: Contabilidad | C75: concentracion_cartera | D75: Concentración de cartera | E75: KPI | F75: cartera top cliente(s) / cartera_total | G75: % | H75: Contabilidad | I75: Contabilidad | J75: Mensual | L75: COCO | M75: Meta: excelente < 15% | N75: Mensual
A76: 137 | B76: Contabilidad | C76: write_off_ratio | D76: Write-off ratio (castigo real) | E76: KPI | F76: cartera_castigada / ventas | G76: % | H76: Contabilidad | I76: Contabilidad | J76: Mensual | L76: COCO | M76: Meta: excelente < 1% | N76: Mensual
A77: 8 | B77: Finanzas | C77: ingresos_no_recurrentes | D77: Ingresos no recurrentes | E77: Input | F77: Ingresos variables / one-off del periodo | G77: COP/USD | H77: Finanzas | I77: Facturación | J77: Mensual | L77: COCO | M77: Serie S5 | N77: Mensual
A78: 146 | B78: Contabilidad | C78: gasto_desarrollo | D78: Gastos de Desarrollo | E78: Input | F78: Gasto del área de desarrollo por concepto | G78: COP/USD | H78: Contabilidad | I78: Contabilidad | J78: Mensual (serie) | K78: detalle: Personal / Honorarios / Servicios / Viajes | L78: COCO | M78: Zoom S15 | N78: Mensual
A79: 147 | B79: Contabilidad | C79: gasto_comercial | D79: Gastos Comercial | E79: Input | F79: Gasto del área comercial por concepto | G79: COP/USD | H79: Contabilidad | I79: Contabilidad | J79: Mensual (serie) | K79: detalle: Personal / Honorario / Seguros / Servicios / Viajes / Diversos | L79: COCO | M79: Zoom S13 | N79: Mensual
A80: 170 | B80: Ventas | C80: distribucion_facturacion_tamano | D80: Distribución facturación por tamaño | E80: KPI | F80: % de facturación por tamaño de cliente | G80: % | H80: Comercial | I80: CRM / facturación | J80: Mensual (serie) | K80: detalle: Grandes / Medianos / Pequeños | L80: COCO | M80: S9 | N80: Mensual
A81: 171 | B81: Finanzas | C81: distribucion_ingresos | D81: Distribución de ingresos por tipo | E81: KPI | F81: % de ingresos por tipo | G81: % | H81: Finanzas | I81: Contabilidad | J81: Anual | K81: detalle: Recurrente / Variable / Implementaciones / Internacional | L81: COCO | M81: S4 (pie por año) | N81: Mensual
A82: 201 | B82: Finanzas | C82: mrr_inicio | D82: MRR inicio | E82: Input | F82: MRR al inicio del periodo | G82: COP/USD | H82: Finanzas | I82: Facturación / CRM | J82: Mensual | L82: Claude | M82: Requerido por GRR, churn, bridge | N82: Mensual
A83: 202 | B83: Finanzas | C83: mrr_final | D83: MRR final | E83: Input | F83: MRR al cierre del periodo | G83: COP/USD | H83: Finanzas | I83: Facturación / CRM | J83: Mensual | L83: Claude | M83: Requerido por ARR, ARPA, MRR intl | N83: Mensual
A84: 203 | B84: Finanzas | C84: ingresos_recurrentes | D84: Ingresos recurrentes | E84: Input | F84: Ingreso recurrente reconocido en el periodo | G84: COP/USD | H84: Finanzas | I84: Facturación | J84: Mensual | L84: Claude | M84: ≈ MRR reconocido del mes | N84: Mensual
A85: 204 | B85: Finanzas | C85: ingresos_totales | D85: Ingresos totales | E85: KPI | F85: ingresos_recurrentes + ingresos_one_off | G85: COP/USD | H85: Finanzas | I85: Contabilidad | J85: Mensual | L85: Claude | M85: Base de muchos KPIs | N85: Mensual
A86: 205 | B86: Finanzas | C86: costo_directo | D86: Costo directo | E86: Input | F86: Costo directo de servicio (COGS) | G86: COP/USD | H86: Finanzas | I86: Contabilidad | J86: Mensual | L86: Claude | M86: Requerido por margen bruto | N86: Mensual
A87: 206 | B87: Finanzas | C87: caja_disponible | D87: Caja disponible | E87: Input | F87: Saldo de caja al cierre | G87: COP/USD | H87: Tesorería | I87: Bancos | J87: Mensual | L87: Claude | M87: Requerido por runway | N87: Mensual
A88: 207 | B88: Finanzas | C88: pagos_periodo | D88: Pagos del periodo | E88: Input | F88: Dinero efectivamente pagado en el periodo | G88: COP/USD | H88: Tesorería | I88: Bancos | J88: Mensual | L88: Claude | M88: Requerido por burn rate | N88: Mensual
A89: 208 | B89: Finanzas | C89: facturacion_periodo | D89: Facturación del periodo | E89: Input | F89: Dinero efectivamente facturado | G89: COP/USD | H89: Facturación | I89: Facturación | J89: Mensual | L89: Claude | M89: Requerido por DSO / cartera | N89: Mensual
A90: 209 | B90: Customer Success | C90: clientes_perdidos | D90: Clientes perdidos | E90: Input | F90: Clientes que se retiran en el periodo | G90: Número | H90: Comercial | I90: CRM | J90: Mensual | L90: Claude | M90: Igual a clientes_retirados; requerido por churn | N90: Mensual
A91: 210 | B91: Ventas | C91: deals_ganados | D91: Deals ganados | E91: Input | F91: Nº de oportunidades ganadas | G91: Número | H91: Ventas | I91: CRM | J91: Mensual | L91: Claude | M91: Requerido por ticket promedio | N91: Mensual
A92: 211 | B92: Ventas | C92: gasto_ventas_comercial | D92: Gasto comercial (ventas) | E92: Input | F92: Gasto del área comercial para adquisición | G92: COP/USD | H92: Comercial | I92: Contabilidad | J92: Mensual | L92: Claude | M92: Requerido por CAC fully loaded | N92: Mensual
A93: 212 | B93: SaaS / Revenue | C93: churn_ingresos_pct | D93: Churn de ingresos % | E93: KPI | F93: churned_mrr / mrr_inicio | G93: % | H93: Finanzas | I93: Contabilidad | J93: Mensual | L93: Claude | M93: Requerido por LTV | N93: Mensual
A94: 213 | B94: P&G oficial | C94: pyg_ingresos_operacionales | D94: P&G · Ingresos operacionales netos | E94: Input | F94: Servicio de software − devoluciones | G94: COP/USD | H94: Finanzas | I94: Estados financieros / Contabilidad | J94: Mensual | K94: pais / compañía | L94: COCO | M94: Ingreso operacional neto del P&G oficial mensual | N94: Mensual
A95: 214 | B95: P&G oficial | C95: pyg_servicio_software | D95: P&G · Servicio de software | E95: Input | F95: Facturación bruta por servicio de software | G95: COP | H95: Finanzas | I95: Estados financieros / Contabilidad | J95: Mensual | K95: pais / compañía | L95: COCO | M95: Antes de devoluciones | N95: Mensual
A96: 215 | B96: P&G oficial | C96: pyg_devoluciones | D96: P&G · Devoluciones en ventas | E96: Input | F96: Devoluciones del periodo (valor negativo) | G96: COP | H96: Finanzas | I96: Estados financieros / Contabilidad | J96: Mensual | K96: pais / compañía | L96: COCO | M96: Resta de ingresos | N96: Mensual
A97: 216 | B97: P&G oficial | C97: pyg_costo_ventas | D97: P&G · Costo de ventas | E97: Input | F97: Costo directo del servicio | G97: COP/USD | H97: Finanzas | I97: Estados financieros / Contabilidad | J97: Mensual | K97: pais / compañía | L97: COCO | M97: COGS del P&G oficial | N97: Mensual
A98: 217 | B98: P&G oficial | C98: pyg_utilidad_bruta | D98: P&G · Utilidad bruta | E98: KPI | F98: ingresos_operacionales − costo_ventas | G98: COP | H98: Finanzas | I98: Estados financieros / Contabilidad | J98: Mensual | K98: pais / compañía | L98: COCO | M98: Margen bruto del P&G oficial | N98: Mensual
A99: 218 | B99: P&G oficial | C99: pyg_gasto_administracion | D99: P&G · Gastos de administración | E99: Input | F99: Gastos operacionales de administración | G99: COP/USD | H99: Finanzas | I99: Estados financieros / Contabilidad | J99: Mensual | K99: pais / compañía | L99: COCO | M99: Línea del P&G oficial | N99: Mensual
A100: 219 | B100: P&G oficial | C100: pyg_gasto_proyectos | D100: P&G · Gastos operación/proyectos | E100: Input | F100: Gastos operacionales / proyectos reclasificados | G100: COP/USD | H100: Finanzas | I100: Estados financieros / Contabilidad | J100: Mensual | K100: pais / compañía | L100: COCO | M100: Línea del P&G oficial | N100: Mensual
A101: 220 | B101: P&G oficial | C101: pyg_gasto_ventas | D101: P&G · Gastos de ventas | E101: Input | F101: Gastos operacionales de ventas | G101: COP/USD | H101: Finanzas | I101: Estados financieros / Contabilidad | J101: Mensual | K101: pais / compañía | L101: COCO | M101: Línea del P&G oficial | N101: Mensual
A102: 221 | B102: P&G oficial | C102: pyg_utilidad_operativa | D102: P&G · Utilidad operativa | E102: KPI | F102: utilidad_bruta − gastos operacionales | G102: COP | H102: Finanzas | I102: Estados financieros / Contabilidad | J102: Mensual | K102: pais / compañía | L102: COCO | M102: Base de EBITDA junio | N102: Mensual
A103: 222 | B103: P&G oficial | C103: pyg_ingresos_no_operacionales | D103: P&G · Ingresos no operacionales | E103: Input | F103: Ingresos financieros / otros no operacionales | G103: COP/USD | H103: Finanzas | I103: Estados financieros / Contabilidad | J103: Mensual | K103: pais / compañía | L103: COCO | M103: Línea del P&G oficial | N103: Mensual
A104: 223 | B104: P&G oficial | C104: pyg_gastos_financieros | D104: P&G · Gastos financieros | E104: Input | F104: Gastos no operacionales / financieros | G104: COP/USD | H104: Finanzas | I104: Estados financieros / Contabilidad | J104: Mensual | K104: pais / compañía | L104: COCO | M104: Línea del P&G oficial | N104: Mensual
...

Sheet BD_Indicadores
A1: BD_Indicadores — tabla de hechos (formato largo). 1 fila = 1 indicador en 1 periodo y dimensiones.
A2: AAAA-MM | B2: lista | C2: lista | D2: lista | E2: lista | F2: lista (Diccionario) | G2: p.ej. Medianos | H2: p.ej. AWS / Comercial | I2: número | J2: COP/USD/%/… | K2: opcional | L2: lista (Diccionario)
A3: periodo | B3: pais | C3: compania | D3: moneda | E3: escenario | F3: codigo_indicador | G3: segmento | H3: detalle | I3: valor | J3: unidad | K3: comentario | L3: area | M3: area_responsable | N3: periodicidad
A4: 2024-01 | B4: Colombia | C4: Coco Colombia | D4: COP | E4: Real | F4: ingresos_totales | I4: 430000000 | J4: COP | L4: =IFERROR(INDEX(Diccionario!$B:$B,MATCH(F4,Diccionario!$C:$C,0)),"") | M4: =IFERROR(INDEX(Diccionario!$H:$H,MATCH(F4,Diccionario!$C:$C,0)),"") | N4: =IFERROR(INDEX(Diccionario!$N:$N,MATCH(F4,Diccionario!$C:$C,0)),"")
A5: 2024-01 | B5: Colombia | C5: Coco Colombia | D5: COP | E5: Real | F5: egresos_totales | I5: 547000000 | J5: COP | L5: =IFERROR(INDEX(Diccionario!$B:$B,MATCH(F5,Diccionario!$C:$C,0)),"") | M5: =IFERROR(INDEX(Diccionario!$H:$H,MATCH(F5,Diccionario!$C:$C,0)),"") | N5: =IFERROR(INDEX(Diccionario!$N:$N,MATCH(F5,Diccionario!$C:$C,0)),"")
A6: 2024-01 | B6: Colombia | C6: Coco Colombia | D6: COP | E6: Real | F6: utilidad_neta | I6: -117000000 | J6: COP | K6: Derivado: ingresos - egresos | L6: =IFERROR(INDEX(Diccionario!$B:$B,MATCH(F6,Diccionario!$C:$C,0)),"") | M6: =IFERROR(INDEX(Diccionario!$H:$H,MATCH(F6,Diccionario!$C:$C,0)),"") | N6: =IFERROR(INDEX(Diccionario!$N:$N,MATCH(F6,Diccionario!$C:$C,0)),"")
A7: 2024-02 | B7: Colombia | C7: Coco Colombia | D7: COP | E7: Real | F7: ingresos_totales | I7: 692000000 | J7: COP | L7: =IFERROR(INDEX(Diccionario!$B:$B,MATCH(F7,Diccionario!$C:$C,0)),"") | M7: =IFERROR(INDEX(Diccionario!$H:$H,MATCH(F7,Diccionario!$C:$C,0)),"") | N7: =IFERROR(INDEX(Diccionario!$N:$N,MATCH(F7,Diccionario!$C:$C,0)),"")
A8: 2024-02 | B8: Colombia | C8: Coco Colombia | D8: COP | E8: Real | F8: egresos_totales | I8: 515000000 | J8: COP | L8: =IFERROR(INDEX(Diccionario!$B:$B,MATCH(F8,Diccionario!$C:$C,0)),"") | M8: =IFERROR(INDEX(Diccionario!$H:$H,MATCH(F8,Diccionario!$C:$C,0)),"") | N8: =IFERROR(INDEX(Diccionario!$N:$N,MATCH(F8,Diccionario!$C:$C,0)),"")
A9: 2024-02 | B9: Colombia | C9: Coco Colombia | D9: COP | E9: Real | F9: utilidad_neta | I9: 177000000 | J9: COP | K9: Derivado: ingresos - egresos | L9: =IFERROR(INDEX(Diccionario!$B:$B,MATCH(F9,Diccionario!$C:$C,0)),"") | M9: =IFERROR(INDEX(Diccionario!$H:$H,MATCH(F9,Diccionario!$C:$C,0)),"") | N9: =IFERROR(INDEX(Diccionario!$N:$N,MATCH(F9,Diccionario!$C:$C,0)),"")
A10: 2024-03 | B10: Colombia | C10: Coco Colombia | D10: COP | E10: Real | F10: ingresos_totales | I10: 582000000 | J10: COP | L10: =IFERROR(INDEX(Diccionario!$B:$B,MATCH(F10,Diccionario!$C:$C,0)),"") | M10: =IFERROR(INDEX(Diccionario!$H:$H,MATCH(F10,Diccionario!$C:$C,0)),"") | N10: =IFERROR(INDEX(Diccionario!$N:$N,MATCH(F10,Diccionario!$C:$C,0)),"")
A11: 2024-03 | B11: Colombia | C11: Coco Colombia | D11: COP | E11: Real | F11: egresos_totales | I11: 571000000 | J11: COP | L11: =IFERROR(INDEX(Diccionario!$B:$B,MATCH(F11,Diccionario!$C:$C,0)),"") | M11: =IFERROR(INDEX(Diccionario!$H:$H,MATCH(F11,Diccionario!$C:$C,0)),"") | N11: =IFERROR(INDEX(Diccionario!$N:$N,MATCH(F11,Diccionario!$C:$C,0)),"")
A12: 2024-03 | B12: Colombia | C12: Coco Colombia | D12: COP | E12: Real | F12: utilidad_neta | I12: 11000000 | J12: COP | K12: Derivado: ingresos - egresos | L12: =IFERROR(INDEX(Diccionario!$B:$B,MATCH(F12,Diccionario!$C:$C,0)),"") | M12: =IFERROR(INDEX(Diccionario!$H:$H,MATCH(F12,Diccionario!$C:$C,0)),"") | N12: =IFERROR(INDEX(Diccionario!$N:$N,MATCH(F12,Diccionario!$C:$C,0)),"")
A13: 2024-04 | B13: Colombia | C13: Coco Colombia | D13: COP | E13: Real | F13: ingresos_totales | I13: 578000000 | J13: COP | L13: =IFERROR(INDEX(Diccionario!$B:$B,MATCH(F13,Diccionario!$C:$C,0)),"") | M13: =IFERROR(INDEX(Diccionario!$H:$H,MATCH(F13,Diccionario!$C:$C,0)),"") | N13: =IFERROR(INDEX(Diccionario!$N:$N,MATCH(F13,Diccionario!$C:$C,0)),"")
A14: 2024-04 | B14: Colombia | C14: Coco Colombia | D14: COP | E14: Real | F14: egresos_totales | I14: 573000000 | J14: COP | L14: =IFERROR(INDEX(Diccionario!$B:$B,MATCH(F14,Diccionario!$C:$C,0)),"") | M14: =IFERROR(INDEX(Diccionario!$H:$H,MATCH(F14,Diccionario!$C:$C,0)),"") | N14: =IFERROR(INDEX(Diccionario!$N:$N,MATCH(F14,Diccionario!$C:$C,0)),"")
A15: 2024-04 | B15: Colombia | C15: Coco Colombia | D15: COP | E15: Real | F15: utilidad_neta | I15: 5000000 | J15: COP | K15: Derivado: ingresos - egresos | L15: =IFERROR(INDEX(Diccionario!$B:$B,MATCH(F15,Diccionario!$C:$C,0)),"") | M15: =IFERROR(INDEX(Diccionario!$H:$H,MATCH(F15,Diccionario!$C:$C,0)),"") | N15: =IFERROR(INDEX(Diccionario!$N:$N,MATCH(F15,Diccionario!$C:$C,0)),"")
A16: 2024-05 | B16: Colombia | C16: Coco Colombia | D16: COP | E16: Real | F16: ingresos_totales | I16: 679000000 | J16: COP | L16: =IFERROR(INDEX(Diccionario!$B:$B,MATCH(F16,Diccionario!$C:$C,0)),"") | M16: =IFERROR(INDEX(Diccionario!$H:$H,MATCH(F16,Diccionario!$C:$C,0)),"") | N16: =IFERROR(INDEX(Diccionario!$N:$N,MATCH(F16,Diccionario!$C:$C,0)),"")
A17: 2024-05 | B17: Colombia | C17: Coco Colombia | D17: COP | E17: Real | F17: egresos_totales | I17: 574000000 | J17: COP | L17: =IFERROR(INDEX(Diccionario!$B:$B,MATCH(F17,Diccionario!$C:$C,0)),"") | M17: =IFERROR(INDEX(Diccionario!$H:$H,MATCH(F17,Diccionario!$C:$C,0)),"") | N17: =IFERROR(INDEX(Diccionario!$N:$N,MATCH(F17,Diccionario!$C:$C,0)),"")
A18: 2024-05 | B18: Colombia | C18: Coco Colombia | D18: COP | E18: Real | F18: utilidad_neta | I18: 105000000 | J18: COP | K18: Derivado: ingresos - egresos | L18: =IFERROR(INDEX(Diccionario!$B:$B,MATCH(F18,Diccionario!$C:$C,0)),"") | M18: =IFERROR(INDEX(Diccionario!$H:$H,MATCH(F18,Diccionario!$C:$C,0)),"") | N18: =IFERROR(INDEX(Diccionario!$N:$N,MATCH(F18,Diccionario!$C:$C,0)),"")
A19: 2024-06 | B19: Colombia | C19: Coco Colombia | D19: COP | E19: Real | F19: ingresos_totales | I19: 684000000 | J19: COP | L19: =IFERROR(INDEX(Diccionario!$B:$B,MATCH(F19,Diccionario!$C:$C,0)),"") | M19: =IFERROR(INDEX(Diccionario!$H:$H,MATCH(F19,Diccionario!$C:$C,0)),"") | N19: =IFERROR(INDEX(Diccionario!$N:$N,MATCH(F19,Diccionario!$C:$C,0)),"")
A20: 2024-06 | B20: Colombia | C20: Coco Colombia | D20: COP | E20: Real | F20: egresos_totales | I20: 611000000 | J20: COP | L20: =IFERROR(INDEX(Diccionario!$B:$B,MATCH(F20,Diccionario!$C:$C,0)),"") | M20: =IFERROR(INDEX(Diccionario!$H:$H,MATCH(F20,Diccionario!$C:$C,0)),"") | N20: =IFERROR(INDEX(Diccionario!$N:$N,MATCH(F20,Diccionario!$C:$C,0)),"")
A21: 2024-06 | B21: Colombia | C21: Coco Colombia | D21: COP | E21: Real | F21: utilidad_neta | I21: 73000000 | J21: COP | K21: Derivado: ingresos - egresos | L21: =IFERROR(INDEX(Diccionario!$B:$B,MATCH(F21,Diccionario!$C:$C,0)),"") | M21: =IFERROR(INDEX(Diccionario!$H:$H,MATCH(F21,Diccionario!$C:$C,0)),"") | N21: =IFERROR(INDEX(Diccionario!$N:$N,MATCH(F21,Diccionario!$C:$C,0)),"")
A22: 2024-07 | B22: Colombia | C22: Coco Colombia | D22: COP | E22: Real | F22: ingresos_totales | I22: 642000000 | J22: COP | L22: =IFERROR(INDEX(Diccionario!$B:$B,MATCH(F22,Diccionario!$C:$C,0)),"") | M22: =IFERROR(INDEX(Diccionario!$H:$H,MATCH(F22,Diccionario!$C:$C,0)),"") | N22: =IFERROR(INDEX(Diccionario!$N:$N,MATCH(F22,Diccionario!$C:$C,0)),"")
A23: 2024-07 | B23: Colombia | C23: Coco Colombia | D23: COP | E23: Real | F23: egresos_totales | I23: 555000000 | J23: COP | L23: =IFERROR(INDEX(Diccionario!$B:$B,MATCH(F23,Diccionario!$C:$C,0)),"") | M23: =IFERROR(INDEX(Diccionario!$H:$H,MATCH(F23,Diccionario!$C:$C,0)),"") | N23: =IFERROR(INDEX(Diccionario!$N:$N,MATCH(F23,Diccionario!$C:$C,0)),"")
A24: 2024-07 | B24: Colombia | C24: Coco Colombia | D24: COP | E24: Real | F24: utilidad_neta | I24: 87000000 | J24: COP | K24: Derivado: ingresos - egresos | L24: =IFERROR(INDEX(Diccionario!$B:$B,MATCH(F24,Diccionario!$C:$C,0)),"") | M24: =IFERROR(INDEX(Diccionario!$H:$H,MATCH(F24,Diccionario!$C:$C,0)),"") | N24: =IFERROR(INDEX(Diccionario!$N:$N,MATCH(F24,Diccionario!$C:$C,0)),"")
A25: 2024-08 | B25: Colombia | C25: Coco Colombia | D25: COP | E25: Real | F25: ingresos_totales | I25: 675000000 | J25: COP | L25: =IFERROR(INDEX(Diccionario!$B:$B,MATCH(F25,Diccionario!$C:$C,0)),"") | M25: =IFERROR(INDEX(Diccionario!$H:$H,MATCH(F25,Diccionario!$C:$C,0)),"") | N25: =IFERROR(INDEX(Diccionario!$N:$N,MATCH(F25,Diccionario!$C:$C,0)),"")
A26: 2024-08 | B26: Colombia | C26: Coco Colombia | D26: COP | E26: Real | F26: egresos_totales | I26: 638000000 | J26: COP | L26: =IFERROR(INDEX(Diccionario!$B:$B,MATCH(F26,Diccionario!$C:$C,0)),"") | M26: =IFERROR(INDEX(Diccionario!$H:$H,MATCH(F26,Diccionario!$C:$C,0)),"") | N26: =IFERROR(INDEX(Diccionario!$N:$N,MATCH(F26,Diccionario!$C:$C,0)),"")
A27: 2024-08 | B27: Colombia | C27: Coco Colombia | D27: COP | E27: Real | F27: utilidad_neta | I27: 37000000 | J27: COP | K27: Derivado: ingresos - egresos | L27: =IFERROR(INDEX(Diccionario!$B:$B,MATCH(F27,Diccionario!$C:$C,0)),"") | M27: =IFERROR(INDEX(Diccionario!$H:$H,MATCH(F27,Diccionario!$C:$C,0)),"") | N27: =IFERROR(INDEX(Diccionario!$N:$N,MATCH(F27,Diccionario!$C:$C,0)),"")
A28: 2024-09 | B28: Colombia | C28: Coco Colombia | D28: COP | E28: Real | F28: ingresos_totales | I28: 663000000 | J28: COP | L28: =IFERROR(INDEX(Diccionario!$B:$B,MATCH(F28,Diccionario!$C:$C,0)),"") | M28: =IFERROR(INDEX(Diccionario!$H:$H,MATCH(F28,Diccionario!$C:$C,0)),"") | N28: =IFERROR(INDEX(Diccionario!$N:$N,MATCH(F28,Diccionario!$C:$C,0)),"")
A29: 2024-09 | B29: Colombia | C29: Coco Colombia | D29: COP | E29: Real | F29: egresos_totales | I29: 679000000 | J29: COP | L29: =IFERROR(INDEX(Diccionario!$B:$B,MATCH(F29,Diccionario!$C:$C,0)),"") | M29: =IFERROR(INDEX(Diccionario!$H:$H,MATCH(F29,Diccionario!$C:$C,0)),"") | N29: =IFERROR(INDEX(Diccionario!$N:$N,MATCH(F29,Diccionario!$C:$C,0)),"")
A30: 2024-09 | B30: Colombia | C30: Coco Colombia | D30: COP | E30: Real | F30: utilidad_neta | I30: -16000000 | J30: COP | K30: Derivado: ingresos - egresos | L30: =IFERROR(INDEX(Diccionario!$B:$B,MATCH(F30,Diccionario!$C:$C,0)),"") | M30: =IFERROR(INDEX(Diccionario!$H:$H,MATCH(F30,Diccionario!$C:$C,0)),"") | N30: =IFERROR(INDEX(Diccionario!$N:$N,MATCH(F30,Diccionario!$C:$C,0)),"")
A31: 2024-10 | B31: Colombia | C31: Coco Colombia | D31: COP | E31: Real | F31: ingresos_totales | I31: 672000000 | J31: COP | L31: =IFERROR(INDEX(Diccionario!$B:$B,MATCH(F31,Diccionario!$C:$C,0)),"") | M31: =IFERROR(INDEX(Diccionario!$H:$H,MATCH(F31,Diccionario!$C:$C,0)),"") | N31: =IFERROR(INDEX(Diccionario!$N:$N,MATCH(F31,Diccionario!$C:$C,0)),"")
A32: 2024-10 | B32: Colombia | C32: Coco Colombia | D32: COP | E32: Real | F32: egresos_totales | I32: 716000000 | J32: COP | L32: =IFERROR(INDEX(Diccionario!$B:$B,MATCH(F32,Diccionario!$C:$C,0)),"") | M32: =IFERROR(INDEX(Diccionario!$H:$H,MATCH(F32,Diccionario!$C:$C,0)),"") | N32: =IFERROR(INDEX(Diccionario!$N:$N,MATCH(F32,Diccionario!$C:$C,0)),"")
A33: 2024-10 | B33: Colombia | C33: Coco Colombia | D33: COP | E33: Real | F33: utilidad_neta | I33: -44000000 | J33: COP | K33: Derivado: ingresos - egresos | L33: =IFERROR(INDEX(Diccionario!$B:$B,MATCH(F33,Diccionario!$C:$C,0)),"") | M33: =IFERROR(INDEX(Diccionario!$H:$H,MATCH(F33,Diccionario!$C:$C,0)),"") | N33: =IFERROR(INDEX(Diccionario!$N:$N,MATCH(F33,Diccionario!$C:$C,0)),"")
A34: 2024-11 | B34: Colombia | C34: Coco Colombia | D34: COP | E34: Real | F34: ingresos_totales | I34: 761000000 | J34: COP | L34: =IFERROR(INDEX(Diccionario!$B:$B,MATCH(F34,Diccionario!$C:$C,0)),"") | M34: =IFERROR(INDEX(Diccionario!$H:$H,MATCH(F34,Diccionario!$C:$C,0)),"") | N34: =IFERROR(INDEX(Diccionario!$N:$N,MATCH(F34,Diccionario!$C:$C,0)),"")
A35: 2024-11 | B35: Colombia | C35: Coco Colombia | D35: COP | E35: Real | F35: egresos_totales | I35: 740000000 | J35: COP | L35: =IFERROR(INDEX(Diccionario!$B:$B,MATCH(F35,Diccionario!$C:$C,0)),"") | M35: =IFERROR(INDEX(Diccionario!$H:$H,MATCH(F35,Diccionario!$C:$C,0)),"") | N35: =IFERROR(INDEX(Diccionario!$N:$N,MATCH(F35,Diccionario!$C:$C,0)),"")
A36: 2024-11 | B36: Colombia | C36: Coco Colombia | D36: COP | E36: Real | F36: utilidad_neta | I36: 21000000 | J36: COP | K36: Derivado: ingresos - egresos | L36: =IFERROR(INDEX(Diccionario!$B:$B,MATCH(F36,Diccionario!$C:$C,0)),"") | M36: =IFERROR(INDEX(Diccionario!$H:$H,MATCH(F36,Diccionario!$C:$C,0)),"") | N36: =IFERROR(INDEX(Diccionario!$N:$N,MATCH(F36,Diccionario!$C:$C,0)),"")
A37: 2024-12 | B37: Colombia | C37: Coco Colombia | D37: COP | E37: Real | F37: ingresos_totales | I37: 1279000000 | J37: COP | L37: =IFERROR(INDEX(Diccionario!$B:$B,MATCH(F37,Diccionario!$C:$C,0)),"") | M37: =IFERROR(INDEX(Diccionario!$H:$H,MATCH(F37,Diccionario!$C:$C,0)),"") | N37: =IFERROR(INDEX(Diccionario!$N:$N,MATCH(F37,Diccionario!$C:$C,0)),"")
A38: 2024-12 | B38: Colombia | C38: Coco Colombia | D38: COP | E38: Real | F38: egresos_totales | I38: 810000000 | J38: COP | L38: =IFERROR(INDEX(Diccionario!$B:$B,MATCH(F38,Diccionario!$C:$C,0)),"") | M38: =IFERROR(INDEX(Diccionario!$H:$H,MATCH(F38,Diccionario!$C:$C,0)),"") | N38: =IFERROR(INDEX(Diccionario!$N:$N,MATCH(F38,Diccionario!$C:$C,0)),"")
A39: 2024-12 | B39: Colombia | C39: Coco Colombia | D39: COP | E39: Real | F39: utilidad_neta | I39: 469000000 | J39: COP | K39: Derivado: ingresos - egresos | L39: =IFERROR(INDEX(Diccionario!$B:$B,MATCH(F39,Diccionario!$C:$C,0)),"") | M39: =IFERROR(INDEX(Diccionario!$H:$H,MATCH(F39,Diccionario!$C:$C,0)),"") | N39: =IFERROR(INDEX(Diccionario!$N:$N,MATCH(F39,Diccionario!$C:$C,0)),"")
A40: 2025-01 | B40: Colombia | C40: Coco Colombia | D40: COP | E40: Real | F40: ingresos_totales | I40: 504000000 | J40: COP | L40: =IFERROR(INDEX(Diccionario!$B:$B,MATCH(F40,Diccionario!$C:$C,0)),"") | M40: =IFERROR(INDEX(Diccionario!$H:$H,MATCH(F40,Diccionario!$C:$C,0)),"") | N40: =IFERROR(INDEX(Diccionario!$N:$N,MATCH(F40,Diccionario!$C:$C,0)),"")
A41: 2025-01 | B41: Colombia | C41: Coco Colombia | D41: COP | E41: Real | F41: egresos_totales | I41: 694000000 | J41: COP | L41: =IFERROR(INDEX(Diccionario!$B:$B,MATCH(F41,Diccionario!$C:$C,0)),"") | M41: =IFERROR(INDEX(Diccionario!$H:$H,MATCH(F41,Diccionario!$C:$C,0)),"") | N41: =IFERROR(INDEX(Diccionario!$N:$N,MATCH(F41,Diccionario!$C:$C,0)),"")
A42: 2025-01 | B42: Colombia | C42: Coco Colombia | D42: COP | E42: Real | F42: utilidad_neta | I42: -190000000 | J42: COP | K42: Derivado: ingresos - egresos | L42: =IFERROR(INDEX(Diccionario!$B:$B,MATCH(F42,Diccionario!$C:$C,0)),"") | M42: =IFERROR(INDEX(Diccionario!$H:$H,MATCH(F42,Diccionario!$C:$C,0)),"") | N42: =IFERROR(INDEX(Diccionario!$N:$N,MATCH(F42,Diccionario!$C:$C,0)),"")
A43: 2025-02 | B43: Colombia | C43: Coco Colombia | D43: COP | E43: Real | F43: ingresos_totales | I43: 564000000 | J43: COP | L43: =IFERROR(INDEX(Diccionario!$B:$B,MATCH(F43,Diccionario!$C:$C,0)),"") | M43: =IFERROR(INDEX(Diccionario!$H:$H,MATCH(F43,Diccionario!$C:$C,0)),"") | N43: =IFERROR(INDEX(Diccionario!$N:$N,MATCH(F43,Diccionario!$C:$C,0)),"")
A44: 2025-02 | B44: Colombia | C44: Coco Colombia | D44: COP | E44: Real | F44: egresos_totales | I44: 688000000 | J44: COP | L44: =IFERROR(INDEX(Diccionario!$B:$B,MATCH(F44,Diccionario!$C:$C,0)),"") | M44: =IFERROR(INDEX(Diccionario!$H:$H,MATCH(F44,Diccionario!$C:$C,0)),"") | N44: =IFERROR(INDEX(Diccionario!$N:$N,MATCH(F44,Diccionario!$C:$C,0)),"")
A45: 2025-02 | B45: Colombia | C45: Coco Colombia | D45: COP | E45: Real | F45: utilidad_neta | I45: -124000000 | J45: COP | K45: Derivado: ingresos - egresos | L45: =IFERROR(INDEX(Diccionario!$B:$B,MATCH(F45,Diccionario!$C:$C,0)),"") | M45: =IFERROR(INDEX(Diccionario!$H:$H,MATCH(F45,Diccionario!$C:$C,0)),"") | N45: =IFERROR(INDEX(Diccionario!$N:$N,MATCH(F45,Diccionario!$C:$C,0)),"")
A46: 2025-03 | B46: Colombia | C46: Coco Colombia | D46: COP | E46: Real | F46: ingresos_totales | I46: 695000000 | J46: COP | L46: =IFERROR(INDEX(Diccionario!$B:$B,MATCH(F46,Diccionario!$C:$C,0)),"") | M46: =IFERROR(INDEX(Diccionario!$H:$H,MATCH(F46,Diccionario!$C:$C,0)),"") | N46: =IFERROR(INDEX(Diccionario!$N:$N,MATCH(F46,Diccionario!$C:$C,0)),"")
A47: 2025-03 | B47: Colombia | C47: Coco Colombia | D47: COP | E47: Real | F47: egresos_totales | I47: 809000000 | J47: COP | L47: =IFERROR(INDEX(Diccionario!$B:$B,MATCH(F47,Diccionario!$C:$C,0)),"") | M47: =IFERROR(INDEX(Diccionario!$H:$H,MATCH(F47,Diccionario!$C:$C,0)),"") | N47: =IFERROR(INDEX(Diccionario!$N:$N,MATCH(F47,Diccionario!$C:$C,0)),"")
A48: 2025-03 | B48: Colombia | C48: Coco Colombia | D48: COP | E48: Real | F48: utilidad_neta | I48: -114000000 | J48: COP | K48: Derivado: ingresos - egresos | L48: =IFERROR(INDEX(Diccionario!$B:$B,MATCH(F48,Diccionario!$C:$C,0)),"") | M48: =IFERROR(INDEX(Diccionario!$H:$H,MATCH(F48,Diccionario!$C:$C,0)),"") | N48: =IFERROR(INDEX(Diccionario!$N:$N,MATCH(F48,Diccionario!$C:$C,0)),"")
A49: 2025-04 | B49: Colombia | C49: Coco Colombia | D49: COP | E49: Real | F49: ingresos_totales | I49: 578000000 | J49: COP | L49: =IFERROR(INDEX(Diccionario!$B:$B,MATCH(F49,Diccionario!$C:$C,0)),"") | M49: =IFERROR(INDEX(Diccionario!$H:$H,MATCH(F49,Diccionario!$C:$C,0)),"") | N49: =IFERROR(INDEX(Diccionario!$N:$N,MATCH(F49,Diccionario!$C:$C,0)),"")
A50: 2025-04 | B50: Colombia | C50: Coco Colombia | D50: COP | E50: Real | F50: egresos_totales | I50: 766600000 | J50: COP | L50: =IFERROR(INDEX(Diccionario!$B:$B,MATCH(F50,Diccionario!$C:$C,0)),"") | M50: =IFERROR(INDEX(Diccionario!$H:$H,MATCH(F50,Diccionario!$C:$C,0)),"") | N50: =IFERROR(INDEX(Diccionario!$N:$N,MATCH(F50,Diccionario!$C:$C,0)),"")
A51: 2025-04 | B51: Colombia | C51: Coco Colombia | D51: COP | E51: Real | F51: utilidad_neta | I51: -188600000 | J51: COP | K51: Derivado: ingresos - egresos | L51: =IFERROR(INDEX(Diccionario!$B:$B,MATCH(F51,Diccionario!$C:$C,0)),"") | M51: =IFERROR(INDEX(Diccionario!$H:$H,MATCH(F51,Diccionario!$C:$C,0)),"") | N51: =IFERROR(INDEX(Diccionario!$N:$N,MATCH(F51,Diccionario!$C:$C,0)),"")
A52: 2025-05 | B52: Colombia | C52: Coco Colombia | D52: COP | E52: Real | F52: ingresos_totales | I52: 716000000 | J52: COP | L52: =IFERROR(INDEX(Diccionario!$B:$B,MATCH(F52,Diccionario!$C:$C,0)),"") | M52: =IFERROR(INDEX(Diccionario!$H:$H,MATCH(F52,Diccionario!$C:$C,0)),"") | N52: =IFERROR(INDEX(Diccionario!$N:$N,MATCH(F52,Diccionario!$C:$C,0)),"")
A53: 2025-05 | B53: Colombia | C53: Coco Colombia | D53: COP | E53: Real | F53: egresos_totales | I53: 729000000 | J53: COP | L53: =IFERROR(INDEX(Diccionario!$B:$B,MATCH(F53,Diccionario!$C:$C,0)),"") | M53: =IFERROR(INDEX(Diccionario!$H:$H,MATCH(F53,Diccionario!$C:$C,0)),"") | N53: =IFERROR(INDEX(Diccionario!$N:$N,MATCH(F53,Diccionario!$C:$C,0)),"")
A54: 2025-05 | B54: Colombia | C54: Coco Colombia | D54: COP | E54: Real | F54: utilidad_neta | I54: -13000000 | J54: COP | K54: Derivado: ingresos - egresos | L54: =IFERROR(INDEX(Diccionario!$B:$B,MATCH(F54,Diccionario!$C:$C,0)),"") | M54: =IFERROR(INDEX(Diccionario!$H:$H,MATCH(F54,Diccionario!$C:$C,0)),"") | N54: =IFERROR(INDEX(Diccionario!$N:$N,MATCH(F54,Diccionario!$C:$C,0)),"")
A55: 2025-06 | B55: Colombia | C55: Coco Colombia | D55: COP | E55: Real | F55: ingresos_totales | I55: 610000000 | J55: COP | L55: =IFERROR(INDEX(Diccionario!$B:$B,MATCH(F55,Diccionario!$C:$C,0)),"") | M55: =IFERROR(INDEX(Diccionario!$H:$H,MATCH(F55,Diccionario!$C:$C,0)),"") | N55: =IFERROR(INDEX(Diccionario!$N:$N,MATCH(F55,Diccionario!$C:$C,0)),"")
A56: 2025-06 | B56: Colombia | C56: Coco Colombia | D56: COP | E56: Real | F56: egresos_totales | I56: 636000000 | J56: COP | L56: =IFERROR(INDEX(Diccionario!$B:$B,MATCH(F56,Diccionario!$C:$C,0)),"") | M56: =IFERROR(INDEX(Diccionario!$H:$H,MATCH(F56,Diccionario!$C:$C,0)),"") | N56: =IFERROR(INDEX(Diccionario!$N:$N,MATCH(F56,Diccionario!$C:$C,0)),"")
A57: 2025-06 | B57: Colombia | C57: Coco Colombia | D57: COP | E57: Real | F57: utilidad_neta | I57: -26000000 | J57: COP | K57: Derivado: ingresos - egresos | L57: =IFERROR(INDEX(Diccionario!$B:$B,MATCH(F57,Diccionario!$C:$C,0)),"") | M57: =IFERROR(INDEX(Diccionario!$H:$H,MATCH(F57,Diccionario!$C:$C,0)),"") | N57: =IFERROR(INDEX(Diccionario!$N:$N,MATCH(F57,Diccionario!$C:$C,0)),"")
A58: 2025-07 | B58: Colombia | C58: Coco Colombia | D58: COP | E58: Real | F58: ingresos_totales | I58: 648000000 | J58: COP | L58: =IFERROR(INDEX(Diccionario!$B:$B,MATCH(F58,Diccionario!$C:$C,0)),"") | M58: =IFERROR(INDEX(Diccionario!$H:$H,MATCH(F58,Diccionario!$C:$C,0)),"") | N58: =IFERROR(INDEX(Diccionario!$N:$N,MATCH(F58,Diccionario!$C:$C,0)),"")
A59: 2025-07 | B59: Colombia | C59: Coco Colombia | D59: COP | E59: Real | F59: egresos_totales | I59: 884000000 | J59: COP | L59: =IFERROR(INDEX(Diccionario!$B:$B,MATCH(F59,Diccionario!$C:$C,0)),"") | M59: =IFERROR(INDEX(Diccionario!$H:$H,MATCH(F59,Diccionario!$C:$C,0)),"") | N59: =IFERROR(INDEX(Diccionario!$N:$N,MATCH(F59,Diccionario!$C:$C,0)),"")
A60: 2025-07 | B60: Colombia | C60: Coco Colombia | D60: COP | E60: Real | F60: utilidad_neta | I60: -236000000 | J60: COP | K60: Derivado: ingresos - egresos | L60: =IFERROR(INDEX(Diccionario!$B:$B,MATCH(F60,Diccionario!$C:$C,0)),"") | M60: =IFERROR(INDEX(Diccionario!$H:$H,MATCH(F60,Diccionario!$C:$C,0)),"") | N60: =IFERROR(INDEX(Diccionario!$N:$N,MATCH(F60,Diccionario!$C:$C,0)),"")
A61: 2025-08 | B61: Colombia | C61: Coco Colombia | D61: COP | E61: Real | F61: ingresos_totales | I61: 634000000 | J61: COP | L61: =IFERROR(INDEX(Diccionario!$B:$B,MATCH(F61,Diccionario!$C:$C,0)),"") | M61: =IFERROR(INDEX(Diccionario!$H:$H,MATCH(F61,Diccionario!$C:$C,0)),"") | N61: =IFERROR(INDEX(Diccionario!$N:$N,MATCH(F61,Diccionario!$C:$C,0)),"")
A62: 2025-08 | B62: Colombia | C62: Coco Colombia | D62: COP | E62: Real | F62: egresos_totales | I62: 673000000 | J62: COP | L62: =IFERROR(INDEX(Diccionario!$B:$B,MATCH(F62,Diccionario!$C:$C,0)),"") | M62: =IFERROR(INDEX(Diccionario!$H:$H,MATCH(F62,Diccionario!$C:$C,0)),"") | N62: =IFERROR(INDEX(Diccionario!$N:$N,MATCH(F62,Diccionario!$C:$C,0)),"")
A63: 2025-08 | B63: Colombia | C63: Coco Colombia | D63: COP | E63: Real | F63: utilidad_neta | I63: -39000000 | J63: COP | K63: Derivado: ingresos - egresos | L63: =IFERROR(INDEX(Diccionario!$B:$B,MATCH(F63,Diccionario!$C:$C,0)),"") | M63: =IFERROR(INDEX(Diccionario!$H:$H,MATCH(F63,Diccionario!$C:$C,0)),"") | N63: =IFERROR(INDEX(Diccionario!$N:$N,MATCH(F63,Diccionario!$C:$C,0)),"")
A64: 2025-09 | B64: Colombia | C64: Coco Colombia | D64: COP | E64: Real | F64: ingresos_totales | I64: 758000000 | J64: COP | L64: =IFERROR(INDEX(Diccionario!$B:$B,MATCH(F64,Diccionario!$C:$C,0)),"") | M64: =IFERROR(INDEX(Diccionario!$H:$H,MATCH(F64,Diccionario!$C:$C,0)),"") | N64: =IFERROR(INDEX(Diccionario!$N:$N,MATCH(F64,Diccionario!$C:$C,0)),"")
A65: 2025-09 | B65: Colombia | C65: Coco Colombia | D65: COP | E65: Real | F65: egresos_totales | I65: 708000000 | J65: COP | L65: =IFERROR(INDEX(Diccionario!$B:$B,MATCH(F65,Diccionario!$C:$C,0)),"") | M65: =IFERROR(INDEX(Diccionario!$H:$H,MATCH(F65,Diccionario!$C:$C,0)),"") | N65: =IFERROR(INDEX(Diccionario!$N:$N,MATCH(F65,Diccionario!$C:$C,0)),"")
A66: 2025-09 | B66: Colombia | C66: Coco Colombia | D66: COP | E66: Real | F66: utilidad_neta | I66: 50000000 | J66: COP | K66: Derivado: ingresos - egresos | L66: =IFERROR(INDEX(Diccionario!$B:$B,MATCH(F66,Diccionario!$C:$C,0)),"") | M66: =IFERROR(INDEX(Diccionario!$H:$H,MATCH(F66,Diccionario!$C:$C,0)),"") | N66: =IFERROR(INDEX(Diccionario!$N:$N,MATCH(F66,Diccionario!$C:$C,0)),"")
A67: 2025-10 | B67: Colombia | C67: Coco Colombia | D67: COP | E67: Real | F67: ingresos_totales | I67: 691000000 | J67: COP | L67: =IFERROR(INDEX(Diccionario!$B:$B,MATCH(F67,Diccionario!$C:$C,0)),"") | M67: =IFERROR(INDEX(Diccionario!$H:$H,MATCH(F67,Diccionario!$C:$C,0)),"") | N67: =IFERROR(INDEX(Diccionario!$N:$N,MATCH(F67,Diccionario!$C:$C,0)),"")
A68: 2025-10 | B68: Colombia | C68: Coco Colombia | D68: COP | E68: Real | F68: egresos_totales | I68: 778000000 | J68: COP | L68: =IFERROR(INDEX(Diccionario!$B:$B,MATCH(F68,Diccionario!$C:$C,0)),"") | M68: =IFERROR(INDEX(Diccionario!$H:$H,MATCH(F68,Diccionario!$C:$C,0)),"") | N68: =IFERROR(INDEX(Diccionario!$N:$N,MATCH(F68,Diccionario!$C:$C,0)),"")
A69: 2025-10 | B69: Colombia | C69: Coco Colombia | D69: COP | E69: Real | F69: utilidad_neta | I69: -87000000 | J69: COP | K69: Derivado: ingresos - egresos | L69: =IFERROR(INDEX(Diccionario!$B:$B,MATCH(F69,Diccionario!$C:$C,0)),"") | M69: =IFERROR(INDEX(Diccionario!$H:$H,MATCH(F69,Diccionario!$C:$C,0)),"") | N69: =IFERROR(INDEX(Diccionario!$N:$N,MATCH(F69,Diccionario!$C:$C,0)),"")
A70: 2025-11 | B70: Colombia | C70: Coco Colombia | D70: COP | E70: Real | F70: ingresos_totales | I70: 700000000 | J70: COP | L70: =IFERROR(INDEX(Diccionario!$B:$B,MATCH(F70,Diccionario!$C:$C,0)),"") | M70: =IFERROR(INDEX(Diccionario!$H:$H,MATCH(F70,Diccionario!$C:$C,0)),"") | N70: =IFERROR(INDEX(Diccionario!$N:$N,MATCH(F70,Diccionario!$C:$C,0)),"")
A71: 2025-11 | B71: Colombia | C71: Coco Colombia | D71: COP | E71: Real | F71: egresos_totales | I71: 739000000 | J71: COP | L71: =IFERROR(INDEX(Diccionario!$B:$B,MATCH(F71,Diccionario!$C:$C,0)),"") | M71: =IFERROR(INDEX(Diccionario!$H:$H,MATCH(F71,Diccionario!$C:$C,0)),"") | N71: =IFERROR(INDEX(Diccionario!$N:$N,MATCH(F71,Diccionario!$C:$C,0)),"")
A72: 2025-11 | B72: Colombia | C72: Coco Colombia | D72: COP | E72: Real | F72: utilidad_neta | I72: -39000000 | J72: COP | K72: Derivado: ingresos - egresos | L72: =IFERROR(INDEX(Diccionario!$B:$B,MATCH(F72,Diccionario!$C:$C,0)),"") | M72: =IFERROR(INDEX(Diccionario!$H:$H,MATCH(F72,Diccionario!$C:$C,0)),"") | N72: =IFERROR(INDEX(Diccionario!$N:$N,MATCH(F72,Diccionario!$C:$C,0)),"")
A73: 2025-12 | B73: Colombia | C73: Coco Colombia | D73: COP | E73: Real | F73: ingresos_totales | I73: 765000000 | J73: COP | L73: =IFERROR(INDEX(Diccionario!$B:$B,MATCH(F73,Diccionario!$C:$C,0)),"") | M73: =IFERROR(INDEX(Diccionario!$H:$H,MATCH(F73,Diccionario!$C:$C,0)),"") | N73: =IFERROR(INDEX(Diccionario!$N:$N,MATCH(F73,Diccionario!$C:$C,0)),"")
A74: 2025-12 | B74: Colombia | C74: Coco Colombia | D74: COP | E74: Real | F74: egresos_totales | I74: 718000000 | J74: COP | L74: =IFERROR(INDEX(Diccionario!$B:$B,MATCH(F74,Diccionario!$C:$C,0)),"") | M74: =IFERROR(INDEX(Diccionario!$H:$H,MATCH(F74,Diccionario!$C:$C,0)),"") | N74: =IFERROR(INDEX(Diccionario!$N:$N,MATCH(F74,Diccionario!$C:$C,0)),"")
A75: 2025-12 | B75: Colombia | C75: Coco Colombia | D75: COP | E75: Real | F75: utilidad_neta | I75: 47000000 | J75: COP | K75: Derivado: ingresos - egresos | L75: =IFERROR(INDEX(Diccionario!$B:$B,MATCH(F75,Diccionario!$C:$C,0)),"") | M75: =IFERROR(INDEX(Diccionario!$H:$H,MATCH(F75,Diccionario!$C:$C,0)),"") | N75: =IFERROR(INDEX(Diccionario!$N:$N,MATCH(F75,Diccionario!$C:$C,0)),"")
A76: 2026-01 | B76: Colombia | C76: Coco Colombia | D76: COP | E76: Real | F76: ingresos_totales | I76: 612247701 | J76: COP | K76: Ajustado al cierre oficial (PDF Estados Financieros Junio 2026); serie mensual del Modelo, suma = 4.472.342.747 | L76: =IFERROR(INDEX(Diccionario!$B:$B,MATCH(F76,Diccionario!$C:$C,0)),"") | M76: =IFERROR(INDEX(Diccionario!$H:$H,MATCH(F76,Diccionario!$C:$C,0)),"") | N76: =IFERROR(INDEX(Diccionario!$N:$N,MATCH(F76,Diccionario!$C:$C,0)),"")
A77: 2026-01 | B77: Colombia | C77: Coco Colombia | D77: COP | E77: Real | F77: egresos_totales | I77: 542000000 | J77: COP | L77: =IFERROR(INDEX(Diccionario!$B:$B,MATCH(F77,Diccionario!$C:$C,0)),"") | M77: =IFERROR(INDEX(Diccionario!$H:$H,MATCH(F77,Diccionario!$C:$C,0)),"") | N77: =IFERROR(INDEX(Diccionario!$N:$N,MATCH(F77,Diccionario!$C:$C,0)),"")
A78: 2026-01 | B78: Colombia | C78: Coco Colombia | D78: COP | E78: Real | F78: utilidad_neta | I78: 91000000 | J78: COP | K78: Derivado: ingresos - egresos | L78: =IFERROR(INDEX(Diccionario!$B:$B,MATCH(F78,Diccionario!$C:$C,0)),"") | M78: =IFERROR(INDEX(Diccionario!$H:$H,MATCH(F78,Diccionario!$C:$C,0)),"") | N78: =IFERROR(INDEX(Diccionario!$N:$N,MATCH(F78,Diccionario!$C:$C,0)),"")
A79: 2026-02 | B79: Colombia | C79: Coco Colombia | D79: COP | E79: Real | F79: ingresos_totales | I79: 744218137 | J79: COP | K79: Ajustado al cierre oficial (PDF Estados Financieros Junio 2026); serie mensual del Modelo, suma = 4.472.342.747 | L79: =IFERROR(INDEX(Diccionario!$B:$B,MATCH(F79,Diccionario!$C:$C,0)),"") | M79: =IFERROR(INDEX(Diccionario!$H:$H,MATCH(F79,Diccionario!$C:$C,0)),"") | N79: =IFERROR(INDEX(Diccionario!$N:$N,MATCH(F79,Diccionario!$C:$C,0)),"")
A80: 2026-02 | B80: Colombia | C80: Coco Colombia | D80: COP | E80: Real | F80: egresos_totales | I80: 684000000 | J80: COP | L80: =IFERROR(INDEX(Diccionario!$B:$B,MATCH(F80,Diccionario!$C:$C,0)),"") | M80: =IFERROR(INDEX(Diccionario!$H:$H,MATCH(F80,Diccionario!$C:$C,0)),"") | N80: =IFERROR(INDEX(Diccionario!$N:$N,MATCH(F80,Diccionario!$C:$C,0)),"")
A81: 2026-02 | B81: Colombia | C81: Coco Colombia | D81: COP | E81: Real | F81: utilidad_neta | I81: 60000000 | J81: COP | K81: Derivado: ingresos - egresos | L81: =IFERROR(INDEX(Diccionario!$B:$B,MATCH(F81,Diccionario!$C:$C,0)),"") | M81: =IFERROR(INDEX(Diccionario!$H:$H,MATCH(F81,Diccionario!$C:$C,0)),"") | N81: =IFERROR(INDEX(Diccionario!$N:$N,MATCH(F81,Diccionario!$C:$C,0)),"")
A82: 2026-03 | B82: Colombia | C82: Coco Colombia | D82: COP | E82: Real | F82: ingresos_totales | I82: 787041187 | J82: COP | K82: Ajustado al cierre oficial (PDF Estados Financieros Junio 2026); serie mensual del Modelo, suma = 4.472.342.747 | L82: =IFERROR(INDEX(Diccionario!$B:$B,MATCH(F82,Diccionario!$C:$C,0)),"") | M82: =IFERROR(INDEX(Diccionario!$H:$H,MATCH(F82,Diccionario!$C:$C,0)),"") | N82: =IFERROR(INDEX(Diccionario!$N:$N,MATCH(F82,Diccionario!$C:$C,0)),"")
A83: 2026-03 | B83: Colombia | C83: Coco Colombia | D83: COP | E83: Real | F83: egresos_totales | I83: 806000000 | J83: COP | L83: =IFERROR(INDEX(Diccionario!$B:$B,MATCH(F83,Diccionario!$C:$C,0)),"") | M83: =IFERROR(INDEX(Diccionario!$H:$H,MATCH(F83,Diccionario!$C:$C,0)),"") | N83: =IFERROR(INDEX(Diccionario!$N:$N,MATCH(F83,Diccionario!$C:$C,0)),"")
A84: 2026-03 | B84: Colombia | C84: Coco Colombia | D84: COP | E84: Real | F84: utilidad_neta | I84: -37000000 | J84: COP | K84: Derivado: ingresos - egresos | L84: =IFERROR(INDEX(Diccionario!$B:$B,MATCH(F84,Diccionario!$C:$C,0)),"") | M84: =IFERROR(INDEX(Diccionario!$H:$H,MATCH(F84,Diccionario!$C:$C,0)),"") | N84: =IFERROR(INDEX(Diccionario!$N:$N,MATCH(F84,Diccionario!$C:$C,0)),"")
A85: 2026-04 | B85: Colombia | C85: Coco Colombia | D85: COP | E85: Real | F85: ingresos_totales | I85: 750867662 | J85: COP | K85: Ajustado al cierre oficial (PDF Estados Financieros Junio 2026); serie mensual del Modelo, suma = 4.472.342.747 | L85: =IFERROR(INDEX(Diccionario!$B:$B,MATCH(F85,Diccionario!$C:$C,0)),"") | M85: =IFERROR(INDEX(Diccionario!$H:$H,MATCH(F85,Diccionario!$C:$C,0)),"") | N85: =IFERROR(INDEX(Diccionario!$N:$N,MATCH(F85,Diccionario!$C:$C,0)),"")
A86: 2026-04 | B86: Colombia | C86: Coco Colombia | D86: COP | E86: Real | F86: egresos_totales | I86: 755000000 | J86: COP | L86: =IFERROR(INDEX(Diccionario!$B:$B,MATCH(F86,Diccionario!$C:$C,0)),"") | M86: =IFERROR(INDEX(Diccionario!$H:$H,MATCH(F86,Diccionario!$C:$C,0)),"") | N86: =IFERROR(INDEX(Diccionario!$N:$N,MATCH(F86,Diccionario!$C:$C,0)),"")
A87: 2026-04 | B87: Colombia | C87: Coco Colombia | D87: COP | E87: Real | F87: utilidad_neta | I87: -1000000 | J87: COP | K87: Derivado: ingresos - egresos | L87: =IFERROR(INDEX(Diccionario!$B:$B,MATCH(F87,Diccionario!$C:$C,0)),"") | M87: =IFERROR(INDEX(Diccionario!$H:$H,MATCH(F87,Diccionario!$C:$C,0)),"") | N87: =IFERROR(INDEX(Diccionario!$N:$N,MATCH(F87,Diccionario!$C:$C,0)),"")
A88: 2026-05 | B88: Colombia | C88: Coco Colombia | D88: COP | E88: Real | F88: ingresos_totales | I88: 826514746 | J88: COP | K88: Ajustado al cierre oficial (PDF Estados Financieros Junio 2026); serie mensual del Modelo, suma = 4.472.342.747 | L88: =IFERROR(INDEX(Diccionario!$B:$B,MATCH(F88,Diccionario!$C:$C,0)),"") | M88: =IFERROR(INDEX(Diccionario!$H:$H,MATCH(F88,Diccionario!$C:$C,0)),"") | N88: =IFERROR(INDEX(Diccionario!$N:$N,MATCH(F88,Diccionario!$C:$C,0)),"")
A89: 2026-05 | B89: Colombia | C89: Coco Colombia | D89: COP | E89: Real | F89: egresos_totales | I89: 720000000 | J89: COP | L89: =IFERROR(INDEX(Diccionario!$B:$B,MATCH(F89,Diccionario!$C:$C,0)),"") | M89: =IFERROR(INDEX(Diccionario!$H:$H,MATCH(F89,Diccionario!$C:$C,0)),"") | N89: =IFERROR(INDEX(Diccionario!$N:$N,MATCH(F89,Diccionario!$C:$C,0)),"")
A90: 2026-05 | B90: Colombia | C90: Coco Colombia | D90: COP | E90: Real | F90: utilidad_neta | I90: 92000000 | J90: COP | K90: Derivado: ingresos - egresos | L90: =IFERROR(INDEX(Diccionario!$B:$B,MATCH(F90,Diccionario!$C:$C,0)),"") | M90: =IFERROR(INDEX(Diccionario!$H:$H,MATCH(F90,Diccionario!$C:$C,0)),"") | N90: =IFERROR(INDEX(Diccionario!$N:$N,MATCH(F90,Diccionario!$C:$C,0)),"")
A91: 2025-06 | B91: Colombia | C91: Coco Colombia | D91: COP | E91: Real | F91: ebitda | I91: 154028000 | J91: COP | L91: =IFERROR(INDEX(Diccionario!$B:$B,MATCH(F91,Diccionario!$C:$C,0)),"") | M91: =IFERROR(INDEX(Diccionario!$H:$H,MATCH(F91,Diccionario!$C:$C,0)),"") | N91: =IFERROR(INDEX(Diccionario!$N:$N,MATCH(F91,Diccionario!$C:$C,0)),"")
A92: 2025-07 | B92: Colombia | C92: Coco Colombia | D92: COP | E92: Real | F92: ebitda | I92: 210623000 | J92: COP | L92: =IFERROR(INDEX(Diccionario!$B:$B,MATCH(F92,Diccionario!$C:$C,0)),"") | M92: =IFERROR(INDEX(Diccionario!$H:$H,MATCH(F92,Diccionario!$C:$C,0)),"") | N92: =IFERROR(INDEX(Diccionario!$N:$N,MATCH(F92,Diccionario!$C:$C,0)),"")
A93: 2025-08 | B93: Colombia | C93: Coco Colombia | D93: COP | E93: Real | F93: ebitda | I93: 219976000 | J93: COP | L93: =IFERROR(INDEX(Diccionario!$B:$B,MATCH(F93,Diccionario!$C:$C,0)),"") | M93: =IFERROR(INDEX(Diccionario!$H:$H,MATCH(F93,Diccionario!$C:$C,0)),"") | N93: =IFERROR(INDEX(Diccionario!$N:$N,MATCH(F93,Diccionario!$C:$C,0)),"")
A94: 2025-09 | B94: Colombia | C94: Coco Colombia | D94: COP | E94: Real | F94: ebitda | I94: 207986000 | J94: COP | L94: =IFERROR(INDEX(Diccionario!$B:$B,MATCH(F94,Diccionario!$C:$C,0)),"") | M94: =IFERROR(INDEX(Diccionario!$H:$H,MATCH(F94,Diccionario!$C:$C,0)),"") | N94: =IFERROR(INDEX(Diccionario!$N:$N,MATCH(F94,Diccionario!$C:$C,0)),"")
A95: 2025-10 | B95: Colombia | C95: Coco Colombia | D95: COP | E95: Real | F95: ebitda | I95: 230467000 | J95: COP | L95: =IFERROR(INDEX(Diccionario!$B:$B,MATCH(F95,Diccionario!$C:$C,0)),"") | M95: =IFERROR(INDEX(Diccionario!$H:$H,MATCH(F95,Diccionario!$C:$C,0)),"") | N95: =IFERROR(INDEX(Diccionario!$N:$N,MATCH(F95,Diccionario!$C:$C,0)),"")
A96: 2025-11 | B96: Colombia | C96: Coco Colombia | D96: COP | E96: Real | F96: ebitda | I96: 240545000 | J96: COP | L96: =IFERROR(INDEX(Diccionario!$B:$B,MATCH(F96,Diccionario!$C:$C,0)),"") | M96: =IFERROR(INDEX(Diccionario!$H:$H,MATCH(F96,Diccionario!$C:$C,0)),"") | N96: =IFERROR(INDEX(Diccionario!$N:$N,MATCH(F96,Diccionario!$C:$C,0)),"")
A97: 2025-12 | B97: Colombia | C97: Coco Colombia | D97: COP | E97: Real | F97: ebitda | I97: 231501000 | J97: COP | L97: =IFERROR(INDEX(Diccionario!$B:$B,MATCH(F97,Diccionario!$C:$C,0)),"") | M97: =IFERROR(INDEX(Diccionario!$H:$H,MATCH(F97,Diccionario!$C:$C,0)),"") | N97: =IFERROR(INDEX(Diccionario!$N:$N,MATCH(F97,Diccionario!$C:$C,0)),"")
A98: 2026-01 | B98: Colombia | C98: Coco Colombia | D98: COP | E98: Real | F98: ebitda | I98: 207987000 | J98: COP | L98: =IFERROR(INDEX(Diccionario!$B:$B,MATCH(F98,Diccionario!$C:$C,0)),"") | M98: =IFERROR(INDEX(Diccionario!$H:$H,MATCH(F98,Diccionario!$C:$C,0)),"") | N98: =IFERROR(INDEX(Diccionario!$N:$N,MATCH(F98,Diccionario!$C:$C,0)),"")
A99: 2026-02 | B99: Colombia | C99: Coco Colombia | D99: COP | E99: Real | F99: ebitda | I99: 191717000 | J99: COP | L99: =IFERROR(INDEX(Diccionario!$B:$B,MATCH(F99,Diccionario!$C:$C,0)),"") | M99: =IFERROR(INDEX(Diccionario!$H:$H,MATCH(F99,Diccionario!$C:$C,0)),"") | N99: =IFERROR(INDEX(Diccionario!$N:$N,MATCH(F99,Diccionario!$C:$C,0)),"")
A100: 2026-03 | B100: Colombia | C100: Coco Colombia | D100: COP | E100: Real | F100: ebitda | I100: 201750000 | J100: COP | L100: =IFERROR(INDEX(Diccionario!$B:$B,MATCH(F100,Diccionario!$C:$C,0)),"") | M100: =IFERROR(INDEX(Diccionario!$H:$H,MATCH(F100,Diccionario!$C:$C,0)),"") | N100: =IFERROR(INDEX(Diccionario!$N:$N,MATCH(F100,Diccionario!$C:$C,0)),"")
...

Sheet PyG_Mensual_Col
A1: P&G Ejecutivo Mensual — Coco Colombia 2026 (COP)
A2: Fuente: estados financieros oficiales. Julio 2026 derivado desde acumulado oficial a julio menos enero-junio.
A4: Concepto | B4: Ene | C4: Feb | D4: Mar | E4: Abr | F4: May | G4: Jun | H4: Jul
A5: Servicio de software | B5: 689690890 | C5: 744218137 | D5: 839105106 | E5: 819197300 | F5: 881948086 | G5: 929451219 | H5: 711900651
A6: (-) Devoluciones | B6: -77443189 | C6: 0 | D6: -52063919 | E6: -68329638 | F6: -55433340 | G6: -177997905 | H6: -32010099
A7: =Ingresos operacionales netos | B7: 612247701 | C7: 744218137 | D7: 787041187 | E7: 750867662 | F7: 826514746 | G7: 751453314 | H7: 679890552
A8: (-) Costo de ventas | B8: 238535794 | C8: 343308791 | D8: 455639201 | E8: 379273594 | F8: 355470523 | G8: 348477606 | H8: 321917837
A9: =Utilidad bruta | B9: 373711907 | C9: 400909346 | D9: 331401986 | E9: 371594068 | F9: 471044223 | G9: 402975708 | H9: 357972713
A10: (-) Gastos de administración | B10: 98722435 | C10: 105633472 | D10: 141811865 | E10: 114280887 | F10: 116808824 | G10: 112288693 | H10: 107932742
A11: (-) Gastos operación / proyectos | B11: 73409852 | C11: 75509638 | D11: 72217138 | E11: 122384514 | F11: 120992711 | G11: 108908060 | H11: 102936374
A12: (-) Gastos de ventas | B12: 131600259 | C12: 173632204 | D12: 139615776 | E12: 130090415 | F12: 120233213 | G12: 146803460 | H12: 117761236
A13: =Utilidad operativa | B13: 69979361 | C13: 46134032 | D13: -22242793 | E13: 4838252 | F13: 113009475 | G13: 34975495 | H13: 29342360
A14: (+) Ingresos no operacionales | B14: 597687 | C14: 13488976 | D14: -10197660 | E14: 906545 | F14: 1366339 | G14: 3920249 | H14: 718311
A15: (-) Gastos financieros | B15: 7091551 | C15: 5574093 | D15: 5497554 | E15: 5038594 | F15: 6000846 | G15: 5552094 | H15: 5353621
A16: =Utilidad neta | B16: 63485497 | C16: 54048915 | D16: -37938007 | E16: 706203 | F16: 108374968 | G16: 33343650 | H16: 24707051

Sheet Subsidiarias_PyG
A1: Estado de Resultados Subsidiarias y Consolidado ? 2026 (USD de presentaci?n; Perú convertido desde PEN)
A2: Julio 2026 actualizado con COCO Colombia, EE.UU., Per? y Costa Rica; cifras en USD de presentaci?n.
A4: periodo | B4: pais | C4: compania | D4: rubro | E4: codigo_indicador | F4: moneda | G4: valor
A5: 2026-04 | B5: EE.UU. | C5: Coco LLC | D5: Ingresos Ordinarios | E5: pyg_ingresos_operacionales | F5: USD | G5: 17616.15
A6: 2026-04 | B6: EE.UU. | C6: Coco LLC | D6: Otros Ingresos | E6: pyg_ingresos_no_operacionales | F6: USD | G6: 0
A7: 2026-04 | B7: EE.UU. | C7: Coco LLC | D7: Costo del servicio | E7: pyg_costo_ventas | F7: USD | G7: 0
A8: 2026-04 | B8: EE.UU. | C8: Coco LLC | D8: Administración | E8: pyg_gasto_administracion | F8: USD | G8: -46372.59
A9: 2026-04 | B9: EE.UU. | C9: Coco LLC | D9: Ventas | E9: pyg_gasto_ventas | F9: USD | G9: 0
A10: 2026-04 | B10: EE.UU. | C10: Coco LLC | D10: Operación | E10: pyg_gasto_proyectos | F10: USD | G10: 0
A11: 2026-04 | B11: EE.UU. | C11: Coco LLC | D11: Gastos financieros | E11: pyg_gastos_financieros | F11: USD | G11: 0
A12: 2026-04 | B12: EE.UU. | C12: Coco LLC | D12: Utilidad | E12: pyg_utilidad_neta | F12: USD | G12: -28756.44
A13: 2026-04 | B13: Perú | C13: Coco Perú | D13: Ingresos Ordinarios | E13: pyg_ingresos_operacionales | F13: USD | G13: 2988.97
A14: 2026-04 | B14: Perú | C14: Coco Perú | D14: Otros Ingresos | E14: pyg_ingresos_no_operacionales | F14: USD | G14: 0
A15: 2026-04 | B15: Perú | C15: Coco Perú | D15: Costo del servicio | E15: pyg_costo_ventas | F15: USD | G15: 0
A16: 2026-04 | B16: Perú | C16: Coco Perú | D16: Administración | E16: pyg_gasto_administracion | F16: USD | G16: 0
... A193: 2026-07 | B193: Costa Rica | C193: Coco Costa Rica | D193: Utilidad | E193: pyg_utilidad_neta | F193: USD | G193: 131027.06

Sheet PyG_Oficial
A1: P&G Oficial y Consolidación — vista de solo lectura
A2: Regenerada con EEFF julio 2026 el 2026-08-12 ? Colombia julio derivado del acumulado oficial.
A4: periodo | B4: pais | C4: compania | D4: moneda | E4: escenario | F4: codigo_indicador | G4: segmento | H4: detalle | I4: valor | J4: unidad | K4: comentario | L4: area_responsable | M4: periodicidad
A5: 2026-01 | B5: Colombia | C5: Coco Colombia | D5: COP | E5: Real | F5: pyg_costo_ventas | I5: 238535794 | J5: COP | K5: P&G ejecutivo oficial (estados financieros mensuales) | L5: Finanzas | M5: Mensual
A6: 2026-01 | B6: Colombia | C6: Coco Colombia | D6: COP | E6: Real | F6: pyg_devoluciones | I6: -77443189 | J6: COP | K6: P&G ejecutivo oficial (estados financieros mensuales) | L6: Finanzas | M6: Mensual
A7: 2026-01 | B7: Colombia | C7: Coco Colombia | D7: COP | E7: Real | F7: pyg_gasto_administracion | I7: 98722435 | J7: COP | K7: P&G ejecutivo oficial (estados financieros mensuales) | L7: Finanzas | M7: Mensual
A8: 2026-01 | B8: Colombia | C8: Coco Colombia | D8: COP | E8: Real | F8: pyg_gasto_proyectos | I8: 73409852 | J8: COP | K8: P&G ejecutivo oficial (estados financieros mensuales) | L8: Finanzas | M8: Mensual
A9: 2026-01 | B9: Colombia | C9: Coco Colombia | D9: COP | E9: Real | F9: pyg_gasto_ventas | I9: 131600259 | J9: COP | K9: P&G ejecutivo oficial (estados financieros mensuales) | L9: Finanzas | M9: Mensual
A10: 2026-01 | B10: Colombia | C10: Coco Colombia | D10: COP | E10: Real | F10: pyg_gastos_financieros | I10: 7091551 | J10: COP | K10: P&G ejecutivo oficial (estados financieros mensuales) | L10: Finanzas | M10: Mensual
A11: 2026-01 | B11: Colombia | C11: Coco Colombia | D11: COP | E11: Real | F11: pyg_ingresos_no_operacionales | I11: 597687 | J11: COP | K11: P&G ejecutivo oficial (estados financieros mensuales) | L11: Finanzas | M11: Mensual
A12: 2026-01 | B12: Colombia | C12: Coco Colombia | D12: COP | E12: Real | F12: pyg_ingresos_operacionales | I12: 612247701 | J12: COP | K12: P&G ejecutivo oficial (estados financieros mensuales) | L12: Finanzas | M12: Mensual
A13: 2026-01 | B13: Colombia | C13: Coco Colombia | D13: COP | E13: Real | F13: pyg_servicio_software | I13: 689690890 | J13: COP | K13: P&G ejecutivo oficial (estados financieros mensuales) | L13: Finanzas | M13: Mensual
A14: 2026-01 | B14: Colombia | C14: Coco Colombia | D14: COP | E14: Real | F14: pyg_utilidad_bruta | I14: 373711907 | J14: COP | K14: P&G ejecutivo oficial (estados financieros mensuales) | L14: Finanzas | M14: Mensual
A15: 2026-01 | B15: Colombia | C15: Coco Colombia | D15: COP | E15: Real | F15: pyg_utilidad_neta | I15: 63485497 | J15: COP | K15: P&G ejecutivo oficial (estados financieros mensuales) | L15: Finanzas | M15: Mensual
A16: 2026-01 | B16: Colombia | C16: Coco Colombia | D16: COP | E16: Real | F16: pyg_utilidad_operativa | I16: 69979361 | J16: COP | K16: P&G ejecutivo oficial (estados financieros mensuales) | L16: Finanzas | M16: Mensual
... A40: 2026-03 | B40: Colombia | C40: Coco Colombia | D40: COP | E40: Real | F40: pyg_utilidad_operativa | I40: -22242793 | J40: COP | K40: P&G ejecutivo oficial (estados financieros mensuales) | L40: Finanzas | M40: Mensual
A41: 2026-04 | B41: Perú | C41: Coco Perú | D41: USD | E41: Real | F41: proinnovate_gastos | G41: PROINNOVATE | I41: 6982.98 | J41: USD | K41: Programa PROINNOVATE Perú (no incluido en consolidado P&G) | L41: Finanzas | M41: Mensual
A42: 2026-04 | B42: Perú | C42: Coco Perú | D42: USD | E42: Real | F42: proinnovate_ingresos | G42: PROINNOVATE | I42: 22965.15 | J42: USD | K42: Programa PROINNOVATE Perú (no incluido en consolidado P&G) | L42: Finanzas | M42: Mensual
A43: 2026-04 | B43: Perú | C43: Coco Perú | D43: USD | E43: Real | F43: proinnovate_resultado | G43: PROINNOVATE | I43: 15982.17 | J43: USD | K43: Programa PROINNOVATE Perú (no incluido en consolidado P&G) | L43: Finanzas | M43: Mensual
A44: 2026-04 | B44: Colombia | C44: Coco Colombia | D44: COP | E44: Real | F44: pyg_costo_ventas | I44: 379273594 | J44: COP | K44: P&G ejecutivo oficial (estados financieros mensuales) | L44: Finanzas | M44: Mensual
A45: 2026-04 | B45: Colombia | C45: Coco Colombia | D45: USD | E45: Real | F45: pyg_costo_ventas | G45: Consolidación USD | I45: 104843.58 | J45: USD | K45: Consolidación subsidiarias (USD). Colombia derivado del P&G oficial / TRM del mes. | L45: Finanzas | M45: Mensual
A46: 2026-04 | B46: Consolidado | C46: Coco Consolidado | D46: USD | E46: Real | F46: pyg_costo_ventas | G46: Consolidación USD | I46: 104843.58 | J46: USD | K46: Consolidado = suma de EE.UU.+Perú+Costa Rica+Colombia (USD). | L46: Finanzas | M46: Mensual
A47: 2026-04 | B47: Costa Rica | C47: Coco Costa Rica | D47: USD | E47: Real | F47: pyg_costo_ventas | G47: Consolidación USD | I47: 0 | J47: USD | K47: Consolidación subsidiarias (USD). Colombia derivado del P&G oficial / TRM del mes. | L47: Finanzas | M47: Mensual
A48: 2026-04 | B48: EE.UU. | C48: Coco LLC | D48: USD | E48: Real | F48: pyg_costo_ventas | G48: Consolidación USD | I48: 0 | J48: USD | K48: Consolidación subsidiarias (USD). Colombia derivado del P&G oficial / TRM del mes. | L48: Finanzas | M48: Mensual
A49: 2026-04 | B49: Perú | C49: Coco Perú | D49: USD | E49: Real | F49: pyg_costo_ventas | G49: Consolidación USD | I49: 0 | J49: USD | K49: Consolidación subsidiarias (USD). Colombia derivado del P&G oficial / TRM del mes. | L49: Finanzas | M49: Mensual
A50: 2026-04 | B50: Colombia | C50: Coco Colombia | D50: COP | E50: Real | F50: pyg_devoluciones | I50: -68329638 | J50: COP | K50: P&G ejecutivo oficial (estados financieros mensuales) | L50: Finanzas | M50: Mensual
A51: 2026-04 | B51: Colombia | C51: Coco Colombia | D51: COP | E51: Real | F51: pyg_gasto_administracion | I51: 114280887 | J51: COP | K51: P&G ejecutivo oficial (estados financieros mensuales) | L51: Finanzas | M51: Mensual
A52: 2026-04 | B52: Colombia | C52: Coco Colombia | D52: USD | E52: Real | F52: pyg_gasto_administracion | G52: Consolidación USD | I52: 31590.96 | J52: USD | K52: Consolidación subsidiarias (USD). Colombia derivado del P&G oficial / TRM del mes. | L52: Finanzas | M52: Mensual
A53: 2026-04 | B53: Consolidado | C53: Coco Consolidado | D53: USD | E53: Real | F53: pyg_gasto_administracion | G53: Consolidación USD | I53: -32101.85 | J53: USD | K53: Consolidado = suma de EE.UU.+Perú+Costa Rica+Colombia (USD). | L53: Finanzas | M53: Mensual
A54: 2026-04 | B54: Costa Rica | C54: Coco Costa Rica | D54: USD | E54: Real | F54: pyg_gasto_administracion | G54: Consolidación USD | I54: -17320.22 | J54: USD | K54: Consolidación subsidiarias (USD). Colombia derivado del P&G oficial / TRM del mes. | L54: Finanzas | M54: Mensual
A55: 2026-04 | B55: EE.UU. | C55: Coco LLC | D55: USD | E55: Real | F55: pyg_gasto_administracion | G55: Consolidación USD | I55: -46372.59 | J55: USD | K55: Consolidación subsidiarias (USD). Colombia derivado del P&G oficial / TRM del mes. | L55: Finanzas | M55: Mensual
A56: 2026-04 | B56: Perú | C56: Coco Perú | D56: USD | E56: Real | F56: pyg_gasto_administracion | G56: Consolidación USD | I56: 0 | J56: USD | K56: Consolidación subsidiarias (USD). Colombia derivado del P&G oficial / TRM del mes. | L56: Finanzas | M56: Mensual
A57: 2026-04 | B57: Colombia | C57: Coco Colombia | D57: COP | E57: Real | F57: pyg_gasto_proyectos | I57: 122384514 | J57: COP | K57: P&G ejecutivo oficial (estados financieros mensuales) | L57: Finanzas | M57: Mensual
A58: 2026-04 | B58: Colombia | C58: Coco Colombia | D58: USD | E58: Real | F58: pyg_gasto_proyectos | G58: Consolidación USD | I58: 33831.07 | J58: USD | K58: Consolidación subsidiarias (USD). Colombia derivado del P&G oficial / TRM del mes. | L58: Finanzas | M58: Mensual
A59: 2026-04 | B59: Consolidado | C59: Coco Consolidado | D59: USD | E59: Real | F59: pyg_gasto_proyectos | G59: Consolidación USD | I59: 33831.07 | J59: USD | K59: Consolidado = suma de EE.UU.+Perú+Costa Rica+Colombia (USD). | L59: Finanzas | M59: Mensual
A60: 2026-04 | B60: Costa Rica | C60: Coco Costa Rica | D60: USD | E60: Real | F60: pyg_gasto_proyectos | G60: Consolidación USD | I60: 0 | J60: USD | K60: Consolidación subsidiarias (USD). Colombia derivado del P&G oficial / TRM del mes. | L60: Finanzas | M60: Mensual
A61: 2026-04 | B61: EE.UU. | C61: Coco LLC | D61: USD | E61: Real | F61: pyg_gasto_proyectos | G61: Consolidación USD | I61: 0 | J61: USD | K61: Consolidación subsidiarias (USD). Colombia derivado del P&G oficial / TRM del mes. | L61: Finanzas | M61: Mensual
A62: 2026-04 | B62: Perú | C62: Coco Perú | D62: USD | E62: Real | F62: pyg_gasto_proyectos | G62: Consolidación USD | I62: 0 | J62: USD | K62: Consolidación subsidiarias (USD). Colombia derivado del P&G oficial / TRM del mes. | L62: Finanzas | M62: Mensual
A63: 2026-04 | B63: Colombia | C63: Coco Colombia | D63: COP | E63: Real | F63: pyg_gasto_ventas | I63: 130090415 | J63: COP | K63: P&G ejecutivo oficial (estados financieros mensuales) | L63: Finanzas | M63: Mensual
A64: 2026-04 | B64: Colombia | C64: Coco Colombia | D64: USD | E64: Real | F64: pyg_gasto_ventas | G64: Consolidación USD | I64: 35961.23 | J64: USD | K64: Consolidación subsidiarias (USD). Colombia derivado del P&G oficial / TRM del mes. | L64: Finanzas | M64: Mensual
A65: 2026-04 | B65: Consolidado | C65: Coco Consolidado | D65: USD | E65: Real | F65: pyg_gasto_ventas | G65: Consolidación USD | I65: 35961.23 | J65: USD | K65: Consolidado = suma de EE.UU.+Perú+Costa Rica+Colombia (USD). | L65: Finanzas | M65: Mensual
A66: 2026-04 | B66: Costa Rica | C66: Coco Costa Rica | D66: USD | E66: Real | F66: pyg_gasto_ventas | G66: Consolidación USD | I66: 0 | J66: USD | K66: Consolidación subsidiarias (USD). Colombia derivado del P&G oficial / TRM del mes. | L66: Finanzas | M66: Mensual
A67: 2026-04 | B67: EE.UU. | C67: Coco LLC | D67: USD | E67: Real | F67: pyg_gasto_ventas | G67: Consolidación USD | I67: 0 | J67: USD | K67: Consolidación subsidiarias (USD). Colombia derivado del P&G oficial / TRM del mes. | L67: Finanzas | M67: Mensual
A68: 2026-04 | B68: Perú | C68: Coco Perú | D68: USD | E68: Real | F68: pyg_gasto_ventas | G68: Consolidación USD | I68: 0 | J68: USD | K68: Consolidación subsidiarias (USD). Colombia derivado del P&G oficial / TRM del mes. | L68: Finanzas | M68: Mensual
A69: 2026-04 | B69: Colombia | C69: Coco Colombia | D69: COP | E69: Real | F69: pyg_gastos_financieros | I69: 5038594 | J69: COP | K69: P&G ejecutivo oficial (estados financieros mensuales) | L69: Finanzas | M69: Mensual
A70: 2026-04 | B70: Colombia | C70: Coco Colombia | D70: USD | E70: Real | F70: pyg_gastos_financieros | G70: Consolidación USD | I70: 1392.83 | J70: USD | K70: Consolidación subsidiarias (USD). Colombia derivado del P&G oficial / TRM del mes. | L70: Finanzas | M70: Mensual
A71: 2026-04 | B71: Consolidado | C71: Coco Consolidado | D71: USD | E71: Real | F71: pyg_gastos_financieros | G71: Consolidación USD | I71: 1568.11 | J71: USD | K71: Consolidado = suma de EE.UU.+Perú+Costa Rica+Colombia (USD). | L71: Finanzas | M71: Mensual
A72: 2026-04 | B72: Costa Rica | C72: Coco Costa Rica | D72: USD | E72: Real | F72: pyg_gastos_financieros | G72: Consolidación USD | I72: 267.92 | J72: USD | K72: Consolidación subsidiarias (USD). Colombia derivado del P&G oficial / TRM del mes. | L72: Finanzas | M72: Mensual
A73: 2026-04 | B73: EE.UU. | C73: Coco LLC | D73: USD | E73: Real | F73: pyg_gastos_financieros | G73: Consolidación USD | I73: 0 | J73: USD | K73: Consolidación subsidiarias (USD). Colombia derivado del P&G oficial / TRM del mes. | L73: Finanzas | M73: Mensual
A74: 2026-04 | B74: Perú | C74: Coco Perú | D74: USD | E74: Real | F74: pyg_gastos_financieros | G74: Consolidación USD | I74: -92.64 | J74: USD | K74: Consolidación subsidiarias (USD). Colombia derivado del P&G oficial / TRM del mes. | L74: Finanzas | M74: Mensual
A75: 2026-04 | B75: Colombia | C75: Coco Colombia | D75: COP | E75: Real | F75: pyg_ingresos_no_operacionales | I75: 906545 | J75: COP | K75: P&G ejecutivo oficial (estados financieros mensuales) | L75: Finanzas | M75: Mensual
A76: 2026-04 | B76: Colombia | C76: Coco Colombia | D76: USD | E76: Real | F76: pyg_ingresos_no_operacionales | G76: Consolidación USD | I76: 250.6 | J76: USD | K76: Consolidación subsidiarias (USD). Colombia derivado del P&G oficial / TRM del mes. | L76: Finanzas | M76: Mensual
A77: 2026-04 | B77: Consolidado | C77: Coco Consolidado | D77: USD | E77: Real | F77: pyg_ingresos_no_operacionales | G77: Consolidación USD | I77: 250.6 | J77: USD | K77: Consolidado = suma de EE.UU.+Perú+Costa Rica+Colombia (USD). | L77: Finanzas | M77: Mensual
A78: 2026-04 | B78: Costa Rica | C78: Coco Costa Rica | D78: USD | E78: Real | F78: pyg_ingresos_no_operacionales | G78: Consolidación USD | I78: 0 | J78: USD | K78: Consolidación subsidiarias (USD). Colombia derivado del P&G oficial / TRM del mes. | L78: Finanzas | M78: Mensual
A79: 2026-04 | B79: EE.UU. | C79: Coco LLC | D79: USD | E79: Real | F79: pyg_ingresos_no_operacionales | G79: Consolidación USD | I79: 0 | J79: USD | K79: Consolidación subsidiarias (USD). Colombia derivado del P&G oficial / TRM del mes. | L79: Finanzas | M79: Mensual
A80: 2026-04 | B80: Perú | C80: Coco Perú | D80: USD | E80: Real | F80: pyg_ingresos_no_operacionales | G80: Consolidación USD | I80: 0 | J80: USD | K80: Consolidación subsidiarias (USD). Colombia derivado del P&G oficial / TRM del mes. | L80: Finanzas | M80: Mensual
A81: 2026-04 | B81: Colombia | C81: Coco Colombia | D81: COP | E81: Real | F81: pyg_ingresos_operacionales | I81: 750867662 | J81: COP | K81: P&G ejecutivo oficial (estados financieros mensuales) | L81: Finanzas | M81: Mensual
A82: 2026-04 | B82: Colombia | C82: Coco Colombia | D82: USD | E82: Real | F82: pyg_ingresos_operacionales | G82: Consolidación USD | I82: 207564.28 | J82: USD | K82: Consolidación subsidiarias (USD). Colombia derivado del P&G oficial / TRM del mes. | L82: Finanzas | M82: Mensual
A83: 2026-04 | B83: Consolidado | C83: Coco Consolidado | D83: USD | E83: Real | F83: pyg_ingresos_operacionales | G83: Consolidación USD | I83: 228169.4 | J83: USD | K83: Consolidado = suma de EE.UU.+Perú+Costa Rica+Colombia (USD). | L83: Finanzas | M83: Mensual
A84: 2026-04 | B84: Costa Rica | C84: Coco Costa Rica | D84: USD | E84: Real | F84: pyg_ingresos_operacionales | G84: Consolidación USD | I84: 0 | J84: USD | K84: Consolidación subsidiarias (USD). Colombia derivado del P&G oficial / TRM del mes. | L84: Finanzas | M84: Mensual
A85: 2026-04 | B85: EE.UU. | C85: Coco LLC | D85: USD | E85: Real | F85: pyg_ingresos_operacionales | G85: Consolidación USD | I85: 17616.15 | J85: USD | K85: Consolidación subsidiarias (USD). Colombia derivado del P&G oficial / TRM del mes. | L85: Finanzas | M85: Mensual
A86: 2026-04 | B86: Perú | C86: Coco Perú | D86: USD | E86: Real | F86: pyg_ingresos_operacionales | G86: Consolidación USD | I86: 2988.97 | J86: USD | K86: Consolidación subsidiarias (USD). Colombia derivado del P&G oficial / TRM del mes. | L86: Finanzas | M86: Mensual
A87: 2026-04 | B87: Colombia | C87: Coco Colombia | D87: COP | E87: Real | F87: pyg_servicio_software | I87: 819197300 | J87: COP | K87: P&G ejecutivo oficial (estados financieros mensuales) | L87: Finanzas | M87: Mensual
A88: 2026-04 | B88: Colombia | C88: Coco Colombia | D88: COP | E88: Real | F88: pyg_utilidad_bruta | I88: 371594068 | J88: COP | K88: P&G ejecutivo oficial (estados financieros mensuales) | L88: Finanzas | M88: Mensual
A89: 2026-04 | B89: Colombia | C89: Coco Colombia | D89: COP | E89: Real | F89: pyg_utilidad_neta | I89: 706203 | J89: COP | K89: P&G ejecutivo oficial (estados financieros mensuales) | L89: Finanzas | M89: Mensual
A90: 2026-04 | B90: Colombia | C90: Coco Colombia | D90: USD | E90: Real | F90: pyg_utilidad_neta | G90: Consolidación USD | I90: 195.22 | J90: USD | K90: Consolidación subsidiarias (USD). Colombia derivado del P&G oficial / TRM del mes. | L90: Finanzas | M90: Mensual
A91: 2026-04 | B91: Consolidado | C91: Coco Consolidado | D91: USD | E91: Real | F91: pyg_utilidad_neta | G91: Consolidación USD | I91: -42531.91 | J91: USD | K91: Consolidado = suma de EE.UU.+Perú+Costa Rica+Colombia (USD). | L91: Finanzas | M91: Mensual
A92: 2026-04 | B92: Costa Rica | C92: Coco Costa Rica | D92: USD | E92: Real | F92: pyg_utilidad_neta | G92: Consolidación USD | I92: -17052.3 | J92: USD | K92: Consolidación subsidiarias (USD). Colombia derivado del P&G oficial / TRM del mes. | L92: Finanzas | M92: Mensual
A93: 2026-04 | B93: EE.UU. | C93: Coco LLC | D93: USD | E93: Real | F93: pyg_utilidad_neta | G93: Consolidación USD | I93: -28756.44 | J93: USD | K93: Consolidación subsidiarias (USD). Colombia derivado del P&G oficial / TRM del mes. | L93: Finanzas | M93: Mensual
A94: 2026-04 | B94: Perú | C94: Coco Perú | D94: USD | E94: Real | F94: pyg_utilidad_neta | G94: Consolidación USD | I94: 3081.61 | J94: USD | K94: Consolidación subsidiarias (USD). Colombia derivado del P&G oficial / TRM del mes. | L94: Finanzas | M94: Mensual
A95: 2026-04 | B95: Colombia | C95: Coco Colombia | D95: COP | E95: Real | F95: pyg_utilidad_operativa | I95: 4838252 | J95: COP | K95: P&G ejecutivo oficial (estados financieros mensuales) | L95: Finanzas | M95: Mensual
A96: 2026-05 | B96: Perú | C96: Coco Perú | D96: USD | E96: Real | F96: proinnovate_gastos | G96: PROINNOVATE | I96: 6069.63 | J96: USD | K96: Programa PROINNOVATE Perú (no incluido en consolidado P&G) | L96: Finanzas | M96: Mensual
A97: 2026-05 | B97: Perú | C97: Coco Perú | D97: USD | E97: Real | F97: proinnovate_ingresos | G97: PROINNOVATE | I97: 0 | J97: USD | K97: Programa PROINNOVATE Perú (no incluido en consolidado P&G) | L97: Finanzas | M97: Mensual
A98: 2026-05 | B98: Perú | C98: Coco Perú | D98: USD | E98: Real | F98: proinnovate_resultado | G98: PROINNOVATE | I98: -6069.63 | J98: USD | K98: Programa PROINNOVATE Perú (no incluido en consolidado P&G) | L98: Finanzas | M98: Mensual
A99: 2026-05 | B99: Colombia | C99: Coco Colombia | D99: COP | E99: Real | F99: pyg_costo_ventas | I99: 355470523 | J99: COP | K99: P&G ejecutivo oficial (estados financieros mensuales) | L99: Finanzas | M99: Mensual
A100: 2026-05 | B100: Colombia | C100: Coco Colombia | D100: USD | E100: Real | F100: pyg_costo_ventas | G100: Consolidación USD | I100: 95710.42 | J100: USD | K100: Consolidación subsidiarias (USD). Colombia derivado del P&G oficial / TRM del mes. | L100: Finanzas | M100: Mensual
A101: 2026-05 | B101: Consolidado | C101: Coco Consolidado | D101: USD | E101: Real | F101: pyg_costo_ventas | G101: Consolidación USD | I101: 100188.8 | J101: USD | K101: Consolidado = suma de EE.UU.+Perú+Costa Rica+Colombia (USD). | L101: Finanzas | M101: Mensual
A102: 2026-05 | B102: Costa Rica | C102: Coco Costa Rica | D102: USD | E102: Real | F102: pyg_costo_ventas | G102: Consolidación USD | I102: 0 | J102: USD | K102: Consolidación subsidiarias (USD). Colombia derivado del P&G oficial / TRM del mes. | L102: Finanzas | M102: Mensual
A103: 2026-05 | B103: EE.UU. | C103: Coco LLC | D103: USD | E103: Real | F103: pyg_costo_ventas | G103: Consolidación USD | I103: 0 | J103: USD | K103: Consolidación subsidiarias (USD). Colombia derivado del P&G oficial / TRM del mes. | L103: Finanzas | M103: Mensual
A104: 2026-05 | B104: Perú | C104: Coco Perú | D104: USD | E104: Real | F104: pyg_costo_ventas | G104: Consolidación USD | I104: 4478.38 | J104: USD | K104: Consolidación subsidiarias (USD). Colombia derivado del P&G oficial / TRM del mes. | L104: Finanzas | M104: Mensual
A105: 2026-05 | B105: Colombia | C105: Coco Colombia | D105: COP | E105: Real | F105: pyg_devoluciones | I105: -55433340 | J105: COP | K105: P&G ejecutivo oficial (estados financieros mensuales) | L105: Finanzas | M105: Mensual
A106: 2026-05 | B106: Colombia | C106: Coco Colombia | D106: COP | E106: Real | F106: pyg_gasto_administracion | I106: 116808824 | J106: COP | K106: P&G ejecutivo oficial (estados financieros mensuales) | L106: Finanzas | M106: Mensual
A107: 2026-05 | B107: Colombia | C107: Coco Colombia | D107: USD | E107: Real | F107: pyg_gasto_administracion | G107: Consolidación USD | I107: 31450.77 | J107: USD | K107: Consolidación subsidiarias (USD). Colombia derivado del P&G oficial / TRM del mes. | L107: Finanzas | M107: Mensual
A108: 2026-05 | B108: Consolidado | C108: Coco Consolidado | D108: USD | E108: Real | F108: pyg_gasto_administracion | G108: Consolidación USD | I108: 53124.59 | J108: USD | K108: Consolidado = suma de EE.UU.+Perú+Costa Rica+Colombia (USD). | L108: Finanzas | M108: Mensual
A109: 2026-05 | B109: Costa Rica | C109: Coco Costa Rica | D109: USD | E109: Real | F109: pyg_gasto_administracion | G109: Consolidación USD | I109: 57.8 | J109: USD | K109: Consolidación subsidiarias (USD). Colombia derivado del P&G oficial / TRM del mes. | L109: Finanzas | M109: Mensual
A110: 2026-05 | B110: EE.UU. | C110: Coco LLC | D110: USD | E110: Real | F110: pyg_gasto_administracion | G110: Consolidación USD | I110: 21616.02 | J110: USD | K110: Consolidación subsidiarias (USD). Colombia derivado del P&G oficial / TRM del mes. | L110: Finanzas | M110: Mensual
A111: 2026-05 | B111: Perú | C111: Coco Perú | D111: USD | E111: Real | F111: pyg_gasto_administracion | G111: Consolidación USD | I111: 0 | J111: USD | K111: Consolidación subsidiarias (USD). Colombia derivado del P&G oficial / TRM del mes. | L111: Finanzas | M111: Mensual
A112: 2026-05 | B112: Colombia | C112: Coco Colombia | D112: COP | E112: Real | F112: pyg_gasto_proyectos | I112: 120992711 | J112: COP | K112: P&G ejecutivo oficial (estados financieros mensuales) | L112: Finanzas | M112: Mensual
A113: 2026-05 | B113: Colombia | C113: Coco Colombia | D113: USD | E113: Real | F113: pyg_gasto_proyectos | G113: Consolidación USD | I113: 32577.28 | J113: USD | K113: Consolidación subsidiarias (USD). Colombia derivado del P&G oficial / TRM del mes. | L113: Finanzas | M113: Mensual
A114: 2026-05 | B114: Consolidado | C114: Coco Consolidado | D114: USD | E114: Real | F114: pyg_gasto_proyectos | G114: Consolidación USD | I114: 40077.28 | J114: USD | K114: Consolidado = suma de EE.UU.+Perú+Costa Rica+Colombia (USD). | L114: Finanzas | M114: Mensual
A115: 2026-05 | B115: Costa Rica | C115: Coco Costa Rica | D115: USD | E115: Real | F115: pyg_gasto_proyectos | G115: Consolidación USD | I115: 0 | J115: USD | K115: Consolidación subsidiarias (USD). Colombia derivado del P&G oficial / TRM del mes. | L115: Finanzas | M115: Mensual
A116: 2026-05 | B116: EE.UU. | C116: Coco LLC | D116: USD | E116: Real | F116: pyg_gasto_proyectos | G116: Consolidación USD | I116: 7500 | J116: USD | K116: Consolidación subsidiarias (USD). Colombia derivado del P&G oficial / TRM del mes. | L116: Finanzas | M116: Mensual
A117: 2026-05 | B117: Perú | C117: Coco Perú | D117: USD | E117: Real | F117: pyg_gasto_proyectos | G117: Consolidación USD | I117: 0 | J117: USD | K117: Consolidación subsidiarias (USD). Colombia derivado del P&G oficial / TRM del mes. | L117: Finanzas | M117: Mensual
A118: 2026-05 | B118: Colombia | C118: Coco Colombia | D118: COP | E118: Real | F118: pyg_gasto_ventas | I118: 120233213 | J118: COP | K118: P&G ejecutivo oficial (estados financieros mensuales) | L118: Finanzas | M118: Mensual
A119: 2026-05 | B119: Colombia | C119: Coco Colombia | D119: USD | E119: Real | F119: pyg_gasto_ventas | G119: Consolidación USD | I119: 32372.79 | J119: USD | K119: Consolidación subsidiarias (USD). Colombia derivado del P&G oficial / TRM del mes. | L119: Finanzas | M119: Mensual
A120: 2026-05 | B120: Consolidado | C120: Coco Consolidado | D120: USD | E120: Real | F120: pyg_gasto_ventas | G120: Consolidación USD | I120: 37672.79 | J120: USD | K120: Consolidado = suma de EE.UU.+Perú+Costa Rica+Colombia (USD). | L120: Finanzas | M120: Mensual
A121: 2026-05 | B121: Costa Rica | C121: Coco Costa Rica | D121: USD | E121: Real | F121: pyg_gasto_ventas | G121: Consolidación USD | I121: 1300 | J121: USD | K121: Consolidación subsidiarias (USD). Colombia derivado del P&G oficial / TRM del mes. | L121: Finanzas | M121: Mensual
A122: 2026-05 | B122: EE.UU. | C122: Coco LLC | D122: USD | E122: Real | F122: pyg_gasto_ventas | G122: Consolidación USD | I122: 4000 | J122: USD | K122: Consolidación subsidiarias (USD). Colombia derivado del P&G oficial / TRM del mes. | L122: Finanzas | M122: Mensual
A123: 2026-05 | B123: Perú | C123: Coco Perú | D123: USD | E123: Real | F123: pyg_gasto_ventas | G123: Consolidación USD | I123: 0 | J123: USD | K123: Consolidación subsidiarias (USD). Colombia derivado del P&G oficial / TRM del mes. | L123: Finanzas | M123: Mensual
A124: 2026-05 | B124: Colombia | C124: Coco Colombia | D124: COP | E124: Real | F124: pyg_gastos_financieros | I124: 6000846 | J124: COP | K124: P&G ejecutivo oficial (estados financieros mensuales) | L124: Finanzas | M124: Mensual
...

Sheet Finanzas
A1: Finanzas — vista de solo lectura
A2: Regenerada desde BD_Indicadores el 2026-07-13 · 186 filas · Editar en BD_Indicadores.
A4: periodo | B4: pais | C4: compania | D4: moneda | E4: escenario | F4: codigo_indicador | G4: segmento | H4: detalle | I4: valor | J4: unidad | K4: comentario | L4: area_responsable | M4: periodicidad
A5: 2023-12 | B5: Colombia | C5: Coco Colombia | E5: Real | F5: distribucion_ingresos | H5: Implementaciones | I5: 0 | J5: % | K5: Año 2023 | L5: Finanzas | M5: =IFERROR(INDEX(Diccionario!$N:$N,MATCH(F1226,Diccionario!$C:$C,0)),"")
A6: 2023-12 | B6: Colombia | C6: Coco Colombia | E6: Real | F6: distribucion_ingresos | H6: Internacional | I6: 0 | J6: % | K6: Año 2023 | L6: Finanzas | M6: =IFERROR(INDEX(Diccionario!$N:$N,MATCH(F1229,Diccionario!$C:$C,0)),"")
A7: 2023-12 | B7: Colombia | C7: Coco Colombia | E7: Real | F7: distribucion_ingresos | H7: Recurrente | I7: 84 | J7: % | K7: Año 2023 | L7: Finanzas | M7: =IFERROR(INDEX(Diccionario!$N:$N,MATCH(F1220,Diccionario!$C:$C,0)),"")
A8: 2023-12 | B8: Colombia | C8: Coco Colombia | E8: Real | F8: distribucion_ingresos | H8: Variable | I8: 16 | J8: % | K8: Año 2023 | L8: Finanzas | M8: =IFERROR(INDEX(Diccionario!$N:$N,MATCH(F1223,Diccionario!$C:$C,0)),"")
A9: 2024-01 | B9: Colombia | C9: Coco Colombia | D9: COP | E9: Real | F9: egresos_totales | I9: 547000000 | J9: COP | L9: Finanzas | M9: =IFERROR(INDEX(Diccionario!$N:$N,MATCH(F5,Diccionario!$C:$C,0)),"")
A10: 2024-01 | B10: Colombia | C10: Coco Colombia | D10: COP | E10: Real | F10: ingresos_no_recurrentes | I10: 24800000 | J10: COP | L10: Finanzas | M10: =IFERROR(INDEX(Diccionario!$N:$N,MATCH(F1055,Diccionario!$C:$C,0)),"")
A11: 2024-01 | B11: Colombia | C11: Coco Colombia | D11: COP | E11: Real | F11: ingresos_recurrentes | I11: 393759551 | J11: COP | L11: Finanzas | M11: =IFERROR(INDEX(Diccionario!$N:$N,MATCH(F1026,Diccionario!$C:$C,0)),"")
A12: 2024-01 | B12: Colombia | C12: Coco Colombia | D12: COP | E12: Real | F12: ingresos_totales | I12: 430000000 | J12: COP | L12: Finanzas | M12: =IFERROR(INDEX(Diccionario!$N:$N,MATCH(F4,Diccionario!$C:$C,0)),"")
A13: 2024-01 | B13: Colombia | C13: Coco Colombia | D13: COP | E13: Real | F13: utilidad_neta | I13: -117000000 | J13: COP | K13: Derivado: ingresos - egresos | L13: Finanzas | M13: =IFERROR(INDEX(Diccionario!$N:$N,MATCH(F6,Diccionario!$C:$C,0)),"")
A14: 2024-02 | B14: Colombia | C14: Coco Colombia | D14: COP | E14: Real | F14: egresos_totales | I14: 515000000 | J14: COP | L14: Finanzas | M14: =IFERROR(INDEX(Diccionario!$N:$N,MATCH(F8,Diccionario!$C:$C,0)),"")
A15: 2024-02 | B15: Colombia | C15: Coco Colombia | D15: COP | E15: Real | F15: ingresos_no_recurrentes | I15: 118729053 | J15: COP | L15: Finanzas | M15: =IFERROR(INDEX(Diccionario!$N:$N,MATCH(F1056,Diccionario!$C:$C,0)),"")
A16: 2024-02 | B16: Colombia | C16: Coco Colombia | D16: COP | E16: Real | F16: ingresos_recurrentes | I16: 546983304 | J16: COP | L16: Finanzas | M16: =IFERROR(INDEX(Diccionario!$N:$N,MATCH(F1027,Diccionario!$C:$C,0)),"")
A17: 2024-02 | B17: Colombia | C17: Coco Colombia | D17: COP | E17: Real | F17: ingresos_totales | I17: 692000000 | J17: COP | L17: Finanzas | M17: =IFERROR(INDEX(Diccionario!$N:$N,MATCH(F7,Diccionario!$C:$C,0)),"")
A18: 2024-02 | B18: Colombia | C18: Coco Colombia | D18: COP | E18: Real | F18: utilidad_neta | I18: 177000000 | J18: COP | K18: Derivado: ingresos - egresos | L18: Finanzas | M18: =IFERROR(INDEX(Diccionario!$N:$N,MATCH(F9,Diccionario!$C:$C,0)),"")
A19: 2024-03 | B19: Colombia | C19: Coco Colombia | D19: COP | E19: Real | F19: egresos_totales | I19: 571000000 | J19: COP | L19: Finanzas | M19: =IFERROR(INDEX(Diccionario!$N:$N,MATCH(F11,Diccionario!$C:$C,0)),"")
A20: 2024-03 | B20: Colombia | C20: Coco Colombia | D20: COP | E20: Real | F20: ingresos_no_recurrentes | I20: 12750000 | J20: COP | L20: Finanzas | M20: =IFERROR(INDEX(Diccionario!$N:$N,MATCH(F1057,Diccionario!$C:$C,0)),"")
A21: 2024-03 | B21: Colombia | C21: Coco Colombia | D21: COP | E21: Real | F21: ingresos_recurrentes | I21: 543692148 | J21: COP | L21: Finanzas | M21: =IFERROR(INDEX(Diccionario!$N:$N,MATCH(F1028,Diccionario!$C:$C,0)),"")
A22: 2024-03 | B22: Colombia | C22: Coco Colombia | D22: COP | E22: Real | F22: ingresos_totales | I22: 582000000 | J22: COP | L22: Finanzas | M22: =IFERROR(INDEX(Diccionario!$N:$N,MATCH(F10,Diccionario!$C:$C,0)),"")
A23: 2024-03 | B23: Colombia | C23: Coco Colombia | D23: COP | E23: Real | F23: utilidad_neta | I23: 11000000 | J23: COP | K23: Derivado: ingresos - egresos | L23: Finanzas | M23: =IFERROR(INDEX(Diccionario!$N:$N,MATCH(F12,Diccionario!$C:$C,0)),"")
A24: 2024-04 | B24: Colombia | C24: Coco Colombia | D24: COP | E24: Real | F24: egresos_totales | I24: 573000000 | J24: COP | L24: Finanzas | M24: =IFERROR(INDEX(Diccionario!$N:$N,MATCH(F14,Diccionario!$C:$C,0)),"")
A25: 2024-04 | B25: Colombia | C25: Coco Colombia | D25: COP | E25: Real | F25: ingresos_no_recurrentes | I25: 39644578 | J25: COP | L25: Finanzas | M25: =IFERROR(INDEX(Diccionario!$N:$N,MATCH(F1058,Diccionario!$C:$C,0)),"")
A26: 2024-04 | B26: Colombia | C26: Coco Colombia | D26: COP | E26: Real | F26: ingresos_recurrentes | I26: 529778177 | J26: COP | L26: Finanzas | M26: =IFERROR(INDEX(Diccionario!$N:$N,MATCH(F1029,Diccionario!$C:$C,0)),"")
A27: 2024-04 | B27: Colombia | C27: Coco Colombia | D27: COP | E27: Real | F27: ingresos_totales | I27: 578000000 | J27: COP | L27: Finanzas | M27: =IFERROR(INDEX(Diccionario!$N:$N,MATCH(F13,Diccionario!$C:$C,0)),"")
A28: 2024-04 | B28: Colombia | C28: Coco Colombia | D28: COP | E28: Real | F28: utilidad_neta | I28: 5000000 | J28: COP | K28: Derivado: ingresos - egresos | L28: Finanzas | M28: =IFERROR(INDEX(Diccionario!$N:$N,MATCH(F15,Diccionario!$C:$C,0)),"")
A29: 2024-05 | B29: Colombia | C29: Coco Colombia | D29: COP | E29: Real | F29: egresos_totales | I29: 574000000 | J29: COP | L29: Finanzas | M29: =IFERROR(INDEX(Diccionario!$N:$N,MATCH(F17,Diccionario!$C:$C,0)),"")
A30: 2024-05 | B30: Colombia | C30: Coco Colombia | D30: COP | E30: Real | F30: ingresos_no_recurrentes | I30: 43120258 | J30: COP | L30: Finanzas | M30: =IFERROR(INDEX(Diccionario!$N:$N,MATCH(F1059,Diccionario!$C:$C,0)),"")
A31: 2024-05 | B31: Colombia | C31: Coco Colombia | D31: COP | E31: Real | F31: ingresos_recurrentes | I31: 605227323 | J31: COP | L31: Finanzas | M31: =IFERROR(INDEX(Diccionario!$N:$N,MATCH(F1030,Diccionario!$C:$C,0)),"")
A32: 2024-05 | B32: Colombia | C32: Coco Colombia | D32: COP | E32: Real | F32: ingresos_totales | I32: 679000000 | J32: COP | L32: Finanzas | M32: =IFERROR(INDEX(Diccionario!$N:$N,MATCH(F16,Diccionario!$C:$C,0)),"")
A33: 2024-05 | B33: Colombia | C33: Coco Colombia | D33: COP | E33: Real | F33: utilidad_neta | I33: 105000000 | J33: COP | K33: Derivado: ingresos - egresos | L33: Finanzas | M33: =IFERROR(INDEX(Diccionario!$N:$N,MATCH(F18,Diccionario!$C:$C,0)),"")
A34: 2024-06 | B34: Colombia | C34: Coco Colombia | D34: COP | E34: Real | F34: egresos_totales | I34: 611000000 | J34: COP | L34: Finanzas | M34: =IFERROR(INDEX(Diccionario!$N:$N,MATCH(F20,Diccionario!$C:$C,0)),"")
A35: 2024-06 | B35: Colombia | C35: Coco Colombia | D35: COP | E35: Real | F35: ingresos_no_recurrentes | I35: 104205606 | J35: COP | L35: Finanzas | M35: =IFERROR(INDEX(Diccionario!$N:$N,MATCH(F1060,Diccionario!$C:$C,0)),"")
A36: 2024-06 | B36: Colombia | C36: Coco Colombia | D36: COP | E36: Real | F36: ingresos_recurrentes | I36: 547523725 | J36: COP | L36: Finanzas | M36: =IFERROR(INDEX(Diccionario!$N:$N,MATCH(F1031,Diccionario!$C:$C,0)),"")
A37: 2024-06 | B37: Colombia | C37: Coco Colombia | D37: COP | E37: Real | F37: ingresos_totales | I37: 684000000 | J37: COP | L37: Finanzas | M37: =IFERROR(INDEX(Diccionario!$N:$N,MATCH(F19,Diccionario!$C:$C,0)),"")
A38: 2024-06 | B38: Colombia | C38: Coco Colombia | D38: COP | E38: Real | F38: utilidad_neta | I38: 73000000 | J38: COP | K38: Derivado: ingresos - egresos | L38: Finanzas | M38: =IFERROR(INDEX(Diccionario!$N:$N,MATCH(F21,Diccionario!$C:$C,0)),"")
A39: 2024-07 | B39: Colombia | C39: Coco Colombia | D39: COP | E39: Real | F39: egresos_totales | I39: 555000000 | J39: COP | L39: Finanzas | M39: =IFERROR(INDEX(Diccionario!$N:$N,MATCH(F23,Diccionario!$C:$C,0)),"")
A40: 2024-07 | B40: Colombia | C40: Coco Colombia | D40: COP | E40: Real | F40: ingresos_no_recurrentes | I40: 38194640 | J40: COP | L40: Finanzas | M40: =IFERROR(INDEX(Diccionario!$N:$N,MATCH(F1061,Diccionario!$C:$C,0)),"")
A41: 2024-07 | B41: Colombia | C41: Coco Colombia | D41: COP | E41: Real | F41: ingresos_recurrentes | I41: 578363325 | J41: COP | L41: Finanzas | M41: =IFERROR(INDEX(Diccionario!$N:$N,MATCH(F1032,Diccionario!$C:$C,0)),"")
A42: 2024-07 | B42: Colombia | C42: Coco Colombia | D42: COP | E42: Real | F42: ingresos_totales | I42: 642000000 | J42: COP | L42: Finanzas | M42: =IFERROR(INDEX(Diccionario!$N:$N,MATCH(F22,Diccionario!$C:$C,0)),"")
A43: 2024-07 | B43: Colombia | C43: Coco Colombia | D43: COP | E43: Real | F43: utilidad_neta | I43: 87000000 | J43: COP | K43: Derivado: ingresos - egresos | L43: Finanzas | M43: =IFERROR(INDEX(Diccionario!$N:$N,MATCH(F24,Diccionario!$C:$C,0)),"")
A44: 2024-08 | B44: Colombia | C44: Coco Colombia | D44: COP | E44: Real | F44: egresos_totales | I44: 638000000 | J44: COP | L44: Finanzas | M44: =IFERROR(INDEX(Diccionario!$N:$N,MATCH(F26,Diccionario!$C:$C,0)),"")
A45: 2024-08 | B45: Colombia | C45: Coco Colombia | D45: COP | E45: Real | F45: ingresos_no_recurrentes | I45: 39148433 | J45: COP | L45: Finanzas | M45: =IFERROR(INDEX(Diccionario!$N:$N,MATCH(F1062,Diccionario!$C:$C,0)),"")
A46: 2024-08 | B46: Colombia | C46: Coco Colombia | D46: COP | E46: Real | F46: ingresos_recurrentes | I46: 602616989 | J46: COP | L46: Finanzas | M46: =IFERROR(INDEX(Diccionario!$N:$N,MATCH(F1033,Diccionario!$C:$C,0)),"")
A47: 2024-08 | B47: Colombia | C47: Coco Colombia | D47: COP | E47: Real | F47: ingresos_totales | I47: 675000000 | J47: COP | L47: Finanzas | M47: =IFERROR(INDEX(Diccionario!$N:$N,MATCH(F25,Diccionario!$C:$C,0)),"")
A48: 2024-08 | B48: Colombia | C48: Coco Colombia | D48: COP | E48: Real | F48: utilidad_neta | I48: 37000000 | J48: COP | K48: Derivado: ingresos - egresos | L48: Finanzas | M48: =IFERROR(INDEX(Diccionario!$N:$N,MATCH(F27,Diccionario!$C:$C,0)),"")
A49: 2024-09 | B49: Colombia | C49: Coco Colombia | D49: COP | E49: Real | F49: egresos_totales | I49: 679000000 | J49: COP | L49: Finanzas | M49: =IFERROR(INDEX(Diccionario!$N:$N,MATCH(F29,Diccionario!$C:$C,0)),"")
A50: 2024-09 | B50: Colombia | C50: Coco Colombia | D50: COP | E50: Real | F50: ingresos_no_recurrentes | I50: 38448771 | J50: COP | L50: Finanzas | M50: =IFERROR(INDEX(Diccionario!$N:$N,MATCH(F1063,Diccionario!$C:$C,0)),"")
A51: 2024-09 | B51: Colombia | C51: Coco Colombia | D51: COP | E51: Real | F51: ingresos_recurrentes | I51: 594469220 | J51: COP | L51: Finanzas | M51: =IFERROR(INDEX(Diccionario!$N:$N,MATCH(F1034,Diccionario!$C:$C,0)),"")
A52: 2024-09 | B52: Colombia | C52: Coco Colombia | D52: COP | E52: Real | F52: ingresos_totales | I52: 663000000 | J52: COP | L52: Finanzas | M52: =IFERROR(INDEX(Diccionario!$N:$N,MATCH(F28,Diccionario!$C:$C,0)),"")
A53: 2024-09 | B53: Colombia | C53: Coco Colombia | D53: COP | E53: Real | F53: utilidad_neta | I53: -16000000 | J53: COP | K53: Derivado: ingresos - egresos | L53: Finanzas | M53: =IFERROR(INDEX(Diccionario!$N:$N,MATCH(F30,Diccionario!$C:$C,0)),"")
A54: 2024-10 | B54: Colombia | C54: Coco Colombia | D54: COP | E54: Real | F54: egresos_totales | I54: 716000000 | J54: COP | L54: Finanzas | M54: =IFERROR(INDEX(Diccionario!$N:$N,MATCH(F32,Diccionario!$C:$C,0)),"")
A55: 2024-10 | B55: Colombia | C55: Coco Colombia | D55: COP | E55: Real | F55: ingresos_no_recurrentes | I55: 17301320 | J55: COP | L55: Finanzas | M55: =IFERROR(INDEX(Diccionario!$N:$N,MATCH(F1064,Diccionario!$C:$C,0)),"")
A56: 2024-10 | B56: Colombia | C56: Coco Colombia | D56: COP | E56: Real | F56: ingresos_recurrentes | I56: 627068547 | J56: COP | L56: Finanzas | M56: =IFERROR(INDEX(Diccionario!$N:$N,MATCH(F1035,Diccionario!$C:$C,0)),"")
A57: 2024-10 | B57: Colombia | C57: Coco Colombia | D57: COP | E57: Real | F57: ingresos_totales | I57: 672000000 | J57: COP | L57: Finanzas | M57: =IFERROR(INDEX(Diccionario!$N:$N,MATCH(F31,Diccionario!$C:$C,0)),"")
A58: 2024-10 | B58: Colombia | C58: Coco Colombia | D58: COP | E58: Real | F58: utilidad_neta | I58: -44000000 | J58: COP | K58: Derivado: ingresos - egresos | L58: Finanzas | M58: =IFERROR(INDEX(Diccionario!$N:$N,MATCH(F33,Diccionario!$C:$C,0)),"")
A59: 2024-11 | B59: Colombia | C59: Coco Colombia | D59: COP | E59: Real | F59: egresos_totales | I59: 740000000 | J59: COP | L59: Finanzas | M59: =IFERROR(INDEX(Diccionario!$N:$N,MATCH(F35,Diccionario!$C:$C,0)),"")
A60: 2024-11 | B60: Colombia | C60: Coco Colombia | D60: COP | E60: Real | F60: ingresos_no_recurrentes | I60: 25645918 | J60: COP | L60: Finanzas | M60: =IFERROR(INDEX(Diccionario!$N:$N,MATCH(F1065,Diccionario!$C:$C,0)),"")
A61: 2024-11 | B61: Colombia | C61: Coco Colombia | D61: COP | E61: Real | F61: ingresos_recurrentes | I61: 702199047 | J61: COP | L61: Finanzas | M61: =IFERROR(INDEX(Diccionario!$N:$N,MATCH(F1036,Diccionario!$C:$C,0)),"")
A62: 2024-11 | B62: Colombia | C62: Coco Colombia | D62: COP | E62: Real | F62: ingresos_totales | I62: 761000000 | J62: COP | L62: Finanzas | M62: =IFERROR(INDEX(Diccionario!$N:$N,MATCH(F34,Diccionario!$C:$C,0)),"")
A63: 2024-11 | B63: Colombia | C63: Coco Colombia | D63: COP | E63: Real | F63: utilidad_neta | I63: 21000000 | J63: COP | K63: Derivado: ingresos - egresos | L63: Finanzas | M63: =IFERROR(INDEX(Diccionario!$N:$N,MATCH(F36,Diccionario!$C:$C,0)),"")
A64: 2024-12 | B64: Colombia | C64: Coco Colombia | D64: COP | E64: Real | F64: egresos_totales | I64: 810000000 | J64: COP | L64: Finanzas | M64: =IFERROR(INDEX(Diccionario!$N:$N,MATCH(F38,Diccionario!$C:$C,0)),"")
A65: 2024-12 | B65: Colombia | C65: Coco Colombia | D65: COP | E65: Real | F65: ingresos_no_recurrentes | I65: 252667553 | J65: COP | L65: Finanzas | M65: =IFERROR(INDEX(Diccionario!$N:$N,MATCH(F1066,Diccionario!$C:$C,0)),"")
A66: 2024-12 | B66: Colombia | C66: Coco Colombia | D66: COP | E66: Real | F66: ingresos_recurrentes | I66: 895000000 | J66: COP | L66: Finanzas | M66: =IFERROR(INDEX(Diccionario!$N:$N,MATCH(F1037,Diccionario!$C:$C,0)),"")
A67: 2024-12 | B67: Colombia | C67: Coco Colombia | D67: COP | E67: Real | F67: ingresos_totales | I67: 1279000000 | J67: COP | L67: Finanzas | M67: =IFERROR(INDEX(Diccionario!$N:$N,MATCH(F37,Diccionario!$C:$C,0)),"")
A68: 2024-12 | B68: Colombia | C68: Coco Colombia | D68: COP | E68: Real | F68: utilidad_neta | I68: 469000000 | J68: COP | K68: Derivado: ingresos - egresos | L68: Finanzas | M68: =IFERROR(INDEX(Diccionario!$N:$N,MATCH(F39,Diccionario!$C:$C,0)),"")
A69: 2025-01 | B69: Colombia | C69: Coco Colombia | D69: COP | E69: Real | F69: egresos_totales | I69: 694000000 | J69: COP | L69: Finanzas | M69: =IFERROR(INDEX(Diccionario!$N:$N,MATCH(F41,Diccionario!$C:$C,0)),"")
A70: 2025-01 | B70: Colombia | C70: Coco Colombia | D70: COP | E70: Real | F70: ingresos_no_recurrentes | I70: 5800000 | J70: COP | L70: Finanzas | M70: =IFERROR(INDEX(Diccionario!$N:$N,MATCH(F1067,Diccionario!$C:$C,0)),"")
A71: 2025-01 | B71: Colombia | C71: Coco Colombia | D71: COP | E71: Real | F71: ingresos_recurrentes | I71: 507300096 | J71: COP | L71: Finanzas | M71: =IFERROR(INDEX(Diccionario!$N:$N,MATCH(F1038,Diccionario!$C:$C,0)),"")
A72: 2025-01 | B72: Colombia | C72: Coco Colombia | D72: COP | E72: Real | F72: ingresos_totales | I72: 504000000 | J72: COP | L72: Finanzas | M72: =IFERROR(INDEX(Diccionario!$N:$N,MATCH(F40,Diccionario!$C:$C,0)),"")
A73: 2025-01 | B73: Colombia | C73: Coco Colombia | D73: COP | E73: Real | F73: utilidad_neta | I73: -190000000 | J73: COP | K73: Derivado: ingresos - egresos | L73: Finanzas | M73: =IFERROR(INDEX(Diccionario!$N:$N,MATCH(F42,Diccionario!$C:$C,0)),"")
A74: 2025-02 | B74: Colombia | C74: Coco Colombia | D74: COP | E74: Real | F74: egresos_totales | I74: 688000000 | J74: COP | L74: Finanzas | M74: =IFERROR(INDEX(Diccionario!$N:$N,MATCH(F44,Diccionario!$C:$C,0)),"")
A75: 2025-02 | B75: Colombia | C75: Coco Colombia | D75: COP | E75: Real | F75: ingresos_no_recurrentes | I75: 0 | J75: COP | L75: Finanzas | M75: =IFERROR(INDEX(Diccionario!$N:$N,MATCH(F1068,Diccionario!$C:$C,0)),"")
A76: 2025-02 | B76: Colombia | C76: Coco Colombia | D76: COP | E76: Real | F76: ingresos_recurrentes | I76: 571613281 | J76: COP | L76: Finanzas | M76: =IFERROR(INDEX(Diccionario!$N:$N,MATCH(F1039,Diccionario!$C:$C,0)),"")
A77: 2025-02 | B77: Colombia | C77: Coco Colombia | D77: COP | E77: Real | F77: ingresos_totales | I77: 564000000 | J77: COP | L77: Finanzas | M77: =IFERROR(INDEX(Diccionario!$N:$N,MATCH(F43,Diccionario!$C:$C,0)),"")
A78: 2025-02 | B78: Colombia | C78: Coco Colombia | D78: COP | E78: Real | F78: utilidad_neta | I78: -124000000 | J78: COP | K78: Derivado: ingresos - egresos | L78: Finanzas | M78: =IFERROR(INDEX(Diccionario!$N:$N,MATCH(F45,Diccionario!$C:$C,0)),"")
A79: 2025-03 | B79: Colombia | C79: Coco Colombia | D79: COP | E79: Real | F79: egresos_totales | I79: 809000000 | J79: COP | L79: Finanzas | M79: =IFERROR(INDEX(Diccionario!$N:$N,MATCH(F47,Diccionario!$C:$C,0)),"")
A80: 2025-03 | B80: Colombia | C80: Coco Colombia | D80: COP | E80: Real | F80: ingresos_no_recurrentes | I80: 2546881 | J80: COP | L80: Finanzas | M80: =IFERROR(INDEX(Diccionario!$N:$N,MATCH(F1069,Diccionario!$C:$C,0)),"")
A81: 2025-03 | B81: Colombia | C81: Coco Colombia | D81: COP | E81: Real | F81: ingresos_recurrentes | I81: 674275375 | J81: COP | L81: Finanzas | M81: =IFERROR(INDEX(Diccionario!$N:$N,MATCH(F1040,Diccionario!$C:$C,0)),"")
A82: 2025-03 | B82: Colombia | C82: Coco Colombia | D82: COP | E82: Real | F82: ingresos_totales | I82: 695000000 | J82: COP | L82: Finanzas | M82: =IFERROR(INDEX(Diccionario!$N:$N,MATCH(F46,Diccionario!$C:$C,0)),"")
A83: 2025-03 | B83: Colombia | C83: Coco Colombia | D83: COP | E83: Real | F83: utilidad_neta | I83: -114000000 | J83: COP | K83: Derivado: ingresos - egresos | L83: Finanzas | M83: =IFERROR(INDEX(Diccionario!$N:$N,MATCH(F48,Diccionario!$C:$C,0)),"")
A84: 2025-04 | B84: Colombia | C84: Coco Colombia | D84: COP | E84: Real | F84: egresos_totales | I84: 766600000 | J84: COP | L84: Finanzas | M84: =IFERROR(INDEX(Diccionario!$N:$N,MATCH(F50,Diccionario!$C:$C,0)),"")
A85: 2025-04 | B85: Colombia | C85: Coco Colombia | D85: COP | E85: Real | F85: ingresos_no_recurrentes | I85: 2546881 | J85: COP | L85: Finanzas | M85: =IFERROR(INDEX(Diccionario!$N:$N,MATCH(F1070,Diccionario!$C:$C,0)),"")
A86: 2025-04 | B86: Colombia | C86: Coco Colombia | D86: COP | E86: Real | F86: ingresos_recurrentes | I86: 583911889 | J86: COP | L86: Finanzas | M86: =IFERROR(INDEX(Diccionario!$N:$N,MATCH(F1041,Diccionario!$C:$C,0)),"")
A87: 2025-04 | B87: Colombia | C87: Coco Colombia | D87: COP | E87: Real | F87: ingresos_totales | I87: 578000000 | J87: COP | L87: Finanzas | M87: =IFERROR(INDEX(Diccionario!$N:$N,MATCH(F49,Diccionario!$C:$C,0)),"")
A88: 2025-04 | B88: Colombia | C88: Coco Colombia | D88: COP | E88: Real | F88: utilidad_neta | I88: -188600000 | J88: COP | K88: Derivado: ingresos - egresos | L88: Finanzas | M88: =IFERROR(INDEX(Diccionario!$N:$N,MATCH(F51,Diccionario!$C:$C,0)),"")
A89: 2025-05 | B89: Colombia | C89: Coco Colombia | D89: COP | E89: Real | F89: egresos_totales | I89: 729000000 | J89: COP | L89: Finanzas | M89: =IFERROR(INDEX(Diccionario!$N:$N,MATCH(F53,Diccionario!$C:$C,0)),"")
A90: 2025-05 | B90: Colombia | C90: Coco Colombia | D90: COP | E90: Real | F90: ingresos_no_recurrentes | I90: 26543424 | J90: COP | L90: Finanzas | M90: =IFERROR(INDEX(Diccionario!$N:$N,MATCH(F1071,Diccionario!$C:$C,0)),"")
A91: 2025-05 | B91: Colombia | C91: Coco Colombia | D91: COP | E91: Real | F91: ingresos_recurrentes | I91: 697602788 | J91: COP | L91: Finanzas | M91: =IFERROR(INDEX(Diccionario!$N:$N,MATCH(F1042,Diccionario!$C:$C,0)),"")
A92: 2025-05 | B92: Colombia | C92: Coco Colombia | D92: COP | E92: Real | F92: ingresos_totales | I92: 716000000 | J92: COP | L92: Finanzas | M92: =IFERROR(INDEX(Diccionario!$N:$N,MATCH(F52,Diccionario!$C:$C,0)),"")
A93: 2025-05 | B93: Colombia | C93: Coco Colombia | D93: COP | E93: Real | F93: mrr_final | I93: 780829403 | J93: COP | L93: Finanzas | M93: =IFERROR(INDEX(Diccionario!$N:$N,MATCH(F1152,Diccionario!$C:$C,0)),"")
A94: 2025-05 | B94: Colombia | C94: Coco Colombia | D94: COP | E94: Real | F94: utilidad_neta | I94: -13000000 | J94: COP | K94: Derivado: ingresos - egresos | L94: Finanzas | M94: =IFERROR(INDEX(Diccionario!$N:$N,MATCH(F54,Diccionario!$C:$C,0)),"")
A95: 2025-06 | B95: Colombia | C95: Coco Colombia | D95: COP | E95: Real | F95: ebitda | I95: 154028000 | J95: COP | L95: Finanzas | M95: =IFERROR(INDEX(Diccionario!$N:$N,MATCH(F91,Diccionario!$C:$C,0)),"")
A96: 2025-06 | B96: Colombia | C96: Coco Colombia | D96: COP | E96: Real | F96: egresos_totales | I96: 636000000 | J96: COP | L96: Finanzas | M96: =IFERROR(INDEX(Diccionario!$N:$N,MATCH(F56,Diccionario!$C:$C,0)),"")
A97: 2025-06 | B97: Colombia | C97: Coco Colombia | D97: COP | E97: Real | F97: ingresos_no_recurrentes | I97: 21130000 | J97: COP | L97: Finanzas | M97: =IFERROR(INDEX(Diccionario!$N:$N,MATCH(F1072,Diccionario!$C:$C,0)),"")
A98: 2025-06 | B98: Colombia | C98: Coco Colombia | D98: COP | E98: Real | F98: ingresos_recurrentes | I98: 589403143 | J98: COP | L98: Finanzas | M98: =IFERROR(INDEX(Diccionario!$N:$N,MATCH(F1043,Diccionario!$C:$C,0)),"")
A99: 2025-06 | B99: Colombia | C99: Coco Colombia | D99: COP | E99: Real | F99: ingresos_totales | I99: 610000000 | J99: COP | L99: Finanzas | M99: =IFERROR(INDEX(Diccionario!$N:$N,MATCH(F55,Diccionario!$C:$C,0)),"")
A100: 2025-06 | B100: Colombia | C100: Coco Colombia | D100: COP | E100: Real | F100: mrr_final | I100: 689843197 | J100: COP | L100: Finanzas | M100: =IFERROR(INDEX(Diccionario!$N:$N,MATCH(F1153,Diccionario!$C:$C,0)),"")
A101: 2025-06 | B101: Colombia | C101: Coco Colombia | D101: COP | E101: Real | F101: utilidad_neta | I101: -26000000 | J101: COP | K101: Derivado: ingresos - egresos | L101: Finanzas | M101: =IFERROR(INDEX(Diccionario!$N:$N,MATCH(F57,Diccionario!$C:$C,0)),"")
...

Sheet Contabilidad
A1: Contabilidad — vista de solo lectura
A2: Regenerada desde BD_Indicadores el 2026-07-13 · 1030 filas · Editar en BD_Indicadores.
A4: periodo | B4: pais | C4: compania | D4: moneda | E4: escenario | F4: codigo_indicador | G4: segmento | H4: detalle | I4: valor | J4: unidad | K4: comentario | L4: area_responsable | M4: periodicidad
A5: 2024-01 | B5: Colombia | C5: Coco Colombia | D5: COP | E5: Real | F5: costo_operacion | H5: Honorario | I5: 7000000 | J5: COP | L5: Contabilidad | M5: =IFERROR(INDEX(Diccionario!$N:$N,MATCH(F597,Diccionario!$C:$C,0)),"")
A6: 2024-01 | B6: Colombia | C6: Coco Colombia | D6: COP | E6: Real | F6: costo_operacion | H6: Personal | I6: 44000000 | J6: COP | L6: Contabilidad | M6: =IFERROR(INDEX(Diccionario!$N:$N,MATCH(F596,Diccionario!$C:$C,0)),"")
A7: 2024-01 | B7: Colombia | C7: Coco Colombia | D7: COP | E7: Real | F7: costo_operacion | H7: Servicios | I7: 5000000 | J7: COP | L7: Contabilidad | M7: =IFERROR(INDEX(Diccionario!$N:$N,MATCH(F598,Diccionario!$C:$C,0)),"")
A8: 2024-01 | B8: Colombia | C8: Coco Colombia | D8: COP | E8: Real | F8: costo_proveedor | H8: AWS | I8: 25000000 | J8: COP | L8: Contabilidad | M8: =IFERROR(INDEX(Diccionario!$N:$N,MATCH(F458,Diccionario!$C:$C,0)),"")
A9: 2024-01 | B9: Colombia | C9: Coco Colombia | D9: COP | E9: Real | F9: costo_proveedor | H9: B2Chat | I9: 1000000 | J9: COP | L9: Contabilidad | M9: =IFERROR(INDEX(Diccionario!$N:$N,MATCH(F459,Diccionario!$C:$C,0)),"")
A10: 2024-01 | B10: Colombia | C10: Coco Colombia | D10: COP | E10: Real | F10: costo_proveedor | H10: IVA | I10: 0 | J10: COP | L10: Contabilidad | M10: =IFERROR(INDEX(Diccionario!$N:$N,MATCH(F457,Diccionario!$C:$C,0)),"")
A11: 2024-01 | B11: Colombia | C11: Coco Colombia | D11: COP | E11: Real | F11: costo_proveedor | H11: Infobip | I11: 85000000 | J11: COP | L11: Contabilidad | M11: =IFERROR(INDEX(Diccionario!$N:$N,MATCH(F456,Diccionario!$C:$C,0)),"")
A12: 2024-01 | B12: Colombia | C12: Coco Colombia | D12: COP | E12: Real | F12: costo_proveedor | H12: Otros | I12: 22000000 | J12: COP | L12: Contabilidad | M12: =IFERROR(INDEX(Diccionario!$N:$N,MATCH(F460,Diccionario!$C:$C,0)),"")
A13: 2024-01 | B13: Colombia | C13: Coco Colombia | D13: COP | E13: Real | F13: gasto_admin | H13: Arrendamiento | I13: 22000000 | J13: COP | L13: Contabilidad | M13: =IFERROR(INDEX(Diccionario!$N:$N,MATCH(F256,Diccionario!$C:$C,0)),"")
A14: 2024-01 | B14: Colombia | C14: Coco Colombia | D14: COP | E14: Real | F14: gasto_admin | H14: Diversos | I14: 3000000 | J14: COP | L14: Contabilidad | M14: =IFERROR(INDEX(Diccionario!$N:$N,MATCH(F260,Diccionario!$C:$C,0)),"")
A15: 2024-01 | B15: Colombia | C15: Coco Colombia | D15: COP | E15: Real | F15: gasto_admin | H15: Honorarios | I15: 14000000 | J15: COP | L15: Contabilidad | M15: =IFERROR(INDEX(Diccionario!$N:$N,MATCH(F255,Diccionario!$C:$C,0)),"")
A16: 2024-01 | B16: Colombia | C16: Coco Colombia | D16: COP | E16: Real | F16: gasto_admin | H16: Personal | I16: 43000000 | J16: COP | L16: Contabilidad | M16: =IFERROR(INDEX(Diccionario!$N:$N,MATCH(F254,Diccionario!$C:$C,0)),"")
A17: 2024-01 | B17: Colombia | C17: Coco Colombia | D17: COP | E17: Real | F17: gasto_admin | H17: Seguros | I17: 3000000 | J17: COP | L17: Contabilidad | M17: =IFERROR(INDEX(Diccionario!$N:$N,MATCH(F257,Diccionario!$C:$C,0)),"")
A18: 2024-01 | B18: Colombia | C18: Coco Colombia | D18: COP | E18: Real | F18: gasto_admin | H18: Servicios | I18: 6000000 | J18: COP | L18: Contabilidad | M18: =IFERROR(INDEX(Diccionario!$N:$N,MATCH(F258,Diccionario!$C:$C,0)),"")
A19: 2024-01 | B19: Colombia | C19: Coco Colombia | D19: COP | E19: Real | F19: gasto_admin | H19: Viajes | I19: 20000000 | J19: COP | L19: Contabilidad | M19: =IFERROR(INDEX(Diccionario!$N:$N,MATCH(F259,Diccionario!$C:$C,0)),"")
A20: 2024-01 | B20: Colombia | C20: Coco Colombia | D20: COP | E20: Real | F20: gasto_area | H20: Administración | I20: 109000000 | J20: COP | L20: Contabilidad | M20: =IFERROR(INDEX(Diccionario!$N:$N,MATCH(F118,Diccionario!$C:$C,0)),"")
A21: 2024-01 | B21: Colombia | C21: Coco Colombia | D21: COP | E21: Real | F21: gasto_area | H21: Comercial | I21: 125000000 | J21: COP | L21: Contabilidad | M21: =IFERROR(INDEX(Diccionario!$N:$N,MATCH(F117,Diccionario!$C:$C,0)),"")
A22: 2024-01 | B22: Colombia | C22: Coco Colombia | D22: COP | E22: Real | F22: gasto_area | H22: Financieros | I22: 3000000 | J22: COP | L22: Contabilidad | M22: =IFERROR(INDEX(Diccionario!$N:$N,MATCH(F114,Diccionario!$C:$C,0)),"")
A23: 2024-01 | B23: Colombia | C23: Coco Colombia | D23: COP | E23: Real | F23: gasto_area | H23: Proveedores | I23: 133000000 | J23: COP | L23: Contabilidad | M23: =IFERROR(INDEX(Diccionario!$N:$N,MATCH(F116,Diccionario!$C:$C,0)),"")
A24: 2024-01 | B24: Colombia | C24: Coco Colombia | D24: COP | E24: Real | F24: gasto_area | H24: TI | I24: 175000000 | J24: COP | L24: Contabilidad | M24: =IFERROR(INDEX(Diccionario!$N:$N,MATCH(F115,Diccionario!$C:$C,0)),"")
A25: 2024-01 | B25: Colombia | C25: Coco Colombia | D25: COP | E25: Real | F25: gasto_comercial | H25: Diversos | I25: 6000000 | J25: COP | L25: Contabilidad | M25: =IFERROR(INDEX(Diccionario!$N:$N,MATCH(F833,Diccionario!$C:$C,0)),"")
A26: 2024-01 | B26: Colombia | C26: Coco Colombia | D26: COP | E26: Real | F26: gasto_comercial | H26: Honorario | I26: 6000000 | J26: COP | L26: Contabilidad | M26: =IFERROR(INDEX(Diccionario!$N:$N,MATCH(F829,Diccionario!$C:$C,0)),"")
A27: 2024-01 | B27: Colombia | C27: Coco Colombia | D27: COP | E27: Real | F27: gasto_comercial | H27: Personal | I27: 85000000 | J27: COP | L27: Contabilidad | M27: =IFERROR(INDEX(Diccionario!$N:$N,MATCH(F828,Diccionario!$C:$C,0)),"")
A28: 2024-01 | B28: Colombia | C28: Coco Colombia | D28: COP | E28: Real | F28: gasto_comercial | H28: Seguros | I28: 3000000 | J28: COP | L28: Contabilidad | M28: =IFERROR(INDEX(Diccionario!$N:$N,MATCH(F830,Diccionario!$C:$C,0)),"")
A29: 2024-01 | B29: Colombia | C29: Coco Colombia | D29: COP | E29: Real | F29: gasto_comercial | H29: Servicios | I29: 17000000 | J29: COP | L29: Contabilidad | M29: =IFERROR(INDEX(Diccionario!$N:$N,MATCH(F831,Diccionario!$C:$C,0)),"")
A30: 2024-01 | B30: Colombia | C30: Coco Colombia | D30: COP | E30: Real | F30: gasto_comercial | H30: Viajes | I30: 10000000 | J30: COP | L30: Contabilidad | M30: =IFERROR(INDEX(Diccionario!$N:$N,MATCH(F832,Diccionario!$C:$C,0)),"")
A31: 2024-01 | B31: Colombia | C31: Coco Colombia | D31: COP | E31: Real | F31: gasto_desarrollo | H31: Honorarios | I31: 6000000 | J31: COP | L31: Contabilidad | M31: =IFERROR(INDEX(Diccionario!$N:$N,MATCH(F717,Diccionario!$C:$C,0)),"")
A32: 2024-01 | B32: Colombia | C32: Coco Colombia | D32: COP | E32: Real | F32: gasto_desarrollo | H32: Personal | I32: 102000000 | J32: COP | L32: Contabilidad | M32: =IFERROR(INDEX(Diccionario!$N:$N,MATCH(F716,Diccionario!$C:$C,0)),"")
A33: 2024-01 | B33: Colombia | C33: Coco Colombia | D33: COP | E33: Real | F33: gasto_desarrollo | H33: Servicios | I33: 9000000 | J33: COP | L33: Contabilidad | M33: =IFERROR(INDEX(Diccionario!$N:$N,MATCH(F718,Diccionario!$C:$C,0)),"")
A34: 2024-01 | B34: Colombia | C34: Coco Colombia | D34: COP | E34: Real | F34: gasto_desarrollo | H34: Viajes | I34: 1000000 | J34: COP | L34: Contabilidad | M34: =IFERROR(INDEX(Diccionario!$N:$N,MATCH(F719,Diccionario!$C:$C,0)),"")
A35: 2024-02 | B35: Colombia | C35: Coco Colombia | D35: COP | E35: Real | F35: costo_operacion | H35: Honorario | I35: 0 | J35: COP | L35: Contabilidad | M35: =IFERROR(INDEX(Diccionario!$N:$N,MATCH(F600,Diccionario!$C:$C,0)),"")
A36: 2024-02 | B36: Colombia | C36: Coco Colombia | D36: COP | E36: Real | F36: costo_operacion | H36: Personal | I36: 45000000 | J36: COP | L36: Contabilidad | M36: =IFERROR(INDEX(Diccionario!$N:$N,MATCH(F599,Diccionario!$C:$C,0)),"")
A37: 2024-02 | B37: Colombia | C37: Coco Colombia | D37: COP | E37: Real | F37: costo_operacion | H37: Servicios | I37: 6000000 | J37: COP | L37: Contabilidad | M37: =IFERROR(INDEX(Diccionario!$N:$N,MATCH(F601,Diccionario!$C:$C,0)),"")
A38: 2024-02 | B38: Colombia | C38: Coco Colombia | D38: COP | E38: Real | F38: costo_proveedor | H38: AWS | I38: 17000000 | J38: COP | L38: Contabilidad | M38: =IFERROR(INDEX(Diccionario!$N:$N,MATCH(F463,Diccionario!$C:$C,0)),"")
A39: 2024-02 | B39: Colombia | C39: Coco Colombia | D39: COP | E39: Real | F39: costo_proveedor | H39: B2Chat | I39: 1000000 | J39: COP | L39: Contabilidad | M39: =IFERROR(INDEX(Diccionario!$N:$N,MATCH(F464,Diccionario!$C:$C,0)),"")
A40: 2024-02 | B40: Colombia | C40: Coco Colombia | D40: COP | E40: Real | F40: costo_proveedor | H40: IVA | I40: 0 | J40: COP | L40: Contabilidad | M40: =IFERROR(INDEX(Diccionario!$N:$N,MATCH(F462,Diccionario!$C:$C,0)),"")
A41: 2024-02 | B41: Colombia | C41: Coco Colombia | D41: COP | E41: Real | F41: costo_proveedor | H41: Infobip | I41: 92000000 | J41: COP | L41: Contabilidad | M41: =IFERROR(INDEX(Diccionario!$N:$N,MATCH(F461,Diccionario!$C:$C,0)),"")
A42: 2024-02 | B42: Colombia | C42: Coco Colombia | D42: COP | E42: Real | F42: costo_proveedor | H42: Otros | I42: 5000000 | J42: COP | L42: Contabilidad | M42: =IFERROR(INDEX(Diccionario!$N:$N,MATCH(F465,Diccionario!$C:$C,0)),"")
A43: 2024-02 | B43: Colombia | C43: Coco Colombia | D43: COP | E43: Real | F43: gasto_admin | H43: Arrendamiento | I43: 22000000 | J43: COP | L43: Contabilidad | M43: =IFERROR(INDEX(Diccionario!$N:$N,MATCH(F263,Diccionario!$C:$C,0)),"")
A44: 2024-02 | B44: Colombia | C44: Coco Colombia | D44: COP | E44: Real | F44: gasto_admin | H44: Diversos | I44: 2000000 | J44: COP | L44: Contabilidad | M44: =IFERROR(INDEX(Diccionario!$N:$N,MATCH(F267,Diccionario!$C:$C,0)),"")
A45: 2024-02 | B45: Colombia | C45: Coco Colombia | D45: COP | E45: Real | F45: gasto_admin | H45: Honorarios | I45: 16000000 | J45: COP | L45: Contabilidad | M45: =IFERROR(INDEX(Diccionario!$N:$N,MATCH(F262,Diccionario!$C:$C,0)),"")
A46: 2024-02 | B46: Colombia | C46: Coco Colombia | D46: COP | E46: Real | F46: gasto_admin | H46: Personal | I46: 44000000 | J46: COP | L46: Contabilidad | M46: =IFERROR(INDEX(Diccionario!$N:$N,MATCH(F261,Diccionario!$C:$C,0)),"")
A47: 2024-02 | B47: Colombia | C47: Coco Colombia | D47: COP | E47: Real | F47: gasto_admin | H47: Seguros | I47: 2000000 | J47: COP | L47: Contabilidad | M47: =IFERROR(INDEX(Diccionario!$N:$N,MATCH(F264,Diccionario!$C:$C,0)),"")
A48: 2024-02 | B48: Colombia | C48: Coco Colombia | D48: COP | E48: Real | F48: gasto_admin | H48: Servicios | I48: 6000000 | J48: COP | L48: Contabilidad | M48: =IFERROR(INDEX(Diccionario!$N:$N,MATCH(F265,Diccionario!$C:$C,0)),"")
A49: 2024-02 | B49: Colombia | C49: Coco Colombia | D49: COP | E49: Real | F49: gasto_admin | H49: Viajes | I49: 24000000 | J49: COP | L49: Contabilidad | M49: =IFERROR(INDEX(Diccionario!$N:$N,MATCH(F266,Diccionario!$C:$C,0)),"")
A50: 2024-02 | B50: Colombia | C50: Coco Colombia | D50: COP | E50: Real | F50: gasto_area | H50: Administración | I50: 124000000 | J50: COP | L50: Contabilidad | M50: =IFERROR(INDEX(Diccionario!$N:$N,MATCH(F123,Diccionario!$C:$C,0)),"")
A51: 2024-02 | B51: Colombia | C51: Coco Colombia | D51: COP | E51: Real | F51: gasto_area | H51: Comercial | I51: 112000000 | J51: COP | L51: Contabilidad | M51: =IFERROR(INDEX(Diccionario!$N:$N,MATCH(F122,Diccionario!$C:$C,0)),"")
A52: 2024-02 | B52: Colombia | C52: Coco Colombia | D52: COP | E52: Real | F52: gasto_area | H52: Financieros | I52: 3000000 | J52: COP | L52: Contabilidad | M52: =IFERROR(INDEX(Diccionario!$N:$N,MATCH(F119,Diccionario!$C:$C,0)),"")
A53: 2024-02 | B53: Colombia | C53: Coco Colombia | D53: COP | E53: Real | F53: gasto_area | H53: Proveedores | I53: 115000000 | J53: COP | L53: Contabilidad | M53: =IFERROR(INDEX(Diccionario!$N:$N,MATCH(F121,Diccionario!$C:$C,0)),"")
A54: 2024-02 | B54: Colombia | C54: Coco Colombia | D54: COP | E54: Real | F54: gasto_area | H54: TI | I54: 161000000 | J54: COP | L54: Contabilidad | M54: =IFERROR(INDEX(Diccionario!$N:$N,MATCH(F120,Diccionario!$C:$C,0)),"")
A55: 2024-02 | B55: Colombia | C55: Coco Colombia | D55: COP | E55: Real | F55: gasto_comercial | H55: Diversos | I55: 3000000 | J55: COP | L55: Contabilidad | M55: =IFERROR(INDEX(Diccionario!$N:$N,MATCH(F839,Diccionario!$C:$C,0)),"")
A56: 2024-02 | B56: Colombia | C56: Coco Colombia | D56: COP | E56: Real | F56: gasto_comercial | H56: Honorario | I56: 3000000 | J56: COP | L56: Contabilidad | M56: =IFERROR(INDEX(Diccionario!$N:$N,MATCH(F835,Diccionario!$C:$C,0)),"")
A57: 2024-02 | B57: Colombia | C57: Coco Colombia | D57: COP | E57: Real | F57: gasto_comercial | H57: Personal | I57: 83000000 | J57: COP | L57: Contabilidad | M57: =IFERROR(INDEX(Diccionario!$N:$N,MATCH(F834,Diccionario!$C:$C,0)),"")
A58: 2024-02 | B58: Colombia | C58: Coco Colombia | D58: COP | E58: Real | F58: gasto_comercial | H58: Seguros | I58: 2000000 | J58: COP | L58: Contabilidad | M58: =IFERROR(INDEX(Diccionario!$N:$N,MATCH(F836,Diccionario!$C:$C,0)),"")
A59: 2024-02 | B59: Colombia | C59: Coco Colombia | D59: COP | E59: Real | F59: gasto_comercial | H59: Servicios | I59: 11000000 | J59: COP | L59: Contabilidad | M59: =IFERROR(INDEX(Diccionario!$N:$N,MATCH(F837,Diccionario!$C:$C,0)),"")
A60: 2024-02 | B60: Colombia | C60: Coco Colombia | D60: COP | E60: Real | F60: gasto_comercial | H60: Viajes | I60: 10000000 | J60: COP | L60: Contabilidad | M60: =IFERROR(INDEX(Diccionario!$N:$N,MATCH(F838,Diccionario!$C:$C,0)),"")
A61: 2024-02 | B61: Colombia | C61: Coco Colombia | D61: COP | E61: Real | F61: gasto_desarrollo | H61: Honorarios | I61: 6000000 | J61: COP | L61: Contabilidad | M61: =IFERROR(INDEX(Diccionario!$N:$N,MATCH(F721,Diccionario!$C:$C,0)),"")
A62: 2024-02 | B62: Colombia | C62: Coco Colombia | D62: COP | E62: Real | F62: gasto_desarrollo | H62: Personal | I62: 99000000 | J62: COP | L62: Contabilidad | M62: =IFERROR(INDEX(Diccionario!$N:$N,MATCH(F720,Diccionario!$C:$C,0)),"")
A63: 2024-02 | B63: Colombia | C63: Coco Colombia | D63: COP | E63: Real | F63: gasto_desarrollo | H63: Servicios | I63: 2000000 | J63: COP | L63: Contabilidad | M63: =IFERROR(INDEX(Diccionario!$N:$N,MATCH(F722,Diccionario!$C:$C,0)),"")
A64: 2024-02 | B64: Colombia | C64: Coco Colombia | D64: COP | E64: Real | F64: gasto_desarrollo | H64: Viajes | I64: 0 | J64: COP | L64: Contabilidad | M64: =IFERROR(INDEX(Diccionario!$N:$N,MATCH(F723,Diccionario!$C:$C,0)),"")
A65: 2024-03 | B65: Colombia | C65: Coco Colombia | D65: COP | E65: Real | F65: costo_operacion | H65: Honorario | I65: 1000000 | J65: COP | L65: Contabilidad | M65: =IFERROR(INDEX(Diccionario!$N:$N,MATCH(F603,Diccionario!$C:$C,0)),"")
A66: 2024-03 | B66: Colombia | C66: Coco Colombia | D66: COP | E66: Real | F66: costo_operacion | H66: Personal | I66: 54000000 | J66: COP | L66: Contabilidad | M66: =IFERROR(INDEX(Diccionario!$N:$N,MATCH(F602,Diccionario!$C:$C,0)),"")
A67: 2024-03 | B67: Colombia | C67: Coco Colombia | D67: COP | E67: Real | F67: costo_operacion | H67: Servicios | I67: 4000000 | J67: COP | L67: Contabilidad | M67: =IFERROR(INDEX(Diccionario!$N:$N,MATCH(F604,Diccionario!$C:$C,0)),"")
A68: 2024-03 | B68: Colombia | C68: Coco Colombia | D68: COP | E68: Real | F68: costo_proveedor | H68: AWS | I68: 21000000 | J68: COP | L68: Contabilidad | M68: =IFERROR(INDEX(Diccionario!$N:$N,MATCH(F468,Diccionario!$C:$C,0)),"")
A69: 2024-03 | B69: Colombia | C69: Coco Colombia | D69: COP | E69: Real | F69: costo_proveedor | H69: B2Chat | I69: 3000000 | J69: COP | L69: Contabilidad | M69: =IFERROR(INDEX(Diccionario!$N:$N,MATCH(F469,Diccionario!$C:$C,0)),"")
A70: 2024-03 | B70: Colombia | C70: Coco Colombia | D70: COP | E70: Real | F70: costo_proveedor | H70: IVA | I70: 0 | J70: COP | L70: Contabilidad | M70: =IFERROR(INDEX(Diccionario!$N:$N,MATCH(F467,Diccionario!$C:$C,0)),"")
A71: 2024-03 | B71: Colombia | C71: Coco Colombia | D71: COP | E71: Real | F71: costo_proveedor | H71: Infobip | I71: 110000000 | J71: COP | L71: Contabilidad | M71: =IFERROR(INDEX(Diccionario!$N:$N,MATCH(F466,Diccionario!$C:$C,0)),"")
A72: 2024-03 | B72: Colombia | C72: Coco Colombia | D72: COP | E72: Real | F72: costo_proveedor | H72: Otros | I72: 5000000 | J72: COP | L72: Contabilidad | M72: =IFERROR(INDEX(Diccionario!$N:$N,MATCH(F470,Diccionario!$C:$C,0)),"")
A73: 2024-03 | B73: Colombia | C73: Coco Colombia | D73: COP | E73: Real | F73: gasto_admin | H73: Arrendamiento | I73: 19000000 | J73: COP | L73: Contabilidad | M73: =IFERROR(INDEX(Diccionario!$N:$N,MATCH(F270,Diccionario!$C:$C,0)),"")
A74: 2024-03 | B74: Colombia | C74: Coco Colombia | D74: COP | E74: Real | F74: gasto_admin | H74: Diversos | I74: 6000000 | J74: COP | L74: Contabilidad | M74: =IFERROR(INDEX(Diccionario!$N:$N,MATCH(F274,Diccionario!$C:$C,0)),"")
A75: 2024-03 | B75: Colombia | C75: Coco Colombia | D75: COP | E75: Real | F75: gasto_admin | H75: Honorarios | I75: 18000000 | J75: COP | L75: Contabilidad | M75: =IFERROR(INDEX(Diccionario!$N:$N,MATCH(F269,Diccionario!$C:$C,0)),"")
A76: 2024-03 | B76: Colombia | C76: Coco Colombia | D76: COP | E76: Real | F76: gasto_admin | H76: Personal | I76: 69000000 | J76: COP | L76: Contabilidad | M76: =IFERROR(INDEX(Diccionario!$N:$N,MATCH(F268,Diccionario!$C:$C,0)),"")
A77: 2024-03 | B77: Colombia | C77: Coco Colombia | D77: COP | E77: Real | F77: gasto_admin | H77: Seguros | I77: 2000000 | J77: COP | L77: Contabilidad | M77: =IFERROR(INDEX(Diccionario!$N:$N,MATCH(F271,Diccionario!$C:$C,0)),"")
A78: 2024-03 | B78: Colombia | C78: Coco Colombia | D78: COP | E78: Real | F78: gasto_admin | H78: Servicios | I78: 1000000 | J78: COP | L78: Contabilidad | M78: =IFERROR(INDEX(Diccionario!$N:$N,MATCH(F272,Diccionario!$C:$C,0)),"")
A79: 2024-03 | B79: Colombia | C79: Coco Colombia | D79: COP | E79: Real | F79: gasto_admin | H79: Viajes | I79: 7000000 | J79: COP | L79: Contabilidad | M79: =IFERROR(INDEX(Diccionario!$N:$N,MATCH(F273,Diccionario!$C:$C,0)),"")
A80: 2024-03 | B80: Colombia | C80: Coco Colombia | D80: COP | E80: Real | F80: gasto_area | H80: Administración | I80: 125000000 | J80: COP | L80: Contabilidad | M80: =IFERROR(INDEX(Diccionario!$N:$N,MATCH(F128,Diccionario!$C:$C,0)),"")
A81: 2024-03 | B81: Colombia | C81: Coco Colombia | D81: COP | E81: Real | F81: gasto_area | H81: Comercial | I81: 132000000 | J81: COP | L81: Contabilidad | M81: =IFERROR(INDEX(Diccionario!$N:$N,MATCH(F127,Diccionario!$C:$C,0)),"")
A82: 2024-03 | B82: Colombia | C82: Coco Colombia | D82: COP | E82: Real | F82: gasto_area | H82: Financieros | I82: 3000000 | J82: COP | L82: Contabilidad | M82: =IFERROR(INDEX(Diccionario!$N:$N,MATCH(F124,Diccionario!$C:$C,0)),"")
A83: 2024-03 | B83: Colombia | C83: Coco Colombia | D83: COP | E83: Real | F83: gasto_area | H83: Proveedores | I83: 130000000 | J83: COP | L83: Contabilidad | M83: =IFERROR(INDEX(Diccionario!$N:$N,MATCH(F126,Diccionario!$C:$C,0)),"")
A84: 2024-03 | B84: Colombia | C84: Coco Colombia | D84: COP | E84: Real | F84: gasto_area | H84: TI | I84: 175000000 | J84: COP | L84: Contabilidad | M84: =IFERROR(INDEX(Diccionario!$N:$N,MATCH(F125,Diccionario!$C:$C,0)),"")
A85: 2024-03 | B85: Colombia | C85: Coco Colombia | D85: COP | E85: Real | F85: gasto_comercial | H85: Diversos | I85: 2000000 | J85: COP | L85: Contabilidad | M85: =IFERROR(INDEX(Diccionario!$N:$N,MATCH(F844,Diccionario!$C:$C,0)),"")
A86: 2024-03 | B86: Colombia | C86: Coco Colombia | D86: COP | E86: Real | F86: gasto_comercial | H86: Honorario | I86: 6000000 | J86: COP | L86: Contabilidad | M86: =IFERROR(INDEX(Diccionario!$N:$N,MATCH(F841,Diccionario!$C:$C,0)),"")
A87: 2024-03 | B87: Colombia | C87: Coco Colombia | D87: COP | E87: Real | F87: gasto_comercial | H87: Personal | I87: 63000000 | J87: COP | L87: Contabilidad | M87: =IFERROR(INDEX(Diccionario!$N:$N,MATCH(F840,Diccionario!$C:$C,0)),"")
A88: 2024-03 | B88: Colombia | C88: Coco Colombia | D88: COP | E88: Real | F88: gasto_comercial | H88: Seguros | I88: 1000000 | J88: COP | L88: Contabilidad | M88: =IFERROR(INDEX(Diccionario!$N:$N,MATCH(F842,Diccionario!$C:$C,0)),"")
A89: 2024-03 | B89: Colombia | C89: Coco Colombia | D89: COP | E89: Real | F89: gasto_comercial | H89: Servicios | I89: 46000000 | J89: COP | L89: Contabilidad | M89: =IFERROR(INDEX(Diccionario!$N:$N,MATCH(F843,Diccionario!$C:$C,0)),"")
A90: 2024-03 | B90: Colombia | C90: Coco Colombia | D90: COP | E90: Real | F90: gasto_desarrollo | H90: Honorarios | I90: 12000000 | J90: COP | L90: Contabilidad | M90: =IFERROR(INDEX(Diccionario!$N:$N,MATCH(F725,Diccionario!$C:$C,0)),"")
A91: 2024-03 | B91: Colombia | C91: Coco Colombia | D91: COP | E91: Real | F91: gasto_desarrollo | H91: Personal | I91: 103000000 | J91: COP | L91: Contabilidad | M91: =IFERROR(INDEX(Diccionario!$N:$N,MATCH(F724,Diccionario!$C:$C,0)),"")
A92: 2024-03 | B92: Colombia | C92: Coco Colombia | D92: COP | E92: Real | F92: gasto_desarrollo | H92: Servicios | I92: 0 | J92: COP | L92: Contabilidad | M92: =IFERROR(INDEX(Diccionario!$N:$N,MATCH(F726,Diccionario!$C:$C,0)),"")
A93: 2024-03 | B93: Colombia | C93: Coco Colombia | D93: COP | E93: Real | F93: gasto_desarrollo | H93: Viajes | I93: 0 | J93: COP | L93: Contabilidad | M93: =IFERROR(INDEX(Diccionario!$N:$N,MATCH(F727,Diccionario!$C:$C,0)),"")
A94: 2024-04 | B94: Colombia | C94: Coco Colombia | D94: COP | E94: Real | F94: costo_operacion | H94: Honorario | I94: 1000000 | J94: COP | L94: Contabilidad | M94: =IFERROR(INDEX(Diccionario!$N:$N,MATCH(F606,Diccionario!$C:$C,0)),"")
A95: 2024-04 | B95: Colombia | C95: Coco Colombia | D95: COP | E95: Real | F95: costo_operacion | H95: Personal | I95: 46000000 | J95: COP | L95: Contabilidad | M95: =IFERROR(INDEX(Diccionario!$N:$N,MATCH(F605,Diccionario!$C:$C,0)),"")
A96: 2024-04 | B96: Colombia | C96: Coco Colombia | D96: COP | E96: Real | F96: costo_operacion | H96: Servicios | I96: 3000000 | J96: COP | L96: Contabilidad | M96: =IFERROR(INDEX(Diccionario!$N:$N,MATCH(F607,Diccionario!$C:$C,0)),"")
A97: 2024-04 | B97: Colombia | C97: Coco Colombia | D97: COP | E97: Real | F97: costo_proveedor | H97: AWS | I97: 18000000 | J97: COP | L97: Contabilidad | M97: =IFERROR(INDEX(Diccionario!$N:$N,MATCH(F473,Diccionario!$C:$C,0)),"")
A98: 2024-04 | B98: Colombia | C98: Coco Colombia | D98: COP | E98: Real | F98: costo_proveedor | H98: B2Chat | I98: 2000000 | J98: COP | L98: Contabilidad | M98: =IFERROR(INDEX(Diccionario!$N:$N,MATCH(F474,Diccionario!$C:$C,0)),"")
A99: 2024-04 | B99: Colombia | C99: Coco Colombia | D99: COP | E99: Real | F99: costo_proveedor | H99: IVA | I99: 0 | J99: COP | L99: Contabilidad | M99: =IFERROR(INDEX(Diccionario!$N:$N,MATCH(F472,Diccionario!$C:$C,0)),"")
A100: 2024-04 | B100: Colombia | C100: Coco Colombia | D100: COP | E100: Real | F100: costo_proveedor | H100: Infobip | I100: 107000000 | J100: COP | L100: Contabilidad | M100: =IFERROR(INDEX(Diccionario!$N:$N,MATCH(F471,Diccionario!$C:$C,0)),"")
A101: 2024-04 | B101: Colombia | C101: Coco Colombia | D101: COP | E101: Real | F101: costo_proveedor | H101: Otros | I101: 4000000 | J101: COP | L101: Contabilidad | M101: =IFERROR(INDEX(Diccionario!$N:$N,MATCH(F475,Diccionario!$C:$C,0)),"")
...

Sheet SaaS_Revenue
A1: SaaS / Revenue — vista de solo lectura
A2: Regenerada desde BD_Indicadores el 2026-07-13 · 2 filas · Editar en BD_Indicadores.
A4: periodo | B4: pais | C4: compania | D4: moneda | E4: escenario | F4: codigo_indicador | G4: segmento | H4: detalle | I4: valor | J4: unidad | K4: comentario | L4: area_responsable | M4: periodicidad
A5: 2026-05 | B5: Colombia | C5: Coco Colombia | D5: COP | E5: Real | F5: arr | I5: 3706946282 | J5: COP | K5: 'Ventas Totales (ARR)' reportado por contabilidad | L5: Finanzas | M5: =IFERROR(INDEX(Diccionario!$N:$N,MATCH(F103,Diccionario!$C:$C,0)),"")
A6: 2026-06 | B6: Colombia | C6: Coco Colombia | D6: COP | E6: Real | F6: arr | I6: 4480477715 | J6: COP | K6: 'Ventas Totales (ARR)' reportado por contabilidad | L6: Finanzas | M6: Mensual

Sheet Ventas
A1: Ventas — vista de solo lectura
A2: Regenerada desde BD_Indicadores el 2026-07-13 · 60 filas · Editar en BD_Indicadores.
A4: periodo | B4: pais | C4: compania | D4: moneda | E4: escenario | F4: codigo_indicador | G4: segmento | H4: detalle | I4: valor | J4: unidad | K4: comentario | L4: area_responsable | M4: periodicidad
A5: 2025-05 | B5: Colombia | C5: Coco Colombia | E5: Real | F5: distribucion_facturacion_tamano | H5: Grandes | I5: 33.9 | J5: % | L5: Comercial | M5: =IFERROR(INDEX(Diccionario!$N:$N,MATCH(F1173,Diccionario!$C:$C,0)),"")
A6: 2025-05 | B6: Colombia | C6: Coco Colombia | E6: Real | F6: distribucion_facturacion_tamano | H6: Medianos | I6: 51.53 | J6: % | L6: Comercial | M6: =IFERROR(INDEX(Diccionario!$N:$N,MATCH(F1186,Diccionario!$C:$C,0)),"")
A7: 2025-05 | B7: Colombia | C7: Coco Colombia | E7: Real | F7: distribucion_facturacion_tamano | H7: Pequeños | I7: 14.57 | J7: % | L7: Comercial | M7: =IFERROR(INDEX(Diccionario!$N:$N,MATCH(F1199,Diccionario!$C:$C,0)),"")
A8: 2025-06 | B8: Colombia | C8: Coco Colombia | E8: Real | F8: distribucion_facturacion_tamano | H8: Grandes | I8: 40 | J8: % | L8: Comercial | M8: =IFERROR(INDEX(Diccionario!$N:$N,MATCH(F1174,Diccionario!$C:$C,0)),"")
A9: 2025-06 | B9: Colombia | C9: Coco Colombia | E9: Real | F9: distribucion_facturacion_tamano | H9: Medianos | I9: 56 | J9: % | L9: Comercial | M9: =IFERROR(INDEX(Diccionario!$N:$N,MATCH(F1187,Diccionario!$C:$C,0)),"")
A10: 2025-06 | B10: Colombia | C10: Coco Colombia | E10: Real | F10: distribucion_facturacion_tamano | H10: Pequeños | I10: 4 | J10: % | L10: Comercial | M10: =IFERROR(INDEX(Diccionario!$N:$N,MATCH(F1200,Diccionario!$C:$C,0)),"")
A11: 2025-07 | B11: Colombia | C11: Coco Colombia | E11: Real | F11: distribucion_facturacion_tamano | H11: Grandes | I11: 37 | J11: % | L11: Comercial | M11: =IFERROR(INDEX(Diccionario!$N:$N,MATCH(F1175,Diccionario!$C:$C,0)),"")
A12: 2025-07 | B12: Colombia | C12: Coco Colombia | E12: Real | F12: distribucion_facturacion_tamano | H12: Medianos | I12: 59 | J12: % | L12: Comercial | M12: =IFERROR(INDEX(Diccionario!$N:$N,MATCH(F1188,Diccionario!$C:$C,0)),"")
A13: 2025-07 | B13: Colombia | C13: Coco Colombia | E13: Real | F13: distribucion_facturacion_tamano | H13: Pequeños | I13: 4 | J13: % | L13: Comercial | M13: =IFERROR(INDEX(Diccionario!$N:$N,MATCH(F1201,Diccionario!$C:$C,0)),"")
A14: 2025-08 | B14: Colombia | C14: Coco Colombia | E14: Real | F14: distribucion_facturacion_tamano | H14: Grandes | I14: 37 | J14: % | L14: Comercial | M14: =IFERROR(INDEX(Diccionario!$N:$N,MATCH(F1176,Diccionario!$C:$C,0)),"")
A15: 2025-08 | B15: Colombia | C15: Coco Colombia | E15: Real | F15: distribucion_facturacion_tamano | H15: Medianos | I15: 49.6 | J15: % | L15: Comercial | M15: =IFERROR(INDEX(Diccionario!$N:$N,MATCH(F1189,Diccionario!$C:$C,0)),"")
A16: 2025-08 | B16: Colombia | C16: Coco Colombia | E16: Real | F16: distribucion_facturacion_tamano | H16: Pequeños | I16: 13.1 | J16: % | L16: Comercial | M16: =IFERROR(INDEX(Diccionario!$N:$N,MATCH(F1202,Diccionario!$C:$C,0)),"")
A17: 2025-09 | B17: Colombia | C17: Coco Colombia | E17: Real | F17: distribucion_facturacion_tamano | H17: Grandes | I17: 20.9 | J17: % | L17: Comercial | M17: =IFERROR(INDEX(Diccionario!$N:$N,MATCH(F1177,Diccionario!$C:$C,0)),"")
A18: 2025-09 | B18: Colombia | C18: Coco Colombia | E18: Real | F18: distribucion_facturacion_tamano | H18: Medianos | I18: 61.7 | J18: % | L18: Comercial | M18: =IFERROR(INDEX(Diccionario!$N:$N,MATCH(F1190,Diccionario!$C:$C,0)),"")
A19: 2025-09 | B19: Colombia | C19: Coco Colombia | E19: Real | F19: distribucion_facturacion_tamano | H19: Pequeños | I19: 17.37 | J19: % | L19: Comercial | M19: =IFERROR(INDEX(Diccionario!$N:$N,MATCH(F1203,Diccionario!$C:$C,0)),"")
A20: 2025-10 | B20: Colombia | C20: Coco Colombia | E20: Real | F20: distribucion_facturacion_tamano | H20: Grandes | I20: 21 | J20: % | L20: Comercial | M20: =IFERROR(INDEX(Diccionario!$N:$N,MATCH(F1178,Diccionario!$C:$C,0)),"")
A21: 2025-10 | B21: Colombia | C21: Coco Colombia | E21: Real | F21: distribucion_facturacion_tamano | H21: Medianos | I21: 65 | J21: % | L21: Comercial | M21: =IFERROR(INDEX(Diccionario!$N:$N,MATCH(F1191,Diccionario!$C:$C,0)),"")
A22: 2025-10 | B22: Colombia | C22: Coco Colombia | E22: Real | F22: distribucion_facturacion_tamano | H22: Pequeños | I22: 10 | J22: % | L22: Comercial | M22: =IFERROR(INDEX(Diccionario!$N:$N,MATCH(F1204,Diccionario!$C:$C,0)),"")
A23: 2025-11 | B23: Colombia | C23: Coco Colombia | E23: Real | F23: distribucion_facturacion_tamano | H23: Grandes | I23: 28 | J23: % | L23: Comercial | M23: =IFERROR(INDEX(Diccionario!$N:$N,MATCH(F1179,Diccionario!$C:$C,0)),"")
A24: 2025-11 | B24: Colombia | C24: Coco Colombia | E24: Real | F24: distribucion_facturacion_tamano | H24: Medianos | I24: 67 | J24: % | L24: Comercial | M24: =IFERROR(INDEX(Diccionario!$N:$N,MATCH(F1192,Diccionario!$C:$C,0)),"")
A25: 2025-11 | B25: Colombia | C25: Coco Colombia | E25: Real | F25: distribucion_facturacion_tamano | H25: Pequeños | I25: 5 | J25: % | L25: Comercial | M25: =IFERROR(INDEX(Diccionario!$N:$N,MATCH(F1205,Diccionario!$C:$C,0)),"")
A26: 2025-12 | B26: Colombia | C26: Coco Colombia | E26: Real | F26: distribucion_facturacion_tamano | H26: Grandes | I26: 16 | J26: % | L26: Comercial | M26: =IFERROR(INDEX(Diccionario!$N:$N,MATCH(F1180,Diccionario!$C:$C,0)),"")
A27: 2025-12 | B27: Colombia | C27: Coco Colombia | E27: Real | F27: distribucion_facturacion_tamano | H27: Medianos | I27: 77 | J27: % | L27: Comercial | M27: =IFERROR(INDEX(Diccionario!$N:$N,MATCH(F1193,Diccionario!$C:$C,0)),"")
A28: 2025-12 | B28: Colombia | C28: Coco Colombia | E28: Real | F28: distribucion_facturacion_tamano | H28: Pequeños | I28: 7 | J28: % | L28: Comercial | M28: =IFERROR(INDEX(Diccionario!$N:$N,MATCH(F1206,Diccionario!$C:$C,0)),"")
A29: 2026-01 | B29: Colombia | C29: Coco Colombia | E29: Real | F29: distribucion_facturacion_tamano | H29: Grandes | I29: 40 | J29: % | L29: Comercial | M29: =IFERROR(INDEX(Diccionario!$N:$N,MATCH(F1181,Diccionario!$C:$C,0)),"")
A30: 2026-01 | B30: Colombia | C30: Coco Colombia | E30: Real | F30: distribucion_facturacion_tamano | H30: Medianos | I30: 55 | J30: % | L30: Comercial | M30: =IFERROR(INDEX(Diccionario!$N:$N,MATCH(F1194,Diccionario!$C:$C,0)),"")
A31: 2026-01 | B31: Colombia | C31: Coco Colombia | E31: Real | F31: distribucion_facturacion_tamano | H31: Pequeños | I31: 5 | J31: % | L31: Comercial | M31: =IFERROR(INDEX(Diccionario!$N:$N,MATCH(F1207,Diccionario!$C:$C,0)),"")
A32: 2026-02 | B32: Colombia | C32: Coco Colombia | E32: Real | F32: distribucion_facturacion_tamano | H32: Grandes | I32: 25 | J32: % | L32: Comercial | M32: =IFERROR(INDEX(Diccionario!$N:$N,MATCH(F1182,Diccionario!$C:$C,0)),"")
A33: 2026-02 | B33: Colombia | C33: Coco Colombia | E33: Real | F33: distribucion_facturacion_tamano | H33: Medianos | I33: 64 | J33: % | L33: Comercial | M33: =IFERROR(INDEX(Diccionario!$N:$N,MATCH(F1195,Diccionario!$C:$C,0)),"")
A34: 2026-02 | B34: Colombia | C34: Coco Colombia | E34: Real | F34: distribucion_facturacion_tamano | H34: Pequeños | I34: 11 | J34: % | L34: Comercial | M34: =IFERROR(INDEX(Diccionario!$N:$N,MATCH(F1208,Diccionario!$C:$C,0)),"")
A35: 2026-02 | B35: Colombia | C35: Coco Colombia | D35: COP | E35: Real | F35: forecast_comercial | I35: 9022720 | J35: COP | K35: Insumo Comercial jul-2026 · oport. con cierre esperado en el mes | L35: Ventas | M35: =IFERROR(INDEX(Diccionario!$N:$N,MATCH(F1289,Diccionario!$C:$C,0)),"")
A36: 2026-03 | B36: Colombia | C36: Coco Colombia | E36: Real | F36: distribucion_facturacion_tamano | H36: Grandes | I36: 23 | J36: % | L36: Comercial | M36: =IFERROR(INDEX(Diccionario!$N:$N,MATCH(F1183,Diccionario!$C:$C,0)),"")
A37: 2026-03 | B37: Colombia | C37: Coco Colombia | E37: Real | F37: distribucion_facturacion_tamano | H37: Medianos | I37: 65 | J37: % | L37: Comercial | M37: =IFERROR(INDEX(Diccionario!$N:$N,MATCH(F1196,Diccionario!$C:$C,0)),"")
A38: 2026-03 | B38: Colombia | C38: Coco Colombia | E38: Real | F38: distribucion_facturacion_tamano | H38: Pequeños | I38: 12 | J38: % | L38: Comercial | M38: =IFERROR(INDEX(Diccionario!$N:$N,MATCH(F1209,Diccionario!$C:$C,0)),"")
A39: 2026-03 | B39: Colombia | C39: Coco Colombia | D39: COP | E39: Real | F39: forecast_comercial | I39: 270528826 | J39: COP | K39: Insumo Comercial jul-2026 · oport. con cierre esperado en el mes | L39: Ventas | M39: =IFERROR(INDEX(Diccionario!$N:$N,MATCH(F1290,Diccionario!$C:$C,0)),"")
A40: 2026-04 | B40: Colombia | C40: Coco Colombia | E40: Real | F40: distribucion_facturacion_tamano | H40: Grandes | I40: 27 | J40: % | L40: Comercial | M40: =IFERROR(INDEX(Diccionario!$N:$N,MATCH(F1184,Diccionario!$C:$C,0)),"")
A41: 2026-04 | B41: Colombia | C41: Coco Colombia | E41: Real | F41: distribucion_facturacion_tamano | H41: Medianos | I41: 67 | J41: % | L41: Comercial | M41: =IFERROR(INDEX(Diccionario!$N:$N,MATCH(F1197,Diccionario!$C:$C,0)),"")
A42: 2026-04 | B42: Colombia | C42: Coco Colombia | E42: Real | F42: distribucion_facturacion_tamano | H42: Pequeños | I42: 6 | J42: % | L42: Comercial | M42: =IFERROR(INDEX(Diccionario!$N:$N,MATCH(F1210,Diccionario!$C:$C,0)),"")
A43: 2026-04 | B43: Colombia | C43: Coco Colombia | D43: COP | E43: Real | F43: forecast_comercial | I43: 307827060 | J43: COP | K43: Insumo Comercial jul-2026 · oport. con cierre esperado en el mes | L43: Ventas | M43: =IFERROR(INDEX(Diccionario!$N:$N,MATCH(F1291,Diccionario!$C:$C,0)),"")
A44: 2026-05 | B44: Colombia | C44: Coco Colombia | E44: Real | F44: distribucion_facturacion_tamano | H44: Grandes | I44: 15 | J44: % | L44: Comercial | M44: =IFERROR(INDEX(Diccionario!$N:$N,MATCH(F1185,Diccionario!$C:$C,0)),"")
A45: 2026-05 | B45: Colombia | C45: Coco Colombia | E45: Real | F45: distribucion_facturacion_tamano | H45: Medianos | I45: 78 | J45: % | L45: Comercial | M45: =IFERROR(INDEX(Diccionario!$N:$N,MATCH(F1198,Diccionario!$C:$C,0)),"")
A46: 2026-05 | B46: Colombia | C46: Coco Colombia | E46: Real | F46: distribucion_facturacion_tamano | H46: Pequeños | I46: 7 | J46: % | L46: Comercial | M46: =IFERROR(INDEX(Diccionario!$N:$N,MATCH(F1211,Diccionario!$C:$C,0)),"")
A47: 2026-05 | B47: Colombia | C47: Coco Colombia | D47: COP | E47: Real | F47: forecast_comercial | I47: 106463773 | J47: COP | K47: Insumo Comercial jul-2026 · oport. con cierre esperado en el mes | L47: Ventas | M47: =IFERROR(INDEX(Diccionario!$N:$N,MATCH(F1292,Diccionario!$C:$C,0)),"")
A48: 2026-07 | B48: Colombia | C48: Coco Colombia | D48: COP | E48: Real | F48: deals_ganados | I48: 0 | J48: Número | K48: Sin cierres registrados en el periodo | L48: Ventas | M48: =IFERROR(INDEX(Diccionario!$N:$N,MATCH(F1288,Diccionario!$C:$C,0)),"")
A49: 2026-07 | B49: Colombia | C49: Coco Colombia | D49: COP | E49: Real | F49: forecast_comercial | I49: 40159561 | J49: COP | K49: Insumo Comercial jul-2026 · oport. con cierre esperado en el mes | L49: Ventas | M49: =IFERROR(INDEX(Diccionario!$N:$N,MATCH(F1293,Diccionario!$C:$C,0)),"")
A50: 2026-07 | B50: Colombia | C50: Coco Colombia | D50: COP | E50: Real | F50: pipeline_ponderado | H50: Jennifer Paola Buitrago | I50: 204094777 | J50: COP | K50: Insumo Comercial jul-2026 · desglose por comercial (Otros = clientes CR/Guatemala, sin código propio en Listas) | L50: Ventas | M50: =IFERROR(INDEX(Diccionario!$N:$N,MATCH(F1297,Diccionario!$C:$C,0)),"")
A51: 2026-07 | B51: Colombia | C51: Coco Colombia | D51: COP | E51: Real | F51: pipeline_ponderado | H51: Lina Gutiérrez | I51: 82400435 | J51: COP | K51: Insumo Comercial jul-2026 · desglose por comercial (Otros = clientes CR/Guatemala, sin código propio en Listas) | L51: Ventas | M51: =IFERROR(INDEX(Diccionario!$N:$N,MATCH(F1301,Diccionario!$C:$C,0)),"")
A52: 2026-07 | B52: Colombia | C52: Coco Colombia | D52: COP | E52: Real | F52: pipeline_ponderado | H52: Luisa Fernanda Moreno Muñoz | I52: 251946912 | J52: COP | K52: Insumo Comercial jul-2026 · desglose por comercial (Otros = clientes CR/Guatemala, sin código propio en Listas) | L52: Ventas | M52: =IFERROR(INDEX(Diccionario!$N:$N,MATCH(F1295,Diccionario!$C:$C,0)),"")
A53: 2026-07 | B53: Colombia | C53: Coco Colombia | D53: COP | E53: Real | F53: pipeline_ponderado | H53: Mariam Naranjo | I53: 150661388 | J53: COP | K53: Insumo Comercial jul-2026 · desglose por comercial (Otros = clientes CR/Guatemala, sin código propio en Listas) | L53: Ventas | M53: =IFERROR(INDEX(Diccionario!$N:$N,MATCH(F1299,Diccionario!$C:$C,0)),"")
A54: 2026-07 | B54: Colombia | C54: Coco Colombia | D54: COP | E54: Real | F54: pipeline_ponderado | H54: Sin asignar | I54: 16298400 | J54: COP | K54: Insumo Comercial jul-2026 · desglose por comercial (Otros = clientes CR/Guatemala, sin código propio en Listas) | L54: Ventas | M54: =IFERROR(INDEX(Diccionario!$N:$N,MATCH(F1305,Diccionario!$C:$C,0)),"")
A55: 2026-07 | B55: Otros | C55: Coco Colombia | D55: COP | E55: Real | F55: pipeline_ponderado | H55: Mariam Naranjo | I55: 28600028 | J55: COP | K55: Insumo Comercial jul-2026 · desglose por comercial (Otros = clientes CR/Guatemala, sin código propio en Listas) | L55: Ventas | M55: =IFERROR(INDEX(Diccionario!$N:$N,MATCH(F1303,Diccionario!$C:$C,0)),"")
A56: 2026-07 | B56: Otros | C56: Coco Colombia | D56: COP | E56: Real | F56: pipeline_ponderado | H56: Mauricio Paba | I56: 0 | J56: COP | K56: Insumo Comercial jul-2026 · desglose por comercial (Otros = clientes CR/Guatemala, sin código propio en Listas) | L56: Ventas | M56: =IFERROR(INDEX(Diccionario!$N:$N,MATCH(F1307,Diccionario!$C:$C,0)),"")
A57: 2026-07 | B57: Colombia | C57: Coco Colombia | D57: COP | E57: Real | F57: pipeline_total | H57: Jennifer Paola Buitrago | I57: 218860706 | J57: COP | K57: Insumo Comercial jul-2026 · desglose por comercial (Otros = clientes CR/Guatemala, sin código propio en Listas) | L57: Ventas | M57: =IFERROR(INDEX(Diccionario!$N:$N,MATCH(F1296,Diccionario!$C:$C,0)),"")
A58: 2026-07 | B58: Colombia | C58: Coco Colombia | D58: COP | E58: Real | F58: pipeline_total | H58: Lina Gutiérrez | I58: 86737300 | J58: COP | K58: Insumo Comercial jul-2026 · desglose por comercial (Otros = clientes CR/Guatemala, sin código propio en Listas) | L58: Ventas | M58: =IFERROR(INDEX(Diccionario!$N:$N,MATCH(F1300,Diccionario!$C:$C,0)),"")
A59: 2026-07 | B59: Colombia | C59: Coco Colombia | D59: COP | E59: Real | F59: pipeline_total | H59: Luisa Fernanda Moreno Muñoz | I59: 366554852 | J59: COP | K59: Insumo Comercial jul-2026 · desglose por comercial (Otros = clientes CR/Guatemala, sin código propio en Listas) | L59: Ventas | M59: =IFERROR(INDEX(Diccionario!$N:$N,MATCH(F1294,Diccionario!$C:$C,0)),"")
A60: 2026-07 | B60: Colombia | C60: Coco Colombia | D60: COP | E60: Real | F60: pipeline_total | H60: Mariam Naranjo | I60: 187535825 | J60: COP | K60: Insumo Comercial jul-2026 · desglose por comercial (Otros = clientes CR/Guatemala, sin código propio en Listas) | L60: Ventas | M60: =IFERROR(INDEX(Diccionario!$N:$N,MATCH(F1298,Diccionario!$C:$C,0)),"")
A61: 2026-07 | B61: Colombia | C61: Coco Colombia | D61: COP | E61: Real | F61: pipeline_total | H61: Sin asignar | I61: 20373000 | J61: COP | K61: Insumo Comercial jul-2026 · desglose por comercial (Otros = clientes CR/Guatemala, sin código propio en Listas) | L61: Ventas | M61: =IFERROR(INDEX(Diccionario!$N:$N,MATCH(F1304,Diccionario!$C:$C,0)),"")
A62: 2026-07 | B62: Otros | C62: Coco Colombia | D62: COP | E62: Real | F62: pipeline_total | H62: Mariam Naranjo | I62: 39017160 | J62: COP | K62: Insumo Comercial jul-2026 · desglose por comercial (Otros = clientes CR/Guatemala, sin código propio en Listas) | L62: Ventas | M62: =IFERROR(INDEX(Diccionario!$N:$N,MATCH(F1302,Diccionario!$C:$C,0)),"")
A63: 2026-07 | B63: Otros | C63: Coco Colombia | D63: COP | E63: Real | F63: pipeline_total | H63: Mauricio Paba | I63: 0 | J63: COP | K63: Insumo Comercial jul-2026 · desglose por comercial (Otros = clientes CR/Guatemala, sin código propio en Listas) | L63: Ventas | M63: =IFERROR(INDEX(Diccionario!$N:$N,MATCH(F1306,Diccionario!$C:$C,0)),"")
A64: 2026-07 | B64: Colombia | C64: Coco Colombia | D64: COP | E64: Real | F64: ventas_cerradas | I64: 0 | J64: COP | K64: Sin cierres registrados en el periodo (todo en pipeline) | L64: Ventas | M64: =IFERROR(INDEX(Diccionario!$N:$N,MATCH(F1287,Diccionario!$C:$C,0)),"")

Sheet Marketing
A1: Marketing — vista de solo lectura
A2: Regenerada desde BD_Indicadores el 2026-07-13 · 51 filas · Editar en BD_Indicadores.
A4: periodo | B4: pais | C4: compania | D4: moneda | E4: escenario | F4: codigo_indicador | G4: segmento | H4: detalle | I4: valor | J4: unidad | K4: comentario | L4: area_responsable | M4: periodicidad
A5: 2025-01 | B5: Colombia | C5: Coco Colombia | E5: Real | F5: leads_generados | H5: Mercadeo | I5: 233 | J5: Número | L5: Marketing | M5: =IFERROR(INDEX(Diccionario!$N:$N,MATCH(F1236,Diccionario!$C:$C,0)),"")
A6: 2025-02 | B6: Colombia | C6: Coco Colombia | E6: Real | F6: leads_generados | H6: Mercadeo | I6: 191 | J6: Número | L6: Marketing | M6: =IFERROR(INDEX(Diccionario!$N:$N,MATCH(F1237,Diccionario!$C:$C,0)),"")
A7: 2025-03 | B7: Colombia | C7: Coco Colombia | D7: COP | E7: Real | F7: cac_fully_loaded | H7: Mercadeo | I7: 53536660 | J7: COP | K7: Q1-2025 | L7: Comercial/Mktg | M7: =IFERROR(INDEX(Diccionario!$N:$N,MATCH(F1260,Diccionario!$C:$C,0)),"")
A8: 2025-03 | B8: Colombia | C8: Coco Colombia | E8: Real | F8: cac_payback_meses | H8: Mercadeo | I8: 2.1 | J8: Meses | K8: Q1-2025 — sin margen bruto | L8: Comercial/Mktg | M8: =IFERROR(INDEX(Diccionario!$N:$N,MATCH(F1278,Diccionario!$C:$C,0)),"")
A9: 2025-03 | B9: Colombia | C9: Coco Colombia | D9: COP | E9: Real | F9: gasto_marketing_total | H9: Mercadeo | I9: 149675351 | J9: COP | K9: Q1-2025 (pauta mercadeo) | L9: Marketing | M9: =IFERROR(INDEX(Diccionario!$N:$N,MATCH(F1254,Diccionario!$C:$C,0)),"")
A10: 2025-03 | B10: Colombia | C10: Coco Colombia | E10: Real | F10: leads_generados | H10: Mercadeo | I10: 117 | J10: Número | L10: Marketing | M10: =IFERROR(INDEX(Diccionario!$N:$N,MATCH(F1238,Diccionario!$C:$C,0)),"")
A11: 2025-03 | B11: Colombia | C11: Coco Colombia | D11: COP | E11: Real | F11: ltv | H11: Mercadeo | I11: 294011510 | J11: COP | K11: Q1-2025 — sin margen bruto | L11: Comercial/Mktg | M11: =IFERROR(INDEX(Diccionario!$N:$N,MATCH(F1266,Diccionario!$C:$C,0)),"")
A12: 2025-03 | B12: Colombia | C12: Coco Colombia | E12: Real | F12: ltv_cac | H12: Mercadeo | I12: 5 | J12: Veces | K12: Q1-2025 — sin margen bruto | L12: Comercial/Mktg | M12: =IFERROR(INDEX(Diccionario!$N:$N,MATCH(F1272,Diccionario!$C:$C,0)),"")
A13: 2025-04 | B13: Colombia | C13: Coco Colombia | E13: Real | F13: leads_generados | H13: Mercadeo | I13: 119 | J13: Número | L13: Marketing | M13: =IFERROR(INDEX(Diccionario!$N:$N,MATCH(F1239,Diccionario!$C:$C,0)),"")
A14: 2025-05 | B14: Colombia | C14: Coco Colombia | E14: Real | F14: leads_generados | H14: Mercadeo | I14: 172 | J14: Número | L14: Marketing | M14: =IFERROR(INDEX(Diccionario!$N:$N,MATCH(F1240,Diccionario!$C:$C,0)),"")
A15: 2025-06 | B15: Colombia | C15: Coco Colombia | D15: COP | E15: Real | F15: cac_fully_loaded | H15: Mercadeo | I15: 50289916 | J15: COP | K15: Q2-2025 | L15: Comercial/Mktg | M15: =IFERROR(INDEX(Diccionario!$N:$N,MATCH(F1261,Diccionario!$C:$C,0)),"")
A16: 2025-06 | B16: Colombia | C16: Coco Colombia | E16: Real | F16: cac_payback_meses | H16: Mercadeo | I16: 1.8 | J16: Meses | K16: Q2-2025 — sin margen bruto | L16: Comercial/Mktg | M16: =IFERROR(INDEX(Diccionario!$N:$N,MATCH(F1279,Diccionario!$C:$C,0)),"")
A17: 2025-06 | B17: Colombia | C17: Coco Colombia | D17: COP | E17: Real | F17: gasto_marketing_total | H17: Mercadeo | I17: 186879929 | J17: COP | K17: Q2-2025 (pauta mercadeo) | L17: Marketing | M17: =IFERROR(INDEX(Diccionario!$N:$N,MATCH(F1255,Diccionario!$C:$C,0)),"")
A18: 2025-06 | B18: Colombia | C18: Coco Colombia | E18: Real | F18: leads_generados | H18: Mercadeo | I18: 238 | J18: Número | L18: Marketing | M18: =IFERROR(INDEX(Diccionario!$N:$N,MATCH(F1241,Diccionario!$C:$C,0)),"")
A19: 2025-06 | B19: Colombia | C19: Coco Colombia | D19: COP | E19: Real | F19: ltv | H19: Mercadeo | I19: 476285903 | J19: COP | K19: Q2-2025 — sin margen bruto | L19: Comercial/Mktg | M19: =IFERROR(INDEX(Diccionario!$N:$N,MATCH(F1267,Diccionario!$C:$C,0)),"")
A20: 2025-06 | B20: Colombia | C20: Coco Colombia | E20: Real | F20: ltv_cac | H20: Mercadeo | I20: 9 | J20: Veces | K20: Q2-2025 — sin margen bruto | L20: Comercial/Mktg | M20: =IFERROR(INDEX(Diccionario!$N:$N,MATCH(F1273,Diccionario!$C:$C,0)),"")
A21: 2025-07 | B21: Colombia | C21: Coco Colombia | E21: Real | F21: leads_generados | H21: Mercadeo | I21: 230 | J21: Número | L21: Marketing | M21: =IFERROR(INDEX(Diccionario!$N:$N,MATCH(F1242,Diccionario!$C:$C,0)),"")
A22: 2025-08 | B22: Colombia | C22: Coco Colombia | E22: Real | F22: leads_generados | H22: Mercadeo | I22: 413 | J22: Número | L22: Marketing | M22: =IFERROR(INDEX(Diccionario!$N:$N,MATCH(F1243,Diccionario!$C:$C,0)),"")
A23: 2025-09 | B23: Colombia | C23: Coco Colombia | D23: COP | E23: Real | F23: cac_fully_loaded | H23: Mercadeo | I23: 34710372 | J23: COP | K23: Q3-2025 | L23: Comercial/Mktg | M23: =IFERROR(INDEX(Diccionario!$N:$N,MATCH(F1262,Diccionario!$C:$C,0)),"")
A24: 2025-09 | B24: Colombia | C24: Coco Colombia | E24: Real | F24: cac_payback_meses | H24: Mercadeo | I24: 1.3 | J24: Meses | K24: Q3-2025 — sin margen bruto | L24: Comercial/Mktg | M24: =IFERROR(INDEX(Diccionario!$N:$N,MATCH(F1280,Diccionario!$C:$C,0)),"")
A25: 2025-09 | B25: Colombia | C25: Coco Colombia | D25: COP | E25: Real | F25: gasto_marketing_total | H25: Mercadeo | I25: 195425338 | J25: COP | K25: Q3-2025 (pauta mercadeo) | L25: Marketing | M25: =IFERROR(INDEX(Diccionario!$N:$N,MATCH(F1256,Diccionario!$C:$C,0)),"")
A26: 2025-09 | B26: Colombia | C26: Coco Colombia | E26: Real | F26: leads_generados | H26: Mercadeo | I26: 777 | J26: Número | L26: Marketing | M26: =IFERROR(INDEX(Diccionario!$N:$N,MATCH(F1244,Diccionario!$C:$C,0)),"")
A27: 2025-09 | B27: Colombia | C27: Coco Colombia | D27: COP | E27: Real | F27: ltv | H27: Mercadeo | I27: 408296920 | J27: COP | K27: Q3-2025 — sin margen bruto | L27: Comercial/Mktg | M27: =IFERROR(INDEX(Diccionario!$N:$N,MATCH(F1268,Diccionario!$C:$C,0)),"")
A28: 2025-09 | B28: Colombia | C28: Coco Colombia | E28: Real | F28: ltv_cac | H28: Mercadeo | I28: 12 | J28: Veces | K28: Q3-2025 — sin margen bruto | L28: Comercial/Mktg | M28: =IFERROR(INDEX(Diccionario!$N:$N,MATCH(F1274,Diccionario!$C:$C,0)),"")
A29: 2025-10 | B29: Colombia | C29: Coco Colombia | E29: Real | F29: leads_generados | H29: Mercadeo | I29: 124 | J29: Número | L29: Marketing | M29: =IFERROR(INDEX(Diccionario!$N:$N,MATCH(F1245,Diccionario!$C:$C,0)),"")
A30: 2025-11 | B30: Colombia | C30: Coco Colombia | E30: Real | F30: leads_generados | H30: Mercadeo | I30: 114 | J30: Número | L30: Marketing | M30: =IFERROR(INDEX(Diccionario!$N:$N,MATCH(F1246,Diccionario!$C:$C,0)),"")
A31: 2025-12 | B31: Colombia | C31: Coco Colombia | D31: COP | E31: Real | F31: cac_fully_loaded | H31: Mercadeo | I31: 42374153 | J31: COP | K31: Q4-2025 | L31: Comercial/Mktg | M31: =IFERROR(INDEX(Diccionario!$N:$N,MATCH(F1263,Diccionario!$C:$C,0)),"")
A32: 2025-12 | B32: Colombia | C32: Coco Colombia | E32: Real | F32: cac_payback_meses | H32: Mercadeo | I32: 1.7 | J32: Meses | K32: Q4-2025 — sin margen bruto | L32: Comercial/Mktg | M32: =IFERROR(INDEX(Diccionario!$N:$N,MATCH(F1281,Diccionario!$C:$C,0)),"")
A33: 2025-12 | B33: Colombia | C33: Coco Colombia | D33: COP | E33: Real | F33: gasto_marketing_total | H33: Mercadeo | I33: 78267175 | J33: COP | K33: Q4-2025 (pauta mercadeo) | L33: Marketing | M33: =IFERROR(INDEX(Diccionario!$N:$N,MATCH(F1257,Diccionario!$C:$C,0)),"")
A34: 2025-12 | B34: Colombia | C34: Coco Colombia | E34: Real | F34: leads_generados | H34: Mercadeo | I34: 514 | J34: Número | L34: Marketing | M34: =IFERROR(INDEX(Diccionario!$N:$N,MATCH(F1247,Diccionario!$C:$C,0)),"")
A35: 2025-12 | B35: Colombia | C35: Coco Colombia | D35: COP | E35: Real | F35: ltv | H35: Mercadeo | I35: 359574204 | J35: COP | K35: Q4-2025 — sin margen bruto | L35: Comercial/Mktg | M35: =IFERROR(INDEX(Diccionario!$N:$N,MATCH(F1269,Diccionario!$C:$C,0)),"")
A36: 2025-12 | B36: Colombia | C36: Coco Colombia | E36: Real | F36: ltv_cac | H36: Mercadeo | I36: 8 | J36: Veces | K36: Q4-2025 — sin margen bruto | L36: Comercial/Mktg | M36: =IFERROR(INDEX(Diccionario!$N:$N,MATCH(F1275,Diccionario!$C:$C,0)),"")
A37: 2026-01 | B37: Colombia | C37: Coco Colombia | E37: Real | F37: leads_generados | H37: Mercadeo | I37: 237 | J37: Número | L37: Marketing | M37: =IFERROR(INDEX(Diccionario!$N:$N,MATCH(F1248,Diccionario!$C:$C,0)),"")
A38: 2026-02 | B38: Colombia | C38: Coco Colombia | E38: Real | F38: leads_generados | H38: Mercadeo | I38: 359 | J38: Número | L38: Marketing | M38: =IFERROR(INDEX(Diccionario!$N:$N,MATCH(F1249,Diccionario!$C:$C,0)),"")
A39: 2026-03 | B39: Colombia | C39: Coco Colombia | D39: COP | E39: Real | F39: cac_fully_loaded | H39: Mercadeo | I39: 1.177229e+08 | J39: COP | K39: Q1-2026 | L39: Comercial/Mktg | M39: =IFERROR(INDEX(Diccionario!$N:$N,MATCH(F1264,Diccionario!$C:$C,0)),"")
A40: 2026-03 | B40: Colombia | C40: Coco Colombia | E40: Real | F40: cac_payback_meses | H40: Mercadeo | I40: 5 | J40: Meses | K40: Q1-2026 — sin margen bruto | L40: Comercial/Mktg | M40: =IFERROR(INDEX(Diccionario!$N:$N,MATCH(F1282,Diccionario!$C:$C,0)),"")
A41: 2026-03 | B41: Colombia | C41: Coco Colombia | D41: COP | E41: Real | F41: gasto_marketing_total | H41: Mercadeo | I41: 80204146 | J41: COP | K41: Q1-2026 (pauta mercadeo) | L41: Marketing | M41: =IFERROR(INDEX(Diccionario!$N:$N,MATCH(F1258,Diccionario!$C:$C,0)),"")
A42: 2026-03 | B42: Colombia | C42: Coco Colombia | E42: Real | F42: leads_generados | H42: Mercadeo | I42: 294 | J42: Número | L42: Marketing | M42: =IFERROR(INDEX(Diccionario!$N:$N,MATCH(F1250,Diccionario!$C:$C,0)),"")
A43: 2026-03 | B43: Colombia | C43: Coco Colombia | D43: COP | E43: Real | F43: ltv | H43: Mercadeo | I43: 152508916 | J43: COP | K43: Q1-2026 — sin margen bruto | L43: Comercial/Mktg | M43: =IFERROR(INDEX(Diccionario!$N:$N,MATCH(F1270,Diccionario!$C:$C,0)),"")
A44: 2026-03 | B44: Colombia | C44: Coco Colombia | E44: Real | F44: ltv_cac | H44: Mercadeo | I44: 1.3 | J44: Veces | K44: Q1-2026 — sin margen bruto | L44: Comercial/Mktg | M44: =IFERROR(INDEX(Diccionario!$N:$N,MATCH(F1276,Diccionario!$C:$C,0)),"")
A45: 2026-04 | B45: Colombia | C45: Coco Colombia | E45: Real | F45: leads_generados | H45: Mercadeo | I45: 156 | J45: Número | L45: Marketing | M45: =IFERROR(INDEX(Diccionario!$N:$N,MATCH(F1251,Diccionario!$C:$C,0)),"")
A46: 2026-05 | B46: Colombia | C46: Coco Colombia | E46: Real | F46: cac_payback_meses | H46: Financiero TTM | I46: =Calc_LTV_Fin!B12 | J46: Meses | K46: TTM a may-2026; margen editable | L46: Comercial/Mktg | M46: =IFERROR(INDEX(Diccionario!$N:$N,MATCH(F1285,Diccionario!$C:$C,0)),"")
A47: 2026-05 | B47: Colombia | C47: Coco Colombia | E47: Real | F47: leads_generados | H47: Mercadeo | I47: 211 | J47: Número | L47: Marketing | M47: =IFERROR(INDEX(Diccionario!$N:$N,MATCH(F1252,Diccionario!$C:$C,0)),"")
A48: 2026-05 | B48: Colombia | C48: Coco Colombia | D48: COP | E48: Real | F48: ltv | H48: Financiero TTM | I48: =Calc_LTV_Fin!B11 | J48: COP | K48: TTM a may-2026; margen editable | L48: Comercial/Mktg | M48: =IFERROR(INDEX(Diccionario!$N:$N,MATCH(F1284,Diccionario!$C:$C,0)),"")
A49: 2026-05 | B49: Colombia | C49: Coco Colombia | E49: Real | F49: ltv_cac | H49: Financiero TTM | I49: =Calc_LTV_Fin!B13 | J49: Veces | K49: TTM a may-2026; margen editable | L49: Comercial/Mktg | M49: =IFERROR(INDEX(Diccionario!$N:$N,MATCH(F1286,Diccionario!$C:$C,0)),"")
A50: 2026-06 | B50: Colombia | C50: Coco Colombia | D50: COP | E50: Real | F50: cac_fully_loaded | H50: Mercadeo | I50: 45216107 | J50: COP | K50: Q2-2026 | L50: Comercial/Mktg | M50: =IFERROR(INDEX(Diccionario!$N:$N,MATCH(F1265,Diccionario!$C:$C,0)),"")
A51: 2026-06 | B51: Colombia | C51: Coco Colombia | E51: Real | F51: cac_payback_meses | H51: Mercadeo | I51: 2.9 | J51: Meses | K51: Q2-2026 — sin margen bruto | L51: Comercial/Mktg | M51: =IFERROR(INDEX(Diccionario!$N:$N,MATCH(F1283,Diccionario!$C:$C,0)),"")
A52: 2026-06 | B52: Colombia | C52: Coco Colombia | D52: COP | E52: Real | F52: gasto_marketing_total | H52: Mercadeo | I52: 62603918 | J52: COP | K52: Q2-2026 (pauta mercadeo) | L52: Marketing | M52: =IFERROR(INDEX(Diccionario!$N:$N,MATCH(F1259,Diccionario!$C:$C,0)),"")
A53: 2026-06 | B53: Colombia | C53: Coco Colombia | E53: Real | F53: leads_generados | H53: Mercadeo | I53: 20 | J53: Número | L53: Marketing | M53: =IFERROR(INDEX(Diccionario!$N:$N,MATCH(F1253,Diccionario!$C:$C,0)),"")
A54: 2026-06 | B54: Colombia | C54: Coco Colombia | D54: COP | E54: Real | F54: ltv | H54: Mercadeo | I54: 115723005 | J54: COP | K54: Q2-2026 — sin margen bruto | L54: Comercial/Mktg | M54: =IFERROR(INDEX(Diccionario!$N:$N,MATCH(F1271,Diccionario!$C:$C,0)),"")
A55: 2026-06 | B55: Colombia | C55: Coco Colombia | E55: Real | F55: ltv_cac | H55: Mercadeo | I55: 2.56 | J55: Veces | K55: Q2-2026 — sin margen bruto | L55: Comercial/Mktg | M55: =IFERROR(INDEX(Diccionario!$N:$N,MATCH(F1277,Diccionario!$C:$C,0)),"")

Sheet Customer_Success
A1: Customer Success — vista de solo lectura
A2: Regenerada desde BD_Indicadores el 2026-07-13 · 8 filas · Editar en BD_Indicadores.
A4: periodo | B4: pais | C4: compania | D4: moneda | E4: escenario | F4: codigo_indicador | G4: segmento | H4: detalle | I4: valor | J4: unidad | K4: comentario | L4: area_responsable | M4: periodicidad
A5: 2026-03 | B5: Colombia | C5: Coco Colombia | E5: Real | F5: nps | H5: Detractores | I5: 7.1 | J5: % | L5: CS | M5: =IFERROR(INDEX(Diccionario!$N:$N,MATCH(F1171,Diccionario!$C:$C,0)),"")
A6: 2026-03 | B6: Colombia | C6: Coco Colombia | E6: Real | F6: nps | H6: Pasivos | I6: 14.3 | J6: % | L6: CS | M6: =IFERROR(INDEX(Diccionario!$N:$N,MATCH(F1168,Diccionario!$C:$C,0)),"")
A7: 2026-03 | B7: Colombia | C7: Coco Colombia | E7: Real | F7: nps | H7: Promotores | I7: 78.6 | J7: % | L7: CS | M7: =IFERROR(INDEX(Diccionario!$N:$N,MATCH(F1165,Diccionario!$C:$C,0)),"")
A8: 2026-04 | B8: Colombia | C8: Coco Colombia | E8: Real | F8: nps | H8: Detractores | I8: 0 | J8: % | L8: CS | M8: =IFERROR(INDEX(Diccionario!$N:$N,MATCH(F1172,Diccionario!$C:$C,0)),"")
A9: 2026-04 | B9: Colombia | C9: Coco Colombia | E9: Real | F9: nps | H9: Pasivos | I9: 0 | J9: % | L9: CS | M9: =IFERROR(INDEX(Diccionario!$N:$N,MATCH(F1169,Diccionario!$C:$C,0)),"")
A10: 2026-04 | B10: Colombia | C10: Coco Colombia | E10: Real | F10: nps | H10: Promotores | I10: 100 | J10: % | L10: CS | M10: =IFERROR(INDEX(Diccionario!$N:$N,MATCH(F1166,Diccionario!$C:$C,0)),"")
A11: 2026-05 | B11: Colombia | C11: Coco Colombia | E11: Real | F11: nps | H11: Pasivos | I11: 8.3 | J11: % | L11: CS | M11: =IFERROR(INDEX(Diccionario!$N:$N,MATCH(F1170,Diccionario!$C:$C,0)),"")
A12: 2026-05 | B12: Colombia | C12: Coco Colombia | E12: Real | F12: nps | H12: Promotores | I12: 91.7 | J12: % | L12: CS | M12: =IFERROR(INDEX(Diccionario!$N:$N,MATCH(F1167,Diccionario!$C:$C,0)),"")

Sheet TRM
A1: TRM mensual (COP por USD) — derivada de ingresos COP / ingresos USD
A2: El dashboard convierte a USD dividiendo el valor COP entre la TRM del periodo. Editable.
A3: periodo | B3: trm_cop_usd | C3: fuente | D3: trm_promedio_mercado
A4: 2024-01 | B4: 4420 | C4: Ingresos COP/USD | D4: 3915.2
A5: 2024-02 | B5: 4420 | C5: Ingresos COP/USD | D5: 3931.44
A6: 2024-03 | B6: 4420 | C6: Ingresos COP/USD | D6: 3899.34
A7: 2024-04 | B7: 4420 | C7: Ingresos COP/USD | D7: 3867.98
A8: 2024-05 | B8: 4420 | C8: Ingresos COP/USD | D8: 3869.1
A9: 2024-06 | B9: 4420 | C9: Ingresos COP/USD | D9: 4042.8
A10: 2024-07 | B10: 4420 | C10: Ingresos COP/USD | D10: 4036.92
A11: 2024-08 | B11: 4420 | C11: Ingresos COP/USD | D11: 4065.55
A12: 2024-09 | B12: 4420 | C12: Ingresos COP/USD | D12: 4182.51
A13: 2024-10 | B13: 4420 | C13: Ingresos COP/USD | D13: 4249.47
A14: 2024-11 | B14: 4420 | C14: Ingresos COP/USD | D14: 4408.65
A15: 2024-12 | B15: 4420 | C15: Ingresos COP/USD | D15: 4385.15
... A33: 2026-06 | B33: 4170 | C33: Ingresos COP/USD | D33: 3571.44
A34: 2023-07 | C34: TRM promedio mensual (mercado) | D34: 4069.23
A35: 2023-08 | C35: TRM promedio mensual (mercado) | D35: 4070.73
A36: 2023-09 | C36: TRM promedio mensual (mercado) | D36: 4004.52
A37: 2023-10 | C37: TRM promedio mensual (mercado) | D37: 4222.43
A38: 2023-11 | C38: TRM promedio mensual (mercado) | D38: 4038.8
A39: 2023-12 | C39: TRM promedio mensual (mercado) | D39: 3948.21
A40: 2026-07 | B40: 3505.2683 | C40: Base previa/impl?cita para convertir Colombia julio

Sheet TRM_Peru
A1: Tasa de cambio Perú — promedio mensual 2026 (S/ por US$)
A2: Fuente: BCRP (promedio del periodo). Julio = promedio del mes hasta la fecha (días hábiles 1–9 jul, provisional).
A4: periodo | B4: par | C4: tc_pen_usd | D4: factor_usd_pen | E4: fuente
A5: 2026-01 | B5: PEN/USD | C5: 3.357 | D5: 0.297885 | E5: BCRP promedio mensual
A6: 2026-02 | B6: PEN/USD | C6: 3.357 | D6: 0.297885 | E6: BCRP promedio mensual
A7: 2026-03 | B7: PEN/USD | C7: 3.447 | D7: 0.290107 | E7: BCRP promedio mensual
A8: 2026-04 | B8: PEN/USD | C8: 3.443 | D8: 0.290444 | E8: BCRP promedio mensual
A9: 2026-05 | B9: PEN/USD | C9: 3.435 | D9: 0.291121 | E9: BCRP promedio mensual
A10: 2026-06 | B10: PEN/USD | C10: 3.405 | D10: 0.293686 | E10: BCRP promedio mensual
A11: 2026-07* | B11: PEN/USD | C11: 3.405 | D11: 0.293686 | E11: Promedio hasta 9-jul (provisional)

Sheet Calc_LTV_Fin
A1: LTV financiero (margen bruto + churn de ingresos TTM)
A2: Cambia solo la celda amarilla (margen bruto) y LTV / payback / LTV:CAC se recalculan. Ventana TTM jun-2025 a may-2026.
A4: Margen bruto (EDITABLE) | B4: 0.51 | C4: Source: Contabilidad, may-2026
A5: ARPA mensual prom. (TTM) | B5: 8307111 | C5: Prom. ARPU mercadeo TTM
A6: Churn de ingresos mensual (TTM) | B6: 0.0102 | C6: Σchurned / Σmrr_inicio (MRR bridge)
A7: Churn de clientes mensual (TTM) | B7: 0.0117 | C7: Account Churn mercadeo (comparativo)
A8: CAC prom. trimestral (TTM) | B8: 64935810 | C8: Prom. CAC mercadeo en la ventana
A10: RESULTADOS
A11: LTV financiero (COP) | B11: =B5*B4/B6
A12: Payback financiero (meses) | B12: =B8/(B5*B4)
A13: LTV:CAC financiero (veces) | B13: =B11/B8

Sheet Analisis_Churn
A1: Análisis de Churn — Informe Contabilidad mayo 2026
A2: Valor de churn en USD. Definición de la cifra (MRR perdido vs. valor de contrato) a confirmar. Total churn = 40.131 USD.
A4: 1. Churn por razón de retiro
A5: Razón | B5: Valor USD | C5: % del total
A6: Cambio de gerente | B6: 3689 | C6: 0.0919
A7: Interoperabilidad | B7: 1381 | C7: 0.0344
A8: No agrega valor | B8: 18462 | C8: 0.46
A9: Piloto no exitoso | B9: 558 | C9: 0.0139
A10: Presupuesto | B10: 16040 | C10: 0.3997
A11: Total | B11: 40131 | C11: 1
A13: 2. Churn por factor
A14: Factor | B14: Valor USD | C14: % del total
A15: Externo | B15: 19436 | C15: 0.4843
A16: Interno | B16: 20694 | C16: 0.5157
A17: Total | B17: 40131 | C17: 1
A19: 3. Churn por tamaño de cliente
A20: Tamaño | B20: Valor USD | C20: Comparativo 'Enero'
A21: Grande | B21: 28116 | C21: 0
A22: Mediano | B22: 8720 | C22: 14164
A23: Pequeño | B23: 3294 | C23: 1731
A24: Total | B24: 40131 | C24: 15895
A26: 4. Notas y hallazgos (CS)
A27: • Salud Total representa el 40% del churn.
A28: • No gastar esfuerzo comercial en clientes con < 3.000 citas mensuales o consultorios particulares.
A29: • El churn de B2C debe medirse aparte del agendamiento.
A30: • Producto: estabilización del bot en Q1.
A31: • Campañas y mejoras para Q3.

Sheet Analisis_Reconciliacion
A1: Facturación Contable vs Ejecutada — mayo 2026 (S2)
A3: Concepto | B3: Contable (COP) | C3: Ejecutada (COP) | D3: Contable (USD) | E3: Ejecutada (USD)
A4: Ingresos operativos | B4: 826514745 | C4: 812464793 | D4: 223987.74 | E4: 220180.16
A5: Otros ingresos | B5: 1366337 | C5: 1366337 | D5: 370.28103 | E5: 370.28103
A6: Egresos | B6: 713505270 | C6: 713505270 | D6: 193361.86 | E6: 193361.86
A7: Financieros | B7: 6000847 | C7: 6000847 | D7: 1626.2458 | E7: 1626.2458
A8: Utilidad | B8: 108374965 | C8: 94325013 | D8: 29369.909 | E8: 25562.334

Sheet CATALOGOS
A1: area | B1: codigo_indicador | D1: paises | E1: escenarios | F1: monedas | G1: companias
A2: Finanzas | B2: ingresos_totales | D2: Colombia | E2: Real | F2: COP | G2: Coco Colombia
A3: Finanzas | B3: ingresos_recurrentes | D3: EE.UU. | E3: Presupuesto | F3: USD | G3: Coco LLC
A4: Finanzas | B4: ingresos_no_recurrentes | D4: Perú | E4: Modelo | G4: Coco Perú
A5: Finanzas | B5: costo_proveedor_ventas_pct | D5: Costa Rica | G5: Coco Costa Rica
A6: Finanzas | B6: ebitda | D6: Consolidado | G6: Coco Consolidado
A7: Finanzas | B7: utilidad_neta | D7: Otros
A8: Finanzas | B8: egresos_totales
A9: Finanzas | B9: burn_rate_neto
A10: Finanzas | B10: runway_meses
A11: Ingresos_MRR | B11: mrr_final
A12: Ingresos_MRR | B12: arr
A13: Ingresos_MRR | B13: arpa
A14: Ingresos_MRR | B14: retained_mrr
A15: Ingresos_MRR | B15: new_mrr
A16: Ingresos_MRR | B16: expansion_mrr
A17: Ingresos_MRR | B17: reactivacion_mrr
A18: Ingresos_MRR | B18: contraction_mrr
A19: Ingresos_MRR | B19: churned_mrr
... A66: Internacional | B66: clientes_internacionales

Sheet LOG
A1: timestamp | B1: usuario | C1: accion | D1: area | E1: hoja | F1: filas_afectadas | G1: detalle
A2: 2026-08-12T14:53:01 | B2: Codex | C2: actualizacion_bd_local | D2: Finanzas | E2: BD_MAESTRA_COCO | F2: 84 | G2: EEFF julio 2026: soporte contable, P&G Colombia mensual, bloque internacional y candidatos intercompa??a.
A3: 2026-08-12T14:55:03 | B3: Codex | C3: correccion_actualizacion_bd_local | D3: Finanzas | E3: BD_MAESTRA_COCO | F3: 84 | G3: Correcci?n: julio Colombia derivado solo con filas COP locales, excluyendo conversiones USD.
C4: Actualizaci?n final julio 2026 | G4: Base maestra actualizada con Colombia, EE.UU., Per? y Costa Rica julio; consolidado USD recalculado; CR julio agregado desde Julio 2026 CR.xlsx.

Sheet Pipeline_Comercial
A1: cliente | B1: comercial | C1: tipo | D1: prob | E1: mes | F1: mrr_cop | G1: impl_cop | H1: citas | I1: valor_cop | J1: ponderado_cop

Sheet EEFF_Resumen
A1: Consolidado financiero estructurado COCO 2026
A2: Resumen ejecutivo de COCO Colombia y sus subsidiarias. Colombia conciliada contra el PDF oficial acumulado a julio de 2026.
A3: ESTADO DE VALIDACIÓN | F3: CORTE OFICIAL COLOMBIA | J3: TRAZABILIDAD
A4: COCO COLOMBIA VALIDADO | F4: Periodo | G4: 2026-01-01 a 2026-07-31 | J4: Archivos fuente | K4: 22
F5: Moneda | G5: COP | J5: Registros base | K5: 986
F6: Fuente | G6: EF Julio COCO 2026.pdf | J6: Reglas de mapeo | K6: 90
F7: Cobertura | G7: Colombia | J7: Cobertura julio | K7: COCO + EE.UU. + Per? + CR
A8: INDICADORES OFICIALES - COCO COLOMBIA (COP)
A9: TOTAL ACTIVOS | E9: TOTAL PASIVOS | I9: TOTAL PATRIMONIO
A10: 6106667432 | E10: 3435007484 | I10: 2671659949
A13: INGRESOS ORDINARIOS | E13: RESULTADO OPERACIONAL | I13: UTILIDAD DEL EJERCICIO
A14: 2709609951 | E14: 276036182 | I14: 246728277
A17: LECTURA DEL ARCHIVO
A18: Colombia | B18: Todas las cifras oficiales acumuladas a julio coinciden; el balance cuadra y los subtotales están definidos por bloque.
A19: Conciliaciones PDF | B19: Se documentan por separado 7 diferencias internas de COP 1-2; no se asignaron a cuentas incorrectas.
A20: Subsidiarias | B20: USA, Perú y Costa Rica permanecen separadas en su moneda de origen; no se suman monedas diferentes.
A21: Grupo | B21: Pendiente definir tasas de cambio y registrar eliminaciones intercompañía.
A22: PENDIENTES PARA CONSOLIDAR EL GRUPO | H22: ESTRUCTURA DEL ARCHIVO
A23: 1 | B23: Definir moneda de presentación y tasas de cierre/promedio. | H23: COCO_Oficial_COP | I23: Validación exclusiva de Colombia contra el PDF oficial acumulado, en COP.
A24: 2 | B24: Conciliar y eliminar saldos y transacciones intercompañía. | H24: Balance_Comun | I24: Balance comparativo por rubro común y entidad.
A25: 3 | B25: Incorporar julio 2026 de Costa Rica. | H25: Resultados_YTD | I25: Resultados acumulados por rubro común y entidad.
A26: 4 | B26: Resolver las alertas de signo y clasificación material. | H26: Mov_Mensuales | I26: Movimientos mensuales de auxiliares.
H27: Base_Homologada | I27: Detalle trazable, sin niveles duplicados.
H28: Homologacion | I28: Catálogo editable de cuentas fuente a rubros comunes.
H29: Intercompanias | I29: Candidatos para conciliación y eliminación.
H30: Alertas | I30: Hallazgos de clasificación, signos, continuidad y cobertura.
H31: Checks | I31: Controles de roll-up, balance y fuente PDF.
H32: Notas_COCO | I32: Detalle validado del PDF de Colombia.
H33: Fuentes | I33: Inventario de los 21 archivos.
A34: Versión 3.1 | Preparado 2026-08-12 | Subtotales definidos | Colombia en COP; subsidiarias en moneda de origen

Sheet EEFF_COCO_Oficial
A1: COCO Colombia - validación contra estados oficiales
A2: Acumulado del 1 de enero al 31 de julio de 2026. Cifras exclusivamente de Colombia, expresadas en pesos colombianos (COP).
A3: Entidad | B3: COCO INVERSIONES TECNOLOGICAS S.A.S | D3: País | E3: Colombia
A4: Periodo | B4: 2026-01-01 al 2026-07-31 | D4: Moneda | E4: COP
A5: Fuente | B5: EF Julio COCO 2026.pdf - estados principales, páginas 1 y 2
A6: ESTADO DE SITUACIÓN FINANCIERA
A7: Concepto | B7: Nota | C7: PDF oficial | D7: Homologado | E7: Diferencia | F7: Estado
A8: Efectivo y equivalentes | B8: 3 | C8: 174266926 | D8: 174266926 | E8: 0 | F8: OK
A9: Inversiones | B9: 4 | C9: 78270032 | D9: 78270032 | E9: 0 | F9: OK
A10: Cuentas comerciales y otras cuentas por cobrar | B10: 5 | C10: 5218154960 | D10: 5218154960 | E10: 0 | F10: OK
A11: Total activos corrientes | C11: 5470691918 | D11: 5470691918 | E11: 0 | F11: OK
A12: Total activos no corrientes | B12: 6 | C12: 635975514 | D12: 635975514 | E12: 0 | F12: OK
A13: TOTAL ACTIVO | C13: 6106667432 | D13: 6106667432 | E13: 0 | F13: OK
A14: Total pasivo corriente | B14: 7 | C14: 793220203 | D14: 793220203 | E14: 0 | F14: OK
A15: Total pasivo no corriente | B15: 7 | C15: 2641787281 | D15: 2641787281 | E15: 0 | F15: OK
A16: TOTAL PASIVO | C16: 3435007484 | D16: 3435007484 | E16: 0 | F16: OK
A17: Patrimonio atribuible a los accionistas | B17: 8 | C17: 830909000 | D17: 830909000 | E17: 0 | F17: OK
A18: Prima en colocación de acciones | B18: 8 | C18: 379430000 | D18: 379430000 | E18: 0 | F18: OK
A19: Utilidades acumuladas | B19: 8 | C19: 1214592672 | D19: 1214592672 | E19: 0 | F19: OK
A20: Utilidad del ejercicio | B20: 8 | C20: 246728277 | D20: 246728277 | E20: 0 | F20: OK
A21: Total patrimonio | C21: 2671659949 | D21: 2671659949 | E21: 0 | F21: OK
A22: TOTAL PASIVO Y PATRIMONIO | C22: 6106667432 | D22: 6106667432 | E22: 0 | F22: OK
A23: ESTADO DE RESULTADOS INTEGRAL - ACUMULADO
A24: Concepto | B24: Nota | C24: PDF oficial | D24: Homologado | E24: Diferencia | F24: Estado
A25: Servicios de software de agendamiento | B25: 9 | C25: 5615511389 | D25: 5615511389 | E25: 0 | F25: OK
A26: Devoluciones | B26: 9 | C26: -463278090 | D26: -463278090 | E26: 0 | F26: OK
A27: Costo de ventas | B27: 10 | C27: 2442623347 | D27: 2442623347 | E27: 0 | F27: OK
A28: TOTAL INGRESOS ORDINARIOS | C28: 2709609951 | D28: 2709609951 | E28: 0 | F28: OK
A29: Gastos de administración | B29: 11 | C29: 797478918 | D29: 797478918 | E29: 0 | F29: OK
A30: Gastos de ventas | B30: 11 | C30: 959736563 | D30: 959736563 | E30: 0 | F30: OK
A31: Gastos operacionales | B31: 11 | C31: 676358287 | D31: 676358287 | E31: 0 | F31: OK
A32: GASTOS DE OPERACIÓN Y PROYECTOS | C32: 2433573769 | D32: 2433573769 | E32: 0 | F32: OK
A33: RESULTADO DE LA OPERACIÓN | C33: 276036182 | D33: 276036182 | E33: 0 | F33: OK
A34: Ingreso no operacional | B34: 12 | C34: 10800447 | D34: 10800447 | E34: 0 | F34: OK
A35: Gastos financieros | B35: 13 | C35: 40108353 | D35: 40108353 | E35: 0 | F35: OK
A36: UTILIDAD DEL EJERCICIO | C36: 246728277 | D36: 246728277 | E36: 0 | F36: OK
A37: CONCILIACIONES DOCUMENTADAS DEL PDF
A38: Concepto | B38: Diferencia COP | C38: Tratamiento | F38: Referencia
A39: Activos no corrientes | B39: 1 | C39: Conciliación separada; prevalece el total oficial. | F39: Pág. 1 vs Nota 6
A40: Pasivo corriente | B40: 1 | C40: Conciliación separada; prevalece el total oficial. | F40: Pág. 1 vs Nota 7
A41: Total ingresos ordinarios | B41: -1 | C41: Conciliación separada; prevalece el subtotal oficial. | F41: Pág. 2
A42: Gastos de operación y proyectos | B42: 1 | C42: Conciliación separada; prevalece el subtotal oficial. | F42: Pág. 2
A43: Gastos financieros | B43: -2 | C43: Se usa COP 40.108.353 del estado principal. | F43: Pág. 2 vs Nota 13
A44: Utilidad del ejercicio | B44: 1 | C44: Conciliación separada; prevalece la utilidad oficial. | F44: Pág. 2
A45: Total pasivo y patrimonio | B45: -1 | C45: Conciliación separada; prevalece el total oficial publicado. | F45: Pág. 1

Sheet EEFF_Balance
A1: Estado de situación financiera homologado
A2: Comparativo por entidad en moneda de origen. Para auxiliares, el resultado YTD abierto se incorpora como línea de patrimonio para que el balance cuadre.
A3: Entidad | C3: COCO | D3: USA | E3: PERU | F3: CR
A4: Moneda | C4: COP | D4: USD | E4: PEN | F4: USD
A5: Periodo | C5: 2026-07 | D5: 2026-07 | E5: 2026-07 | F5: 2026-06
A6: Código | B6: Rubro común | C6: COCO | D6: USA | E6: PERU | F6: CR
B7: ACTIVOS CORRIENTES
A8: BS-A-010 | B8: Efectivo y equivalentes | C8: 174266926 | D8: 302331.63 | E8: 50601.54 | F8: 621.14
A9: BS-A-020 | B9: Inversiones corrientes | C9: 78270032 | D9: 0 | E9: 0 | F9: 0
A10: BS-A-030 | B10: Cuentas comerciales por cobrar | C10: 1688457915 | D10: 6068.8 | E10: 14863.59 | F10: 0
A11: BS-A-040 | B11: Anticipos y otras cuentas por cobrar | C11: 274303229 | D11: 0 | E11: 0 | F11: 0
A12: BS-A-050 | B12: Activos por impuestos corrientes | C12: 866147225 | D12: 0 | E12: 4194.36 | F12: 0
A13: BS-A-060 | B13: Otras cuentas por cobrar | C13: 2389246591 | D13: 616411.67 | E13: 0 | F13: 0
A14: SUBTOTAL_RECEIVABLES | B14: Subtotal cuentas por cobrar, anticipos e impuestos | C14: 5218154960 | D14: 622480.47 | E14: 19057.95 | F14: 0
A15: TOTAL_CA | B15: Total activos corrientes | C15: 5470691918 | D15: 924812.1 | E15: 69659.49 | F15: 621.14
B16: ACTIVOS NO CORRIENTES
A17: BS-A-110 | B17: Propiedad, planta y equipo | C17: 275293525 | D17: 8817.22 | E17: 8811.86 | F17: 0
A18: BS-A-120 | B18: Depreciación acumulada | C18: -49318012 | D18: -4924 | E18: 0 | F18: 0
A19: BS-A-130 | B19: Activos intangibles | C19: 410000000 | D19: 0 | E19: 0 | F19: 0
A20: BS-A-140 | B20: Conciliación estado oficial vs notas | C20: 1 | D20: 0 | E20: 0 | F20: 0
A21: TOTAL_NCA | B21: Total activos no corrientes | C21: 635975514 | D21: 3893.22 | E21: 8811.86 | F21: 0
A22: TOTAL_ASSETS | B22: TOTAL ACTIVOS | C22: 6106667432 | D22: 928705.32 | E22: 78471.35 | F22: 621.14
B23: PASIVOS CORRIENTES
A24: BS-L-010 | B24: Obligaciones financieras | C24: 104555195 | D24: 0 | E24: 0 | F24: 0
A25: BS-L-020 | B25: Cuentas comerciales por pagar | C25: 384931931 | D25: 0 | E25: 8755.88 | F25: 0
A26: BS-L-030 | B26: Otras cuentas por pagar | C26: 18828373 | D26: 0 | E26: 0 | F26: 92
A27: BS-L-040 | B27: Impuestos por pagar | C27: 19229474 | D27: 0 | E27: 3475.36 | F27: 0
A28: BS-L-050 | B28: Obligaciones laborales | C28: 265675229 | D28: 0 | E28: 0 | F28: 0
A29: BS-L-060 | B29: Pasivos por contratos y anticipos | C29: 0 | D29: 580342.75 | E29: 0 | F29: 0
A30: BS-L-070 | B30: Conciliación estado oficial vs notas | C30: 1 | D30: 0 | E30: 0 | F30: 0
A31: TOTAL_CL | B31: Total pasivos corrientes / sin plazo | C31: 793220203 | D31: 580342.75 | E31: 12231.24 | F31: 92
B32: PASIVOS NO CORRIENTES
A33: BS-L-110 | B33: Cuentas por pagar a vinculadas | C33: 2641787281 | D33: 0 | E33: 0 | F33: 0
A34: TOTAL_NCL | B34: Total pasivos no corrientes | C34: 2641787281 | D34: 0 | E34: 0 | F34: 0
A35: TOTAL_LIAB | B35: TOTAL PASIVOS | C35: 3435007484 | D35: 580342.75 | E35: 12231.24 | F35: 92
B36: PATRIMONIO
A37: BS-E-010 | B37: Capital social | C37: 830909000 | D37: 383868 | E37: 14208.08 | F37: 45201.79
A38: BS-E-020 | B38: Prima en colocación de acciones | C38: 379430000 | D38: 0 | E38: 0 | F38: 0
A39: BS-E-030 | B39: Resultados acumulados | C39: 1214592672 | D39: 0 | E39: 26659.66 | F39: 0
A40: BS-E-040 | B40: Resultado registrado en libros | C40: 0 | D40: 13042.5 | E40: 0 | F40: -22674.27
A41: BS-E-050 | B41: Resultado del periodo reportado - COCO | C41: 246728277 | D41: 0 | E41: 0 | F41: 0
A42: OPEN_PNL | B42: Resultado YTD abierto - subsidiarias | C42: 0 | D42: -48547.93 | E42: 25372.37 | F42: -21998.38
A43: TOTAL_EQUITY | B43: TOTAL PATRIMONIO | C43: 2671659949 | D43: 348362.57 | E43: 66240.11 | F43: 529.14
A44: BS-C-900 | B44: Conciliación del total oficial pasivo y patrimonio | C44: -1 | D44: 0 | E44: 0 | F44: 0
A45: TOTAL_LE | B45: TOTAL PASIVO Y PATRIMONIO | C45: 6106667432 | D45: 928705.32 | E45: 78471.35 | F45: 621.14
A46: BALANCE_CHECK | B46: DIFERENCIA DE BALANCE | C46: 0 | D46: 0 | E46: 0 | F46: 0

Sheet EEFF_Resultados_YTD
A1: Estado de resultados homologado - YTD
A2: Comparativo por entidad en moneda de origen. Los periodos se muestran en el encabezado; no se suman monedas diferentes.
A3: Entidad | C3: COCO | D3: USA | E3: PERU | F3: CR
A4: Moneda | C4: COP | D4: USD | E4: PEN | F4: USD
A5: Periodo | C5: 2026-07 | D5: 2026-07 | E5: 2026-07 | F5: 2026-07
A6: Código | B6: Rubro común | C6: COCO | D6: USA | E6: PERU | F6: CR
B7: INGRESOS OPERACIONALES
A8: PL-R-010 | B8: Ingresos por servicios | C8: 5615511389 | D8: 39010.5 | E8: 19307.26 | F8: 134104
A9: PL-R-020 | B9: (-) Devoluciones | C9: -463278090 | D9: 0 | E9: 0 | F9: 0
A10: TOTAL_REV | B10: Ingresos operacionales netos | C10: 5152233299 | D10: 39010.5 | E10: 19307.26 | F10: 134104
B11: COSTO DE VENTAS
A12: PL-C-010 | B12: Costo de ventas / desarrollo | C12: 2442623347 | D12: 0 | E12: 0 | F12: 0
A13: PL-G-900 | B13: Conciliación del total oficial de ingresos ordinarios | C13: -1 | D13: 0 | E13: 0 | F13: 0
A14: GROSS | B14: Utilidad bruta | C14: 2709609951 | D14: 39010.5 | E14: 19307.26 | F14: 134104
B15: GASTOS DE ADMINISTRACIÓN
A16: PL-O-010 | B16: Gastos de personal | C16: 0 | D16: 42187.99 | E16: 0 | F16: 12292.37
A17: PL-O-020 | B17: Honorarios y servicios profesionales | C17: 0 | D17: 21252.46 | E17: 5446.95 | F17: 270.35
A18: PL-O-030 | B18: Impuestos y contribuciones | C18: 0 | D18: 4024.05 | E18: 0 | F18: 576.65
A19: PL-O-040 | B19: Arrendamientos | C19: 0 | D19: 85.06 | E19: 0 | F19: 0
A20: PL-O-050 | B20: Seguros | C20: 0 | D20: 0 | E20: 0 | F20: 9276.53
A21: PL-O-060 | B21: Tecnología y procesamiento de datos | C21: 0 | D21: 9512.58 | E21: 0 | F21: 149.81
A22: PL-O-070 | B22: Telecomunicaciones | C22: 0 | D22: 479.01 | E22: 0 | F22: 0
A23: PL-O-080 | B23: Correo y mensajería | C23: 0 | D23: 57.32 | E23: 0 | F23: 0
A24: PL-O-090 | B24: Viajes y representación | C24: 0 | D24: 252.15 | E24: 0 | F24: 2100
A25: PL-O-100 | B25: Otros servicios administrativos | C25: 0 | D25: 773.99 | E25: 0 | F25: 0
A26: PL-O-110 | B26: Suministros y oficina | C26: 0 | D26: 117.68 | E26: 0 | F26: 173.61
A27: PL-O-120 | B27: Alimentación y restaurante | C27: 0 | D27: 3873.99 | E27: 0 | F27: 0
... A30: TOTAL_ADMIN | B30: Subtotal gastos de administración | C30: 797478918 | D30: 82674.03 | E30: 5446.95 | F30: 24839.32
B31: OTROS GASTOS OPERACIONALES
A32: PL-O-210 | B32: Gastos operacionales - COCO | C32: 676358287 | D32: 0 | E32: 0 | F32: 0
A33: TOTAL_OTHER_OPEX | B33: Subtotal otros gastos operacionales | C33: 676358287 | D33: 0 | E33: 0 | F33: 0
B34: GASTOS DE VENTAS
A35: PL-S-010 | B35: Honorarios comerciales y técnicos | C35: 0 | D35: 0 | E35: 32310.82 | F35: 0
A36: PL-S-020 | B36: Mercadeo y publicidad | C36: 0 | D36: 400 | E36: 1706.19 | F36: 0
A37: PL-S-030 | B37: Otros servicios comerciales | C37: 0 | D37: 4148 | E37: 0 | F37: 0
A38: PL-S-040 | B38: Viajes comerciales | C38: 0 | D38: 0 | E38: 13643.11 | F38: 0
A39: PL-S-050 | B39: Transporte comercial | C39: 0 | D39: 0 | E39: 545.37 | F39: 0
A40: PL-S-060 | B40: Otros gastos comerciales | C40: 0 | D40: 0 | E40: 4076.42 | F40: 0
A41: PL-S-200 | B41: Gastos de ventas - COCO | C41: 959736563 | D41: 0 | E41: 0 | F41: 0
A42: TOTAL_SELLING | B42: Subtotal gastos de ventas | C42: 959736563 | D42: 4548 | E42: 52281.91 | F42: 0
A43: PL-O-900 | B43: Conciliación del total oficial de gastos operacionales | C43: 1 | D43: 0 | E43: 0 | F43: 0
A44: TOTAL_OPEX | B44: Total gastos operacionales | C44: 2433573769 | D44: 87222.03 | E44: 57728.86 | F44: 24839.32
A45: OPERATING_RESULT | B45: Resultado operacional | C45: 276036182 | D45: -48211.53 | E45: -38421.6 | F45: 109264.68
B46: NO OPERACIONALES E IMPUESTOS
A47: PL-NO-010 | B47: Ingresos financieros | C47: 10800447 | D47: 576.14 | E47: 0 | F47: 0
A48: PL-NO-020 | B48: Otros ingresos | C48: 0 | D48: 0 | E48: 64960.94 | F48: 0
A49: TOTAL_NONOP_INCOME | B49: Subtotal ingresos no operacionales | C49: 10800447 | D49: 576.14 | E49: 64960.94 | F49: 0
A50: PL-F-010 | B50: Gastos financieros | C50: 40108353 | D50: 912.54 | E50: 1166.97 | F50: 236
A51: PL-T-010 | B51: Impuesto de renta | C51: 0 | D51: 0 | E51: 0 | F51: 0
A52: TOTAL_FIN_TAX | B52: Subtotal gastos financieros e impuestos | C52: 40108353 | D52: 912.54 | E52: 1166.97 | F52: 236
A53: PL-N-900 | B53: Conciliación de la utilidad oficial | C53: 1 | D53: 0 | E53: 0 | F53: 0
A54: NET_RESULT | B54: Resultado neto calculado | C54: 246728277 | D54: -48547.93 | E54: 25372.37 | F54: 109028.68

Sheet EEFF_Movimientos
A1: Movimientos mensuales homologados
A2: Saldos y movimientos de los auxiliares por rubro común. COCO no se incluye porque el PDF solo contiene estados acumulados.
A3: Entidad | B3: Periodo | C3: Moneda | D3: Código común | E3: Rubro común | F3: Saldo inicial fuente | G3: Débitos | H3: Créditos | I3: Saldo final fuente | J3: Saldo presentación
A4: USA | B4: 2026-01 | C4: USD | D4: BS-A-010 | E4: Efectivo y equivalentes | F4: 379731 | G4: 3749.86 | H4: 13923.39 | I4: 369557.47 | J4: 369557.47
A5: USA | B5: 2026-01 | C5: USD | D5: BS-A-030 | E5: Cuentas comerciales por cobrar | F5: 3151.25 | G5: 3498.8 | H5: 517 | I5: 6133.05 | J5: 6133.05
A6: USA | B6: 2026-01 | C6: USD | D6: BS-A-040 | E6: Anticipos y otras cuentas por cobrar | F6: 0 | G6: 0 | H6: 0 | I6: 0 | J6: 0
A7: USA | B7: 2026-01 | C7: USD | D7: BS-A-050 | E7: Activos por impuestos corrientes | F7: 0 | G7: 0 | H7: 0 | I7: 0 | J7: 0
A8: USA | B8: 2026-01 | C8: USD | D8: BS-A-060 | E8: Otras cuentas por cobrar | F8: 591811 | G8: 6028 | H8: 3108.29 | I8: 594730.71 | J8: 594730.71
A9: USA | B9: 2026-01 | C9: USD | D9: BS-A-110 | E9: Propiedad, planta y equipo | F9: 7484 | G9: 1333.22 | H9: 0 | I9: 8817.22 | J9: 8817.22
A10: USA | B10: 2026-01 | C10: USD | D10: BS-A-120 | E10: Depreciación acumulada | F10: -4924 | G10: 0 | H10: 0 | I10: -4924 | J10: -4924
A11: USA | B11: 2026-01 | C11: USD | D11: BS-E-010 | E11: Capital social | F11: -383868 | G11: 0 | H11: 0 | I11: -383868 | J11: 383868
A12: USA | B12: 2026-01 | C12: USD | D12: BS-E-030 | E12: Resultados acumulados | F12: 0 | G12: 0 | H12: 0 | I12: 0 | J12: 0
A13: USA | B13: 2026-01 | C13: USD | D13: BS-E-040 | E13: Resultado registrado en libros | F13: -13042.5 | G13: 0 | H13: 0 | I13: -13042.5 | J13: 13042.5
A14: USA | B14: 2026-01 | C14: USD | D14: BS-L-010 | E14: Obligaciones financieras | F14: 0 | G14: 2769.96 | H14: 2769.96 | I14: 0 | J14: 0
A15: USA | B15: 2026-01 | C15: USD | D15: BS-L-020 | E15: Cuentas comerciales por pagar | F15: 0 | G15: 0 | H15: 0 | I15: 0 | J15: 0
... A763: CR | B763: 2026-06 | C763: USD | D763: PL-S-060 | E763: Otros gastos comerciales | F763: 0 | G763: 0 | H763: 0 | I763: 0 | J763: 0

Sheet EEFF_Base_Homologada
A1: Base homologada de cuentas
A2: Solo contiene cuentas de detalle para evitar doble conteo. Los rubros se consultan desde Homologacion y conservan la trazabilidad a archivo y fila/página.
A3: Archivo fuente | B3: Referencia | C3: Entidad | D3: País | E3: Periodo | F3: Fin periodo | G3: Moneda | H3: Estado fuente | I3: Código fuente | J3: Cuenta fuente | K3: Detalle / tercero | L3: Saldo inicial | M3: Débitos | N3: Créditos | O3: Saldo final fuente | P3: Clave mapeo | Q3: Código común | R3: Estado común | S3: Categoría | T3: Rubro común | U3: Subrubro | V3: Naturaleza | W3: Factor signo | X3: Saldo presentación | Y3: Confianza | Z3: Revisar | AA3: Fundamento
A4: Abril 2026 CR.xlsx | B4: Fila 6 | C4: CR | D4: Costa Rica | E4: 2026-04 | F4: 46142 | G4: USD | H4: Auxiliar contable | I4: 11100501 | J4: MONEDA NACIONAL | L4: 473.04 | M4: 10781.96 | N4: 11319.07 | O4: -64.07 | P4: AUX|111005 | Q4: BS-A-010 | R4: Balance | S4: Activos corrientes | T4: Efectivo y equivalentes | U4: Bancos - cuenta corriente | V4: Deudora | W4: 1 | X4: -64.07 | Y4: Alta | Z4: NO | AA4: Cuenta bancaria disponible
A5: Abril 2026 CR.xlsx | B5: Fila 11 | C5: CR | D5: Costa Rica | E5: 2026-04 | F5: 46142 | G5: USD | H5: Auxiliar contable | I5: 23050102 | J5: CTAS CTE COMERCIALES | K5: NEXUS HEALTH STRATEGIES | L5: -92 | M5: 0 | N5: 0 | O5: -92 | P5: AUX|230505 | Q5: BS-L-030 | R5: Balance | S5: Pasivos corrientes | T5: Otras cuentas por pagar | U5: Cuentas corrientes comerciales | V5: Acreedora | W5: -1 | X5: 92 | Y5: Alta | Z5: NO | AA5: Cuenta comercial por pagar
A6: Abril 2026 CR.xlsx | B6: Fila 16 | C6: CR | D6: Costa Rica | E6: 2026-04 | F6: 46142 | G6: USD | H6: Auxiliar contable | I6: 31050502 | J6: CAPITAL AUTORIZADO | K6: COCO TECH AI COSTA RICA SOCIEDAD ANONIMA | L6: -6882.83 | M6: 0 | N6: 0 | O6: -6882.83 | P6: AUX|310505 | Q6: BS-E-010 | R6: Balance | S6: Patrimonio | T6: Capital social | U6: Capital autorizado/pagado | V6: Acreedora | W6: -1 | X6: 6882.83 | Y6: Alta | Z6: NO | AA6: Capital social
A7: Abril 2026 CR.xlsx | B7: Fila 19 | C7: CR | D7: Costa Rica | E7: 2026-04 | F7: 46142 | G7: USD | H7: Auxiliar contable | I7: 31150502 | J7: CUOTAS O PARTES DE INTERES SOCIAL | L7: -22786 | M7: 0 | N7: 10781.96 | O7: -33567.96 | P7: AUX|311505 | Q7: BS-E-010 | R7: Balance | S7: Patrimonio | T7: Capital social | U7: Aportes sociales | V7: Acreedora | W7: -1 | X7: 33567.96 | Y7: Alta | Z7: NO | AA7: Aportes de socios
A8: Abril 2026 CR.xlsx | B8: Fila 23 | C8: CR | D8: Costa Rica | E8: 2026-04 | F8: 46142 | G8: USD | H8: Auxiliar contable | I8: 36100102 | J8: PERDIDA DEL EJERCICIO | L8: 22674.27 | M8: 0 | N8: 0 | O8: 22674.27 | P8: AUX|361005 | Q8: BS-E-040 | R8: Balance | S8: Patrimonio | T8: Resultado registrado en libros | U8: Pérdida registrada | V8: Acreedora | W8: -1 | X8: -22674.27 | Y8: Media | Z8: SI | AA8: No concilia con el resultado YTD de cuentas 4 y 5; revisar signo y cierre
A9: Abril 2026 CR.xlsx | B9: Fila 28 | C9: CR | D9: Costa Rica | E9: 2026-04 | F9: 46142 | G9: USD | H9: Auxiliar contable | I9: 51050601 | J9: SUELDOS | K9: NARANJO BUSTOS MARIAM | L9: 3600 | M9: 1200 | N9: 0 | O9: 4800 | P9: AUX|510506 | Q9: PL-O-010 | R9: Resultados | S9: Gastos de administración | T9: Gastos de personal | U9: Sueldos | V9: Deudora | W9: 1 | X9: 4800 | Y9: Alta | Z9: NO | AA9: Remuneración laboral
A10: Abril 2026 CR.xlsx | B10: Fila 30 | C10: CR | D10: Costa Rica | E10: 2026-04 | F10: 46142 | G10: USD | H10: Auxiliar contable | I10: 51052105 | J10: VIATICOS | L10: 900 | M10: 300 | N10: 0 | O10: 1200 | P10: AUX|510521 | Q10: PL-O-090 | R10: Resultados | S10: Gastos de administración | T10: Viajes y representación | U10: Viáticos | V10: Deudora | W10: 1 | X10: 1200 | Y10: Alta | Z10: NO | AA10: Viáticos administrativos
A11: Abril 2026 CR.xlsx | B11: Fila 32 | C11: CR | D11: Costa Rica | E11: 2026-04 | F11: 46142 | G11: USD | H11: Auxiliar contable | I11: 51053101 | J11: PRESTACIONES SOCIALES | K11: NARANJO BUSTOS MARIAM | L11: 1212.37 | M11: 400 | N11: 0 | O11: 1612.37 | P11: AUX|510531 | Q11: PL-O-010 | R11: Resultados | S11: Gastos de administración | T11: Gastos de personal | U11: Prestaciones sociales | V11: Deudora | W11: 1 | X11: 1612.37 | Y11: Alta | Z11: NO | AA11: Prestaciones laborales
A12: Abril 2026 CR.xlsx | B12: Fila 35 | C12: CR | D12: Costa Rica | E12: 2026-04 | F12: 46142 | G12: USD | H12: Auxiliar contable | I12: 51102501 | J12: ASESORIA JURIDICA | K12: MUÑOZ CHACON FRANCISCO JAVIER | L12: 270.35 | M12: 0 | N12: 0 | O12: 270.35 | P12: AUX|511025 | Q12: PL-O-020 | R12: Resultados | S12: Gastos de administración | T12: Honorarios y servicios profesionales | U12: Asesoría jurídica | V12: Deudora | W12: 1 | X12: 270.35 | Y12: Alta | Z12: NO | AA12: Servicio profesional jurídico
A13: Abril 2026 CR.xlsx | B13: Fila 38 | C13: CR | D13: Costa Rica | E13: 2026-04 | F13: 46142 | G13: USD | H13: Auxiliar contable | I13: 51150501 | J13: INDUSTRIA Y COMERCIO | K13: MINISTERIO DE HACIENDA | L13: 252.73 | M13: 0 | N13: 0 | O13: 252.73 | P13: AUX|511505 | Q13: PL-O-030 | R13: Resultados | S13: Gastos de administración | T13: Impuestos y contribuciones | U13: Industria, comercio y otros | V13: Deudora | W13: 1 | X13: 252.73 | Y13: Alta | Z13: NO | AA13: Impuestos no asociados a renta
A14: Abril 2026 CR.xlsx | B14: Fila 39 | C14: CR | D14: Costa Rica | E14: 2026-04 | F14: 46142 | G14: USD | H14: Auxiliar contable | I14: 51150502 | J14: INDUSTRIA Y COMERCIO | K14: MINISTERIO DE HACIENDA | L14: 26.55 | M14: 115.64 | N14: 0 | O14: 142.19 | P14: AUX|511505 | Q14: PL-O-030 | R14: Resultados | S14: Gastos de administración | T14: Impuestos y contribuciones | U14: Industria, comercio y otros | V14: Deudora | W14: 1 | X14: 142.19 | Y14: Alta | Z14: NO | AA14: Impuestos no asociados a renta
